Workbook
Name _CCC10: #REF!
Name _CCC2: #REF!
Name _CCC3: #REF!
Name _CCC4: #REF!
Name _CCC5: #REF!
Name _CCC6: #REF!
Name _CCC7: #REF!
Name _CCC8: #REF!
Name _CCC9: #REF!
Name _mo12: #REF!
Name _MO5: #REF!
Name _mo7: #REF!
Name _NSA1: #REF!
Name _NSA10: #REF!
Name _NSA2: #REF!
Name _NSA3: #REF!
Name _NSA4: #REF!
Name _NSA5: #REF!
Name _NSA6: #REF!
Name _NSA7: #REF!
Name _NSA8: #REF!
Name _NSA9: #REF!
Name _X1: '[1]06-00'!#REF!
Name _X11: #REF!
Name a: #REF!
Name Actual_PtaxandERAF_Report: #REF!
Name Analysis_Actuals: '[2] Analysis for Actuals'!$B$10:$J$81
Name azaz: #REF!
Name CALGRANT_FALLSPRING: #REF!
Name CCC_BASE_92: #REF!
Name CCC_BASE_93: #REF!
Name CCC_BASE_94: #REF!
Name CO_APPORT_REV_9: #REF!
Name CO_NET_LR_86: #REF!
Name CO_NET_LR_87: #REF!
Name CO_NET_LR_88: #REF!
Name CO_NET_LR_89: #REF!
Name CO_NET_LR_90: #REF!
Name CO_P98_LR_93: #REF!
Name CO_P98_LR_94: #REF!
Name CO_SE_SHARE_92: #REF!
Name CO_SE_SHARE_93: #REF!
Name CO_SE_SHARE_94: #REF!
Name CO_SE_TR_91: #REF!
Name CO_SE_TR_92: #REF!
Name CO_SE_TR_93: #REF!
Name CO_SE_TR_94: #REF!
Name CO_SHIFT_92: #REF!
Name CO_SHIFT_93: #REF!
Name CO_SHIFT_94: #REF!
Name CO_TR_91: #REF!
Name CO_TR_92: #REF!
Name CO_TR_93: #REF!
Name CO_TR_94: #REF!
Name COUNTY_PTAX: '[3]1d.County ptax11-15-2015'!$D$2:$AP$247
Name COUNTYERAFREPORT: [4]!NEWERAFModPtax6[[Left Blank]:[Total Positive ERAF to Distribute]]
Name CountyTOT_PTR_A: #REF!
Name d: #REF!
Name Data_Actuals: '[2]EF2016-2017P3 (Actuals)'!$B$8:$M$79
Name Database_MI: #REF!

Sheet 1. Data Dictionary
A1: Data Dictionary
A2: Factor | B2: Current Law Definition | C2: Changes to Definition in this Simulation
A3: Noncredit FTES (excluding CDCP noncredit FTES). | B3: The funding rate is unchanged from current practice. For purposes of our estimates, we calculate growth from prior year FTES, adding any restoration that occurs. | C3: No Change
A4: CDCP noncredit FTES | B4: The funding rate is unchanged from current practice. For purposes of our estimates, we calculate growth from prior year FTES, adding any restoration that occurs. | C4: No Change
A5: Base Allocation (70%)
A6: Credit Full-Time Equivalent Students (FTES) | B6: Three-year rolling average of funded FTES. Specifically, average equal to the sum of the annually funded credit FTES from the current year, the prior year, and the year prior to the prior year, all divided by three. Credit FTES for these purposes excludes FTES of special admit students and inmates in correctional facilities. | C6: No Change
A7: Basic Allocation | B7: Number of colleges and comprehensive centers in the community college district (with funding consistent with the basic allocation formula established by the Board of Governors as of the 2015-16 fiscal year). | C7: No Change
A8: Special Admit Students FTES | B8: Funded FTES generated by students who meet the requirements of ECS 76002, 76003, and 76004 | C8: No Change
A9: Students in Correctional Facilities FTES | B9: Funded FTES generated by students who meet the requirements of ECS 84810.5(a). | C9: No Change
A10: Supplemental Allocation (20%)
A11: Pell Grant Recipients | B11: Headcount of all students in the prior year who were recipients of financial aid under the Federal Pell Grant program. | C11: No Change
A12: AB 540 Students | B12: Headcount of all students in the prior year who were granted an exemption from nonresident tuition pursuant to ECS 68130.5. | C12: No Change
A13: California College Promise Grant Recipients | B13: Headcount of all students in the prior year who were received a fee waiver pursuant to Section 76300. | C13: No Change
A14: Student Success Allocation (10%)
A15: Associate Degrees for Transfer | B15: Count of all Chancellor's Office approved associate degrees for transfer granted based on prior year data. | C15: Use a three year average of 2016-17, 2017-18, and 2018-19 (projected). Count only the highest outcome a student attains of ADT, associate degree, baccalaureate degree, and credit certificate (16 units or greater). Count the outcome only if a student took 9 or more units in the district in the academic year of the award.
A16: Associate Degrees | B16: Count of all Chancellor's Office approved associate degrees granted (excluding associate degrees for transfer granted) based on prior year data. | C16: Use a three year average of 2016-17, 2017-18, and 2018-19 (projected). Count only the highest outcome a student attains of ADT, associate degree, baccalaureate degree, and credit certificate (16 units or greater). Count the outcome only if a student took 9 or more units in the district in the academic year of the award.
A17: Baccalaureate Degrees | B17: Count of all Chancellor's Office approved baccalaureate degrees granted based on prior year data. | C17: Use a three year average of 2016-17, 2017-18, and 2018-19 (projected). Count only the highest outcome a student attains of ADT, associate degree, baccalaureate degree, and credit certificate (16 units or greater). Count the outcome only if a student took 9 or more units in the district in the academic year of the award.
A18: Credit Certificates | B18: Count of all Chancellor's Office approved credit certificates requiring 16 or more units granted based on prior year data. | C18: Use a three year average of 2016-17, 2017-18, and 2018-19 (projected). Count only the highest outcome a student attains of ADT, associate degree, baccalaureate degree, and credit certificate (16 units or greater). Count the outcome only if a student took 9 or more units in the district in the academic year of the award.
A19: Completion of Transfer-Level Mathematics and English | B19: Count of all first-time students who successfully completes both transfer-level mathematics and English courses within the same district within the first academic year (summer, fall, and spring) of enrollment based on prior year data. | C19: Use a three year average of 2016-17, 2017-18, and 2018-19 (projected).
A20: Completion of Nine CTE Units | B20: Count of all students who successfully completed nine or more career technical education (CTE) units within the same district based on prior year data. CTE courses are SAM A, B, C courses or all courses with a CTE TOP Code. | C20: Use a three year average of 2016-17, 2017-18, and 2018-19 (projected).
A21: Successful Transfer to Four-Year University | B21: Count of all students who successfully transferred to a four-year university based on prior year data. | C21: The student has completed 12 or more semester units, or the equivalent, in the community college district in the year prior to the prior year and has an enrollment record in the prior prior year. Use a three year average of 2016-17, 2017-18, and 2018-19 (projected).
A22: Regional Living Wage | B22: Count of all students who obtained a regional living wage within one year of community college completion based on prior year data. | C22: Use a three year average of 2016-17, 2017-18, and 2018-19 (projected).
A23: Equity Component
A24: Pell Grant Recipients | B24: Outcomes for all students who received financial aid under the Federal Pell Grant program. | C24: Use a three year average of 2016-17, 2017-18, and 2018-19 (projected).
A25: California College Promise Grant Recipients | B25: Outcomes for all students who received a fee waiver pursuant to Section 76300. | C25: Use a three year average of 2016-17, 2017-18, and 2018-19 (projected).

Sheet 2. Weighting
A1: Total SCFF 2019-20
A3: Total SCFF Target for 19-20 (before Hold Harmless) | B3: 7.4972375e+09 | G3: TCR 19-20 Calculated | H3: ='3. HH-Total'!N78 -> 7.3370407e+09
A4: Base NonCredit and CDCP | B4: =SUM(C15:C16) -> 3.4120934e+08 | G4: Hold Harmless Calculated | H4: ='3. HH-Total'!M78 -> 2.4845495e+08
B5: =B3-B4 -> 7.1560281e+09 | G5: TCR 19-20 DOF Enacted | H5: 7.3370407e+09
A6: Base | B6: =B$5*C6 -> 5.0092197e+09 | C6: 0.7 | G6: Hold Harmless DOF Enacted | H6: 1.8262402e+08
A7: Supplemental | B7: =B$5*C7 -> 1.4312056e+09 | C7: 0.2
A8: Success | B8: =B$5*C8 -> 7.1560281e+08 | C8: 0.1
A9: COLA 19-20 | B9: 0.0326
A13: CCC Funding Formula Factors for 2019-20 70/20/10
B14: Counts | C14: Funding | E14: 2019-20 Rates
A15: Non-Credit FTES (Rate from DOF) | B15: ='5a. Base Counts'!C78 -> 35123.935 | C15: =B15*E15 -> 1.1885435e+08 | E15: 3383.8562
A16: Non-Credit CDCP FTES (Rate from DOF) | B16: ='5a. Base Counts'!D78 -> 39437.772 | C16: =B16*E16 -> 2.2235499e+08 | E16: 5638.1225
A17: Base Allocation: 70%
B18: Counts | C18: Funding | E18: 2019-20 Rates
A19: Basic Allocation | C19: ='5. Base Allocation'!B78 -> 6.2872988e+08
A20: Credit FTES | B20: ='5a. Base Counts'!B78 -> 1003674 | C20: =C25+C26 -> 4.1491829e+09 | E20: 4123.5
A21: Credit Special Admits and Students in Correctional Facilities FTES (Rates from DOF) | B21: ='5a. Base Counts'!E78 -> 40889.824 | C21: ='Differential Districts'!F34 -> 2.3104445e+08 | E21: 5638.1225
A22: Total calculated | B22: =SUM(B20:B21) -> 1044563.8 | C22: =SUM(C19:C21) -> 5.0089572e+09
A23: Total Base per formula | C23: =B6 -> 5.0092197e+09
A24: Credit FTES Total (regular and differential) | C24: =C23-(C19+C21) -> 4.1494453e+09
A25: Differential districts | B25: ='Differential Districts'!E15 -> 108631.63 | C25: ='Differential Districts'!F15 -> 4.5847561e+08
A26: Non differential districts credit FTES | B26: =B20-B25 -> 895042.38 | C26: =B26*E20 -> 3.6907073e+09
A28: Supplemental Allocation: 20%
B30: Points | C30: Total Counts1 | D30: Total Points | E30: Total Dollars
A31: Supplemental Metrics | B31: (a) | C31: (b) | D31: (c) = (a) * (b) | E31: (d) = (c) * B37
A32: Pell Grant | B32: 1 | C32: ='6a. Supp Counts'!F78 -> 437357 | D32: =B32*C32 -> 437357 | E32: =D32*B$38 -> 4.2545912e+08
A33: AB 540 Students | B33: 1 | C33: ='6a. Supp Counts'!G78 -> 57994 | D33: =B33*C33 -> 57994 | E33: =D33*B$38 -> 56416329
A34: California Promise Grant Students | B34: 1 | C34: ='6a. Supp Counts'!H78 -> 975878 | D34: =B34*C34 -> 975878 | E34: =D34*B$38 -> 9.4933017e+08
A35: Total calculated | E35: =E32+E33+E34 -> 1.4312056e+09
A36: Total per formula | B36: =SUM(B32:B34) -> 3 | C36: =SUM(C32:C34) -> 1471229 | D36: =SUM(D32:D34) -> 1471229 | E36: =B7 -> 1.4312056e+09
A38: Supplemental Rate Per Point | B38: =E36/D36 -> 972.79596
A40: Student Success Incentive Allocation: 10%
B41: Points | C41: Total Counts1 | D41: Total Points | E41: Total Dollars
B42: (a) | C42: (b) | D42: (c) = (a) * (b) | E42: (d) = (c) * B54
A43: Success Metrics
A44: Associate degree for transfer | B44: 4 | C44: ='7b. Success proj 1819'!B76 -> 51998 | D44: =B44*C44 -> 207992 | E44: =D44*B$55 -> 1.0394862e+08
A45: Associate degree | B45: 3 | C45: ='7b. Success proj 1819'!C76 -> 62587 | D45: =B45*C45 -> 187761 | E45: =D45*B$55 -> 93837731
A46: Bachelor degree | B46: 3 | C46: ='7b. Success proj 1819'!D76 -> 212 | D46: =B46*C46 -> 636 | E46: =D46*B$55 -> 317855.13
A47: Credit certificates requiring 16+ units | B47: 2 | C47: ='7b. Success proj 1819'!E76 -> 23172 | D47: =B47*C47 -> 46344 | E47: =D47*B$55 -> 23161443
A48: Completion of transfer-level math and English | B48: 2 | C48: ='7b. Success proj 1819'!F76 -> 28604 | D48: =B48*C48 -> 57208 | E48: =D48*B$55 -> 28590969
A49: Transfer to 4-year institutions | B49: 1.5 | C49: ='7b. Success proj 1819'!H76 -> 131379 | D49: =B49*C49 -> 197068.5 | E49: =D49*B$55 -> 98489361
A50: Completion of 9 CTE units | B50: 1 | C50: ='7b. Success proj 1819'!G76 -> 180888 | D50: =B50*C50 -> 180888 | E50: =D50*B$55 -> 90402796
A51: Attainment of regional living wage | B51: 1 | C51: ='7b. Success proj 1819'!I76 -> 202282 | D51: =B51*C51 -> 202282 | E51: =D51*B$55 -> 1.0109492e+08
A53: Total calculated | B53: =SUM(B44:B51) -> 17.5 | C53: =SUM(C44:C51) -> 681122 | D53: =SUM(D44:D51) -> 1080179.5 | E53: =SUM(E44:E51) -> 5.398437e+08
A55: Success Rate per Point | B55: =E82/D82 -> 499.77221
B57: Points | C57: Total Counts1 | D57: Total Points | E57: Total Dollars
A58: Pell Grant recipients | B58: (a) | C58: (b) | D58: (c) = (a) * (b) | E58: (d) = (c) * B79
A59: Associate degree for transfer | B59: 6 | C59: ='7b. Success proj 1819'!J76 -> 28208 | D59: =B59*C59 -> 169248 | E59: =D59*B$80 -> 21146362
A60: Associate degree | B60: 4.5 | C60: ='7b. Success proj 1819'!K76 -> 33480 | D60: =B60*C60 -> 150660 | E60: =D60*B$80 -> 18823920
A61: Bachelor degree | B61: 4.5 | C61: ='7b. Success proj 1819'!L76 -> 100 | D61: =B61*C61 -> 450 | E61: =D61*B$80 -> 56224.374
A62: Credit certificates requiring 16+ units | B62: 3 | C62: ='7b. Success proj 1819'!M76 -> 10389 | D62: =B62*C62 -> 31167 | E62: =D62*B$80 -> 3894100.1
A63: Completion of transfer-level math and English | B63: 3 | C63: ='7b. Success proj 1819'!N76 -> 10855 | D63: =B63*C63 -> 32565 | E63: =D63*B$80 -> 4068770.5
A64: Transfer to 4-year institutions | B64: 2.25 | C64: ='7b. Success proj 1819'!P76 -> 55661 | D64: =B64*C64 -> 125237.25 | E64: =D64*B$80 -> 15647524
A65: Completion of 9 CTE units | B65: 1.5 | C65: ='7b. Success proj 1819'!O76 -> 78119 | D65: =B65*C65 -> 117178.5 | E65: =D65*B$80 -> 14640640
A66: Attainment of regional living wage | B66: 1.5 | C66: ='7b. Success proj 1819'!Q76 -> 54894 | D66: =B66*C66 -> 82341 | E66: =D66*B$80 -> 10287936
A68: California College Promise Grant recipients
A69: Associate degree for transfer | B69: 4 | C69: ='7b. Success proj 1819'!R76 -> 38541 | D69: =B69*C69 -> 154164 | E69: =D69*B$80 -> 19261721
A70: Associate degree | B70: 3 | C70: ='7b. Success proj 1819'!S76 -> 47074 | D70: =B70*C70 -> 141222 | E70: =D70*B$80 -> 17644708
A71: Bachelor degree | B71: 3 | C71: ='7b. Success proj 1819'!T76 -> 168 | D71: =B71*C71 -> 504 | E71: =D71*B$80 -> 62971.299
A72: Credit certificates requiring 16+ units | B72: 2 | C72: ='7b. Success proj 1819'!U76 -> 15378 | D72: =B72*C72 -> 30756 | E72: =D72*B$80 -> 3842748.6
A73: Completion of transfer-level math and English | B73: 2 | C73: ='7b. Success proj 1819'!V76 -> 15664 | D73: =B73*C73 -> 31328 | E73: =D73*B$80 -> 3914216
A74: Transfer to 4-year institutions | B74: 1.5 | C74: ='7b. Success proj 1819'!X76 -> 82274 | D74: =B74*C74 -> 123411 | E74: =D74*B$80 -> 15419347
A75: Completion of 9 CTE units | B75: 1 | C75: ='7b. Success proj 1819'!W76 -> 119026 | D75: =B75*C75 -> 119026 | E75: =D75*B$80 -> 14871472
A76: Attainment of regional living wage | B76: 1 | C76: ='7b. Success proj 1819'!Y76 -> 97456 | D76: =B76*C76 -> 97456 | E76: =D76*B$80 -> 12176450
A78: Total calculated | B78: =SUM(B59:B76) -> 43.75 | C78: =SUM(C59:C76) -> 687287 | D78: =SUM(D59:D76) -> 1406713.8 | E78: =SUM(E59:E76) -> 1.7575911e+08
A80: Rate per point for completions of Pell grant recipients and California Promise Grant recipients - 18-19 | B80: =B55/4 -> 124.94305 | E80: =E53+E78 -> 7.1560281e+08
A82: Total Student Success Allocation | D82: =D53+(D78/4) -> 1431857.9 | E82: =B8 -> 7.1560281e+08
A84: Rates | B84: 17-18 | C84: 18-19 | D84: 19-20
A85: Base (Credit FTES) | B85: 3727 | D85: =E20 -> 4123.5
A86: Supplemental | B86: 919 | D86: =B38 -> 972.79596
A87: Success | B87: 440 | D87: =B55 -> 499.77221
A88: Success for Pell Grant recipients and California Promise Grant recipients | B88: 111 | D88: =B80 -> 124.94305

Sheet Differential Districts
B1: 2017-18 rate | D1: 2019-20 Rate
A2: Credit FTES | B2: ='2. Weighting'!B85 -> 3727 | D2: ='2. Weighting'!E20 -> 4123.5
A3: Districts with Differential Rates | B3: 2017-18 per SCFF Statute | C3: 2017-18 rate as % of regular 2018 rate | D3: New Rate (2019-20 adjusted) | E3: 3-yr avg Credit FTES | F3: Differential total $ credit FTES with 1920 rates
A5: Foothill-De Anza | B5: 3745 | C5: =B5/B$2 -> 1.0048296 | D5: =D$2*C5 -> 4143.4149 | E5: ='5a. Base Counts'!B22 -> 21924.874 | F5: =D5*E5 -> 90843852
A6: Lake Tahoe | B6: 3817.5887 | C6: =B6/B$2 -> 1.0243061 | D6: =D$2*C6 -> 4223.7261 | E6: ='5a. Base Counts'!B29 -> 1595.5535 | F6: =D6*E6 -> 6739180.7
A7: Lassen | B7: 3794.1259 | C7: =B7/B$2 -> 1.0180107 | D7: =D$2*C7 -> 4197.7672 | E7: ='5a. Base Counts'!B30 -> 755.73115 | F7: =D7*E7 -> 3172383.4
A8: Marin | B8: 4261.4665 | C8: =B8/B$2 -> 1.1434039 | D8: =D$2*C8 -> 4714.8261 | E8: ='5a. Base Counts'!B34 -> 2960.3378 | F8: =D8*E8 -> 13957478
A9: MiraCosta | B9: 3733.8826 | C9: =B9/B$2 -> 1.0018467 | D9: =D$2*C9 -> 4131.1148 | E9: ='5a. Base Counts'!B37 -> 9235.1822 | F9: =D9*E9 -> 38151598
A10: San Francisco | B10: 3756.2121 | C10: =B10/B$2 -> 1.007838 | D10: =D$2*C10 -> 4155.8199 | E10: ='5a. Base Counts'!B54 -> 16320.546 | F10: =D10*E10 -> 67825248
A11: San Jose-Evergreen | B11: 3743.7854 | C11: =B11/B$2 -> 1.0045037 | D11: =D$2*C11 -> 4142.0711 | E11: ='5a. Base Counts'!B56 -> 11791.251 | F11: =D11*E11 -> 48840201
A12: Santa Monica | B12: 3776.4503 | C12: =B12/B$2 -> 1.0132681 | D12: =D$2*C12 -> 4178.2111 | E12: ='5a. Base Counts'!B61 -> 18684.956 | F12: =D12*E12 -> 78069689
A13: South Orange | B13: 3825.5597 | C13: =B13/B$2 -> 1.0264448 | D13: =D$2*C13 -> 4232.5451 | E13: ='5a. Base Counts'!B68 -> 22488.816 | F13: =D13*E13 -> 95184925
A14: West Kern | B14: 4934.025 | C14: =B14/B$2 -> 1.3238597 | D14: =D$2*C14 -> 5458.9354 | E14: ='5a. Base Counts'!B74 -> 2874.3797 | F14: =D14*E14 -> 15691053
E15: =SUM(E5:E14) -> 108631.63 | F15: =SUM(F5:F14) -> 4.5847561e+08
D17: 2019-20 Rate | E17: 3-yr avg Special admit/Students in Correctional FTES | F17: Differential total $ special admit and students in correctional FTES with 1920 rates
A18: Special Admit/Students in Correctional Facilities | D18: ='2. Weighting'!E21 -> 5638.1225
A19: Districts with Differential Rates
A21: Foothill-De Anza | C21: =C5 -> 1.0048296 | D21: =D$18*C21 -> 5665.3525 | E21: ='5a. Base Counts'!E22 -> 835.09333 | F21: =D21*E21 -> 4731098.1
A22: Lake Tahoe | C22: =C6 -> 1.0243061 | D22: =D$18*C22 -> 5775.1631 | E22: ='5a. Base Counts'!E29 -> 132.84987 | F22: =D22*E22 -> 767229.66
A23: Lassen | C23: =C7 -> 1.0180107 | D23: =D$18*C23 -> 5739.6691 | E23: ='5a. Base Counts'!E30 -> 899.75536 | F23: =D23*E23 -> 5164298
A24: Marin | C24: =C8 -> 1.1434039 | D24: =D$18*C24 -> 6446.6514 | E24: ='5a. Base Counts'!E34 -> 143.66333 | F24: =D24*E24 -> 926147.43
A25: MiraCosta | C25: =C9 -> 1.0018467 | D25: =D$18*C25 -> 5648.5343 | E25: ='5a. Base Counts'!E37 -> 103.71 | F25: =D25*E25 -> 585809.49
A26: San Francisco | C26: =C10 -> 1.007838 | D26: =D$18*C26 -> 5682.3139 | E26: ='5a. Base Counts'!E54 -> 312.91 | F26: =D26*E26 -> 1778052.8
A27: San Jose-Evergreen | C27: =C11 -> 1.0045037 | D27: =D$18*C27 -> 5663.515 | E27: ='5a. Base Counts'!E56 -> 269.75333 | F27: =D27*E27 -> 1527752.1
A28: Santa Monica | C28: =C12 -> 1.0132681 | D28: =D$18*C28 -> 5712.9298 | E28: ='5a. Base Counts'!E61 -> 266.29667 | F28: =D28*E28 -> 1521334.2
A29: South Orange | C29: =C13 -> 1.0264448 | D29: =D$18*C29 -> 5787.2214 | E29: ='5a. Base Counts'!E68 -> 821.27 | F29: =D29*E29 -> 4752871.3
A30: West Kern | C30: =C14 -> 1.3238597 | D30: =D$18*C30 -> 7464.083 | E30: ='5a. Base Counts'!E74 -> 49.299305 | F30: =D30*E30 -> 367974.11
E31: =SUM(E21:E30) -> 3834.6012 | F31: =SUM(F21:F30) -> 22122567
A33: Special Admit students nondifferential | E33: ='5a. Base Counts'!E78-'Differential Districts'!E31 -> 37055.223 | F33: =E33*D18 -> 2.0892189e+08
A34: Total differential and nondifferential | F34: =SUM(F31,F33) -> 2.3104445e+08

Sheet 3. HH-Total
B1: 2019-20 | G1: COLA | H1: 0.0271 | J1: ='2. Weighting'!B9 -> 0.0326
B2: Base Allocation (70%) | C2: Base (Noncredit and CDCP) | D2: Supplemental Allocation (20%) | E2: Student Success Allocation (10%) | F2: 2019-20 TCR Calculated | G2: 2017-18 R1-February Total Computational Revenue (TCR) | H2: 2017-18 TCR plus 17-18 COLA | I2: 2019-20 Minimum (2017-18 TCR Plus 17-18 COLA plus 18-19 COLA) | J2: Is 2019-20 TCR minimum larger than 2019-20 TCR Calculated? | K2: Hold Harmless amount | L2: If Basic Aid, then By Formula | M2: Hold Harmless Amount for Non Basic Aid districts | N2: 2019-20 Student Centered Funding Formula (SCFF) | O2: Annual % increase (change from 2018-19 TCR)
A3: District
A6: Allan Hancock | B6: ='5. Base Allocation'!G6 -> 43277346 | C6: =SUM('5. Base Allocation'!D6:E6) -> 2524254.7 | D6: ='6. Supplemental Allocation'!E6 -> 11705654 | E6: ='7. Success Allocation'!AF6 -> 6022630 | F6: =SUM(B6:E6) -> 63529885 | G6: 58423221 | H6: =(G6*H$1)+G6 -> 60006490 | I6: =(H6*J$1)+H6 -> 61962702 | J6: =IF(I6>F6,"Y"," " ) | K6: =IF((I6-F6)>1,(I6-F6),0) -> 0 | M6: =IF(L6="x",0,K6) -> 0 | N6: =F6+M6 -> 63529885 | O6: =(N6-H6)/H6 -> 0.058716888
A7: Antelope | B7: ='5. Base Allocation'!G7 -> 52485431 | C7: =SUM('5. Base Allocation'!D7:E7) -> 320851.32 | D7: ='6. Supplemental Allocation'!E7 -> 22000753 | E7: ='7. Success Allocation'!AF7 -> 6858936.3 | F7: =SUM(B7:E7) -> 81665972 | G7: 62613062 | H7: =(G7*H$1)+G7 -> 64309876 | I7: =(H7*J$1)+H7 -> 66406378 | J7: =IF(I7>F7,"Y"," " ) | K7: =IF((I7-F7)>1,(I7-F7),0) -> 0 | M7: =IF(L7="x",0,K7) -> 0 | N7: =F7+M7 -> 81665972 | O7: =(N7-H7)/H7 -> 0.26988229
A8: Barstow | B8: ='5. Base Allocation'!G8 -> 15616275 | C8: =SUM('5. Base Allocation'!D8:E8) -> 114667.61 | D8: ='6. Supplemental Allocation'!E8 -> 5084804.5 | E8: ='7. Success Allocation'!AF8 -> 1840942.2 | F8: =SUM(B8:E8) -> 22656689 | G8: 18681460 | H8: =(G8*H$1)+G8 -> 19187728 | I8: =(H8*J$1)+H8 -> 19813247 | J8: =IF(I8>F8,"Y"," " ) | K8: =IF((I8-F8)>1,(I8-F8),0) -> 0 | M8: =IF(L8="x",0,K8) -> 0 | N8: =F8+M8 -> 22656689 | O8: =(N8-H8)/H8 -> 0.18079064
A9: Butte | B9: ='5. Base Allocation'!G9 -> 45027897 | C9: =SUM('5. Base Allocation'!D9:E9) -> 4134774.7 | D9: ='6. Supplemental Allocation'!E9 -> 12607436 | E9: ='7. Success Allocation'!AF9 -> 7091455.4 | F9: =SUM(B9:E9) -> 68861562 | G9: 58869732 | H9: =(G9*H$1)+G9 -> 60465102 | I9: =(H9*J$1)+H9 -> 62436264 | J9: =IF(I9>F9,"Y"," " ) | K9: =IF((I9-F9)>1,(I9-F9),0) -> 0 | M9: =IF(L9="x",0,K9) -> 0 | N9: =F9+M9 -> 68861562 | O9: =(N9-H9)/H9 -> 0.13886457
A10: Cabrillo | B10: ='5. Base Allocation'!G10 -> 46030053 | C10: =SUM('5. Base Allocation'!D10:E10) -> 2848229.4 | D10: ='6. Supplemental Allocation'!E10 -> 9263935.9 | E10: ='7. Success Allocation'!AF10 -> 5098113.9 | F10: =SUM(B10:E10) -> 63240332 | G10: 61066687 | H10: =(G10*H$1)+G10 -> 62721594 | I10: =(H10*J$1)+H10 -> 64766318 | J10: =IF(I10>F10,"Y"," " ) -> Y | K10: =IF((I10-F10)>1,(I10-F10),0) -> 1525986 | M10: =IF(L10="x",0,K10) -> 1525986 | N10: =F10+M10 -> 64766318 | O10: =(N10-H10)/H10 -> 0.0326
A11: Cerritos | B11: ='5. Base Allocation'!G11 -> 71428552 | C11: =SUM('5. Base Allocation'!D11:E11) -> 2431479.5 | D11: ='6. Supplemental Allocation'!E11 -> 28669270 | E11: ='7. Success Allocation'!AF11 -> 11023663 | F11: =SUM(B11:E11) -> 1.1355296e+08 | G11: 93447643 | H11: =(G11*H$1)+G11 -> 95980074 | I11: =(H11*J$1)+H11 -> 99109025 | J11: =IF(I11>F11,"Y"," " ) | K11: =IF((I11-F11)>1,(I11-F11),0) -> 0 | M11: =IF(L11="x",0,K11) -> 0 | N11: =F11+M11 -> 1.1355296e+08 | O11: =(N11-H11)/H11 -> 0.18308894
A12: Chabot-Las Positas | B12: ='5. Base Allocation'!G12 -> 75647977 | C12: =SUM('5. Base Allocation'!D12:E12) -> 630265.78 | D12: ='6. Supplemental Allocation'!E12 -> 16014167 | E12: ='7. Success Allocation'!AF12 -> 9380162.2 | F12: =SUM(B12:E12) -> 1.0167257e+08 | G12: 107679794 | H12: =(G12*H$1)+G12 -> 1.1059792e+08 | I12: =(H12*J$1)+H12 -> 1.1420341e+08 | J12: =IF(I12>F12,"Y"," " ) -> Y | K12: =IF((I12-F12)>1,(I12-F12),0) -> 12530836 | M12: =IF(L12="x",0,K12) -> 12530836 | N12: =F12+M12 -> 1.1420341e+08 | O12: =(N12-H12)/H12 -> 0.0326
A13: Chaffey | B13: ='5. Base Allocation'!G13 -> 75223813 | C13: =SUM('5. Base Allocation'!D13:E13) -> 1197061.7 | D13: ='6. Supplemental Allocation'!E13 -> 27023299 | E13: ='7. Success Allocation'!AF13 -> 10113984 | F13: =SUM(B13:E13) -> 1.1355816e+08 | G13: 93669819 | H13: =(G13*H$1)+G13 -> 96208271 | I13: =(H13*J$1)+H13 -> 99344661 | J13: =IF(I13>F13,"Y"," " ) | K13: =IF((I13-F13)>1,(I13-F13),0) -> 0 | M13: =IF(L13="x",0,K13) -> 0 | N13: =F13+M13 -> 1.1355816e+08 | O13: =(N13-H13)/H13 -> 0.18033675
A14: Citrus | B14: ='5. Base Allocation'!G14 -> 52196342 | C14: =SUM('5. Base Allocation'!D14:E14) -> 1619531.1 | D14: ='6. Supplemental Allocation'!E14 -> 16367292 | E14: ='7. Success Allocation'!AF14 -> 7913455.7 | F14: =SUM(B14:E14) -> 78096621 | G14: 68139191 | H14: =(G14*H$1)+G14 -> 69985763 | I14: =(H14*J$1)+H14 -> 72267299 | J14: =IF(I14>F14,"Y"," " ) | K14: =IF((I14-F14)>1,(I14-F14),0) -> 0 | M14: =IF(L14="x",0,K14) -> 0 | N14: =F14+M14 -> 78096621 | O14: =(N14-H14)/H14 -> 0.11589297
A15: Coast | B15: ='5. Base Allocation'!G15 -> 1.4046044e+08 | C15: =SUM('5. Base Allocation'!D15:E15) -> 3102393.4 | D15: ='6. Supplemental Allocation'!E15 -> 43674647 | E15: ='7. Success Allocation'!AF15 -> 22704777 | F15: =SUM(B15:E15) -> 2.0994226e+08 | G15: 184284255 | H15: =(G15*H$1)+G15 -> 1.8927836e+08 | I15: =(H15*J$1)+H15 -> 1.9544883e+08 | J15: =IF(I15>F15,"Y"," " ) | K15: =IF((I15-F15)>1,(I15-F15),0) -> 0 | M15: =IF(L15="x",0,K15) -> 0 | N15: =F15+M15 -> 2.0994226e+08 | O15: =(N15-H15)/H15 -> 0.10917203
A16: Compton | B16: ='5. Base Allocation'!G16 -> 29447376 | C16: =SUM('5. Base Allocation'!D16:E16) -> 59555.869 | D16: ='6. Supplemental Allocation'!E16 -> 6702564.1 | E16: ='7. Success Allocation'!AF16 -> 2438232.5 | F16: =SUM(B16:E16) -> 38647729 | G16: 35475170 | H16: =(G16*H$1)+G16 -> 36436547 | I16: =(H16*J$1)+H16 -> 37624379 | J16: =IF(I16>F16,"Y"," " ) | K16: =IF((I16-F16)>1,(I16-F16),0) -> 0 | M16: =IF(L16="x",0,K16) -> 0 | N16: =F16+M16 -> 38647729 | O16: =(N16-H16)/H16 -> 0.060685821
A17: Contra Costa | B17: ='5. Base Allocation'!G17 -> 1.2498775e+08 | C17: =SUM('5. Base Allocation'!D17:E17) -> 524948.89 | D17: ='6. Supplemental Allocation'!E17 -> 27244124 | E17: ='7. Success Allocation'!AF17 -> 16118404 | F17: =SUM(B17:E17) -> 1.6887522e+08 | G17: 170246475 | H17: =(G17*H$1)+G17 -> 1.7486015e+08 | I17: =(H17*J$1)+H17 -> 1.805606e+08 | J17: =IF(I17>F17,"Y"," " ) -> Y | K17: =IF((I17-F17)>1,(I17-F17),0) -> 11685374 | M17: =IF(L17="x",0,K17) -> 11685374 | N17: =F17+M17 -> 1.805606e+08 | O17: =(N17-H17)/H17 -> 0.0326
... A33: Los Rios | B33: ='5. Base Allocation'!G33 -> 2.3516904e+08 | C33: =SUM('5. Base Allocation'!D33:E33) -> 943768.78 | D33: ='6. Supplemental Allocation'!E33 -> 69337005 | E33: ='7. Success Allocation'!AF33 -> 31054190 | F33: =SUM(B33:E33) -> 3.3650401e+08 | G33: 303959995 | H33: =(G33*H$1)+G33 -> 3.1219731e+08 | I33: =(H33*J$1)+H33 -> 3.2237494e+08 | J33: =IF(I33>F33,"Y"," " ) | K33: =IF((I33-F33)>1,(I33-F33),0) -> 0 | M33: =IF(L33="x",0,K33) -> 0 | N33: =F33+M33 -> 3.3650401e+08 | O33: =(N33-H33)/H33 -> 0.07785684
A34: Marin | B34: ='5. Base Allocation'!G34 -> 4855471.5 | C34: =SUM('5. Base Allocation'!D34:E34) -> 979615.09 | D34: ='6. Supplemental Allocation'!E34 -> 3067225.7 | E34: ='7. Success Allocation'!AF34 -> 1590837.4 | F34: =SUM(B34:E34) -> 10493150 | G34: 25606935 | H34: =(G34*H$1)+G34 -> 26300883 | I34: =(H34*J$1)+H34 -> 27158292 | J34: =IF(I34>F34,"Y"," " ) -> Y | K34: =IF((I34-F34)>1,(I34-F34),0) -> 16665142 | L34: x | M34: =IF(L34="x",0,K34) -> 0 | N34: =F34+M34 -> 10493150 | O34: =(N34-H34)/H34 -> -0.60103432
A35: Mendocino | B35: ='5. Base Allocation'!G35 -> 17938321 | C35: =SUM('5. Base Allocation'!D35:E35) -> 452369.47 | D35: ='6. Supplemental Allocation'!E35 -> 3983599.4 | E35: ='7. Success Allocation'!AF35 -> 1878362.6 | F35: =SUM(B35:E35) -> 24252652 | G35: 22434165 | H35: =(G35*H$1)+G35 -> 23042131 | I35: =(H35*J$1)+H35 -> 23793304 | J35: =IF(I35>F35,"Y"," " ) | K35: =IF((I35-F35)>1,(I35-F35),0) -> 0 | M35: =IF(L35="x",0,K35) -> 0 | N35: =F35+M35 -> 24252652 | O35: =(N35-H35)/H35 -> 0.052535132
A36: Merced | B36: ='5. Base Allocation'!G36 -> 42343131 | C36: =SUM('5. Base Allocation'!D36:E36) -> 5485849.8 | D36: ='6. Supplemental Allocation'!E36 -> 13899309 | E36: ='7. Success Allocation'!AF36 -> 6195176.4 | F36: =SUM(B36:E36) -> 67923466 | G36: 56496411 | H36: =(G36*H$1)+G36 -> 58027464 | I36: =(H36*J$1)+H36 -> 59919159 | J36: =IF(I36>F36,"Y"," " ) | K36: =IF((I36-F36)>1,(I36-F36),0) -> 0 | M36: =IF(L36="x",0,K36) -> 0 | N36: =F36+M36 -> 67923466 | O36: =(N36-H36)/H36 -> 0.17053998
A37: MiraCosta | B37: ='5. Base Allocation'!G37 -> 7327199.8 | C37: =SUM('5. Base Allocation'!D37:E37) -> 2545866.8 | D37: ='6. Supplemental Allocation'!E37 -> 13784519 | E37: ='7. Success Allocation'!AF37 -> 7402126.3 | F37: =SUM(B37:E37) -> 31059712 | G37: 63540067 | H37: =(G37*H$1)+G37 -> 65262003 | I37: =(H37*J$1)+H37 -> 67389544 | J37: =IF(I37>F37,"Y"," " ) -> Y | K37: =IF((I37-F37)>1,(I37-F37),0) -> 36329833 | L37: x | M37: =IF(L37="x",0,K37) -> 0 | N37: =F37+M37 -> 31059712 | O37: =(N37-H37)/H37 -> -0.52407664
A38: Monterey | B38: ='5. Base Allocation'!G38 -> 29147368 | C38: =SUM('5. Base Allocation'!D38:E38) -> 1025803.7 | D38: ='6. Supplemental Allocation'!E38 -> 7356283 | E38: ='7. Success Allocation'!AF38 -> 3976343.9 | F38: =SUM(B38:E38) -> 41505799 | G38: 38888873 | H38: =(G38*H$1)+G38 -> 39942761 | I38: =(H38*J$1)+H38 -> 41244895 | J38: =IF(I38>F38,"Y"," " ) | K38: =IF((I38-F38)>1,(I38-F38),0) -> 0 | M38: =IF(L38="x",0,K38) -> 0 | N38: =F38+M38 -> 41505799 | O38: =(N38-H38)/H38 -> 0.039131935
A39: Mt. San Antonio | B39: ='5. Base Allocation'!G39 -> 1.0999044e+08 | C39: =SUM('5. Base Allocation'!D39:E39) -> 43612915 | D39: ='6. Supplemental Allocation'!E39 -> 37544087 | E39: ='7. Success Allocation'!AF39 -> 13977536 | F39: =SUM(B39:E39) -> 2.0512498e+08 | G39: 176424297 | H39: =(G39*H$1)+G39 -> 1.812054e+08 | I39: =(H39*J$1)+H39 -> 1.8711269e+08 | J39: =IF(I39>F39,"Y"," " ) | K39: =IF((I39-F39)>1,(I39-F39),0) -> 0 | M39: =IF(L39="x",0,K39) -> 0 | N39: =F39+M39 -> 2.0512498e+08 | O39: =(N39-H39)/H39 -> 0.13200261
A40: Mt. San Jacinto | B40: ='5. Base Allocation'!G40 -> 53093514 | C40: =SUM('5. Base Allocation'!D40:E40) -> 2255378.6 | D40: ='6. Supplemental Allocation'!E40 -> 21251700 | E40: ='7. Success Allocation'!AF40 -> 7416744.6 | F40: =SUM(B40:E40) -> 84017337 | G40: 71517436 | H40: =(G40*H$1)+G40 -> 73455559 | I40: =(H40*J$1)+H40 -> 75850210 | J40: =IF(I40>F40,"Y"," " ) | K40: =IF((I40-F40)>1,(I40-F40),0) -> 0 | M40: =IF(L40="x",0,K40) -> 0 | N40: =F40+M40 -> 84017337 | O40: =(N40-H40)/H40 -> 0.14378461
A41: Napa | B41: ='5. Base Allocation'!G41 -> 23825034 | C41: =SUM('5. Base Allocation'!D41:E41) -> 1398680.8 | D41: ='6. Supplemental Allocation'!E41 -> 5408745.5 | E41: ='7. Success Allocation'!AF41 -> 3241928.6 | F41: =SUM(B41:E41) -> 33874389 | G41: 31620290 | H41: =(G41*H$1)+G41 -> 32477200 | I41: =(H41*J$1)+H41 -> 33535957 | J41: =IF(I41>F41,"Y"," " ) | K41: =IF((I41-F41)>1,(I41-F41),0) -> 0 | M41: =IF(L41="x",0,K41) -> 0 | N41: =F41+M41 -> 33874389 | O41: =(N41-H41)/H41 -> 0.04302062
A42: North Orange | B42: ='5. Base Allocation'!G42 -> 1.2567415e+08 | C42: =SUM('5. Base Allocation'!D42:E42) -> 17100139 | D42: ='6. Supplemental Allocation'!E42 -> 36481794 | E42: ='7. Success Allocation'!AF42 -> 17154275 | F42: =SUM(B42:E42) -> 1.9641035e+08 | G42: 202056270 | H42: =(G42*H$1)+G42 -> 2.0753199e+08 | I42: =(H42*J$1)+H42 -> 2.1429754e+08 | J42: =IF(I42>F42,"Y"," " ) -> Y | K42: =IF((I42-F42)>1,(I42-F42),0) -> 17887185 | M42: =IF(L42="x",0,K42) -> 17887185 | N42: =F42+M42 -> 2.1429754e+08 | O42: =(N42-H42)/H42 -> 0.0326
A43: Ohlone | B43: ='5. Base Allocation'!G43 -> 34980592 | C43: =SUM('5. Base Allocation'!D43:E43) -> 14076.562 | D43: ='6. Supplemental Allocation'!E43 -> 4920401.9 | E43: ='7. Success Allocation'!AF43 -> 4169099.8 | F43: =SUM(B43:E43) -> 44084170 | G43: 48764473 | H43: =(G43*H$1)+G43 -> 50085990 | I43: =(H43*J$1)+H43 -> 51718793 | J43: =IF(I43>F43,"Y"," " ) -> Y | K43: =IF((I43-F43)>1,(I43-F43),0) -> 7634623 | M43: =IF(L43="x",0,K43) -> 7634623 | N43: =F43+M43 -> 51718793 | O43: =(N43-H43)/H43 -> 0.0326
A44: Palo Verde | B44: ='5. Base Allocation'!G44 -> 14642160 | C44: =SUM('5. Base Allocation'!D44:E44) -> 127482.56 | D44: ='6. Supplemental Allocation'!E44 -> 3551678 | E44: ='7. Success Allocation'!AF44 -> 1023471 | F44: =SUM(B44:E44) -> 19344792 | G44: 16636774 | H44: =(G44*H$1)+G44 -> 17087631 | I44: =(H44*J$1)+H44 -> 17644687 | J44: =IF(I44>F44,"Y"," " ) | K44: =IF((I44-F44)>1,(I44-F44),0) -> 0 | M44: =IF(L44="x",0,K44) -> 0 | N44: =F44+M44 -> 19344792 | O44: =(N44-H44)/H44 -> 0.13209329
A45: Palomar | B45: ='5. Base Allocation'!G45 -> 79606427 | C45: =SUM('5. Base Allocation'!D45:E45) -> 3148760.8 | D45: ='6. Supplemental Allocation'!E45 -> 20702071 | E45: ='7. Success Allocation'!AF45 -> 9955899.8 | F45: =SUM(B45:E45) -> 1.1341316e+08 | G45: 108548444 | H45: =(G45*H$1)+G45 -> 1.1149011e+08 | I45: =(H45*J$1)+H45 -> 1.1512468e+08 | J45: =IF(I45>F45,"Y"," " ) -> Y | K45: =IF((I45-F45)>1,(I45-F45),0) -> 1711526.4 | M45: =IF(L45="x",0,K45) -> 1711526.4 | N45: =F45+M45 -> 1.1512468e+08 | O45: =(N45-H45)/H45 -> 0.0326
A46: Pasadena | B46: ='5. Base Allocation'!G46 -> 1.0276055e+08 | C46: =SUM('5. Base Allocation'!D46:E46) -> 5411051.6 | D46: ='6. Supplemental Allocation'!E46 -> 29492255 | E46: ='7. Success Allocation'!AF46 -> 14002805 | F46: =SUM(B46:E46) -> 1.5166667e+08 | G46: 134464486 | H46: =(G46*H$1)+G46 -> 1.3810847e+08 | I46: =(H46*J$1)+H46 -> 1.4261081e+08 | J46: =IF(I46>F46,"Y"," " ) | K46: =IF((I46-F46)>1,(I46-F46),0) -> 0 | M46: =IF(L46="x",0,K46) -> 0 | N46: =F46+M46 -> 1.5166667e+08 | O46: =(N46-H46)/H46 -> 0.098170602
A47: Peralta | B47: ='5. Base Allocation'!G47 -> 90491628 | C47: =SUM('5. Base Allocation'!D47:E47) -> 367340.15 | D47: ='6. Supplemental Allocation'!E47 -> 22486179 | E47: ='7. Success Allocation'!AF47 -> 9667500 | F47: =SUM(B47:E47) -> 1.2301265e+08 | G47: 114674531 | H47: =(G47*H$1)+G47 -> 1.1778221e+08 | I47: =(H47*J$1)+H47 -> 1.2162191e+08 | J47: =IF(I47>F47,"Y"," " ) | K47: =IF((I47-F47)>1,(I47-F47),0) -> 0 | M47: =IF(L47="x",0,K47) -> 0 | N47: =F47+M47 -> 1.2301265e+08 | O47: =(N47-H47)/H47 -> 0.044407693
A48: Rancho Santiago | B48: ='5. Base Allocation'!G48 -> 1.0831799e+08 | C48: =SUM('5. Base Allocation'!D48:E48) -> 31709982 | D48: ='6. Supplemental Allocation'!E48 -> 27167273 | E48: ='7. Success Allocation'!AF48 -> 15814605 | F48: =SUM(B48:E48) -> 1.8300985e+08 | G48: 164850888 | H48: =(G48*H$1)+G48 -> 1.6931835e+08 | I48: =(H48*J$1)+H48 -> 1.7483813e+08 | J48: =IF(I48>F48,"Y"," " ) | K48: =IF((I48-F48)>1,(I48-F48),0) -> 0 | M48: =IF(L48="x",0,K48) -> 0 | N48: =F48+M48 -> 1.8300985e+08 | O48: =(N48-H48)/H48 -> 0.080862465
A49: Redwoods | B49: ='5. Base Allocation'!G49 -> 21126249 | C49: =SUM('5. Base Allocation'!D49:E49) -> 663180.43 | D49: ='6. Supplemental Allocation'!E49 -> 5434038.2 | E49: ='7. Success Allocation'!AF49 -> 2720135.2 | F49: =SUM(B49:E49) -> 29943603 | G49: 26897607 | H49: =(G49*H$1)+G49 -> 27626532 | I49: =(H49*J$1)+H49 -> 28527157 | J49: =IF(I49>F49,"Y"," " ) | K49: =IF((I49-F49)>1,(I49-F49),0) -> 0 | M49: =IF(L49="x",0,K49) -> 0 | N49: =F49+M49 -> 29943603 | O49: =(N49-H49)/H49 -> 0.083871221
... A55: San Joaquin Delta | B55: ='5. Base Allocation'!G55 -> 70145492 | C55: =SUM('5. Base Allocation'!D55:E55) -> 570687.35 | D55: ='6. Supplemental Allocation'!E55 -> 21848024 | E55: ='7. Success Allocation'!AF55 -> 10507492 | F55: =SUM(B55:E55) -> 1.030717e+08 | G55: 90280054 | H55: =(G55*H$1)+G55 -> 92726643 | I55: =(H55*J$1)+H55 -> 95749532 | J55: =IF(I55>F55,"Y"," " ) | K55: =IF((I55-F55)>1,(I55-F55),0) -> 0 | M55: =IF(L55="x",0,K55) -> 0 | N55: =F55+M55 -> 1.030717e+08 | O55: =(N55-H55)/H55 -> 0.11156504
A56: San Jose | B56: ='5. Base Allocation'!G56 -> 9611863.4 | C56: =SUM('5. Base Allocation'!D56:E56) -> 849652.43 | D56: ='6. Supplemental Allocation'!E56 -> 16676641 | E56: ='7. Success Allocation'!AF56 -> 6830792.9 | F56: =SUM(B56:E56) -> 33968950 | G56: 70622433 | H56: =(G56*H$1)+G56 -> 72536301 | I56: =(H56*J$1)+H56 -> 74900984 | J56: =IF(I56>F56,"Y"," " ) -> Y | K56: =IF((I56-F56)>1,(I56-F56),0) -> 40932035 | L56: x | M56: =IF(L56="x",0,K56) -> 0 | N56: =F56+M56 -> 33968950 | O56: =(N56-H56)/H56 -> -0.53169724
A57: San Luis Obispo | B57: ='5. Base Allocation'!G57 -> 36476144 | C57: =SUM('5. Base Allocation'!D57:E57) -> 2824390.6 | D57: ='6. Supplemental Allocation'!E57 -> 8367018 | E57: ='7. Success Allocation'!AF57 -> 5057851 | F57: =SUM(B57:E57) -> 52725403 | G57: 49069768 | H57: =(G57*H$1)+G57 -> 50399559 | I57: =(H57*J$1)+H57 -> 52042584 | J57: =IF(I57>F57,"Y"," " ) | K57: =IF((I57-F57)>1,(I57-F57),0) -> 0 | M57: =IF(L57="x",0,K57) -> 0 | N57: =F57+M57 -> 52725403 | O57: =(N57-H57)/H57 -> 0.046148112
A58: San Mateo | B58: ='5. Base Allocation'!G58 -> 76566804 | C58: =SUM('5. Base Allocation'!D58:E58) -> 121863.94 | D58: ='6. Supplemental Allocation'!E58 -> 14429482 | E58: ='7. Success Allocation'!AF58 -> 9849448.3 | F58: =SUM(B58:E58) -> 1.009676e+08 | G58: 98289606 | H58: =(G58*H$1)+G58 -> 1.0095325e+08 | I58: =(H58*J$1)+H58 -> 1.0424433e+08 | J58: =IF(I58>F58,"Y"," " ) -> Y | K58: =IF((I58-F58)>1,(I58-F58),0) -> 3276731.9 | L58: x | M58: =IF(L58="x",0,K58) -> 0 | N58: =F58+M58 -> 1.009676e+08 | O58: =(N58-H58)/H58 -> 0.00014208762
A59: Santa Barbara | B59: ='5. Base Allocation'!G59 -> 53636912 | C59: =SUM('5. Base Allocation'!D59:E59) -> 5496355.4 | D59: ='6. Supplemental Allocation'!E59 -> 13069514 | E59: ='7. Success Allocation'!AF59 -> 8228093.6 | F59: =SUM(B59:E59) -> 80430874 | G59: 72610515 | H59: =(G59*H$1)+G59 -> 74578260 | I59: =(H59*J$1)+H59 -> 77009511 | J59: =IF(I59>F59,"Y"," " ) | K59: =IF((I59-F59)>1,(I59-F59),0) -> 0 | M59: =IF(L59="x",0,K59) -> 0 | N59: =F59+M59 -> 80430874 | O59: =(N59-H59)/H59 -> 0.078476145
A60: Santa Clarita | B60: ='5. Base Allocation'!G60 -> 73130945 | C60: =SUM('5. Base Allocation'!D60:E60) -> 1845416 | D60: ='6. Supplemental Allocation'!E60 -> 14247570 | E60: ='7. Success Allocation'!AF60 -> 10772809 | F60: =SUM(B60:E60) -> 99996739 | G60: 94448588 | H60: =(G60*H$1)+G60 -> 97008145 | I60: =(H60*J$1)+H60 -> 1.0017061e+08 | J60: =IF(I60>F60,"Y"," " ) -> Y | K60: =IF((I60-F60)>1,(I60-F60),0) -> 173870.94 | M60: =IF(L60="x",0,K60) -> 173870.94 | N60: =F60+M60 -> 1.0017061e+08 | O60: =(N60-H60)/H60 -> 0.0326
A61: Santa Monica | B61: ='5. Base Allocation'!G61 -> 9592377.4 | C61: =SUM('5. Base Allocation'!D61:E61) -> 2693049.8 | D61: ='6. Supplemental Allocation'!E61 -> 27413390 | E61: ='7. Success Allocation'!AF61 -> 12325351 | F61: =SUM(B61:E61) -> 52024168 | G61: 129918589 | H61: =(G61*H$1)+G61 -> 1.3343938e+08 | I61: =(H61*J$1)+H61 -> 1.3778951e+08 | J61: =IF(I61>F61,"Y"," " ) -> Y | K61: =IF((I61-F61)>1,(I61-F61),0) -> 85765338 | M61: =IF(L61="x",0,K61) -> 85765338 | N61: =F61+M61 -> 1.3778951e+08 | O61: =(N61-H61)/H61 -> 0.0326
A62: Sequoias | B62: ='5. Base Allocation'!G62 -> 49310200 | C62: =SUM('5. Base Allocation'!D62:E62) -> 1356776.3 | D62: ='6. Supplemental Allocation'!E62 -> 16687342 | E62: ='7. Success Allocation'!AF62 -> 6693105.7 | F62: =SUM(B62:E62) -> 74047424 | G62: 61392655 | H62: =(G62*H$1)+G62 -> 63056396 | I62: =(H62*J$1)+H62 -> 65112034 | J62: =IF(I62>F62,"Y"," " ) | K62: =IF((I62-F62)>1,(I62-F62),0) -> 0 | M62: =IF(L62="x",0,K62) -> 0 | N62: =F62+M62 -> 74047424 | O62: =(N62-H62)/H62 -> 0.17430472
A63: Shasta Tehama | B63: ='5. Base Allocation'!G63 -> 33589110 | C63: =SUM('5. Base Allocation'!D63:E63) -> 439806.74 | D63: ='6. Supplemental Allocation'!E63 -> 12727090 | E63: ='7. Success Allocation'!AF63 -> 5147903.7 | F63: =SUM(B63:E63) -> 51903910 | G63: 41789199 | H63: =(G63*H$1)+G63 -> 42921686 | I63: =(H63*J$1)+H63 -> 44320933 | J63: =IF(I63>F63,"Y"," " ) | K63: =IF((I63-F63)>1,(I63-F63),0) -> 0 | M63: =IF(L63="x",0,K63) -> 0 | N63: =F63+M63 -> 51903910 | O63: =(N63-H63)/H63 -> 0.20927006
A64: Sierra | B64: ='5. Base Allocation'!G64 -> 61853026 | C64: =SUM('5. Base Allocation'!D64:E64) -> 1363556.5 | D64: ='6. Supplemental Allocation'!E64 -> 17461687 | E64: ='7. Success Allocation'!AF64 -> 10138473 | F64: =SUM(B64:E64) -> 90816743 | G64: 86569715 | H64: =(G64*H$1)+G64 -> 88915754 | I64: =(H64*J$1)+H64 -> 91814408 | J64: =IF(I64>F64,"Y"," " ) -> Y | K64: =IF((I64-F64)>1,(I64-F64),0) -> 997664.74 | M64: =IF(L64="x",0,K64) -> 997664.74 | N64: =F64+M64 -> 91814408 | O64: =(N64-H64)/H64 -> 0.0326
A65: Siskiyous | B65: ='5. Base Allocation'!G65 -> 11273303 | C65: =SUM('5. Base Allocation'!D65:E65) -> 4745068.1 | D65: ='6. Supplemental Allocation'!E65 -> 2071082.6 | E65: ='7. Success Allocation'!AF65 -> 1559445.5 | F65: =SUM(B65:E65) -> 19648899 | G65: 18150995 | H65: =(G65*H$1)+G65 -> 18642887 | I65: =(H65*J$1)+H65 -> 19250645 | J65: =IF(I65>F65,"Y"," " ) | K65: =IF((I65-F65)>1,(I65-F65),0) -> 0 | M65: =IF(L65="x",0,K65) -> 0 | N65: =F65+M65 -> 19648899 | O65: =(N65-H65)/H65 -> 0.053962259
A66: Solano | B66: ='5. Base Allocation'!G66 -> 33892286 | C66: =SUM('5. Base Allocation'!D66:E66) -> 317044.24 | D66: ='6. Supplemental Allocation'!E66 -> 7502202.4 | E66: ='7. Success Allocation'!AF66 -> 4237100.1 | F66: =SUM(B66:E66) -> 45948632 | G66: 48526065 | H66: =(G66*H$1)+G66 -> 49841121 | I66: =(H66*J$1)+H66 -> 51465942 | J66: =IF(I66>F66,"Y"," " ) -> Y | K66: =IF((I66-F66)>1,(I66-F66),0) -> 5517309.6 | M66: =IF(L66="x",0,K66) -> 5517309.6 | N66: =F66+M66 -> 51465942 | O66: =(N66-H66)/H66 -> 0.0326
A67: Sonoma | B67: ='5. Base Allocation'!G67 -> 78657425 | C67: =SUM('5. Base Allocation'!D67:E67) -> 12467104 | D67: ='6. Supplemental Allocation'!E67 -> 15168807 | E67: ='7. Success Allocation'!AF67 -> 10116889 | F67: =SUM(B67:E67) -> 1.1641023e+08 | G67: 106270424 | H67: =(G67*H$1)+G67 -> 1.0915035e+08 | I67: =(H67*J$1)+H67 -> 1.1270865e+08 | J67: =IF(I67>F67,"Y"," " ) | K67: =IF((I67-F67)>1,(I67-F67),0) -> 0 | M67: =IF(L67="x",0,K67) -> 0 | N67: =F67+M67 -> 1.1641023e+08 | O67: =(N67-H67)/H67 -> 0.066512594
A68: South Orange County | B68: ='5. Base Allocation'!G68 -> 14069879 | C68: =SUM('5. Base Allocation'!D68:E68) -> 14474961 | D68: ='6. Supplemental Allocation'!E68 -> 19534716 | E68: ='7. Success Allocation'!AF68 -> 16108033 | F68: =SUM(B68:E68) -> 64187589 | G68: 152673419 | H68: =(G68*H$1)+G68 -> 1.5681087e+08 | I68: =(H68*J$1)+H68 -> 1.619229e+08 | J68: =IF(I68>F68,"Y"," " ) -> Y | K68: =IF((I68-F68)>1,(I68-F68),0) -> 97735314 | L68: x | M68: =IF(L68="x",0,K68) -> 0 | N68: =F68+M68 -> 64187589 | O68: =(N68-H68)/H68 -> -0.59066875
A69: Southwestern | B69: ='5. Base Allocation'!G69 -> 68140252 | C69: =SUM('5. Base Allocation'!D69:E69) -> 1025565.2 | D69: ='6. Supplemental Allocation'!E69 -> 21386919 | E69: ='7. Success Allocation'!AF69 -> 8070540.4 | F69: =SUM(B69:E69) -> 98623276 | G69: 92612800 | H69: =(G69*H$1)+G69 -> 95122607 | I69: =(H69*J$1)+H69 -> 98223604 | J69: =IF(I69>F69,"Y"," " ) | K69: =IF((I69-F69)>1,(I69-F69),0) -> 0 | M69: =IF(L69="x",0,K69) -> 0 | N69: =F69+M69 -> 98623276 | O69: =(N69-H69)/H69 -> 0.036801655
A70: State Center | B70: ='5. Base Allocation'!G70 -> 1.4512753e+08 | C70: =SUM('5. Base Allocation'!D70:E70) -> 2184313.8 | D70: ='6. Supplemental Allocation'!E70 -> 49996848 | E70: ='7. Success Allocation'!AF70 -> 21300229 | F70: =SUM(B70:E70) -> 2.1860892e+08 | G70: 181156108 | H70: =(G70*H$1)+G70 -> 1.8606544e+08 | I70: =(H70*J$1)+H70 -> 1.9213117e+08 | J70: =IF(I70>F70,"Y"," " ) | K70: =IF((I70-F70)>1,(I70-F70),0) -> 0 | M70: =IF(L70="x",0,K70) -> 0 | N70: =F70+M70 -> 2.1860892e+08 | O70: =(N70-H70)/H70 -> 0.17490345
A71: Ventura | B71: ='5. Base Allocation'!G71 -> 1.2381471e+08 | C71: =SUM('5. Base Allocation'!D71:E71) -> 460364.6 | D71: ='6. Supplemental Allocation'!E71 -> 31324030 | E71: ='7. Success Allocation'!AF71 -> 19138121 | F71: =SUM(B71:E71) -> 1.7473723e+08 | G71: 153823885 | H71: =(G71*H$1)+G71 -> 1.5799251e+08 | I71: =(H71*J$1)+H71 -> 1.6314307e+08 | J71: =IF(I71>F71,"Y"," " ) | K71: =IF((I71-F71)>1,(I71-F71),0) -> 0 | M71: =IF(L71="x",0,K71) -> 0 | N71: =F71+M71 -> 1.7473723e+08 | O71: =(N71-H71)/H71 -> 0.10598423
A72: Victor Valley | B72: ='5. Base Allocation'!G72 -> 42815469 | C72: =SUM('5. Base Allocation'!D72:E72) -> 174336.27 | D72: ='6. Supplemental Allocation'!E72 -> 17910146 | E72: ='7. Success Allocation'!AF72 -> 5496588.5 | F72: =SUM(B72:E72) -> 66396540 | G72: 54747776 | H72: =(G72*H$1)+G72 -> 56231441 | I72: =(H72*J$1)+H72 -> 58064586 | J72: =IF(I72>F72,"Y"," " ) | K72: =IF((I72-F72)>1,(I72-F72),0) -> 0 | M72: =IF(L72="x",0,K72) -> 0 | N72: =F72+M72 -> 66396540 | O72: =(N72-H72)/H72 -> 0.18077253
A73: West Hills | B73: ='5. Base Allocation'!G73 -> 32854644 | C73: =SUM('5. Base Allocation'!D73:E73) -> 997673.61 | D73: ='6. Supplemental Allocation'!E73 -> 9272691.1 | E73: ='7. Success Allocation'!AF73 -> 4194963 | F73: =SUM(B73:E73) -> 47319972 | G73: 37644442 | H73: =(G73*H$1)+G73 -> 38664606 | I73: =(H73*J$1)+H73 -> 39925073 | J73: =IF(I73>F73,"Y"," " ) | K73: =IF((I73-F73)>1,(I73-F73),0) -> 0 | M73: =IF(L73="x",0,K73) -> 0 | N73: =F73+M73 -> 47319972 | O73: =(N73-H73)/H73 -> 0.22385759
A74: West Kern | B74: ='5. Base Allocation'!G74 -> 5610148.1 | C74: =SUM('5. Base Allocation'!D74:E74) -> 0 | D74: ='6. Supplemental Allocation'!E74 -> 4990443.3 | E74: ='7. Success Allocation'!AF74 -> 3474229 | F74: =SUM(B74:E74) -> 14074820 | G74: 24502556 | H74: =(G74*H$1)+G74 -> 25166575 | I74: =(H74*J$1)+H74 -> 25987006 | J74: =IF(I74>F74,"Y"," " ) -> Y | K74: =IF((I74-F74)>1,(I74-F74),0) -> 11912185 | M74: =IF(L74="x",0,K74) -> 11912185 | N74: =F74+M74 -> 25987006 | O74: =(N74-H74)/H74 -> 0.0326
A75: West Valley-Mission2 | B75: ='5. Base Allocation'!G75 -> 50482848 | C75: =SUM('5. Base Allocation'!D75:E75) -> 4283051.3 | D75: ='6. Supplemental Allocation'!E75 -> 7618937.9 | E75: ='7. Success Allocation'!AF75 -> 6635163.3 | F75: =SUM(B75:E75) -> 69020000 | G75: 73379536 | H75: =(G75*H$1)+G75 -> 75368121 | I75: =(H75*J$1)+H75 -> 77825122 | J75: =IF(I75>F75,"Y"," " ) -> Y | K75: =IF((I75-F75)>1,(I75-F75),0) -> 8805121.9 | L75: x | M75: =IF(L75="x",0,K75) -> 0 | N75: =F75+M75 -> 69020000 | O75: =(N75-H75)/H75 -> -0.0842282
A76: Yosemite | B76: ='5. Base Allocation'!G76 -> 74460893 | C76: =SUM('5. Base Allocation'!D76:E76) -> 2671182.3 | D76: ='6. Supplemental Allocation'!E76 -> 27388097 | E76: ='7. Success Allocation'!AF76 -> 9837172.7 | F76: =SUM(B76:E76) -> 1.1435735e+08 | G76: 95628458 | H76: =(G76*H$1)+G76 -> 98219989 | I76: =(H76*J$1)+H76 -> 1.0142196e+08 | J76: =IF(I76>F76,"Y"," " ) | K76: =IF((I76-F76)>1,(I76-F76),0) -> 0 | M76: =IF(L76="x",0,K76) -> 0 | N76: =F76+M76 -> 1.1435735e+08 | O76: =(N76-H76)/H76 -> 0.16429808
A77: Yuba | B77: ='5. Base Allocation'!G77 -> 40533106 | C77: =SUM('5. Base Allocation'!D77:E77) -> 410382.91 | D77: ='6. Supplemental Allocation'!E77 -> 11384631 | E77: ='7. Success Allocation'!AF77 -> 5277094.8 | F77: =SUM(B77:E77) -> 57605214 | G77: 49580375 | H77: =(G77*H$1)+G77 -> 50924003 | I77: =(H77*J$1)+H77 -> 52584126 | J77: =IF(I77>F77,"Y"," " ) | K77: =IF((I77-F77)>1,(I77-F77),0) -> 0 | M77: =IF(L77="x",0,K77) -> 0 | N77: =F77+M77 -> 57605214 | O77: =(N77-H77)/H77 -> 0.13119965
A78: Statewide Total | B78: =SUM(B6:B77) -> 4.6403862e+09 | C78: =SUM(C6:C77) -> 3.4120934e+08 | D78: =SUM(D6:D77) -> 1.4312056e+09 | E78: =SUM(E6:E77) -> 6.7578455e+08 | F78: =SUM(F6:F77) -> 7.0885857e+09 | G78: 6766922198 | H78: =SUM(H6:H77) -> 6.9503058e+09 | I78: =SUM(I6:I77) -> 7.1768858e+09 | K78: =SUM(K6:K77) -> 4.5219912e+08 | L78: =COUNTA(L6:L77) -> 6 | M78: =SUM(M6:M77) -> 2.4845495e+08 | N78: =SUM(N6:N77) -> 7.3370407e+09 | O78: =(N78-H78)/H78 -> 0.055642858
M80: =COUNTIF(M6:M77,">0") -> 16

Sheet 4. Compare
B2: 2018-19 (2017-18 plus COLA) | C2: 2019-20 Student Centered Funding Formula (SCFF) | E2: Difference 2019-20 SCFF minus 2018-19 TCR P1 | F2: Annual % increase (change from 2018-19 TCR)
A3: District
A6: Allan Hancock | B6: ='3. HH-Total'!H6 -> 60006490 | C6: ='3. HH-Total'!N6 -> 63529885 | E6: =C6-B6 -> 3523394.4 | F6: =E6/B6 -> 0.058716888
A7: Antelope | B7: ='3. HH-Total'!H7 -> 64309876 | C7: ='3. HH-Total'!N7 -> 81665972 | E7: =C7-B7 -> 17356096 | F7: =E7/B7 -> 0.26988229
A8: Barstow | B8: ='3. HH-Total'!H8 -> 19187728 | C8: ='3. HH-Total'!N8 -> 22656689 | E8: =C8-B8 -> 3468961.6 | F8: =E8/B8 -> 0.18079064
A9: Butte | B9: ='3. HH-Total'!H9 -> 60465102 | C9: ='3. HH-Total'!N9 -> 68861562 | E9: =C9-B9 -> 8396460.6 | F9: =E9/B9 -> 0.13886457
A10: Cabrillo | B10: ='3. HH-Total'!H10 -> 62721594 | C10: ='3. HH-Total'!N10 -> 64766318 | E10: =C10-B10 -> 2044724 | F10: =E10/B10 -> 0.0326
A11: Cerritos | B11: ='3. HH-Total'!H11 -> 95980074 | C11: ='3. HH-Total'!N11 -> 1.1355296e+08 | E11: =C11-B11 -> 17572890 | F11: =E11/B11 -> 0.18308894
A12: Chabot-Las Positas | B12: ='3. HH-Total'!H12 -> 1.1059792e+08 | C12: ='3. HH-Total'!N12 -> 1.1420341e+08 | E12: =C12-B12 -> 3605492.1 | F12: =E12/B12 -> 0.0326
A13: Chaffey | B13: ='3. HH-Total'!H13 -> 96208271 | C13: ='3. HH-Total'!N13 -> 1.1355816e+08 | E13: =C13-B13 -> 17349887 | F13: =E13/B13 -> 0.18033675
A14: Citrus | B14: ='3. HH-Total'!H14 -> 69985763 | C14: ='3. HH-Total'!N14 -> 78096621 | E14: =C14-B14 -> 8110857.9 | F14: =E14/B14 -> 0.11589297
A15: Coast | B15: ='3. HH-Total'!H15 -> 1.8927836e+08 | C15: ='3. HH-Total'!N15 -> 2.0994226e+08 | E15: =C15-B15 -> 20663903 | F15: =E15/B15 -> 0.10917203
A16: Compton | B16: ='3. HH-Total'!H16 -> 36436547 | C16: ='3. HH-Total'!N16 -> 38647729 | E16: =C16-B16 -> 2211181.8 | F16: =E16/B16 -> 0.060685821
A17: Contra Costa | B17: ='3. HH-Total'!H17 -> 1.7486015e+08 | C17: ='3. HH-Total'!N17 -> 1.805606e+08 | E17: =C17-B17 -> 5700441 | F17: =E17/B17 -> 0.0326
... A77: Yuba | B77: ='3. HH-Total'!H77 -> 50924003 | C77: ='3. HH-Total'!N77 -> 57605214 | E77: =C77-B77 -> 6681211.2 | F77: =E77/B77 -> 0.13119965
A78: Statewide Total | B78: =SUM(B6:B77) -> 6.9503058e+09 | C78: ='3. HH-Total'!N78 -> 7.3370407e+09 | E78: =C78-B78 -> 3.8673488e+08 | F78: =E78/B78 -> 0.055642858

Sheet 5. Base Allocation
H2: RATES DOF
A3: District | B3: Basic Allocation DOF | C3: Base | F3: Special Admit Students and Students in Correctional Facilities Credit FTES | G3: Base Allocation Total (70%) | I3: Base FTES | L3: Special Admit Students and Students in Correctional Facilities Credit FTES
C4: Credit | D4: Noncredit | E4: CDCP | F4: Credit | I4: Credit | J4: Noncredit | K4: CDCP | L4: Credit
A6: Allan Hancock | B6: 6742470.1 | C6: ='5a. Base Counts'!B6*I6 -> 33873118 | D6: ='5a. Base Counts'!C6*J6 -> 1215345.8 | E6: ='5a. Base Counts'!D6*K6 -> 1308908.9 | F6: ='5a. Base Counts'!E6*L6 -> 2661757.6 | G6: =SUM(B6+C6+F6) -> 43277346 | I6: ='2. Weighting'!E$20 -> 4123.5 | J6: ='2. Weighting'!E$15 -> 3383.8562 | K6: ='2. Weighting'!E$16 -> 5638.1225 | L6: ='2. Weighting'!E$21 -> 5638.1225
A7: Antelope | B7: 6742470.1 | C7: ='5a. Base Counts'!B7*I7 -> 43594517 | D7: ='5a. Base Counts'!C7*J7 -> 28909.45 | E7: ='5a. Base Counts'!D7*K7 -> 291941.87 | F7: ='5a. Base Counts'!E7*L7 -> 2148444.2 | G7: =SUM(B7+C7+F7) -> 52485431 | I7: ='2. Weighting'!E$20 -> 4123.5 | J7: ='2. Weighting'!E$15 -> 3383.8562 | K7: ='2. Weighting'!E$16 -> 5638.1225 | L7: ='2. Weighting'!E$21 -> 5638.1225
A8: Barstow | B8: 5332192.5 | C8: ='5a. Base Counts'!B8*I8 -> 10284082 | D8: ='5a. Base Counts'!C8*J8 -> 114667.61 | E8: ='5a. Base Counts'!D8*K8 -> 0 | F8: ='5a. Base Counts'!E8*L8 -> 0 | G8: =SUM(B8+C8+F8) -> 15616275 | I8: ='2. Weighting'!E$20 -> 4123.5 | J8: ='2. Weighting'!E$15 -> 3383.8562 | K8: ='2. Weighting'!E$16 -> 5638.1225 | L8: ='2. Weighting'!E$21 -> 5638.1225
A9: Butte | B9: 6742470.1 | C9: ='5a. Base Counts'!B9*I9 -> 37212755 | D9: ='5a. Base Counts'!C9*J9 -> 3990514 | E9: ='5a. Base Counts'!D9*K9 -> 144260.76 | F9: ='5a. Base Counts'!E9*L9 -> 1072671.6 | G9: =SUM(B9+C9+F9) -> 45027897 | I9: ='2. Weighting'!E$20 -> 4123.5 | J9: ='2. Weighting'!E$15 -> 3383.8562 | K9: ='2. Weighting'!E$16 -> 5638.1225 | L9: ='2. Weighting'!E$21 -> 5638.1225
A10: Cabrillo | B10: 6742470.1 | C10: ='5a. Base Counts'!B10*I10 -> 38180462 | D10: ='5a. Base Counts'!C10*J10 -> 2356416 | E10: ='5a. Base Counts'!D10*K10 -> 491813.42 | F10: ='5a. Base Counts'!E10*L10 -> 1107120.5 | G10: =SUM(B10+C10+F10) -> 46030053 | I10: ='2. Weighting'!E$20 -> 4123.5 | J10: ='2. Weighting'!E$15 -> 3383.8562 | K10: ='2. Weighting'!E$16 -> 5638.1225 | L10: ='2. Weighting'!E$21 -> 5638.1225
A11: Cerritos | B11: 5393976.1 | C11: ='5a. Base Counts'!B11*I11 -> 65357305 | D11: ='5a. Base Counts'!C11*J11 -> 1079608 | E11: ='5a. Base Counts'!D11*K11 -> 1351871.4 | F11: ='5a. Base Counts'!E11*L11 -> 677270.07 | G11: =SUM(B11+C11+F11) -> 71428552 | I11: ='2. Weighting'!E$20 -> 4123.5 | J11: ='2. Weighting'!E$15 -> 3383.8562 | K11: ='2. Weighting'!E$16 -> 5638.1225 | L11: ='2. Weighting'!E$21 -> 5638.1225
A12: Chabot-Las Positas | B12: 8765209.6 | C12: ='5a. Base Counts'!B12*I12 -> 64366605 | D12: ='5a. Base Counts'!C12*J12 -> 630265.78 | E12: ='5a. Base Counts'!D12*K12 -> 0 | F12: ='5a. Base Counts'!E12*L12 -> 2516162.5 | G12: =SUM(B12+C12+F12) -> 75647977 | I12: ='2. Weighting'!E$20 -> 4123.5 | J12: ='2. Weighting'!E$15 -> 3383.8562 | K12: ='2. Weighting'!E$16 -> 5638.1225 | L12: ='2. Weighting'!E$21 -> 5638.1225
A13: Chaffey | B13: 8090964.1 | C13: ='5a. Base Counts'!B13*I13 -> 65131654 | D13: ='5a. Base Counts'!C13*J13 -> 1197061.7 | E13: ='5a. Base Counts'!D13*K13 -> 0 | F13: ='5a. Base Counts'!E13*L13 -> 2001195.2 | G13: =SUM(B13+C13+F13) -> 75223813 | I13: ='2. Weighting'!E$20 -> 4123.5 | J13: ='2. Weighting'!E$15 -> 3383.8562 | K13: ='2. Weighting'!E$16 -> 5638.1225 | L13: ='2. Weighting'!E$21 -> 5638.1225
A14: Citrus | B14: 5393976.1 | C14: ='5a. Base Counts'!B14*I14 -> 44713855 | D14: ='5a. Base Counts'!C14*J14 -> 1084435.7 | E14: ='5a. Base Counts'!D14*K14 -> 535095.41 | F14: ='5a. Base Counts'!E14*L14 -> 2088510.9 | G14: =SUM(B14+C14+F14) -> 52196342 | I14: ='2. Weighting'!E$20 -> 4123.5 | J14: ='2. Weighting'!E$15 -> 3383.8562 | K14: ='2. Weighting'!E$16 -> 5638.1225 | L14: ='2. Weighting'!E$21 -> 5638.1225
A15: Coast | B15: 12810690 | C15: ='5a. Base Counts'!B15*I15 -> 1.2651142e+08 | D15: ='5a. Base Counts'!C15*J15 -> 160327.11 | E15: ='5a. Base Counts'!D15*K15 -> 2942066.3 | F15: ='5a. Base Counts'!E15*L15 -> 1138336.9 | G15: =SUM(B15+C15+F15) -> 1.4046044e+08 | I15: ='2. Weighting'!E$20 -> 4123.5 | J15: ='2. Weighting'!E$15 -> 3383.8562 | K15: ='2. Weighting'!E$16 -> 5638.1225 | L15: ='2. Weighting'!E$21 -> 5638.1225
A16: Compton | B16: 4045480 | C16: ='5a. Base Counts'!B16*I16 -> 23964209 | D16: ='5a. Base Counts'!C16*J16 -> 59555.869 | E16: ='5a. Base Counts'!D16*K16 -> 0 | F16: ='5a. Base Counts'!E16*L16 -> 1437687.5 | G16: =SUM(B16+C16+F16) -> 29447376 | I16: ='2. Weighting'!E$20 -> 4123.5 | J16: ='2. Weighting'!E$15 -> 3383.8562 | K16: ='2. Weighting'!E$16 -> 5638.1225 | L16: ='2. Weighting'!E$21 -> 5638.1225
A17: Contra Costa | B17: 15507678 | C17: ='5a. Base Counts'!B17*I17 -> 1.0404195e+08 | D17: ='5a. Base Counts'!C17*J17 -> 524948.89 | E17: ='5a. Base Counts'!D17*K17 -> 0 | F17: ='5a. Base Counts'!E17*L17 -> 5438119.5 | G17: =SUM(B17+C17+F17) -> 1.2498775e+08 | I17: ='2. Weighting'!E$20 -> 4123.5 | J17: ='2. Weighting'!E$15 -> 3383.8562 | K17: ='2. Weighting'!E$16 -> 5638.1225 | L17: ='2. Weighting'!E$21 -> 5638.1225
... A21: Feather River | B21: 5332192.5 | C21: ='5a. Base Counts'!B21*I21 -> 5490875.1 | D21: ='5a. Base Counts'!C21*J21 -> 127289.39 | E21: ='5a. Base Counts'!D21*K21 -> 0 | F21: ='5a. Base Counts'!E21*L21 -> 1340295.9 | G21: =SUM(B21+C21+F21) -> 12163363 | I21: ='2. Weighting'!E$20 -> 4123.5 | J21: ='2. Weighting'!E$15 -> 3383.8562 | K21: ='2. Weighting'!E$16 -> 5638.1225 | L21: ='2. Weighting'!E$21 -> 5638.1225
A22: Foothill-De Anza3 | B22: 10787952 | C22: ='5a. Base Counts'!B22*I22 -> 90407220 | D22: ='5a. Base Counts'!C22*J22 -> 778275.65 | E22: ='5a. Base Counts'!D22*K22 -> 1782905.9 | F22: ='5a. Base Counts'!E22*L22 -> 4708358.5 | G22: =SUM(B22+C22+F22) -> 1.0590353e+08 | I22: ='2. Weighting'!E20+'2. Weighting'!I20 -> 4123.5 | J22: ='2. Weighting'!E$15 -> 3383.8562 | K22: ='2. Weighting'!E$16 -> 5638.1225 | L22: ='2. Weighting'!E$21 -> 5638.1225
A23: Gavilan | B23: 5332192.5 | C23: ='5a. Base Counts'!B23*I23 -> 18781730 | D23: ='5a. Base Counts'!C23*J23 -> 591781.18 | E23: ='5a. Base Counts'!D23*K23 -> 669940.51 | F23: ='5a. Base Counts'!E23*L23 -> 1357847.8 | G23: =SUM(B23+C23+F23) -> 25471770 | I23: ='2. Weighting'!E$20 -> 4123.5 | J23: ='2. Weighting'!E$15 -> 3383.8562 | K23: ='2. Weighting'!E$16 -> 5638.1225 | L23: ='2. Weighting'!E$21 -> 5638.1225
A24: Glendale | B24: 6742470.1 | C24: ='5a. Base Counts'!B24*I24 -> 43993118 | D24: ='5a. Base Counts'!C24*J24 -> 452375.14 | E24: ='5a. Base Counts'!D24*K24 -> 13488625 | F24: ='5a. Base Counts'!E24*L24 -> 1850488.2 | G24: =SUM(B24+C24+F24) -> 52586076 | I24: ='2. Weighting'!E$20 -> 4123.5 | J24: ='2. Weighting'!E$15 -> 3383.8562 | K24: ='2. Weighting'!E$16 -> 5638.1225 | L24: ='2. Weighting'!E$21 -> 5638.1225
A25: Grossmont-Cuyamaca | B25: 8765209.6 | C25: ='5a. Base Counts'!B25*I25 -> 70701554 | D25: ='5a. Base Counts'!C25*J25 -> 50994.713 | E25: ='5a. Base Counts'!D25*K25 -> 0 | F25: ='5a. Base Counts'!E25*L25 -> 1632029.7 | G25: =SUM(B25+C25+F25) -> 81098793 | I25: ='2. Weighting'!E$20 -> 4123.5 | J25: ='2. Weighting'!E$15 -> 3383.8562 | K25: ='2. Weighting'!E$16 -> 5638.1225 | L25: ='2. Weighting'!E$21 -> 5638.1225
A26: Hartnell | B26: 4382603.3 | C26: ='5a. Base Counts'!B26*I26 -> 29675905 | D26: ='5a. Base Counts'!C26*J26 -> 73158.971 | E26: ='5a. Base Counts'!D26*K26 -> 115017.7 | F26: ='5a. Base Counts'!E26*L26 -> 929031.18 | G26: =SUM(B26+C26+F26) -> 34987539 | I26: ='2. Weighting'!E$20 -> 4123.5 | J26: ='2. Weighting'!E$15 -> 3383.8562 | K26: ='2. Weighting'!E$16 -> 5638.1225 | L26: ='2. Weighting'!E$21 -> 5638.1225
A27: Imperial | B27: 4045480 | C27: ='5a. Base Counts'!B27*I27 -> 29769526 | D27: ='5a. Base Counts'!C27*J27 -> 109197.04 | E27: ='5a. Base Counts'!D27*K27 -> 59801.686 | F27: ='5a. Base Counts'!E27*L27 -> 1650389 | G27: =SUM(B27+C27+F27) -> 35465394 | I27: ='2. Weighting'!E$20 -> 4123.5 | J27: ='2. Weighting'!E$15 -> 3383.8562 | K27: ='2. Weighting'!E$16 -> 5638.1225 | L27: ='2. Weighting'!E$21 -> 5638.1225
A28: Kern | B28: 17024735 | C28: ='5a. Base Counts'!B28*I28 -> 90114800 | D28: ='5a. Base Counts'!C28*J28 -> 257759.61 | E28: ='5a. Base Counts'!D28*K28 -> 328627.37 | F28: ='5a. Base Counts'!E28*L28 -> 6597103.2 | G28: =SUM(B28+C28+F28) -> 1.1373664e+08 | I28: ='2. Weighting'!E$20 -> 4123.5 | J28: ='2. Weighting'!E$15 -> 3383.8562 | K28: ='2. Weighting'!E$16 -> 5638.1225 | L28: ='2. Weighting'!E$21 -> 5638.1225
A29: Lake Tahoe | B29: 5332192.5 | C29: ='5a. Base Counts'!B29*I29 -> 0 | D29: ='5a. Base Counts'!C29*J29 -> 189371.96 | E29: ='5a. Base Counts'!D29*K29 -> 11163.483 | F29: ='5a. Base Counts'!E29*L29 -> 749023.83 | G29: =SUM(B29+C29+F29) -> 6081216.4 | I29: ='2. Weighting'!E20*'2. Weighting'!I21 -> 0 | J29: ='2. Weighting'!E$15 -> 3383.8562 | K29: ='2. Weighting'!E$16 -> 5638.1225 | L29: ='2. Weighting'!E$21 -> 5638.1225
A30: Lassen | B30: 5332192.5 | C30: ='5a. Base Counts'!B30*I30 -> 0 | D30: ='5a. Base Counts'!C30*J30 -> 16366.585 | E30: ='5a. Base Counts'!D30*K30 -> 11332.626 | F30: ='5a. Base Counts'!E30*L30 -> 5072930.9 | G30: =SUM(B30+C30+F30) -> 10405123 | I30: ='2. Weighting'!E20*'2. Weighting'!I22 -> 0 | J30: ='2. Weighting'!E$15 -> 3383.8562 | K30: ='2. Weighting'!E$16 -> 5638.1225 | L30: ='2. Weighting'!E$21 -> 5638.1225
A31: Long Beach | B31: 8090964.1 | C31: ='5a. Base Counts'!B31*I31 -> 75537503 | D31: ='5a. Base Counts'!C31*J31 -> 107606.63 | E31: ='5a. Base Counts'!D31*K31 -> 2223825.9 | F31: ='5a. Base Counts'!E31*L31 -> 1136307.2 | G31: =SUM(B31+C31+F31) -> 84764774 | I31: ='2. Weighting'!E$20 -> 4123.5 | J31: ='2. Weighting'!E$15 -> 3383.8562 | K31: ='2. Weighting'!E$16 -> 5638.1225 | L31: ='2. Weighting'!E$21 -> 5638.1225
A32: Los Angeles | B32: 40454814 | C32: ='5a. Base Counts'!B32*I32 -> 3.486403e+08 | D32: ='5a. Base Counts'!C32*J32 -> 9533315.5 | E32: ='5a. Base Counts'!D32*K32 -> 26429846 | F32: ='5a. Base Counts'!E32*L32 -> 31674089 | G32: =SUM(B32+C32+F32) -> 4.207692e+08 | I32: ='2. Weighting'!E$20 -> 4123.5 | J32: ='2. Weighting'!E$15 -> 3383.8562 | K32: ='2. Weighting'!E$16 -> 5638.1225 | L32: ='2. Weighting'!E$21 -> 5638.1225
A33: Los Rios | B33: 26295631 | C33: ='5a. Base Counts'!B33*I33 -> 2.0450097e+08 | D33: ='5a. Base Counts'!C33*J33 -> 943768.78 | E33: ='5a. Base Counts'!D33*K33 -> 0 | F33: ='5a. Base Counts'!E33*L33 -> 4372439.2 | G33: =SUM(B33+C33+F33) -> 2.3516904e+08 | I33: ='2. Weighting'!E$20 -> 4123.5 | J33: ='2. Weighting'!E$15 -> 3383.8562 | K33: ='2. Weighting'!E$16 -> 5638.1225 | L33: ='2. Weighting'!E$21 -> 5638.1225
A34: Marin | B34: 4045480 | C34: ='5a. Base Counts'!B34*I34 -> 0 | D34: ='5a. Base Counts'!C34*J34 -> 979615.09 | E34: ='5a. Base Counts'!D34*K34 -> 0 | F34: ='5a. Base Counts'!E34*L34 -> 809991.47 | G34: =SUM(B34+C34+F34) -> 4855471.5 | I34: ='2. Weighting'!E20*'2. Weighting'!I23 -> 0 | J34: ='2. Weighting'!E$15 -> 3383.8562 | K34: ='2. Weighting'!E$16 -> 5638.1225 | L34: ='2. Weighting'!E$21 -> 5638.1225
A35: Mendocino | B35: 6343562.3 | C35: ='5a. Base Counts'!B35*I35 -> 10015088 | D35: ='5a. Base Counts'!C35*J35 -> 91792.74 | E35: ='5a. Base Counts'!D35*K35 -> 360576.73 | F35: ='5a. Base Counts'!E35*L35 -> 1579670.4 | G35: =SUM(B35+C35+F35) -> 17938321 | I35: ='2. Weighting'!E$20 -> 4123.5 | J35: ='2. Weighting'!E$15 -> 3383.8562 | K35: ='2. Weighting'!E$16 -> 5638.1225 | L35: ='2. Weighting'!E$21 -> 5638.1225
A36: Merced | B36: 5393974 | C36: ='5a. Base Counts'!B36*I36 -> 35380606 | D36: ='5a. Base Counts'!C36*J36 -> 1597913.3 | E36: ='5a. Base Counts'!D36*K36 -> 3887936.5 | F36: ='5a. Base Counts'!E36*L36 -> 1568551.4 | G36: =SUM(B36+C36+F36) -> 42343131 | I36: ='2. Weighting'!E$20 -> 4123.5 | J36: ='2. Weighting'!E$15 -> 3383.8562 | K36: ='2. Weighting'!E$16 -> 5638.1225 | L36: ='2. Weighting'!E$21 -> 5638.1225
A37: MiraCosta | B37: 6742470.1 | C37: ='5a. Base Counts'!B37*I37 -> 0 | D37: ='5a. Base Counts'!C37*J37 -> 2545866.8 | E37: ='5a. Base Counts'!D37*K37 -> 0 | F37: ='5a. Base Counts'!E37*L37 -> 584729.68 | G37: =SUM(B37+C37+F37) -> 7327199.8 | I37: ='2. Weighting'!E20*'2. Weighting'!I24 -> 0 | J37: ='2. Weighting'!E$15 -> 3383.8562 | K37: ='2. Weighting'!E$16 -> 5638.1225 | L37: ='2. Weighting'!E$21 -> 5638.1225
A38: Monterey | B38: 4382603.3 | C38: ='5a. Base Counts'!B38*I38 -> 23845394 | D38: ='5a. Base Counts'!C38*J38 -> 996241.11 | E38: ='5a. Base Counts'!D38*K38 -> 29562.556 | F38: ='5a. Base Counts'!E38*L38 -> 919371.04 | G38: =SUM(B38+C38+F38) -> 29147368 | I38: ='2. Weighting'!E$20 -> 4123.5 | J38: ='2. Weighting'!E$15 -> 3383.8562 | K38: ='2. Weighting'!E$16 -> 5638.1225 | L38: ='2. Weighting'!E$21 -> 5638.1225
A39: Mt. San Antonio | B39: 6742470.1 | C39: ='5a. Base Counts'!B39*I39 -> 1.0295976e+08 | D39: ='5a. Base Counts'!C39*J39 -> 5555344.4 | E39: ='5a. Base Counts'!D39*K39 -> 38057571 | F39: ='5a. Base Counts'!E39*L39 -> 288211.21 | G39: =SUM(B39+C39+F39) -> 1.0999044e+08 | I39: ='2. Weighting'!E$20 -> 4123.5 | J39: ='2. Weighting'!E$15 -> 3383.8562 | K39: ='2. Weighting'!E$16 -> 5638.1225 | L39: ='2. Weighting'!E$21 -> 5638.1225
A40: Mt. San Jacinto | B40: 6742470.1 | C40: ='5a. Base Counts'!B40*I40 -> 45362963 | D40: ='5a. Base Counts'!C40*J40 -> 769827.29 | E40: ='5a. Base Counts'!D40*K40 -> 1485551.3 | F40: ='5a. Base Counts'!E40*L40 -> 988080.96 | G40: =SUM(B40+C40+F40) -> 53093514 | I40: ='2. Weighting'!E$20 -> 4123.5 | J40: ='2. Weighting'!E$15 -> 3383.8562 | K40: ='2. Weighting'!E$16 -> 5638.1225 | L40: ='2. Weighting'!E$21 -> 5638.1225
A41: Napa | B41: 4719726.5 | C41: ='5a. Base Counts'!B41*I41 -> 18349442 | D41: ='5a. Base Counts'!C41*J41 -> 1377838.6 | E41: ='5a. Base Counts'!D41*K41 -> 20842.259 | F41: ='5a. Base Counts'!E41*L41 -> 755865.49 | G41: =SUM(B41+C41+F41) -> 23825034 | I41: ='2. Weighting'!E$20 -> 4123.5 | J41: ='2. Weighting'!E$15 -> 3383.8562 | K41: ='2. Weighting'!E$16 -> 5638.1225 | L41: ='2. Weighting'!E$21 -> 5638.1225
A42: North Orange | B42: 10787952 | C42: ='5a. Base Counts'!B42*I42 -> 1.1111713e+08 | D42: ='5a. Base Counts'!C42*J42 -> 16911769 | E42: ='5a. Base Counts'!D42*K42 -> 188369.67 | F42: ='5a. Base Counts'!E42*L42 -> 3769066.1 | G42: =SUM(B42+C42+F42) -> 1.2567415e+08 | I42: ='2. Weighting'!E$20 -> 4123.5 | J42: ='2. Weighting'!E$15 -> 3383.8562 | K42: ='2. Weighting'!E$16 -> 5638.1225 | L42: ='2. Weighting'!E$21 -> 5638.1225
A43: Ohlone | B43: 5393974 | C43: ='5a. Base Counts'!B43*I43 -> 29189826 | D43: ='5a. Base Counts'!C43*J43 -> 169.19281 | E43: ='5a. Base Counts'!D43*K43 -> 13907.369 | F43: ='5a. Base Counts'!E43*L43 -> 396792.27 | G43: =SUM(B43+C43+F43) -> 34980592 | I43: ='2. Weighting'!E$20 -> 4123.5 | J43: ='2. Weighting'!E$15 -> 3383.8562 | K43: ='2. Weighting'!E$16 -> 5638.1225 | L43: ='2. Weighting'!E$21 -> 5638.1225
A44: Palo Verde | B44: 5500755.2 | C44: ='5a. Base Counts'!B44*I44 -> 5546298.1 | D44: ='5a. Base Counts'!C44*J44 -> 93541.065 | E44: ='5a. Base Counts'!D44*K44 -> 33941.497 | F44: ='5a. Base Counts'!E44*L44 -> 3595107 | G44: =SUM(B44+C44+F44) -> 14642160 | I44: ='2. Weighting'!E$20 -> 4123.5 | J44: ='2. Weighting'!E$15 -> 3383.8562 | K44: ='2. Weighting'!E$16 -> 5638.1225 | L44: ='2. Weighting'!E$21 -> 5638.1225
A45: Palomar | B45: 6742470.1 | C45: ='5a. Base Counts'!B45*I45 -> 69926006 | D45: ='5a. Base Counts'!C45*J45 -> 922247.45 | E45: ='5a. Base Counts'!D45*K45 -> 2226513.4 | F45: ='5a. Base Counts'!E45*L45 -> 2937950.4 | G45: =SUM(B45+C45+F45) -> 79606427 | I45: ='2. Weighting'!E$20 -> 4123.5 | J45: ='2. Weighting'!E$15 -> 3383.8562 | K45: ='2. Weighting'!E$16 -> 5638.1225 | L45: ='2. Weighting'!E$21 -> 5638.1225
A46: Pasadena | B46: 8090964.1 | C46: ='5a. Base Counts'!B46*I46 -> 93050076 | D46: ='5a. Base Counts'!C46*J46 -> 470853.47 | E46: ='5a. Base Counts'!D46*K46 -> 4940198.1 | F46: ='5a. Base Counts'!E46*L46 -> 1619513.1 | G46: =SUM(B46+C46+F46) -> 1.0276055e+08 | I46: ='2. Weighting'!E$20 -> 4123.5 | J46: ='2. Weighting'!E$15 -> 3383.8562 | K46: ='2. Weighting'!E$16 -> 5638.1225 | L46: ='2. Weighting'!E$21 -> 5638.1225
A47: Peralta | B47: 16181921 | C47: ='5a. Base Counts'!B47*I47 -> 68082664 | D47: ='5a. Base Counts'!C47*J47 -> 367340.15 | E47: ='5a. Base Counts'!D47*K47 -> 0 | F47: ='5a. Base Counts'!E47*L47 -> 6227043.2 | G47: =SUM(B47+C47+F47) -> 90491628 | I47: ='2. Weighting'!E$20 -> 4123.5 | J47: ='2. Weighting'!E$15 -> 3383.8562 | K47: ='2. Weighting'!E$16 -> 5638.1225 | L47: ='2. Weighting'!E$21 -> 5638.1225
A48: Rancho Santiago | B48: 12136444 | C48: ='5a. Base Counts'!B48*I48 -> 79690260 | D48: ='5a. Base Counts'!C48*J48 -> 3964142.4 | E48: ='5a. Base Counts'!D48*K48 -> 27745840 | F48: ='5a. Base Counts'!E48*L48 -> 16491283 | G48: =SUM(B48+C48+F48) -> 1.0831799e+08 | I48: ='2. Weighting'!E$20 -> 4123.5 | J48: ='2. Weighting'!E$15 -> 3383.8562 | K48: ='2. Weighting'!E$16 -> 5638.1225 | L48: ='2. Weighting'!E$21 -> 5638.1225
A49: Redwoods | B49: 6006439 | C49: ='5a. Base Counts'!B49*I49 -> 12937124 | D49: ='5a. Base Counts'!C49*J49 -> 368964.4 | E49: ='5a. Base Counts'!D49*K49 -> 294216.02 | F49: ='5a. Base Counts'!E49*L49 -> 2182686.4 | G49: =SUM(B49+C49+F49) -> 21126249 | I49: ='2. Weighting'!E$20 -> 4123.5 | J49: ='2. Weighting'!E$15 -> 3383.8562 | K49: ='2. Weighting'!E$16 -> 5638.1225 | L49: ='2. Weighting'!E$21 -> 5638.1225
... A53: San Diego | B53: 20901658 | C53: ='5a. Base Counts'!B53*I53 -> 1.3119367e+08 | D53: ='5a. Base Counts'!C53*J53 -> 6923020.1 | E53: ='5a. Base Counts'!D53*K53 -> 33691841 | F53: ='5a. Base Counts'!E53*L53 -> 6515057.3 | G53: =SUM(B53+C53+F53) -> 1.5861039e+08 | I53: ='2. Weighting'!E$20 -> 4123.5 | J53: ='2. Weighting'!E$15 -> 3383.8562 | K53: ='2. Weighting'!E$16 -> 5638.1225 | L53: ='2. Weighting'!E$21 -> 5638.1225
A54: San Francisco | B54: 13653502 | C54: ='5a. Base Counts'!B54*I54 -> 0 | D54: ='5a. Base Counts'!C54*J54 -> 5691016.2 | E54: ='5a. Base Counts'!D54*K54 -> 21862233 | F54: ='5a. Base Counts'!E54*L54 -> 1764224.9 | G54: =SUM(B54+C54+F54) -> 15417727 | I54: ='2. Weighting'!E20*'2. Weighting'!I25 -> 0 | J54: ='2. Weighting'!E$15 -> 3383.8562 | K54: ='2. Weighting'!E$16 -> 5638.1225 | L54: ='2. Weighting'!E$21 -> 5638.1225
A55: San Joaquin Delta | B55: 6742470.1 | C55: ='5a. Base Counts'!B55*I55 -> 60053206 | D55: ='5a. Base Counts'!C55*J55 -> 570687.35 | E55: ='5a. Base Counts'!D55*K55 -> 0 | F55: ='5a. Base Counts'!E55*L55 -> 3349815.3 | G55: =SUM(B55+C55+F55) -> 70145492 | I55: ='2. Weighting'!E$20 -> 4123.5 | J55: ='2. Weighting'!E$15 -> 3383.8562 | K55: ='2. Weighting'!E$16 -> 5638.1225 | L55: ='2. Weighting'!E$21 -> 5638.1225
A56: San Jose | B56: 8090961 | C56: ='5a. Base Counts'!B56*I56 -> 0 | D56: ='5a. Base Counts'!C56*J56 -> 849652.43 | E56: ='5a. Base Counts'!D56*K56 -> 0 | F56: ='5a. Base Counts'!E56*L56 -> 1520902.3 | G56: =SUM(B56+C56+F56) -> 9611863.4 | I56: ='2. Weighting'!E20*'2. Weighting'!I26 -> 0 | J56: ='2. Weighting'!E$15 -> 3383.8562 | K56: ='2. Weighting'!E$16 -> 5638.1225 | L56: ='2. Weighting'!E$21 -> 5638.1225
A57: San Luis Obispo | B57: 5393974 | C57: ='5a. Base Counts'!B57*I57 -> 25399637 | D57: ='5a. Base Counts'!C57*J57 -> 1538222.1 | E57: ='5a. Base Counts'!D57*K57 -> 1286168.5 | F57: ='5a. Base Counts'!E57*L57 -> 5682532.1 | G57: =SUM(B57+C57+F57) -> 36476144 | I57: ='2. Weighting'!E$20 -> 4123.5 | J57: ='2. Weighting'!E$15 -> 3383.8562 | K57: ='2. Weighting'!E$16 -> 5638.1225 | L57: ='2. Weighting'!E$21 -> 5638.1225
A58: San Mateo | B58: 12136441 | C58: ='5a. Base Counts'!B58*I58 -> 59060089 | D58: ='5a. Base Counts'!C58*J58 -> 121863.94 | E58: ='5a. Base Counts'!D58*K58 -> 0 | F58: ='5a. Base Counts'!E58*L58 -> 5370274.1 | G58: =SUM(B58+C58+F58) -> 76566804 | I58: ='2. Weighting'!E$20 -> 4123.5 | J58: ='2. Weighting'!E$15 -> 3383.8562 | K58: ='2. Weighting'!E$16 -> 5638.1225 | L58: ='2. Weighting'!E$21 -> 5638.1225
A59: Santa Barbara | B59: 7416716.6 | C59: ='5a. Base Counts'!B59*I59 -> 45530051 | D59: ='5a. Base Counts'!C59*J59 -> 3603524.9 | E59: ='5a. Base Counts'!D59*K59 -> 1892830.5 | F59: ='5a. Base Counts'!E59*L59 -> 690143.78 | G59: =SUM(B59+C59+F59) -> 53636912 | I59: ='2. Weighting'!E$20 -> 4123.5 | J59: ='2. Weighting'!E$15 -> 3383.8562 | K59: ='2. Weighting'!E$16 -> 5638.1225 | L59: ='2. Weighting'!E$21 -> 5638.1225
A60: Santa Clarita | B60: 6742470.1 | C60: ='5a. Base Counts'!B60*I60 -> 61451246 | D60: ='5a. Base Counts'!C60*J60 -> 822773.36 | E60: ='5a. Base Counts'!D60*K60 -> 1022642.7 | F60: ='5a. Base Counts'!E60*L60 -> 4937228.7 | G60: =SUM(B60+C60+F60) -> 73130945 | I60: ='2. Weighting'!E$20 -> 4123.5 | J60: ='2. Weighting'!E$15 -> 3383.8562 | K60: ='2. Weighting'!E$16 -> 5638.1225 | L60: ='2. Weighting'!E$21 -> 5638.1225
A61: Santa Monica | B61: 8090964.1 | C61: ='5a. Base Counts'!B61*I61 -> 0 | D61: ='5a. Base Counts'!C61*J61 -> 2176485 | E61: ='5a. Base Counts'!D61*K61 -> 516564.78 | F61: ='5a. Base Counts'!E61*L61 -> 1501413.2 | G61: =SUM(B61+C61+F61) -> 9592377.4 | I61: ='2. Weighting'!E20*'2. Weighting'!I27 -> 0 | J61: ='2. Weighting'!E$15 -> 3383.8562 | K61: ='2. Weighting'!E$16 -> 5638.1225 | L61: ='2. Weighting'!E$21 -> 5638.1225
A62: Sequoias | B62: 8090964.1 | C62: ='5a. Base Counts'!B62*I62 -> 38309645 | D62: ='5a. Base Counts'!C62*J62 -> 969756.79 | E62: ='5a. Base Counts'!D62*K62 -> 387019.52 | F62: ='5a. Base Counts'!E62*L62 -> 2909590.7 | G62: =SUM(B62+C62+F62) -> 49310200 | I62: ='2. Weighting'!E$20 -> 4123.5 | J62: ='2. Weighting'!E$15 -> 3383.8562 | K62: ='2. Weighting'!E$16 -> 5638.1225 | L62: ='2. Weighting'!E$21 -> 5638.1225
A63: Shasta Tehama | B63: 4045480 | C63: ='5a. Base Counts'!B63*I63 -> 25176777 | D63: ='5a. Base Counts'!C63*J63 -> 386075.43 | E63: ='5a. Base Counts'!D63*K63 -> 53731.307 | F63: ='5a. Base Counts'!E63*L63 -> 4366853.3 | G63: =SUM(B63+C63+F63) -> 33589110 | I63: ='2. Weighting'!E$20 -> 4123.5 | J63: ='2. Weighting'!E$15 -> 3383.8562 | K63: ='2. Weighting'!E$16 -> 5638.1225 | L63: ='2. Weighting'!E$21 -> 5638.1225
A64: Sierra | B64: 6911032.8 | C64: ='5a. Base Counts'!B64*I64 -> 52129754 | D64: ='5a. Base Counts'!C64*J64 -> 1291200.6 | E64: ='5a. Base Counts'!D64*K64 -> 72355.905 | F64: ='5a. Base Counts'!E64*L64 -> 2812239.1 | G64: =SUM(B64+C64+F64) -> 61853026 | I64: ='2. Weighting'!E$20 -> 4123.5 | J64: ='2. Weighting'!E$15 -> 3383.8562 | K64: ='2. Weighting'!E$16 -> 5638.1225 | L64: ='2. Weighting'!E$21 -> 5638.1225
A65: Siskiyous | B65: 5332192.5 | C65: ='5a. Base Counts'!B65*I65 -> 5683598.7 | D65: ='5a. Base Counts'!C65*J65 -> 419744.8 | E65: ='5a. Base Counts'!D65*K65 -> 4325323.2 | F65: ='5a. Base Counts'!E65*L65 -> 257511.85 | G65: =SUM(B65+C65+F65) -> 11273303 | I65: ='2. Weighting'!E$20 -> 4123.5 | J65: ='2. Weighting'!E$15 -> 3383.8562 | K65: ='2. Weighting'!E$16 -> 5638.1225 | L65: ='2. Weighting'!E$21 -> 5638.1225
A66: Solano | B66: 6742469.1 | C66: ='5a. Base Counts'!B66*I66 -> 24985116 | D66: ='5a. Base Counts'!C66*J66 -> 317044.24 | E66: ='5a. Base Counts'!D66*K66 -> 0 | F66: ='5a. Base Counts'!E66*L66 -> 2164700.7 | G66: =SUM(B66+C66+F66) -> 33892286 | I66: ='2. Weighting'!E$20 -> 4123.5 | J66: ='2. Weighting'!E$15 -> 3383.8562 | K66: ='2. Weighting'!E$16 -> 5638.1225 | L66: ='2. Weighting'!E$21 -> 5638.1225
A67: Sonoma | B67: 9776581.4 | C67: ='5a. Base Counts'!B67*I67 -> 65792637 | D67: ='5a. Base Counts'!C67*J67 -> 8572909.5 | E67: ='5a. Base Counts'!D67*K67 -> 3894194.8 | F67: ='5a. Base Counts'!E67*L67 -> 3088206.4 | G67: =SUM(B67+C67+F67) -> 78657425 | I67: ='2. Weighting'!E$20 -> 4123.5 | J67: ='2. Weighting'!E$15 -> 3383.8562 | K67: ='2. Weighting'!E$16 -> 5638.1225 | L67: ='2. Weighting'!E$21 -> 5638.1225
A68: South Orange County | B68: 9439458.2 | C68: ='5a. Base Counts'!B68*I68 -> 0 | D68: ='5a. Base Counts'!C68*J68 -> 7036323.1 | E68: ='5a. Base Counts'!D68*K68 -> 7438638.1 | F68: ='5a. Base Counts'!E68*L68 -> 4630420.8 | G68: =SUM(B68+C68+F68) -> 14069879 | I68: ='2. Weighting'!E20*'2. Weighting'!I28 -> 0 | J68: ='2. Weighting'!E$15 -> 3383.8562 | K68: ='2. Weighting'!E$16 -> 5638.1225 | L68: ='2. Weighting'!E$21 -> 5638.1225
A69: Southwestern | B69: 9439458.2 | C69: ='5a. Base Counts'!B69*I69 -> 56846058 | D69: ='5a. Base Counts'!C69*J69 -> 964523.1 | E69: ='5a. Base Counts'!D69*K69 -> 61042.073 | F69: ='5a. Base Counts'!E69*L69 -> 1854735.6 | G69: =SUM(B69+C69+F69) -> 68140252 | I69: ='2. Weighting'!E$20 -> 4123.5 | J69: ='2. Weighting'!E$15 -> 3383.8562 | K69: ='2. Weighting'!E$16 -> 5638.1225 | L69: ='2. Weighting'!E$21 -> 5638.1225
A70: State Center | B70: 15507678 | C70: ='5a. Base Counts'!B70*I70 -> 1.1861858e+08 | D70: ='5a. Base Counts'!C70*J70 -> 1138554.8 | E70: ='5a. Base Counts'!D70*K70 -> 1045759 | F70: ='5a. Base Counts'!E70*L70 -> 11001274 | G70: =SUM(B70+C70+F70) -> 1.4512753e+08 | I70: ='2. Weighting'!E$20 -> 4123.5 | J70: ='2. Weighting'!E$15 -> 3383.8562 | K70: ='2. Weighting'!E$16 -> 5638.1225 | L70: ='2. Weighting'!E$21 -> 5638.1225
A71: Ventura | B71: 13484938 | C71: ='5a. Base Counts'!B71*I71 -> 98068341 | D71: ='5a. Base Counts'!C71*J71 -> 429242.16 | E71: ='5a. Base Counts'!D71*K71 -> 31122.436 | F71: ='5a. Base Counts'!E71*L71 -> 12261432 | G71: =SUM(B71+C71+F71) -> 1.2381471e+08 | I71: ='2. Weighting'!E$20 -> 4123.5 | J71: ='2. Weighting'!E$15 -> 3383.8562 | K71: ='2. Weighting'!E$16 -> 5638.1225 | L71: ='2. Weighting'!E$21 -> 5638.1225
A72: Victor Valley | B72: 4045480 | C72: ='5a. Base Counts'!B72*I72 -> 38196555 | D72: ='5a. Base Counts'!C72*J72 -> 174336.27 | E72: ='5a. Base Counts'!D72*K72 -> 0 | F72: ='5a. Base Counts'!E72*L72 -> 573434.64 | G72: =SUM(B72+C72+F72) -> 42815469 | I72: ='2. Weighting'!E$20 -> 4123.5 | J72: ='2. Weighting'!E$15 -> 3383.8562 | K72: ='2. Weighting'!E$16 -> 5638.1225 | L72: ='2. Weighting'!E$21 -> 5638.1225
A73: West Hills | B73: 8428084.3 | C73: ='5a. Base Counts'!B73*I73 -> 21743322 | D73: ='5a. Base Counts'!C73*J73 -> 997673.61 | E73: ='5a. Base Counts'!D73*K73 -> 0 | F73: ='5a. Base Counts'!E73*L73 -> 2683237.7 | G73: =SUM(B73+C73+F73) -> 32854644 | I73: ='2. Weighting'!E$20 -> 4123.5 | J73: ='2. Weighting'!E$15 -> 3383.8562 | K73: ='2. Weighting'!E$16 -> 5638.1225 | L73: ='2. Weighting'!E$21 -> 5638.1225
A74: West Kern | B74: 5332192.5 | C74: ='5a. Base Counts'!B74*I74 -> 0 | D74: ='5a. Base Counts'!C74*J74 -> 0 | E74: ='5a. Base Counts'!D74*K74 -> 0 | F74: ='5a. Base Counts'!E74*L74 -> 277955.52 | G74: =SUM(B74+C74+F74) -> 5610148.1 | I74: ='2. Weighting'!E20*'2. Weighting'!I29 -> 0 | J74: ='2. Weighting'!E$15 -> 3383.8562 | K74: ='2. Weighting'!E$16 -> 5638.1225 | L74: ='2. Weighting'!E$21 -> 5638.1225
A75: West Valley-Mission2 | B75: 8090961 | C75: ='5a. Base Counts'!B75*I75 -> 40022315 | D75: ='5a. Base Counts'!C75*J75 -> 4247326.1 | E75: ='5a. Base Counts'!D75*K75 -> 35725.222 | F75: ='5a. Base Counts'!E75*L75 -> 2369571.3 | G75: =SUM(B75+C75+F75) -> 50482848 | I75: ='2. Weighting'!E$20 -> 4123.5 | J75: ='2. Weighting'!E$15 -> 3383.8562 | K75: ='2. Weighting'!E$16 -> 5638.1225 | L75: ='2. Weighting'!E$21 -> 5638.1225
A76: Yosemite | B76: 8765209.6 | C76: ='5a. Base Counts'!B76*I76 -> 63043078 | D76: ='5a. Base Counts'!C76*J76 -> 1053924.5 | E76: ='5a. Base Counts'!D76*K76 -> 1617257.8 | F76: ='5a. Base Counts'!E76*L76 -> 2652605.1 | G76: =SUM(B76+C76+F76) -> 74460893 | I76: ='2. Weighting'!E$20 -> 4123.5 | J76: ='2. Weighting'!E$15 -> 3383.8562 | K76: ='2. Weighting'!E$16 -> 5638.1225 | L76: ='2. Weighting'!E$21 -> 5638.1225
A77: Yuba | B77: 10113702 | C77: ='5a. Base Counts'!B77*I77 -> 29817366 | D77: ='5a. Base Counts'!C77*J77 -> 397828.7 | E77: ='5a. Base Counts'!D77*K77 -> 12554.219 | F77: ='5a. Base Counts'!E77*L77 -> 602037.95 | G77: =SUM(B77+C77+F77) -> 40533106 | I77: ='2. Weighting'!E$20 -> 4123.5 | J77: ='2. Weighting'!E$15 -> 3383.8562 | K77: ='2. Weighting'!E$16 -> 5638.1225 | L77: ='2. Weighting'!E$21 -> 5638.1225
A78: Statewide Total | B78: =SUM(B6:B77) -> 6.2872988e+08 | C78: =SUM(C6:C77) -> 3.7811145e+09 | D78: =SUM(D6:D77) -> 1.1885435e+08 | E78: =SUM(E6:E77) -> 2.2235499e+08 | F78: =SUM(F6:F77) -> 2.3054184e+08 | G78: =SUM(G6:G77) -> 4.6403862e+09
G79: ='2. Weighting'!C23 -> 5.0092197e+09

Sheet 5a. Base Counts
B2: 2019-20 Using Projections
B3: Credit FTES (Three year average 2017-18, 2018-19, projected 2019-20) | C3: Noncredit (Single year 2019-20) | D3: CDCP (Single year 2019-20) | E3: Special Admit Students and Students in Correctional Facilities Credit FTES (Single Year 2019-20)
A6: Allan Hancock | B6: =AVERAGE('5b. Base Hist'!Z11,'5b. Base Hist'!T11,'5b. Base Hist'!N11) -> 8214.6522 | C6: ='5b. Base Hist'!V11 -> 359.16 | D6: ='5b. Base Hist'!W11 -> 232.15333 | E6: ='5b. Base Hist'!X11+'5b. Base Hist'!Y11 -> 472.1
A7: Antelope | B7: =AVERAGE('5b. Base Hist'!Z12,'5b. Base Hist'!T12,'5b. Base Hist'!N12) -> 10572.212 | C7: ='5b. Base Hist'!V12 -> 8.5433447 | D7: ='5b. Base Hist'!W12 -> 51.779981 | E7: ='5b. Base Hist'!X12+'5b. Base Hist'!Y12 -> 381.05667
A8: Barstow | B8: =AVERAGE('5b. Base Hist'!Z13,'5b. Base Hist'!T13,'5b. Base Hist'!N13) -> 2494.0178 | C8: ='5b. Base Hist'!V13 -> 33.886667 | D8: ='5b. Base Hist'!W13 -> 0 | E8: ='5b. Base Hist'!X13+'5b. Base Hist'!Y13 -> 0
A9: Butte | B9: =AVERAGE('5b. Base Hist'!Z14,'5b. Base Hist'!T14,'5b. Base Hist'!N14) -> 9024.5556 | C9: ='5b. Base Hist'!V14 -> 1179.28 | D9: ='5b. Base Hist'!W14 -> 25.586667 | E9: ='5b. Base Hist'!X14+'5b. Base Hist'!Y14 -> 190.25333
A10: Cabrillo | B10: =AVERAGE('5b. Base Hist'!Z15,'5b. Base Hist'!T15,'5b. Base Hist'!N15) -> 9259.2367 | C10: ='5b. Base Hist'!V15 -> 696.37 | D10: ='5b. Base Hist'!W15 -> 87.23 | E10: ='5b. Base Hist'!X15+'5b. Base Hist'!Y15 -> 196.36333
A11: Cerritos | B11: =AVERAGE('5b. Base Hist'!Z16,'5b. Base Hist'!T16,'5b. Base Hist'!N16) -> 15849.959 | C11: ='5b. Base Hist'!V16 -> 319.04667 | D11: ='5b. Base Hist'!W16 -> 239.77333 | E11: ='5b. Base Hist'!X16+'5b. Base Hist'!Y16 -> 120.12333
A12: Chabot-Las Positas | B12: =AVERAGE('5b. Base Hist'!Z17,'5b. Base Hist'!T17,'5b. Base Hist'!N17) -> 15609.702 | C12: ='5b. Base Hist'!V17 -> 186.25667 | D12: ='5b. Base Hist'!W17 -> 0 | E12: ='5b. Base Hist'!X17+'5b. Base Hist'!Y17 -> 446.27667
A13: Chaffey | B13: =AVERAGE('5b. Base Hist'!Z18,'5b. Base Hist'!T18,'5b. Base Hist'!N18) -> 15795.236 | C13: ='5b. Base Hist'!V18 -> 353.75667 | D13: ='5b. Base Hist'!W18 -> 0 | E13: ='5b. Base Hist'!X18+'5b. Base Hist'!Y18 -> 354.94
A14: Citrus | B14: =AVERAGE('5b. Base Hist'!Z19,'5b. Base Hist'!T19,'5b. Base Hist'!N19) -> 10843.666 | C14: ='5b. Base Hist'!V19 -> 320.47333 | D14: ='5b. Base Hist'!W19 -> 94.906667 | E14: ='5b. Base Hist'!X19+'5b. Base Hist'!Y19 -> 370.42667
A15: Coast | B15: =AVERAGE('5b. Base Hist'!Z20,'5b. Base Hist'!T20,'5b. Base Hist'!N20) -> 30680.591 | C15: ='5b. Base Hist'!V20 -> 47.38 | D15: ='5b. Base Hist'!W20 -> 521.81667 | E15: ='5b. Base Hist'!X20+'5b. Base Hist'!Y20 -> 201.9
A16: Compton | B16: =AVERAGE('5b. Base Hist'!Z21,'5b. Base Hist'!T21,'5b. Base Hist'!N21) -> 5811.6185 | C16: ='5b. Base Hist'!V21 -> 17.6 | D16: ='5b. Base Hist'!W21 -> 0 | E16: ='5b. Base Hist'!X21+'5b. Base Hist'!Y21 -> 254.99402
A17: Contra Costa | B17: =AVERAGE('5b. Base Hist'!Z22,'5b. Base Hist'!T22,'5b. Base Hist'!N22) -> 25231.466 | C17: ='5b. Base Hist'!V22 -> 155.13333 | D17: ='5b. Base Hist'!W22 -> 0 | E17: ='5b. Base Hist'!X22+'5b. Base Hist'!Y22 -> 964.52667
... A77: Yuba | B77: =AVERAGE('5b. Base Hist'!Z82,'5b. Base Hist'!T82,'5b. Base Hist'!N82) -> 7231.0819 | C77: ='5b. Base Hist'!V82 -> 117.56667 | D77: ='5b. Base Hist'!W82 -> 2.2266667 | E77: ='5b. Base Hist'!X82+'5b. Base Hist'!Y82 -> 106.77986
A78: Statewide Total | B78: =SUM(B6:B77) -> 1003674 | C78: =SUM(C6:C77) -> 35123.935 | D78: =SUM(D6:D77) -> 39437.772 | E78: =SUM(E6:E77) -> 40889.824

Sheet 5b. Base Hist
B5: 2016-17 | I5: 2017-18 | O5: 2018-19 | U5: Projections use change between 1617 and1718 and change between 1718 and 1819 and weight the latter twice as much
U6: 2019-20 Projected
U7: Reported
A8: FTES Data | B8: 2016-17 FTES | E8: Inmates in Correctional Facilities Education FTES | F8: Special Admit FTES | G8: Excluding Inmates and Special Admit | I8: 2017-18 FTES | L8: Inmates in Correctional Facilities Education FTES | M8: Special Admit FTES | N8: Excluding Inmates and Special Admit | O8: 2018-19 FTES | R8: Inmates in Correctional Facilities Education FTES | S8: Special Admit FTES | T8: Excluding Inmates and Special Admit | U8: Credit FTES | V8: FTES Noncredit Including growth FTES | W8: FTES CDCP including growth | X8: Inmates in Correctional Facilities Education FTES | Y8: Special Admit FTES | Z8: Excluding Inmates and Special Admit
A9: District | B9: Credit | C9: Noncredit | D9: CDCP | E9: Credit | F9: Credit | G9: Credit | I9: Credit | J9: Noncredit | K9: CDCP | L9: Credit | M9: Credit | N9: Credit | O9: Reported Credit FTES | P9: FTES Noncredit Including growth FTES | Q9: FTES CDCP including growth | T9: Credit
A11: =[9]NamesDistrictCollegeCenter!B11 -> Allan Hancock Joint CCD | B11: 9202.61 | C11: 499.92 | D11: 319.04 | E11: 106.5 | F11: 425.76 | G11: =B11-E11-F11 -> 8670.35 | I11: 7860.16 | J11: 431.7 | K11: 261.7 | L11: 83.47 | M11: 436.82 | N11: =I11-L11-M11 -> 7339.87 | O11: 8984.08 | P11: 401.82 | Q11: 255.44 | R11: 73.67 | S11: 420.1 | T11: =O11-R11-S11 -> 8490.31 | U11: =IF(((((I11-B11)+(2*(O11-I11)))/3)+O11)>0,((((I11-B11)+(2*(O11-I11)))/3)+O11),O11) -> 9285.8767 | V11: =IF(((((J11-C11)+(2*(P11-J11)))/3)+P11)>0,((((J11-C11)+(2*(P11-J11)))/3)+P11),P11) -> 359.16 | W11: =IF(((((K11-D11)+(2*(Q11-K11)))/3)+Q11)>0,((((K11-D11)+(2*(Q11-K11)))/3)+Q11),Q11) -> 232.15333 | X11: =IF(((((L11-E11)+(2*(R11-L11)))/3)+R11)>0,((((L11-E11)+(2*(R11-L11)))/3)+R11),R11) -> 59.46 | Y11: =IF(((((M11-F11)+(2*(S11-M11)))/3)+S11)>0,((((M11-F11)+(2*(S11-M11)))/3)+S11),S11) -> 412.64 | Z11: =IF(((((N11-G11)+(2*(T11-N11)))/3)+T11)>0,((((N11-G11)+(2*(T11-N11)))/3)+T11),T11) -> 8813.7767
A12: =[9]NamesDistrictCollegeCenter!B12 -> Antelope Valley CCD | B12: 10523.45 | C12: 4.5 | D12: 39.28 | E12: 8.68 | F12: 302.6 | G12: =B12-E12-F12 -> 10212.17 | I12: 10527.04 | J12: 7.919966 | K12: 80.880058 | L12: 1.79 | M12: 308.01 | N12: =I12-L12-M12 -> 10217.24 | O12: 10968.8 | P12: 7.61 | Q12: 55.1 | R12: 11.01 | S12: 341.84 | T12: =O12-R12-S12 -> 10615.95 | U12: =IF(((((I12-B12)+(2*(O12-I12)))/3)+O12)>0,((((I12-B12)+(2*(O12-I12)))/3)+O12),O12) -> 11264.503 | V12: =IF(((((J12-C12)+(2*(P12-J12)))/3)+P12)>0,((((J12-C12)+(2*(P12-J12)))/3)+P12),P12) -> 8.5433447 | W12: =IF(((((K12-D12)+(2*(Q12-K12)))/3)+Q12)>0,((((K12-D12)+(2*(Q12-K12)))/3)+Q12),Q12) -> 51.779981 | X12: =IF(((((L12-E12)+(2*(R12-L12)))/3)+R12)>0,((((L12-E12)+(2*(R12-L12)))/3)+R12),R12) -> 14.86 | Y12: =IF(((((M12-F12)+(2*(S12-M12)))/3)+S12)>0,((((M12-F12)+(2*(S12-M12)))/3)+S12),S12) -> 366.19667 | Z12: =IF(((((N12-G12)+(2*(T12-N12)))/3)+T12)>0,((((N12-G12)+(2*(T12-N12)))/3)+T12),T12) -> 10883.447
A13: =[9]NamesDistrictCollegeCenter!B13 -> Barstow CCD | B13: 2565.1499 | C13: 17.72 | D13: 0 | F13: 39.21 | G13: =B13-E13-F13 -> 2525.9399 | I13: 2320.71 | J13: 29.82 | K13: 0 | M13: 43.74 | N13: =I13-L13-M13 -> 2276.97 | O13: 2552.27 | P13: 29.84 | Q13: 0 | R13: 0 | S13: 0 | T13: =O13-R13-S13 -> 2552.27 | U13: =IF(((((I13-B13)+(2*(O13-I13)))/3)+O13)>0,((((I13-B13)+(2*(O13-I13)))/3)+O13),O13) -> 2625.1634 | V13: =IF(((((J13-C13)+(2*(P13-J13)))/3)+P13)>0,((((J13-C13)+(2*(P13-J13)))/3)+P13),P13) -> 33.886667 | W13: =IF(((((K13-D13)+(2*(Q13-K13)))/3)+Q13)>0,((((K13-D13)+(2*(Q13-K13)))/3)+Q13),Q13) -> 0 | X13: =IF(((((L13-E13)+(2*(R13-L13)))/3)+R13)>0,((((L13-E13)+(2*(R13-L13)))/3)+R13),R13) -> 0 | Y13: =IF(((((M13-F13)+(2*(S13-M13)))/3)+S13)>0,((((M13-F13)+(2*(S13-M13)))/3)+S13),S13) -> 0 | Z13: =IF(((((N13-G13)+(2*(T13-N13)))/3)+T13)>0,((((N13-G13)+(2*(T13-N13)))/3)+T13),T13) -> 2652.8134
A14: =[9]NamesDistrictCollegeCenter!B14 -> Butte-Glenn CCD | B14: 8717.92 | C14: 1245.24 | D14: 23.44 | F14: 172.12 | G14: =B14-E14-F14 -> 8545.8 | I14: 9162.4001 | J14: 1195.77 | K14: 25.05 | M14: 185.72 | N14: =I14-L14-M14 -> 8976.6801 | O14: 9162.4 | P14: 1195.77 | Q14: 25.05 | R14: 0 | S14: 185.72 | T14: =O14-R14-S14 -> 8976.68 | U14: =IF(((((I14-B14)+(2*(O14-I14)))/3)+O14)>0,((((I14-B14)+(2*(O14-I14)))/3)+O14),O14) -> 9310.56 | V14: =IF(((((J14-C14)+(2*(P14-J14)))/3)+P14)>0,((((J14-C14)+(2*(P14-J14)))/3)+P14),P14) -> 1179.28 | W14: =IF(((((K14-D14)+(2*(Q14-K14)))/3)+Q14)>0,((((K14-D14)+(2*(Q14-K14)))/3)+Q14),Q14) -> 25.586667 | X14: =IF(((((L14-E14)+(2*(R14-L14)))/3)+R14)>0,((((L14-E14)+(2*(R14-L14)))/3)+R14),R14) -> 0 | Y14: =IF(((((M14-F14)+(2*(S14-M14)))/3)+S14)>0,((((M14-F14)+(2*(S14-M14)))/3)+S14),S14) -> 190.25333 | Z14: =IF(((((N14-G14)+(2*(T14-N14)))/3)+T14)>0,((((N14-G14)+(2*(T14-N14)))/3)+T14),T14) -> 9120.3066
A15: =[9]NamesDistrictCollegeCenter!B15 -> Cabrillo CCD | B15: 10208.64 | C15: 181.86 | D15: 2.96 | F15: 300.29 | G15: =B15-E15-F15 -> 9908.35 | I15: 8791.82 | J15: 136.63 | K15: 15 | M15: 285.12 | N15: =I15-L15-M15 -> 8506.7 | O15: 9763.41 | P15: 481.52 | Q15: 55.93 | R15: 0 | S15: 234.9 | T15: =O15-R15-S15 -> 9528.51 | U15: =IF(((((I15-B15)+(2*(O15-I15)))/3)+O15)>0,((((I15-B15)+(2*(O15-I15)))/3)+O15),O15) -> 9938.8633 | V15: =IF(((((J15-C15)+(2*(P15-J15)))/3)+P15)>0,((((J15-C15)+(2*(P15-J15)))/3)+P15),P15) -> 696.37 | W15: =IF(((((K15-D15)+(2*(Q15-K15)))/3)+Q15)>0,((((K15-D15)+(2*(Q15-K15)))/3)+Q15),Q15) -> 87.23 | X15: =IF(((((L15-E15)+(2*(R15-L15)))/3)+R15)>0,((((L15-E15)+(2*(R15-L15)))/3)+R15),R15) -> 0 | Y15: =IF(((((M15-F15)+(2*(S15-M15)))/3)+S15)>0,((((M15-F15)+(2*(S15-M15)))/3)+S15),S15) -> 196.36333 | Z15: =IF(((((N15-G15)+(2*(T15-N15)))/3)+T15)>0,((((N15-G15)+(2*(T15-N15)))/3)+T15),T15) -> 9742.5
A16: =[9]NamesDistrictCollegeCenter!B16 -> Cerritos CCD | B16: 16303.43 | C16: 138.5 | D16: 279.76 | F16: 81.08 | G16: =B16-E16-F16 -> 16222.35 | I16: 16254.43 | J16: 273.91 | K16: 249.77 | M16: 91 | N16: =I16-L16-M16 -> 16163.43 | O16: 15924.63 | P16: 273.91 | Q16: 249.77 | R16: 0 | S16: 106.49 | T16: =O16-R16-S16 -> 15818.14 | U16: =IF(((((I16-B16)+(2*(O16-I16)))/3)+O16)>0,((((I16-B16)+(2*(O16-I16)))/3)+O16),O16) -> 15688.43 | V16: =IF(((((J16-C16)+(2*(P16-J16)))/3)+P16)>0,((((J16-C16)+(2*(P16-J16)))/3)+P16),P16) -> 319.04667 | W16: =IF(((((K16-D16)+(2*(Q16-K16)))/3)+Q16)>0,((((K16-D16)+(2*(Q16-K16)))/3)+Q16),Q16) -> 239.77333 | X16: =IF(((((L16-E16)+(2*(R16-L16)))/3)+R16)>0,((((L16-E16)+(2*(R16-L16)))/3)+R16),R16) -> 0 | Y16: =IF(((((M16-F16)+(2*(S16-M16)))/3)+S16)>0,((((M16-F16)+(2*(S16-M16)))/3)+S16),S16) -> 120.12333 | Z16: =IF(((((N16-G16)+(2*(T16-N16)))/3)+T16)>0,((((N16-G16)+(2*(T16-N16)))/3)+T16),T16) -> 15568.307
A17: =[9]NamesDistrictCollegeCenter!B17 -> Chabot-Las Positas CCD | B17: 15460.45 | C17: 164.83 | D17: 0 | F17: 212.72 | G17: =B17-E17-F17 -> 15247.73 | I17: 18651.603 | J17: 171.55 | K17: 0 | M17: 278.6 | N17: =I17-L17-M17 -> 18373.003 | O17: 15239.66 | P17: 179.03 | Q17: 0 | R17: 0 | S17: 366.03 | T17: =O17-R17-S17 -> 14873.63 | U17: =IF(((((I17-B17)+(2*(O17-I17)))/3)+O17)>0,((((I17-B17)+(2*(O17-I17)))/3)+O17),O17) -> 14028.749 | V17: =IF(((((J17-C17)+(2*(P17-J17)))/3)+P17)>0,((((J17-C17)+(2*(P17-J17)))/3)+P17),P17) -> 186.25667 | W17: =IF(((((K17-D17)+(2*(Q17-K17)))/3)+Q17)>0,((((K17-D17)+(2*(Q17-K17)))/3)+Q17),Q17) -> 0 | X17: =IF(((((L17-E17)+(2*(R17-L17)))/3)+R17)>0,((((L17-E17)+(2*(R17-L17)))/3)+R17),R17) -> 0 | Y17: =IF(((((M17-F17)+(2*(S17-M17)))/3)+S17)>0,((((M17-F17)+(2*(S17-M17)))/3)+S17),S17) -> 446.27667 | Z17: =IF(((((N17-G17)+(2*(T17-N17)))/3)+T17)>0,((((N17-G17)+(2*(T17-N17)))/3)+T17),T17) -> 13582.472
A18: =[9]NamesDistrictCollegeCenter!B18 -> Chaffey CCD | B18: 16000.02 | C18: 385.28 | D18: 0 | F18: 131.12 | G18: =B18-E18-F18 -> 15868.9 | I18: 14222.03 | J18: 404.9 | K18: 0 | L18: 59.64 | M18: 182.02 | N18: =I18-L18-M18 -> 13980.37 | O18: 16545.68 | P18: 370.29 | Q18: 0 | R18: 47.26 | S18: 240.26 | T18: =O18-R18-S18 -> 16258.16 | U18: =IF(((((I18-B18)+(2*(O18-I18)))/3)+O18)>0,((((I18-B18)+(2*(O18-I18)))/3)+O18),O18) -> 17502.117 | V18: =IF(((((J18-C18)+(2*(P18-J18)))/3)+P18)>0,((((J18-C18)+(2*(P18-J18)))/3)+P18),P18) -> 353.75667 | W18: =IF(((((K18-D18)+(2*(Q18-K18)))/3)+Q18)>0,((((K18-D18)+(2*(Q18-K18)))/3)+Q18),Q18) -> 0 | X18: =IF(((((L18-E18)+(2*(R18-L18)))/3)+R18)>0,((((L18-E18)+(2*(R18-L18)))/3)+R18),R18) -> 58.886667 | Y18: =IF(((((M18-F18)+(2*(S18-M18)))/3)+S18)>0,((((M18-F18)+(2*(S18-M18)))/3)+S18),S18) -> 296.05333 | Z18: =IF(((((N18-G18)+(2*(T18-N18)))/3)+T18)>0,((((N18-G18)+(2*(T18-N18)))/3)+T18),T18) -> 17147.177
A19: =[9]NamesDistrictCollegeCenter!B19 -> Citrus CCD | B19: 11468.25 | C19: 219.1 | D19: 113.84 | F19: 129.29 | G19: =B19-E19-F19 -> 11338.96 | I19: 11617.945 | J19: 295.13 | K19: 99.64 | M19: 208.13 | N19: =I19-L19-M19 -> 11409.815 | O19: 11053.78 | P19: 295.13 | Q19: 99.64 | R19: 0 | S19: 289.74 | T19: =O19-R19-S19 -> 10764.04 | U19: =IF(((((I19-B19)+(2*(O19-I19)))/3)+O19)>0,((((I19-B19)+(2*(O19-I19)))/3)+O19),O19) -> 10727.568 | V19: =IF(((((J19-C19)+(2*(P19-J19)))/3)+P19)>0,((((J19-C19)+(2*(P19-J19)))/3)+P19),P19) -> 320.47333 | W19: =IF(((((K19-D19)+(2*(Q19-K19)))/3)+Q19)>0,((((K19-D19)+(2*(Q19-K19)))/3)+Q19),Q19) -> 94.906667 | X19: =IF(((((L19-E19)+(2*(R19-L19)))/3)+R19)>0,((((L19-E19)+(2*(R19-L19)))/3)+R19),R19) -> 0 | Y19: =IF(((((M19-F19)+(2*(S19-M19)))/3)+S19)>0,((((M19-F19)+(2*(S19-M19)))/3)+S19),S19) -> 370.42667 | Z19: =IF(((((N19-G19)+(2*(T19-N19)))/3)+T19)>0,((((N19-G19)+(2*(T19-N19)))/3)+T19),T19) -> 10357.142
A20: =[9]NamesDistrictCollegeCenter!B20 -> Coast CCD | B20: 29983.06 | C20: 309.27 | D20: 0 | F20: 78.42 | G20: =B20-E20-F20 -> 29904.64 | I20: 32276.79 | J20: 349.01011 | K20: 0 | L20: 201.08 | M20: 187.33 | N20: =I20-L20-M20 -> 31888.38 | O20: 30455.94 | P20: 47.38 | Q20: 313.09 | R20: 0 | S20: 174.29 | T20: =O20-R20-S20 -> 30281.65 | U20: =IF(((((I20-B20)+(2*(O20-I20)))/3)+O20)>0,((((I20-B20)+(2*(O20-I20)))/3)+O20),O20) -> 30006.617 | V20: =IF(((((J20-C20)+(2*(P20-J20)))/3)+P20)>0,((((J20-C20)+(2*(P20-J20)))/3)+P20),P20) -> 47.38 | W20: =IF(((((K20-D20)+(2*(Q20-K20)))/3)+Q20)>0,((((K20-D20)+(2*(Q20-K20)))/3)+Q20),Q20) -> 521.81667 | X20: =IF(((((L20-E20)+(2*(R20-L20)))/3)+R20)>0,((((L20-E20)+(2*(R20-L20)))/3)+R20),R20) -> 0 | Y20: =IF(((((M20-F20)+(2*(S20-M20)))/3)+S20)>0,((((M20-F20)+(2*(S20-M20)))/3)+S20),S20) -> 201.9 | Z20: =IF(((((N20-G20)+(2*(T20-N20)))/3)+T20)>0,((((N20-G20)+(2*(T20-N20)))/3)+T20),T20) -> 29871.743
A21: =[9]NamesDistrictCollegeCenter!B21 -> Compton CCD | B21: 5088.51 | C21: 21.28 | D21: 0 | F21: 195.16 | G21: =B21-E21-F21 -> 4893.35 | I21: 5961.6899 | J21: 18.52 | K21: 0 | M21: 245.21 | N21: =I21-L21-M21 -> 5716.4799 | O21: 5961.69 | P21: 18.52 | Q21: 0 | R21: 0 | S21: 241.07041 | T21: =O21-R21-S21 -> 5720.6196 | U21: =IF(((((I21-B21)+(2*(O21-I21)))/3)+O21)>0,((((I21-B21)+(2*(O21-I21)))/3)+O21),O21) -> 6252.75 | V21: =IF(((((J21-C21)+(2*(P21-J21)))/3)+P21)>0,((((J21-C21)+(2*(P21-J21)))/3)+P21),P21) -> 17.6 | W21: =IF(((((K21-D21)+(2*(Q21-K21)))/3)+Q21)>0,((((K21-D21)+(2*(Q21-K21)))/3)+Q21),Q21) -> 0 | X21: =IF(((((L21-E21)+(2*(R21-L21)))/3)+R21)>0,((((L21-E21)+(2*(R21-L21)))/3)+R21),R21) -> 0 | Y21: =IF(((((M21-F21)+(2*(S21-M21)))/3)+S21)>0,((((M21-F21)+(2*(S21-M21)))/3)+S21),S21) -> 254.99402 | Z21: =IF(((((N21-G21)+(2*(T21-N21)))/3)+T21)>0,((((N21-G21)+(2*(T21-N21)))/3)+T21),T21) -> 5997.756
A22: =[9]NamesDistrictCollegeCenter!B22 -> Contra Costa CCD | B22: 23962.51 | C22: 153.79 | D22: 0 | F22: 583.12 | G22: =B22-E22-F22 -> 23379.39 | I22: 29269.36 | J22: 148.56 | K22: 0 | M22: 1002.35 | N22: =I22-L22-M22 -> 28267.01 | O22: 25136.88 | P22: 153.55 | Q22: 0 | R22: 0 | S22: 895.81 | T22: =O22-R22-S22 -> 24241.07 | U22: =IF(((((I22-B22)+(2*(O22-I22)))/3)+O22)>0,((((I22-B22)+(2*(O22-I22)))/3)+O22),O22) -> 24150.843 | V22: =IF(((((J22-C22)+(2*(P22-J22)))/3)+P22)>0,((((J22-C22)+(2*(P22-J22)))/3)+P22),P22) -> 155.13333 | W22: =IF(((((K22-D22)+(2*(Q22-K22)))/3)+Q22)>0,((((K22-D22)+(2*(Q22-K22)))/3)+Q22),Q22) -> 0 | X22: =IF(((((L22-E22)+(2*(R22-L22)))/3)+R22)>0,((((L22-E22)+(2*(R22-L22)))/3)+R22),R22) -> 0 | Y22: =IF(((((M22-F22)+(2*(S22-M22)))/3)+S22)>0,((((M22-F22)+(2*(S22-M22)))/3)+S22),S22) -> 964.52667 | Z22: =IF(((((N22-G22)+(2*(T22-N22)))/3)+T22)>0,((((N22-G22)+(2*(T22-N22)))/3)+T22),T22) -> 23186.317
A23: =[9]NamesDistrictCollegeCenter!B23 -> Copper Mountain CCD | B23: 1318.93 | C23: 91.78 | D23: 3.13 | F23: 3.38 | G23: =B23-E23-F23 -> 1315.55 | I23: 1431.83 | J23: 87.31 | K23: 2.98 | M23: 3.64 | N23: =I23-L23-M23 -> 1428.19 | O23: 1452.68 | P23: 66.606677 | Q23: 1.44 | R23: 0 | S23: 0 | T23: =O23-R23-S23 -> 1452.68 | U23: =IF(((((I23-B23)+(2*(O23-I23)))/3)+O23)>0,((((I23-B23)+(2*(O23-I23)))/3)+O23),O23) -> 1504.2133 | V23: =IF(((((J23-C23)+(2*(P23-J23)))/3)+P23)>0,((((J23-C23)+(2*(P23-J23)))/3)+P23),P23) -> 51.314461 | W23: =IF(((((K23-D23)+(2*(Q23-K23)))/3)+Q23)>0,((((K23-D23)+(2*(Q23-K23)))/3)+Q23),Q23) -> 0.36333333 | X23: =IF(((((L23-E23)+(2*(R23-L23)))/3)+R23)>0,((((L23-E23)+(2*(R23-L23)))/3)+R23),R23) -> 0 | Y23: =IF(((((M23-F23)+(2*(S23-M23)))/3)+S23)>0,((((M23-F23)+(2*(S23-M23)))/3)+S23),S23) -> 0 | Z23: =IF(((((N23-G23)+(2*(T23-N23)))/3)+T23)>0,((((N23-G23)+(2*(T23-N23)))/3)+T23),T23) -> 1506.5533
A24: =[9]NamesDistrictCollegeCenter!B24 -> Desert CCD | B24: 7758.61 | C24: 40.67 | D24: 738.4 | F24: 45.02 | G24: =B24-E24-F24 -> 7713.59 | I24: 9398.6091 | J24: 59.72 | K24: 668.2 | M24: 298.45 | N24: =I24-L24-M24 -> 9100.1591 | O24: 8637.27 | P24: 303.9 | Q24: 1465.7436 | R24: 0 | S24: 0 | T24: =O24-R24-S24 -> 8637.27 | U24: =IF(((((I24-B24)+(2*(O24-I24)))/3)+O24)>0,((((I24-B24)+(2*(O24-I24)))/3)+O24),O24) -> 8676.377 | V24: =IF(((((J24-C24)+(2*(P24-J24)))/3)+P24)>0,((((J24-C24)+(2*(P24-J24)))/3)+P24),P24) -> 473.03667 | W24: =IF(((((K24-D24)+(2*(Q24-K24)))/3)+Q24)>0,((((K24-D24)+(2*(Q24-K24)))/3)+Q24),Q24) -> 1974.0394 | X24: =IF(((((L24-E24)+(2*(R24-L24)))/3)+R24)>0,((((L24-E24)+(2*(R24-L24)))/3)+R24),R24) -> 0 | Y24: =IF(((((M24-F24)+(2*(S24-M24)))/3)+S24)>0,((((M24-F24)+(2*(S24-M24)))/3)+S24),S24) -> 0 | Z24: =IF(((((N24-G24)+(2*(T24-N24)))/3)+T24)>0,((((N24-G24)+(2*(T24-N24)))/3)+T24),T24) -> 8790.867
A25: =[9]NamesDistrictCollegeCenter!B25 -> El Camino CCD | B25: 17898.23 | C25: 30.3 | D25: 0 | F25: 233.94 | G25: =B25-E25-F25 -> 17664.29 | I25: 19587.66 | J25: 55.19 | K25: 0 | M25: 360.76 | N25: =I25-L25-M25 -> 19226.9 | O25: 18479.54 | P25: 55.19 | Q25: 0 | R25: 0 | S25: 541.31 | T25: =O25-R25-S25 -> 17938.23 | U25: =IF(((((I25-B25)+(2*(O25-I25)))/3)+O25)>0,((((I25-B25)+(2*(O25-I25)))/3)+O25),O25) -> 18303.937 | V25: =IF(((((J25-C25)+(2*(P25-J25)))/3)+P25)>0,((((J25-C25)+(2*(P25-J25)))/3)+P25),P25) -> 63.486667 | W25: =IF(((((K25-D25)+(2*(Q25-K25)))/3)+Q25)>0,((((K25-D25)+(2*(Q25-K25)))/3)+Q25),Q25) -> 0 | X25: =IF(((((L25-E25)+(2*(R25-L25)))/3)+R25)>0,((((L25-E25)+(2*(R25-L25)))/3)+R25),R25) -> 0 | Y25: =IF(((((M25-F25)+(2*(S25-M25)))/3)+S25)>0,((((M25-F25)+(2*(S25-M25)))/3)+S25),S25) -> 703.95 | Z25: =IF(((((N25-G25)+(2*(T25-N25)))/3)+T25)>0,((((N25-G25)+(2*(T25-N25)))/3)+T25),T25) -> 17599.987
A26: =[9]NamesDistrictCollegeCenter!B26 -> Feather River CCD | B26: 1580.29 | C26: 33.3 | D26: 0 | E26: 273.92 | F26: 116.74 | G26: =B26-E26-F26 -> 1189.63 | I26: 1599.3681 | J26: 39.2 | K26: 0 | L26: 301.23 | M26: 92.89 | N26: =I26-L26-M26 -> 1205.2481 | O26: 1603.11 | P26: 37.07 | Q26: 0 | R26: 257.66215 | S26: 0 | T26: =O26-R26-S26 -> 1345.4479 | U26: =IF(((((I26-B26)+(2*(O26-I26)))/3)+O26)>0,((((I26-B26)+(2*(O26-I26)))/3)+O26),O26) -> 1611.964 | V26: =IF(((((J26-C26)+(2*(P26-J26)))/3)+P26)>0,((((J26-C26)+(2*(P26-J26)))/3)+P26),P26) -> 37.616667 | W26: =IF(((((K26-D26)+(2*(Q26-K26)))/3)+Q26)>0,((((K26-D26)+(2*(Q26-K26)))/3)+Q26),Q26) -> 0 | X26: =IF(((((L26-E26)+(2*(R26-L26)))/3)+R26)>0,((((L26-E26)+(2*(R26-L26)))/3)+R26),R26) -> 237.72024 | Y26: =IF(((((M26-F26)+(2*(S26-M26)))/3)+S26)>0,((((M26-F26)+(2*(S26-M26)))/3)+S26),S26) -> 0 | Z26: =IF(((((N26-G26)+(2*(T26-N26)))/3)+T26)>0,((((N26-G26)+(2*(T26-N26)))/3)+T26),T26) -> 1444.1204
A27: =[9]NamesDistrictCollegeCenter!B27 -> Foothill-DeAnza CCD | B27: 25518.78 | C27: 264.29 | D27: 184.45 | F27: 693.85 | G27: =B27-E27-F27 -> 24824.93 | I27: 23961.87 | J27: 238.57 | K27: 283.28 | M27: 575.87 | N27: =I27-L27-M27 -> 23386 | O27: 22677.1 | P27: 238.57 | Q27: 283.28 | R27: 0 | S27: 755 | T27: =O27-R27-S27 -> 21922.1 | U27: =IF(((((I27-B27)+(2*(O27-I27)))/3)+O27)>0,((((I27-B27)+(2*(O27-I27)))/3)+O27),O27) -> 21301.617 | V27: =IF(((((J27-C27)+(2*(P27-J27)))/3)+P27)>0,((((J27-C27)+(2*(P27-J27)))/3)+P27),P27) -> 229.99667 | W27: =IF(((((K27-D27)+(2*(Q27-K27)))/3)+Q27)>0,((((K27-D27)+(2*(Q27-K27)))/3)+Q27),Q27) -> 316.22333 | X27: =IF(((((L27-E27)+(2*(R27-L27)))/3)+R27)>0,((((L27-E27)+(2*(R27-L27)))/3)+R27),R27) -> 0 | Y27: =IF(((((M27-F27)+(2*(S27-M27)))/3)+S27)>0,((((M27-F27)+(2*(S27-M27)))/3)+S27),S27) -> 835.09333 | Z27: =IF(((((N27-G27)+(2*(T27-N27)))/3)+T27)>0,((((N27-G27)+(2*(T27-N27)))/3)+T27),T27) -> 20466.523
A28: =[9]NamesDistrictCollegeCenter!B28 -> Gavilan Joint CCD | B28: 4751.6037 | C28: 454.979 | D28: 114.54 | E28: 0.54 | F28: 189.99 | G28: =B28-E28-F28 -> 4561.0737 | I28: 4106.62 | J28: 481.47 | K28: 117.69 | L28: 0.44 | M28: 187.71 | N28: =I28-L28-M28 -> 3918.47 | O28: 4934.71 | P28: 292.22 | Q28: 117.74 | R28: 0 | S28: 220.04 | T28: =O28-R28-S28 -> 4714.67 | U28: =IF(((((I28-B28)+(2*(O28-I28)))/3)+O28)>0,((((I28-B28)+(2*(O28-I28)))/3)+O28),O28) -> 5271.7754 | V28: =IF(((((J28-C28)+(2*(P28-J28)))/3)+P28)>0,((((J28-C28)+(2*(P28-J28)))/3)+P28),P28) -> 174.88367 | W28: =IF(((((K28-D28)+(2*(Q28-K28)))/3)+Q28)>0,((((K28-D28)+(2*(Q28-K28)))/3)+Q28),Q28) -> 118.82333 | X28: =IF(((((L28-E28)+(2*(R28-L28)))/3)+R28)>0,((((L28-E28)+(2*(R28-L28)))/3)+R28),R28) -> 0 | Y28: =IF(((((M28-F28)+(2*(S28-M28)))/3)+S28)>0,((((M28-F28)+(2*(S28-M28)))/3)+S28),S28) -> 240.83333 | Z28: =IF(((((N28-G28)+(2*(T28-N28)))/3)+T28)>0,((((N28-G28)+(2*(T28-N28)))/3)+T28),T28) -> 5031.2688
A29: =[9]NamesDistrictCollegeCenter!B29 -> Glendale CCD | B29: 12449.54 | C29: 243.85 | D29: 2847.21 | F29: 230.88 | G29: =B29-E29-F29 -> 12218.66 | I29: 11026.53 | J29: 272.56 | K29: 2656.3 | M29: 282.49 | N29: =I29-L29-M29 -> 10744.04 | O29: 11143.41 | P29: 183.49377 | Q29: 2536.14 | R29: 0 | S29: 299.6 | T29: =O29-R29-S29 -> 10843.81 | U29: =IF(((((I29-B29)+(2*(O29-I29)))/3)+O29)>0,((((I29-B29)+(2*(O29-I29)))/3)+O29),O29) -> 10746.993 | V29: =IF(((((J29-C29)+(2*(P29-J29)))/3)+P29)>0,((((J29-C29)+(2*(P29-J29)))/3)+P29),P29) -> 133.68628 | W29: =IF(((((K29-D29)+(2*(Q29-K29)))/3)+Q29)>0,((((K29-D29)+(2*(Q29-K29)))/3)+Q29),Q29) -> 2392.3967 | X29: =IF(((((L29-E29)+(2*(R29-L29)))/3)+R29)>0,((((L29-E29)+(2*(R29-L29)))/3)+R29),R29) -> 0 | Y29: =IF(((((M29-F29)+(2*(S29-M29)))/3)+S29)>0,((((M29-F29)+(2*(S29-M29)))/3)+S29),S29) -> 328.21 | Z29: =IF(((((N29-G29)+(2*(T29-N29)))/3)+T29)>0,((((N29-G29)+(2*(T29-N29)))/3)+T29),T29) -> 10418.783
A30: =[9]NamesDistrictCollegeCenter!B30 -> Grossmont-Cuyamaca CCD | B30: 19064.97 | C30: 20.18 | D30: 0 | F30: 317.76 | G30: =B30-E30-F30 -> 18747.21 | I30: 17160.77 | J30: 19.71 | K30: 0 | M30: 334.9 | N30: =I30-L30-M30 -> 16825.87 | O30: 17730.4 | P30: 17.02 | Q30: 0 | R30: 5.42 | S30: 298.79 | T30: =O30-R30-S30 -> 17426.19 | U30: =IF(((((I30-B30)+(2*(O30-I30)))/3)+O30)>0,((((I30-B30)+(2*(O30-I30)))/3)+O30),O30) -> 17475.42 | V30: =IF(((((J30-C30)+(2*(P30-J30)))/3)+P30)>0,((((J30-C30)+(2*(P30-J30)))/3)+P30),P30) -> 15.07 | W30: =IF(((((K30-D30)+(2*(Q30-K30)))/3)+Q30)>0,((((K30-D30)+(2*(Q30-K30)))/3)+Q30),Q30) -> 0 | X30: =IF(((((L30-E30)+(2*(R30-L30)))/3)+R30)>0,((((L30-E30)+(2*(R30-L30)))/3)+R30),R30) -> 9.0333333 | Y30: =IF(((((M30-F30)+(2*(S30-M30)))/3)+S30)>0,((((M30-F30)+(2*(S30-M30)))/3)+S30),S30) -> 280.43 | Z30: =IF(((((N30-G30)+(2*(T30-N30)))/3)+T30)>0,((((N30-G30)+(2*(T30-N30)))/3)+T30),T30) -> 17185.957
A31: =[9]NamesDistrictCollegeCenter!B31 -> Hartnell CCD | B31: 7340.3599 | C31: 4.43 | D31: 0 | F31: 33.53 | G31: =B31-E31-F31 -> 7306.8299 | I31: 7356.0899 | J31: 2.91 | K31: 0 | L31: 65.25 | M31: 48.47 | N31: =I31-L31-M31 -> 7242.3699 | O31: 7327.45 | P31: 14.44 | Q31: 12.24 | R31: 77.93 | S31: 50.386017 | T31: =O31-R31-S31 -> 7199.134 | U31: =IF(((((I31-B31)+(2*(O31-I31)))/3)+O31)>0,((((I31-B31)+(2*(O31-I31)))/3)+O31),O31) -> 7313.6001 | V31: =IF(((((J31-C31)+(2*(P31-J31)))/3)+P31)>0,((((J31-C31)+(2*(P31-J31)))/3)+P31),P31) -> 21.62 | W31: =IF(((((K31-D31)+(2*(Q31-K31)))/3)+Q31)>0,((((K31-D31)+(2*(Q31-K31)))/3)+Q31),Q31) -> 20.4 | X31: =IF(((((L31-E31)+(2*(R31-L31)))/3)+R31)>0,((((L31-E31)+(2*(R31-L31)))/3)+R31),R31) -> 108.13333 | Y31: =IF(((((M31-F31)+(2*(S31-M31)))/3)+S31)>0,((((M31-F31)+(2*(S31-M31)))/3)+S31),S31) -> 56.643361 | Z31: =IF(((((N31-G31)+(2*(T31-N31)))/3)+T31)>0,((((N31-G31)+(2*(T31-N31)))/3)+T31),T31) -> 7148.8234
A32: =[9]NamesDistrictCollegeCenter!B32 -> Imperial CCD | B32: 6799.88 | C32: 38.44 | D32: 15.96 | E32: 55.11 | F32: 21.49 | G32: =B32-E32-F32 -> 6723.28 | I32: 7347.2481 | J32: 24.1 | K32: 24.22 | L32: 167.75 | M32: 61.2 | N32: =I32-L32-M32 -> 7118.2981 | O32: 7403.73 | P32: 31.87 | Q32: 14.4 | R32: 219.04 | S32: 1.9395992 | T32: =O32-R32-S32 -> 7182.7504 | U32: =IF(((((I32-B32)+(2*(O32-I32)))/3)+O32)>0,((((I32-B32)+(2*(O32-I32)))/3)+O32),O32) -> 7623.8406 | V32: =IF(((((J32-C32)+(2*(P32-J32)))/3)+P32)>0,((((J32-C32)+(2*(P32-J32)))/3)+P32),P32) -> 32.27 | W32: =IF(((((K32-D32)+(2*(Q32-K32)))/3)+Q32)>0,((((K32-D32)+(2*(Q32-K32)))/3)+Q32),Q32) -> 10.606667 | X32: =IF(((((L32-E32)+(2*(R32-L32)))/3)+R32)>0,((((L32-E32)+(2*(R32-L32)))/3)+R32),R32) -> 290.78 | Y32: =IF(((((M32-F32)+(2*(S32-M32)))/3)+S32)>0,((((M32-F32)+(2*(S32-M32)))/3)+S32),S32) -> 1.9395992 | Z32: =IF(((((N32-G32)+(2*(T32-N32)))/3)+T32)>0,((((N32-G32)+(2*(T32-N32)))/3)+T32),T32) -> 7357.3913
A33: =[9]NamesDistrictCollegeCenter!B33 -> Kern CCD | B33: 21647.56 | C33: 74.24 | D33: 0 | E33: 3.88 | F33: 1141.01 | G33: =B33-E33-F33 -> 20502.67 | I33: 22475.839 | J33: 26.64 | K33: 29.99 | L33: 476.99 | M33: 1325.59 | N33: =I33-L33-M33 -> 20673.259 | O33: 23271.77 | P33: 65.88 | Q33: 40.97 | R33: 735.11 | S33: 556.4372 | T33: =O33-R33-S33 -> 21980.223 | U33: =IF(((((I33-B33)+(2*(O33-I33)))/3)+O33)>0,((((I33-B33)+(2*(O33-I33)))/3)+O33),O33) -> 24078.484 | V33: =IF(((((J33-C33)+(2*(P33-J33)))/3)+P33)>0,((((J33-C33)+(2*(P33-J33)))/3)+P33),P33) -> 76.173333 | W33: =IF(((((K33-D33)+(2*(Q33-K33)))/3)+Q33)>0,((((K33-D33)+(2*(Q33-K33)))/3)+Q33),Q33) -> 58.286667 | X33: =IF(((((L33-E33)+(2*(R33-L33)))/3)+R33)>0,((((L33-E33)+(2*(R33-L33)))/3)+R33),R33) -> 1064.8933 | Y33: =IF(((((M33-F33)+(2*(S33-M33)))/3)+S33)>0,((((M33-F33)+(2*(S33-M33)))/3)+S33),S33) -> 105.19533 | Z33: =IF(((((N33-G33)+(2*(T33-N33)))/3)+T33)>0,((((N33-G33)+(2*(T33-N33)))/3)+T33),T33) -> 22908.395
A34: =[9]NamesDistrictCollegeCenter!B34 -> Lake Tahoe CCD | B34: 1663.3 | C34: 56.419921 | D34: 14.09 | E34: 690.1 | F34: 30.88 | G34: =B34-E34-F34 -> 942.32 | I34: 1628.82 | J34: 40.14 | K34: 9.87 | L34: 741.25 | M34: 41.54 | N34: =I34-L34-M34 -> 846.03 | O34: 1834.13 | P34: 52.89 | Q34: 5.98 | R34: 132.84987 | S34: 0 | T34: =O34-R34-S34 -> 1701.2801 | U34: =IF(((((I34-B34)+(2*(O34-I34)))/3)+O34)>0,((((I34-B34)+(2*(O34-I34)))/3)+O34),O34) -> 1959.51 | V34: =IF(((((J34-C34)+(2*(P34-J34)))/3)+P34)>0,((((J34-C34)+(2*(P34-J34)))/3)+P34),P34) -> 55.96336 | W34: =IF(((((K34-D34)+(2*(Q34-K34)))/3)+Q34)>0,((((K34-D34)+(2*(Q34-K34)))/3)+Q34),Q34) -> 1.98 | X34: =IF(((((L34-E34)+(2*(R34-L34)))/3)+R34)>0,((((L34-E34)+(2*(R34-L34)))/3)+R34),R34) -> 132.84987 | Y34: =IF(((((M34-F34)+(2*(S34-M34)))/3)+S34)>0,((((M34-F34)+(2*(S34-M34)))/3)+S34),S34) -> 0 | Z34: =IF(((((N34-G34)+(2*(T34-N34)))/3)+T34)>0,((((N34-G34)+(2*(T34-N34)))/3)+T34),T34) -> 2239.3502
A35: =[9]NamesDistrictCollegeCenter!B35 -> Lassen CCD | B35: 1570.5699 | C35: 23.93 | D35: 1.62 | E35: 497 | F35: 35.5 | G35: =B35-E35-F35 -> 1038.0699 | I35: 1341.9 | J35: 12.96 | K35: 2.6 | L35: 613.04 | M35: 88.43 | N35: =I35-L35-M35 -> 640.43 | O35: 1581.71 | P35: 10.28 | Q35: 2.05 | R35: 761.86122 | S35: 0 | T35: =O35-R35-S35 -> 819.84878 | U35: =IF(((((I35-B35)+(2*(O35-I35)))/3)+O35)>0,((((I35-B35)+(2*(O35-I35)))/3)+O35),O35) -> 1665.36 | V35: =IF(((((J35-C35)+(2*(P35-J35)))/3)+P35)>0,((((J35-C35)+(2*(P35-J35)))/3)+P35),P35) -> 4.8366667 | W35: =IF(((((K35-D35)+(2*(Q35-K35)))/3)+Q35)>0,((((K35-D35)+(2*(Q35-K35)))/3)+Q35),Q35) -> 2.01 | X35: =IF(((((L35-E35)+(2*(R35-L35)))/3)+R35)>0,((((L35-E35)+(2*(R35-L35)))/3)+R35),R35) -> 899.75536 | Y35: =IF(((((M35-F35)+(2*(S35-M35)))/3)+S35)>0,((((M35-F35)+(2*(S35-M35)))/3)+S35),S35) -> 0 | Z35: =IF(((((N35-G35)+(2*(T35-N35)))/3)+T35)>0,((((N35-G35)+(2*(T35-N35)))/3)+T35),T35) -> 806.91466
A36: =[9]NamesDistrictCollegeCenter!B36 -> Long Beach CCD | B36: 20580.63 | C36: 108.52 | D36: 386.81 | F36: 105.44 | G36: =B36-E36-F36 -> 20475.19 | I36: 18388.58 | J36: 100.53 | K36: 407.61 | M36: 76.14 | N36: =I36-L36-M36 -> 18312.44 | O36: 18747.16 | P36: 60.89 | Q36: 395.54 | R36: 0 | S36: 157.24 | T36: =O36-R36-S36 -> 18589.92 | U36: =IF(((((I36-B36)+(2*(O36-I36)))/3)+O36)>0,((((I36-B36)+(2*(O36-I36)))/3)+O36),O36) -> 18255.53 | V36: =IF(((((J36-C36)+(2*(P36-J36)))/3)+P36)>0,((((J36-C36)+(2*(P36-J36)))/3)+P36),P36) -> 31.8 | W36: =IF(((((K36-D36)+(2*(Q36-K36)))/3)+Q36)>0,((((K36-D36)+(2*(Q36-K36)))/3)+Q36),Q36) -> 394.42667 | X36: =IF(((((L36-E36)+(2*(R36-L36)))/3)+R36)>0,((((L36-E36)+(2*(R36-L36)))/3)+R36),R36) -> 0 | Y36: =IF(((((M36-F36)+(2*(S36-M36)))/3)+S36)>0,((((M36-F36)+(2*(S36-M36)))/3)+S36),S36) -> 201.54 | Z36: =IF(((((N36-G36)+(2*(T36-N36)))/3)+T36)>0,((((N36-G36)+(2*(T36-N36)))/3)+T36),T36) -> 18053.99
A37: =[9]NamesDistrictCollegeCenter!B37 -> Los Angeles CCD | B37: 101333.93 | C37: 2226.65 | D37: 4423.7 | E37: =41.86+13.74 -> 55.6 | F37: 5149.4 | G37: =B37-E37-F37 -> 96128.932 | I37: 93053.62 | J37: 2917.27 | K37: 4074.59 | L37: 27.63 | M37: 5496.54 | N37: =I37-L37-M37 -> 87529.45 | O37: 90768.6 | P37: 2719.16 | Q37: 4512.28 | R37: 20 | S37: 5496.54 | T37: =O37-R37-S37 -> 85252.06 | U37: =IF(((((I37-B37)+(2*(O37-I37)))/3)+O37)>0,((((I37-B37)+(2*(O37-I37)))/3)+O37),O37) -> 86485.149 | V37: =IF(((((J37-C37)+(2*(P37-J37)))/3)+P37)>0,((((J37-C37)+(2*(P37-J37)))/3)+P37),P37) -> 2817.2933 | W37: =IF(((((K37-D37)+(2*(Q37-K37)))/3)+Q37)>0,((((K37-D37)+(2*(Q37-K37)))/3)+Q37),Q37) -> 4687.7033 | X37: =IF(((((L37-E37)+(2*(R37-L37)))/3)+R37)>0,((((L37-E37)+(2*(R37-L37)))/3)+R37),R37) -> 5.59 | Y37: =IF(((((M37-F37)+(2*(S37-M37)))/3)+S37)>0,((((M37-F37)+(2*(S37-M37)))/3)+S37),S37) -> 5612.2533 | Z37: =IF(((((N37-G37)+(2*(T37-N37)))/3)+T37)>0,((((N37-G37)+(2*(T37-N37)))/3)+T37),T37) -> 80867.306
A38: =[9]NamesDistrictCollegeCenter!B38 -> Los Rios CCD | B38: 52402.09 | C38: 237.67 | D38: 0 | F38: 358.34 | G38: =B38-E38-F38 -> 52043.75 | I38: 44183.24 | J38: 129.82 | K38: 0 | L38: 60.8 | M38: 449.12 | N38: =I38-L38-M38 -> 43673.32 | O38: 52019.38 | P38: 240.84 | Q38: 0 | R38: 93.53 | S38: 545.43 | T38: =O38-R38-S38 -> 51380.42 | U38: =IF(((((I38-B38)+(2*(O38-I38)))/3)+O38)>0,((((I38-B38)+(2*(O38-I38)))/3)+O38),O38) -> 54503.857 | V38: =IF(((((J38-C38)+(2*(P38-J38)))/3)+P38)>0,((((J38-C38)+(2*(P38-J38)))/3)+P38),P38) -> 278.90333 | W38: =IF(((((K38-D38)+(2*(Q38-K38)))/3)+Q38)>0,((((K38-D38)+(2*(Q38-K38)))/3)+Q38),Q38) -> 0 | X38: =IF(((((L38-E38)+(2*(R38-L38)))/3)+R38)>0,((((L38-E38)+(2*(R38-L38)))/3)+R38),R38) -> 135.61667 | Y38: =IF(((((M38-F38)+(2*(S38-M38)))/3)+S38)>0,((((M38-F38)+(2*(S38-M38)))/3)+S38),S38) -> 639.89667 | Z38: =IF(((((N38-G38)+(2*(T38-N38)))/3)+T38)>0,((((N38-G38)+(2*(T38-N38)))/3)+T38),T38) -> 53728.343
A39: =[9]NamesDistrictCollegeCenter!B39 -> Marin CCD | B39: 3452.66 | C39: 270.67 | D39: 0 | F39: 150.64 | G39: =B39-E39-F39 -> 3302.02 | I39: 3439.73 | J39: 284.79 | K39: 0 | M39: 201.12 | N39: =I39-L39-M39 -> 3238.61 | O39: 3090.03 | P39: 284.79 | Q39: 0 | R39: 0 | S39: 156.55 | T39: =O39-R39-S39 -> 2933.48 | U39: =IF(((((I39-B39)+(2*(O39-I39)))/3)+O39)>0,((((I39-B39)+(2*(O39-I39)))/3)+O39),O39) -> 2852.5867 | V39: =IF(((((J39-C39)+(2*(P39-J39)))/3)+P39)>0,((((J39-C39)+(2*(P39-J39)))/3)+P39),P39) -> 289.49667 | W39: =IF(((((K39-D39)+(2*(Q39-K39)))/3)+Q39)>0,((((K39-D39)+(2*(Q39-K39)))/3)+Q39),Q39) -> 0 | X39: =IF(((((L39-E39)+(2*(R39-L39)))/3)+R39)>0,((((L39-E39)+(2*(R39-L39)))/3)+R39),R39) -> 0 | Y39: =IF(((((M39-F39)+(2*(S39-M39)))/3)+S39)>0,((((M39-F39)+(2*(S39-M39)))/3)+S39),S39) -> 143.66333 | Z39: =IF(((((N39-G39)+(2*(T39-N39)))/3)+T39)>0,((((N39-G39)+(2*(T39-N39)))/3)+T39),T39) -> 2708.9233
A40: =[9]NamesDistrictCollegeCenter!B40 -> Mendocino-Lake CCD | B40: 2983.31 | C40: 42.12 | D40: 39.6 | F40: 398.58 | G40: =B40-E40-F40 -> 2584.73 | I40: 2369.96 | J40: 36.4 | K40: 49.79 | M40: 205.79 | N40: =I40-L40-M40 -> 2164.17 | O40: 2803.41 | P40: 31.98 | Q40: 56.25 | R40: 0 | S40: 288.98 | T40: =O40-R40-S40 -> 2514.43 | U40: =IF(((((I40-B40)+(2*(O40-I40)))/3)+O40)>0,((((I40-B40)+(2*(O40-I40)))/3)+O40),O40) -> 2887.9267 | V40: =IF(((((J40-C40)+(2*(P40-J40)))/3)+P40)>0,((((J40-C40)+(2*(P40-J40)))/3)+P40),P40) -> 27.126667 | W40: =IF(((((K40-D40)+(2*(Q40-K40)))/3)+Q40)>0,((((K40-D40)+(2*(Q40-K40)))/3)+Q40),Q40) -> 63.953333 | X40: =IF(((((L40-E40)+(2*(R40-L40)))/3)+R40)>0,((((L40-E40)+(2*(R40-L40)))/3)+R40),R40) -> 0 | Y40: =IF(((((M40-F40)+(2*(S40-M40)))/3)+S40)>0,((((M40-F40)+(2*(S40-M40)))/3)+S40),S40) -> 280.17667 | Z40: =IF(((((N40-G40)+(2*(T40-N40)))/3)+T40)>0,((((N40-G40)+(2*(T40-N40)))/3)+T40),T40) -> 2607.75
A41: =[9]NamesDistrictCollegeCenter!B41 -> Merced CCD | B41: 8760.98 | C41: 228.53 | D41: 560.37 | E41: 45.26 | F41: 357.36 | G41: =B41-E41-F41 -> 8358.36 | I41: 8379.03 | J41: 183.32 | K41: 690.09 | L41: 75 | M41: 519.14 | N41: =I41-L41-M41 -> 7784.89 | O41: 8971.49 | P41: 365.7 | Q41: 663.84 | R41: 147.21 | S41: 72.941232 | T41: =O41-R41-S41 -> 8751.3388 | U41: =IF(((((I41-B41)+(2*(O41-I41)))/3)+O41)>0,((((I41-B41)+(2*(O41-I41)))/3)+O41),O41) -> 9239.1467 | V41: =IF(((((J41-C41)+(2*(P41-J41)))/3)+P41)>0,((((J41-C41)+(2*(P41-J41)))/3)+P41),P41) -> 472.21667 | W41: =IF(((((K41-D41)+(2*(Q41-K41)))/3)+Q41)>0,((((K41-D41)+(2*(Q41-K41)))/3)+Q41),Q41) -> 689.58 | X41: =IF(((((L41-E41)+(2*(R41-L41)))/3)+R41)>0,((((L41-E41)+(2*(R41-L41)))/3)+R41),R41) -> 205.26333 | Y41: =IF(((((M41-F41)+(2*(S41-M41)))/3)+S41)>0,((((M41-F41)+(2*(S41-M41)))/3)+S41),S41) -> 72.941232 | Z41: =IF(((((N41-G41)+(2*(T41-N41)))/3)+T41)>0,((((N41-G41)+(2*(T41-N41)))/3)+T41),T41) -> 9204.4813
A42: =[9]NamesDistrictCollegeCenter!B42 -> MiraCosta CCD | B42: 10299.25 | C42: 782.45 | D42: 0 | F42: 151.13 | G42: =B42-E42-F42 -> 10148.12 | I42: 10274.23 | J42: 759.88 | K42: 0 | M42: 150.49 | N42: =I42-L42-M42 -> 10123.74 | O42: 9249.71 | P42: 759.88 | Q42: 0 | R42: 0 | S42: 122.55 | T42: =O42-R42-S42 -> 9127.16 | U42: =IF(((((I42-B42)+(2*(O42-I42)))/3)+O42)>0,((((I42-B42)+(2*(O42-I42)))/3)+O42),O42) -> 8558.3567 | V42: =IF(((((J42-C42)+(2*(P42-J42)))/3)+P42)>0,((((J42-C42)+(2*(P42-J42)))/3)+P42),P42) -> 752.35667 | W42: =IF(((((K42-D42)+(2*(Q42-K42)))/3)+Q42)>0,((((K42-D42)+(2*(Q42-K42)))/3)+Q42),Q42) -> 0 | X42: =IF(((((L42-E42)+(2*(R42-L42)))/3)+R42)>0,((((L42-E42)+(2*(R42-L42)))/3)+R42),R42) -> 0 | Y42: =IF(((((M42-F42)+(2*(S42-M42)))/3)+S42)>0,((((M42-F42)+(2*(S42-M42)))/3)+S42),S42) -> 103.71 | Z42: =IF(((((N42-G42)+(2*(T42-N42)))/3)+T42)>0,((((N42-G42)+(2*(T42-N42)))/3)+T42),T42) -> 8454.6467
A43: =[9]NamesDistrictCollegeCenter!B43 -> Monterey Peninsula CCD | B43: 6258.5701 | C43: 355.9 | D43: 82.58 | F43: 120.21 | G43: =B43-E43-F43 -> 6138.3601 | I43: 5956.3 | J43: 230.02 | K43: 87.89 | M43: 140.1 | N43: =I43-L43-M43 -> 5816.2 | O43: 5968.8 | P43: 293.83 | Q43: 37.24 | R43: 0 | S43: 149.9 | T43: =O43-R43-S43 -> 5818.9 | U43: =IF(((((I43-B43)+(2*(O43-I43)))/3)+O43)>0,((((I43-B43)+(2*(O43-I43)))/3)+O43),O43) -> 5876.3766 | V43: =IF(((((J43-C43)+(2*(P43-J43)))/3)+P43)>0,((((J43-C43)+(2*(P43-J43)))/3)+P43),P43) -> 294.41 | W43: =IF(((((K43-D43)+(2*(Q43-K43)))/3)+Q43)>0,((((K43-D43)+(2*(Q43-K43)))/3)+Q43),Q43) -> 5.2433333 | X43: =IF(((((L43-E43)+(2*(R43-L43)))/3)+R43)>0,((((L43-E43)+(2*(R43-L43)))/3)+R43),R43) -> 0 | Y43: =IF(((((M43-F43)+(2*(S43-M43)))/3)+S43)>0,((((M43-F43)+(2*(S43-M43)))/3)+S43),S43) -> 163.06333 | Z43: =IF(((((N43-G43)+(2*(T43-N43)))/3)+T43)>0,((((N43-G43)+(2*(T43-N43)))/3)+T43),T43) -> 5713.3133
A44: =[9]NamesDistrictCollegeCenter!B44 -> Mt. San Antonio CCD | B44: 24240.05 | C44: 1697.18 | D44: 5080.4 | F44: 24.49 | G44: =B44-E44-F44 -> 24215.56 | I44: 24977.135 | J44: 1557.81 | K44: 6169.37 | M44: 108.69 | N44: =I44-L44-M44 -> 24868.445 | O44: 24957.29 | P44: 1636.03 | Q44: 6299.98 | R44: 0 | S44: 57.306977 | T44: =O44-R44-S44 -> 24899.983 | U44: =IF(((((I44-B44)+(2*(O44-I44)))/3)+O44)>0,((((I44-B44)+(2*(O44-I44)))/3)+O44),O44) -> 25189.755 | V44: =IF(((((J44-C44)+(2*(P44-J44)))/3)+P44)>0,((((J44-C44)+(2*(P44-J44)))/3)+P44),P44) -> 1641.72 | W44: =IF(((((K44-D44)+(2*(Q44-K44)))/3)+Q44)>0,((((K44-D44)+(2*(Q44-K44)))/3)+Q44),Q44) -> 6750.0433 | X44: =IF(((((L44-E44)+(2*(R44-L44)))/3)+R44)>0,((((L44-E44)+(2*(R44-L44)))/3)+R44),R44) -> 0 | Y44: =IF(((((M44-F44)+(2*(S44-M44)))/3)+S44)>0,((((M44-F44)+(2*(S44-M44)))/3)+S44),S44) -> 51.118295 | Z44: =IF(((((N44-G44)+(2*(T44-N44)))/3)+T44)>0,((((N44-G44)+(2*(T44-N44)))/3)+T44),T44) -> 25138.637
A45: =[9]NamesDistrictCollegeCenter!B45 -> Mt. San Jacinto CCD | B45: 11828.49 | C45: 320.34 | D45: 271.38 | F45: 100.61 | G45: =B45-E45-F45 -> 11727.88 | I45: 10195.46 | J45: 367.36 | K45: 242.17 | M45: 79.69 | N45: =I45-L45-M45 -> 10115.77 | O45: 11454.47 | P45: 274.04 | Q45: 260.8 | R45: 0 | S45: 141.21 | T45: =O45-R45-S45 -> 11313.26 | U45: =IF(((((I45-B45)+(2*(O45-I45)))/3)+O45)>0,((((I45-B45)+(2*(O45-I45)))/3)+O45),O45) -> 11749.467 | V45: =IF(((((J45-C45)+(2*(P45-J45)))/3)+P45)>0,((((J45-C45)+(2*(P45-J45)))/3)+P45),P45) -> 227.5 | W45: =IF(((((K45-D45)+(2*(Q45-K45)))/3)+Q45)>0,((((K45-D45)+(2*(Q45-K45)))/3)+Q45),Q45) -> 263.48333 | X45: =IF(((((L45-E45)+(2*(R45-L45)))/3)+R45)>0,((((L45-E45)+(2*(R45-L45)))/3)+R45),R45) -> 0 | Y45: =IF(((((M45-F45)+(2*(S45-M45)))/3)+S45)>0,((((M45-F45)+(2*(S45-M45)))/3)+S45),S45) -> 175.25 | Z45: =IF(((((N45-G45)+(2*(T45-N45)))/3)+T45)>0,((((N45-G45)+(2*(T45-N45)))/3)+T45),T45) -> 11574.217
A46: =[9]NamesDistrictCollegeCenter!B46 -> Napa Valley CCD | B46: 4841 | C46: 453.46 | D46: 11.99 | F46: 129.39 | G46: =B46-E46-F46 -> 4711.61 | I46: 4749.63 | J46: 418.75 | K46: 5.77 | M46: 185.77 | N46: =I46-L46-M46 -> 4563.86 | O46: 4597.67 | P46: 418.75 | Q46: 5.77 | R46: 0 | S46: 143.47 | T46: =O46-R46-S46 -> 4454.2 | U46: =IF(((((I46-B46)+(2*(O46-I46)))/3)+O46)>0,((((I46-B46)+(2*(O46-I46)))/3)+O46),O46) -> 4465.9067 | V46: =IF(((((J46-C46)+(2*(P46-J46)))/3)+P46)>0,((((J46-C46)+(2*(P46-J46)))/3)+P46),P46) -> 407.18 | W46: =IF(((((K46-D46)+(2*(Q46-K46)))/3)+Q46)>0,((((K46-D46)+(2*(Q46-K46)))/3)+Q46),Q46) -> 3.6966667 | X46: =IF(((((L46-E46)+(2*(R46-L46)))/3)+R46)>0,((((L46-E46)+(2*(R46-L46)))/3)+R46),R46) -> 0 | Y46: =IF(((((M46-F46)+(2*(S46-M46)))/3)+S46)>0,((((M46-F46)+(2*(S46-M46)))/3)+S46),S46) -> 134.06333 | Z46: =IF(((((N46-G46)+(2*(T46-N46)))/3)+T46)>0,((((N46-G46)+(2*(T46-N46)))/3)+T46),T46) -> 4331.8433
A47: =[9]NamesDistrictCollegeCenter!B47 -> North Orange County CCD | B47: 32051.03 | C47: 2631.79 | D47: 2565.56 | F47: 263.71 | G47: =B47-E47-F47 -> 31787.32 | I47: 27208.32 | J47: 2573.57 | K47: 2664.91 | M47: 251.8 | N47: =I47-L47-M47 -> 26956.52 | O47: 28054.18 | P47: 4039.74 | Q47: 1066.14 | R47: 0 | S47: 504.2 | T47: =O47-R47-S47 -> 27549.98 | U47: =IF(((((I47-B47)+(2*(O47-I47)))/3)+O47)>0,((((I47-B47)+(2*(O47-I47)))/3)+O47),O47) -> 27003.85 | V47: =IF(((((J47-C47)+(2*(P47-J47)))/3)+P47)>0,((((J47-C47)+(2*(P47-J47)))/3)+P47),P47) -> 4997.78 | W47: =IF(((((K47-D47)+(2*(Q47-K47)))/3)+Q47)>0,((((K47-D47)+(2*(Q47-K47)))/3)+Q47),Q47) -> 33.41 | X47: =IF(((((L47-E47)+(2*(R47-L47)))/3)+R47)>0,((((L47-E47)+(2*(R47-L47)))/3)+R47),R47) -> 0 | Y47: =IF(((((M47-F47)+(2*(S47-M47)))/3)+S47)>0,((((M47-F47)+(2*(S47-M47)))/3)+S47),S47) -> 668.49667 | Z47: =IF(((((N47-G47)+(2*(T47-N47)))/3)+T47)>0,((((N47-G47)+(2*(T47-N47)))/3)+T47),T47) -> 26335.353
A48: =[9]NamesDistrictCollegeCenter!B48 -> Ohlone CCD | B48: 8239.9999 | C48: 0 | D48: 0 | F48: 1307.92 | G48: =B48-E48-F48 -> 6932.0799 | I48: 6833.46 | J48: 0 | K48: 0 | M48: 943.95 | N48: =I48-L48-M48 -> 5889.51 | O48: 7850.49 | P48: 0.03 | Q48: 1.48 | R48: 0 | S48: 492.6 | T48: =O48-R48-S48 -> 7357.89 | U48: =IF(((((I48-B48)+(2*(O48-I48)))/3)+O48)>0,((((I48-B48)+(2*(O48-I48)))/3)+O48),O48) -> 8059.6634 | V48: =IF(((((J48-C48)+(2*(P48-J48)))/3)+P48)>0,((((J48-C48)+(2*(P48-J48)))/3)+P48),P48) -> 0.05 | W48: =IF(((((K48-D48)+(2*(Q48-K48)))/3)+Q48)>0,((((K48-D48)+(2*(Q48-K48)))/3)+Q48),Q48) -> 2.4666667 | X48: =IF(((((L48-E48)+(2*(R48-L48)))/3)+R48)>0,((((L48-E48)+(2*(R48-L48)))/3)+R48),R48) -> 0 | Y48: =IF(((((M48-F48)+(2*(S48-M48)))/3)+S48)>0,((((M48-F48)+(2*(S48-M48)))/3)+S48),S48) -> 70.376667 | Z48: =IF(((((N48-G48)+(2*(T48-N48)))/3)+T48)>0,((((N48-G48)+(2*(T48-N48)))/3)+T48),T48) -> 7989.2867
A49: =[9]NamesDistrictCollegeCenter!B49 -> Palo Verde CCD | B49: 1957.93 | C49: 21.96 | D49: 115.11 | E49: 890.02 | F49: 58.77 | G49: =B49-E49-F49 -> 1009.14 | I49: 2051.5483 | J49: 12.51 | K49: 101.02 | L49: 816.79 | M49: 50.25 | N49: =I49-L49-M49 -> 1184.5083 | O49: 2067.14 | P49: 23.48 | Q49: 6.02 | R49: 723.94755 | S49: 0 | T49: =O49-R49-S49 -> 1343.1924 | U49: =IF(((((I49-B49)+(2*(O49-I49)))/3)+O49)>0,((((I49-B49)+(2*(O49-I49)))/3)+O49),O49) -> 2108.7406 | V49: =IF(((((J49-C49)+(2*(P49-J49)))/3)+P49)>0,((((J49-C49)+(2*(P49-J49)))/3)+P49),P49) -> 27.643333 | W49: =IF(((((K49-D49)+(2*(Q49-K49)))/3)+Q49)>0,((((K49-D49)+(2*(Q49-K49)))/3)+Q49),Q49) -> 6.02 | X49: =IF(((((L49-E49)+(2*(R49-L49)))/3)+R49)>0,((((L49-E49)+(2*(R49-L49)))/3)+R49),R49) -> 637.64259 | Y49: =IF(((((M49-F49)+(2*(S49-M49)))/3)+S49)>0,((((M49-F49)+(2*(S49-M49)))/3)+S49),S49) -> 0 | Z49: =IF(((((N49-G49)+(2*(T49-N49)))/3)+T49)>0,((((N49-G49)+(2*(T49-N49)))/3)+T49),T49) -> 1507.438
A50: =[9]NamesDistrictCollegeCenter!B50 -> Palomar CCD | B50: 17424.79 | C50: 289.81 | D50: 504.25 | F50: 453.88 | G50: =B50-E50-F50 -> 16970.91 | I50: 18449.84 | J50: 276.86 | K50: 422.24 | L50: 1.52 | M50: 522.44 | N50: =I50-L50-M50 -> 17925.88 | O50: 17225.78 | P50: 276.86 | Q50: 422.24 | R50: 13.22 | S50: 495 | T50: =O50-R50-S50 -> 16717.56 | U50: =IF(((((I50-B50)+(2*(O50-I50)))/3)+O50)>0,((((I50-B50)+(2*(O50-I50)))/3)+O50),O50) -> 16751.423 | V50: =IF(((((J50-C50)+(2*(P50-J50)))/3)+P50)>0,((((J50-C50)+(2*(P50-J50)))/3)+P50),P50) -> 272.54333 | W50: =IF(((((K50-D50)+(2*(Q50-K50)))/3)+Q50)>0,((((K50-D50)+(2*(Q50-K50)))/3)+Q50),Q50) -> 394.90333 | X50: =IF(((((L50-E50)+(2*(R50-L50)))/3)+R50)>0,((((L50-E50)+(2*(R50-L50)))/3)+R50),R50) -> 21.526667 | Y50: =IF(((((M50-F50)+(2*(S50-M50)))/3)+S50)>0,((((M50-F50)+(2*(S50-M50)))/3)+S50),S50) -> 499.56 | Z50: =IF(((((N50-G50)+(2*(T50-N50)))/3)+T50)>0,((((N50-G50)+(2*(T50-N50)))/3)+T50),T50) -> 16230.337
A51: =[9]NamesDistrictCollegeCenter!B51 -> Pasadena Area CCD | B51: 22765.3 | C51: 166.57 | D51: 1056.35 | F51: 252.26 | G51: =B51-E51-F51 -> 22513.04 | I51: 22801.97 | J51: 152.77 | K51: 1033.81 | M51: 206.91 | N51: =I51-L51-M51 -> 22595.06 | O51: 22816.07 | P51: 147.35621 | Q51: 943.76 | R51: 0 | S51: 264.18 | T51: =O51-R51-S51 -> 22551.89 | U51: =IF(((((I51-B51)+(2*(O51-I51)))/3)+O51)>0,((((I51-B51)+(2*(O51-I51)))/3)+O51),O51) -> 22837.693 | V51: =IF(((((J51-C51)+(2*(P51-J51)))/3)+P51)>0,((((J51-C51)+(2*(P51-J51)))/3)+P51),P51) -> 139.14701 | W51: =IF(((((K51-D51)+(2*(Q51-K51)))/3)+Q51)>0,((((K51-D51)+(2*(Q51-K51)))/3)+Q51),Q51) -> 876.21333 | X51: =IF(((((L51-E51)+(2*(R51-L51)))/3)+R51)>0,((((L51-E51)+(2*(R51-L51)))/3)+R51),R51) -> 0 | Y51: =IF(((((M51-F51)+(2*(S51-M51)))/3)+S51)>0,((((M51-F51)+(2*(S51-M51)))/3)+S51),S51) -> 287.24333 | Z51: =IF(((((N51-G51)+(2*(T51-N51)))/3)+T51)>0,((((N51-G51)+(2*(T51-N51)))/3)+T51),T51) -> 22550.45
A52: =[9]NamesDistrictCollegeCenter!B52 -> Peralta CCD | B52: 15624.75 | C52: 143.57 | D52: 0 | F52: 1093.24 | G52: =B52-E52-F52 -> 14531.51 | I52: 18684.53 | J52: 117.31 | K52: 0 | M52: 0 | N52: =I52-L52-M52 -> 18684.53 | O52: 16601.38 | P52: 117.31 | Q52: 0 | R52: 0 | S52: 881.32 | T52: =O52-R52-S52 -> 15720.06 | U52: =IF(((((I52-B52)+(2*(O52-I52)))/3)+O52)>0,((((I52-B52)+(2*(O52-I52)))/3)+O52),O52) -> 16232.54 | V52: =IF(((((J52-C52)+(2*(P52-J52)))/3)+P52)>0,((((J52-C52)+(2*(P52-J52)))/3)+P52),P52) -> 108.55667 | W52: =IF(((((K52-D52)+(2*(Q52-K52)))/3)+Q52)>0,((((K52-D52)+(2*(Q52-K52)))/3)+Q52),Q52) -> 0 | X52: =IF(((((L52-E52)+(2*(R52-L52)))/3)+R52)>0,((((L52-E52)+(2*(R52-L52)))/3)+R52),R52) -> 0 | Y52: =IF(((((M52-F52)+(2*(S52-M52)))/3)+S52)>0,((((M52-F52)+(2*(S52-M52)))/3)+S52),S52) -> 1104.4533 | Z52: =IF(((((N52-G52)+(2*(T52-N52)))/3)+T52)>0,((((N52-G52)+(2*(T52-N52)))/3)+T52),T52) -> 15128.087
A53: =[9]NamesDistrictCollegeCenter!B53 -> Rancho Santiago CCD | B53: 21499.15 | C53: 854.66 | D53: 5163.5 | E53: 6.72 | F53: 1944.53 | G53: =B53-E53-F53 -> 19547.9 | I53: 23301.943 | J53: 1092.28 | K53: 4981.71 | M53: 2196.94 | N53: =I53-L53-M53 -> 21105.003 | O53: 21492.12 | P53: 1092.28 | Q53: 4981.71 | R53: 0 | S53: 2583.27 | T53: =O53-R53-S53 -> 18908.85 | U53: =IF(((((I53-B53)+(2*(O53-I53)))/3)+O53)>0,((((I53-B53)+(2*(O53-I53)))/3)+O53),O53) -> 20886.502 | V53: =IF(((((J53-C53)+(2*(P53-J53)))/3)+P53)>0,((((J53-C53)+(2*(P53-J53)))/3)+P53),P53) -> 1171.4867 | W53: =IF(((((K53-D53)+(2*(Q53-K53)))/3)+Q53)>0,((((K53-D53)+(2*(Q53-K53)))/3)+Q53),Q53) -> 4921.1133 | X53: =IF(((((L53-E53)+(2*(R53-L53)))/3)+R53)>0,((((L53-E53)+(2*(R53-L53)))/3)+R53),R53) -> 0 | Y53: =IF(((((M53-F53)+(2*(S53-M53)))/3)+S53)>0,((((M53-F53)+(2*(S53-M53)))/3)+S53),S53) -> 2924.96 | Z53: =IF(((((N53-G53)+(2*(T53-N53)))/3)+T53)>0,((((N53-G53)+(2*(T53-N53)))/3)+T53),T53) -> 17963.782
A54: =[9]NamesDistrictCollegeCenter!B54 -> Redwoods CCD | B54: 3900.86 | C54: 31.84 | D54: 85.85 | F54: 209.78 | G54: =B54-E54-F54 -> 3691.08 | I54: 3477.45 | J54: 87 | K54: 83.5 | M54: 165.43 | N54: =I54-L54-M54 -> 3312.02 | O54: 3470.29 | P54: 89.19 | Q54: 65.18 | R54: 116.57 | S54: 190.75 | T54: =O54-R54-S54 -> 3162.97 | U54: =IF(((((I54-B54)+(2*(O54-I54)))/3)+O54)>0,((((I54-B54)+(2*(O54-I54)))/3)+O54),O54) -> 3324.38 | V54: =IF(((((J54-C54)+(2*(P54-J54)))/3)+P54)>0,((((J54-C54)+(2*(P54-J54)))/3)+P54),P54) -> 109.03667 | W54: =IF(((((K54-D54)+(2*(Q54-K54)))/3)+Q54)>0,((((K54-D54)+(2*(Q54-K54)))/3)+Q54),Q54) -> 52.183333 | X54: =IF(((((L54-E54)+(2*(R54-L54)))/3)+R54)>0,((((L54-E54)+(2*(R54-L54)))/3)+R54),R54) -> 194.28333 | Y54: =IF(((((M54-F54)+(2*(S54-M54)))/3)+S54)>0,((((M54-F54)+(2*(S54-M54)))/3)+S54),S54) -> 192.84667 | Z54: =IF(((((N54-G54)+(2*(T54-N54)))/3)+T54)>0,((((N54-G54)+(2*(T54-N54)))/3)+T54),T54) -> 2937.25
A55: =[9]NamesDistrictCollegeCenter!B55 -> Rio Hondo CCD | B55: 11122.72 | C55: 462.45 | D55: 34.29 | F55: 197.97 | G55: =B55-E55-F55 -> 10924.75 | I55: 12782.115 | J55: 452.83 | K55: 36.49 | M55: 442.48 | N55: =I55-L55-M55 -> 12339.635 | O55: 12504.11 | P55: 452.83 | Q55: 36.49 | R55: 0 | S55: 360.98 | T55: =O55-R55-S55 -> 12143.13 | U55: =IF(((((I55-B55)+(2*(O55-I55)))/3)+O55)>0,((((I55-B55)+(2*(O55-I55)))/3)+O55),O55) -> 12871.905 | V55: =IF(((((J55-C55)+(2*(P55-J55)))/3)+P55)>0,((((J55-C55)+(2*(P55-J55)))/3)+P55),P55) -> 449.62333 | W55: =IF(((((K55-D55)+(2*(Q55-K55)))/3)+Q55)>0,((((K55-D55)+(2*(Q55-K55)))/3)+Q55),Q55) -> 37.223333 | X55: =IF(((((L55-E55)+(2*(R55-L55)))/3)+R55)>0,((((L55-E55)+(2*(R55-L55)))/3)+R55),R55) -> 0 | Y55: =IF(((((M55-F55)+(2*(S55-M55)))/3)+S55)>0,((((M55-F55)+(2*(S55-M55)))/3)+S55),S55) -> 388.15 | Z55: =IF(((((N55-G55)+(2*(T55-N55)))/3)+T55)>0,((((N55-G55)+(2*(T55-N55)))/3)+T55),T55) -> 12483.755
A56: =[9]NamesDistrictCollegeCenter!B56 -> Riverside CCD | B56: 29578.89 | C56: 73.45 | D56: 0 | F56: 712.52 | G56: =B56-E56-F56 -> 28866.37 | I56: 30445.289 | J56: 82.07 | K56: 0 | L56: 34.91 | M56: 802.83 | N56: =I56-L56-M56 -> 29607.549 | O56: 29802.73 | P56: 145.31 | Q56: 0 | R56: 83 | S56: 850 | T56: =O56-R56-S56 -> 28869.73 | U56: =IF(((((I56-B56)+(2*(O56-I56)))/3)+O56)>0,((((I56-B56)+(2*(O56-I56)))/3)+O56),O56) -> 29663.157 | V56: =IF(((((J56-C56)+(2*(P56-J56)))/3)+P56)>0,((((J56-C56)+(2*(P56-J56)))/3)+P56),P56) -> 190.34333 | W56: =IF(((((K56-D56)+(2*(Q56-K56)))/3)+Q56)>0,((((K56-D56)+(2*(Q56-K56)))/3)+Q56),Q56) -> 0 | X56: =IF(((((L56-E56)+(2*(R56-L56)))/3)+R56)>0,((((L56-E56)+(2*(R56-L56)))/3)+R56),R56) -> 126.69667 | Y56: =IF(((((M56-F56)+(2*(S56-M56)))/3)+S56)>0,((((M56-F56)+(2*(S56-M56)))/3)+S56),S56) -> 911.55 | Z56: =IF(((((N56-G56)+(2*(T56-N56)))/3)+T56)>0,((((N56-G56)+(2*(T56-N56)))/3)+T56),T56) -> 28624.91
A57: =[9]NamesDistrictCollegeCenter!B57 -> San Bernardino CCD | B57: 14114.1 | C57: 139.13 | D57: 0 | F57: 117.7 | G57: =B57-E57-F57 -> 13996.4 | I57: 15066.39 | J57: 162.56999 | K57: 75.200007 | M57: 229.32 | N57: =I57-L57-M57 -> 14837.07 | O57: 15138.77 | P57: 294.24 | Q57: 46.34 | R57: 0 | S57: 348.40757 | T57: =O57-R57-S57 -> 14790.362 | U57: =IF(((((I57-B57)+(2*(O57-I57)))/3)+O57)>0,((((I57-B57)+(2*(O57-I57)))/3)+O57),O57) -> 15504.453 | V57: =IF(((((J57-C57)+(2*(P57-J57)))/3)+P57)>0,((((J57-C57)+(2*(P57-J57)))/3)+P57),P57) -> 389.83334 | W57: =IF(((((K57-D57)+(2*(Q57-K57)))/3)+Q57)>0,((((K57-D57)+(2*(Q57-K57)))/3)+Q57),Q57) -> 52.166664 | X57: =IF(((((L57-E57)+(2*(R57-L57)))/3)+R57)>0,((((L57-E57)+(2*(R57-L57)))/3)+R57),R57) -> 0 | Y57: =IF(((((M57-F57)+(2*(S57-M57)))/3)+S57)>0,((((M57-F57)+(2*(S57-M57)))/3)+S57),S57) -> 465.00595 | Z57: =IF(((((N57-G57)+(2*(T57-N57)))/3)+T57)>0,((((N57-G57)+(2*(T57-N57)))/3)+T57),T57) -> 15039.447
A58: =[9]NamesDistrictCollegeCenter!B58 -> San Diego CCD | B58: 34927.69 | C58: 2061.91 | D58: 6532.08 | F58: 630.18 | G58: =B58-E58-F58 -> 34297.51 | I58: 35115.99 | J58: 2049.9 | K58: 6114.81 | M58: 864.16 | N58: =I58-L58-M58 -> 34251.83 | O58: 32509.53 | P58: 2049.9 | Q58: 6114.81 | R58: 0 | S58: 992.19 | T58: =O58-R58-S58 -> 31517.34 | U58: =IF(((((I58-B58)+(2*(O58-I58)))/3)+O58)>0,((((I58-B58)+(2*(O58-I58)))/3)+O58),O58) -> 30834.657 | V58: =IF(((((J58-C58)+(2*(P58-J58)))/3)+P58)>0,((((J58-C58)+(2*(P58-J58)))/3)+P58),P58) -> 2045.8967 | W58: =IF(((((K58-D58)+(2*(Q58-K58)))/3)+Q58)>0,((((K58-D58)+(2*(Q58-K58)))/3)+Q58),Q58) -> 5975.72 | X58: =IF(((((L58-E58)+(2*(R58-L58)))/3)+R58)>0,((((L58-E58)+(2*(R58-L58)))/3)+R58),R58) -> 0 | Y58: =IF(((((M58-F58)+(2*(S58-M58)))/3)+S58)>0,((((M58-F58)+(2*(S58-M58)))/3)+S58),S58) -> 1155.5367 | Z58: =IF(((((N58-G58)+(2*(T58-N58)))/3)+T58)>0,((((N58-G58)+(2*(T58-N58)))/3)+T58),T58) -> 29679.12
A59: =[9]NamesDistrictCollegeCenter!B59 -> San Francisco CCD | B59: 14108.98 | C59: 1699.39 | D59: 4713.15 | E59: 3.59 | F59: 203.6 | G59: =B59-E59-F59 -> 13901.79 | I59: 16031.34 | J59: 1734.96 | K59: 4542.28 | L59: 7.68 | M59: 305.15 | N59: =I59-L59-M59 -> 15718.51 | O59: 16460.46 | P59: 1695.9583 | Q59: 4177.63 | R59: 19.91 | S59: 271.84 | T59: =O59-R59-S59 -> 16168.71 | U59: =IF(((((I59-B59)+(2*(O59-I59)))/3)+O59)>0,((((I59-B59)+(2*(O59-I59)))/3)+O59),O59) -> 17387.327 | V59: =IF(((((J59-C59)+(2*(P59-J59)))/3)+P59)>0,((((J59-C59)+(2*(P59-J59)))/3)+P59),P59) -> 1681.8138 | W59: =IF(((((K59-D59)+(2*(Q59-K59)))/3)+Q59)>0,((((K59-D59)+(2*(Q59-K59)))/3)+Q59),Q59) -> 3877.5733 | X59: =IF(((((L59-E59)+(2*(R59-L59)))/3)+R59)>0,((((L59-E59)+(2*(R59-L59)))/3)+R59),R59) -> 29.426667 | Y59: =IF(((((M59-F59)+(2*(S59-M59)))/3)+S59)>0,((((M59-F59)+(2*(S59-M59)))/3)+S59),S59) -> 283.48333 | Z59: =IF(((((N59-G59)+(2*(T59-N59)))/3)+T59)>0,((((N59-G59)+(2*(T59-N59)))/3)+T59),T59) -> 17074.417
A60: =[9]NamesDistrictCollegeCenter!B60 -> San Joaquin Delta CCD | B60: 13337.72 | C60: 175.49 | D60: 0 | F60: 425.5 | G60: =B60-E60-F60 -> 12912.22 | I60: 15729.64 | J60: 170.36 | K60: 0 | L60: 20.09 | M60: 481.3 | N60: =I60-L60-M60 -> 15228.25 | O60: 14732.93 | P60: 170.36 | Q60: 0 | R60: 13.44 | S60: 528.42 | T60: =O60-R60-S60 -> 14191.07 | U60: =IF(((((I60-B60)+(2*(O60-I60)))/3)+O60)>0,((((I60-B60)+(2*(O60-I60)))/3)+O60),O60) -> 14865.763 | V60: =IF(((((J60-C60)+(2*(P60-J60)))/3)+P60)>0,((((J60-C60)+(2*(P60-J60)))/3)+P60),P60) -> 168.65 | W60: =IF(((((K60-D60)+(2*(Q60-K60)))/3)+Q60)>0,((((K60-D60)+(2*(Q60-K60)))/3)+Q60),Q60) -> 0 | X60: =IF(((((L60-E60)+(2*(R60-L60)))/3)+R60)>0,((((L60-E60)+(2*(R60-L60)))/3)+R60),R60) -> 15.703333 | Y60: =IF(((((M60-F60)+(2*(S60-M60)))/3)+S60)>0,((((M60-F60)+(2*(S60-M60)))/3)+S60),S60) -> 578.43333 | Z60: =IF(((((N60-G60)+(2*(T60-N60)))/3)+T60)>0,((((N60-G60)+(2*(T60-N60)))/3)+T60),T60) -> 14271.627
A61: =[9]NamesDistrictCollegeCenter!B61 -> San Jose-Evergreen CCD | B61: 11234.88 | C61: 116.72 | D61: 0 | F61: 193.38 | G61: =B61-E61-F61 -> 11041.5 | I61: 11715.93 | J61: 197.11002 | K61: 0 | M61: 308.31 | N61: =I61-L61-M61 -> 11407.62 | O61: 12055.63 | P61: 213.42 | Q61: 0 | R61: 0 | S61: 262.19 | T61: =O61-R61-S61 -> 11793.44 | U61: =IF(((((I61-B61)+(2*(O61-I61)))/3)+O61)>0,((((I61-B61)+(2*(O61-I61)))/3)+O61),O61) -> 12442.447 | V61: =IF(((((J61-C61)+(2*(P61-J61)))/3)+P61)>0,((((J61-C61)+(2*(P61-J61)))/3)+P61),P61) -> 251.08999 | W61: =IF(((((K61-D61)+(2*(Q61-K61)))/3)+Q61)>0,((((K61-D61)+(2*(Q61-K61)))/3)+Q61),Q61) -> 0 | X61: =IF(((((L61-E61)+(2*(R61-L61)))/3)+R61)>0,((((L61-E61)+(2*(R61-L61)))/3)+R61),R61) -> 0 | Y61: =IF(((((M61-F61)+(2*(S61-M61)))/3)+S61)>0,((((M61-F61)+(2*(S61-M61)))/3)+S61),S61) -> 269.75333 | Z61: =IF(((((N61-G61)+(2*(T61-N61)))/3)+T61)>0,((((N61-G61)+(2*(T61-N61)))/3)+T61),T61) -> 12172.693
A62: =[9]NamesDistrictCollegeCenter!B62 -> San Luis Obispo County CCD | B62: 6739.42 | C62: 149.56 | D62: 239.43 | E62: 20.8 | F62: 562.09 | G62: =B62-E62-F62 -> 6156.53 | I62: 7933.11 | J62: 337.21 | K62: 161.71 | L62: 39.18 | M62: 769.85 | N62: =I62-L62-M62 -> 7124.08 | O62: 6801.35 | P62: 370.1 | Q62: 217.1 | R62: 110.22 | S62: 772.89 | T62: =O62-R62-S62 -> 5918.24 | U62: =IF(((((I62-B62)+(2*(O62-I62)))/3)+O62)>0,((((I62-B62)+(2*(O62-I62)))/3)+O62),O62) -> 6444.74 | V62: =IF(((((J62-C62)+(2*(P62-J62)))/3)+P62)>0,((((J62-C62)+(2*(P62-J62)))/3)+P62),P62) -> 454.57667 | W62: =IF(((((K62-D62)+(2*(Q62-K62)))/3)+Q62)>0,((((K62-D62)+(2*(Q62-K62)))/3)+Q62),Q62) -> 228.12 | X62: =IF(((((L62-E62)+(2*(R62-L62)))/3)+R62)>0,((((L62-E62)+(2*(R62-L62)))/3)+R62),R62) -> 163.70667 | Y62: =IF(((((M62-F62)+(2*(S62-M62)))/3)+S62)>0,((((M62-F62)+(2*(S62-M62)))/3)+S62),S62) -> 844.17 | Z62: =IF(((((N62-G62)+(2*(T62-N62)))/3)+T62)>0,((((N62-G62)+(2*(T62-N62)))/3)+T62),T62) -> 5436.8633
A63: =[9]NamesDistrictCollegeCenter!B63 -> San Mateo County CCD | B63: 16348.83 | C63: 57.88 | D63: 0 | E63: 4.6 | F63: 563.44 | G63: =B63-E63-F63 -> 15780.79 | I63: 15681 | J63: 41.48 | K63: 0 | M63: 847.58 | N63: =I63-L63-M63 -> 14833.42 | O63: 15232.02 | P63: 41.48 | Q63: 0 | R63: 3.26 | S63: 851.36 | T63: =O63-R63-S63 -> 14377.4 | U63: =IF(((((I63-B63)+(2*(O63-I63)))/3)+O63)>0,((((I63-B63)+(2*(O63-I63)))/3)+O63),O63) -> 14710.09 | V63: =IF(((((J63-C63)+(2*(P63-J63)))/3)+P63)>0,((((J63-C63)+(2*(P63-J63)))/3)+P63),P63) -> 36.013333 | W63: =IF(((((K63-D63)+(2*(Q63-K63)))/3)+Q63)>0,((((K63-D63)+(2*(Q63-K63)))/3)+Q63),Q63) -> 0 | X63: =IF(((((L63-E63)+(2*(R63-L63)))/3)+R63)>0,((((L63-E63)+(2*(R63-L63)))/3)+R63),R63) -> 3.9 | Y63: =IF(((((M63-F63)+(2*(S63-M63)))/3)+S63)>0,((((M63-F63)+(2*(S63-M63)))/3)+S63),S63) -> 948.59333 | Z63: =IF(((((N63-G63)+(2*(T63-N63)))/3)+T63)>0,((((N63-G63)+(2*(T63-N63)))/3)+T63),T63) -> 13757.597
A64: =[9]NamesDistrictCollegeCenter!B64 -> Santa Barbara CCD | B64: 11805.67 | C64: 2.74 | D64: 571.46 | F64: 709.7 | G64: =B64-E64-F64 -> 11095.97 | I64: 11660.82 | J64: 294.71 | K64: 489.98 | L64: 3.25 | M64: 726.33 | N64: =I64-L64-M64 -> 10931.24 | O64: 11437.29 | P64: 698.44 | Q64: 413.72 | R64: 4.05 | S64: 357.25 | T64: =O64-R64-S64 -> 11075.99 | U64: =IF(((((I64-B64)+(2*(O64-I64)))/3)+O64)>0,((((I64-B64)+(2*(O64-I64)))/3)+O64),O64) -> 11239.987 | V64: =IF(((((J64-C64)+(2*(P64-J64)))/3)+P64)>0,((((J64-C64)+(2*(P64-J64)))/3)+P64),P64) -> 1064.9167 | W64: =IF(((((K64-D64)+(2*(Q64-K64)))/3)+Q64)>0,((((K64-D64)+(2*(Q64-K64)))/3)+Q64),Q64) -> 335.72 | X64: =IF(((((L64-E64)+(2*(R64-L64)))/3)+R64)>0,((((L64-E64)+(2*(R64-L64)))/3)+R64),R64) -> 5.6666667 | Y64: =IF(((((M64-F64)+(2*(S64-M64)))/3)+S64)>0,((((M64-F64)+(2*(S64-M64)))/3)+S64),S64) -> 116.74 | Z64: =IF(((((N64-G64)+(2*(T64-N64)))/3)+T64)>0,((((N64-G64)+(2*(T64-N64)))/3)+T64),T64) -> 11117.58
A65: =[9]NamesDistrictCollegeCenter!B65 -> Santa Clarita CCD | B65: 16098.7 | C65: 221.52 | D65: 123.86 | E65: 2.39 | F65: 675.23 | G65: =B65-E65-F65 -> 15421.08 | I65: 16308.519 | J65: 237.74 | K65: 167 | L65: 27.8 | M65: 983.67 | N65: =I65-L65-M65 -> 15297.049 | O65: 15732.13 | P65: 237.74 | Q65: 167 | R65: 22.73 | S65: 840.5 | T65: =O65-R65-S65 -> 14868.9 | U65: =IF(((((I65-B65)+(2*(O65-I65)))/3)+O65)>0,((((I65-B65)+(2*(O65-I65)))/3)+O65),O65) -> 15417.81 | V65: =IF(((((J65-C65)+(2*(P65-J65)))/3)+P65)>0,((((J65-C65)+(2*(P65-J65)))/3)+P65),P65) -> 243.14667 | W65: =IF(((((K65-D65)+(2*(Q65-K65)))/3)+Q65)>0,((((K65-D65)+(2*(Q65-K65)))/3)+Q65),Q65) -> 181.38 | X65: =IF(((((L65-E65)+(2*(R65-L65)))/3)+R65)>0,((((L65-E65)+(2*(R65-L65)))/3)+R65),R65) -> 27.82 | Y65: =IF(((((M65-F65)+(2*(S65-M65)))/3)+S65)>0,((((M65-F65)+(2*(S65-M65)))/3)+S65),S65) -> 847.86667 | Z65: =IF(((((N65-G65)+(2*(T65-N65)))/3)+T65)>0,((((N65-G65)+(2*(T65-N65)))/3)+T65),T65) -> 14542.124
A66: =[9]NamesDistrictCollegeCenter!B66 -> Santa Monica CCD | B66: 22257.88 | C66: 584.5 | D66: 167.47 | F66: 247.18 | G66: =B66-E66-F66 -> 22010.7 | I66: 17871.4 | J66: 599.81 | K66: 157.57 | M66: 273.43 | N66: =I66-L66-M66 -> 17597.97 | O66: 19636.32 | P66: 622.78 | Q66: 119.98 | R66: 0 | S66: 263.9 | T66: =O66-R66-S66 -> 19372.42 | U66: =IF(((((I66-B66)+(2*(O66-I66)))/3)+O66)>0,((((I66-B66)+(2*(O66-I66)))/3)+O66),O66) -> 19350.773 | V66: =IF(((((J66-C66)+(2*(P66-J66)))/3)+P66)>0,((((J66-C66)+(2*(P66-J66)))/3)+P66),P66) -> 643.19667 | W66: =IF(((((K66-D66)+(2*(Q66-K66)))/3)+Q66)>0,((((K66-D66)+(2*(Q66-K66)))/3)+Q66),Q66) -> 91.62 | X66: =IF(((((L66-E66)+(2*(R66-L66)))/3)+R66)>0,((((L66-E66)+(2*(R66-L66)))/3)+R66),R66) -> 0 | Y66: =IF(((((M66-F66)+(2*(S66-M66)))/3)+S66)>0,((((M66-F66)+(2*(S66-M66)))/3)+S66),S66) -> 266.29667 | Z66: =IF(((((N66-G66)+(2*(T66-N66)))/3)+T66)>0,((((N66-G66)+(2*(T66-N66)))/3)+T66),T66) -> 19084.477
A67: =[9]NamesDistrictCollegeCenter!B67 -> Sequoias CCD | B67: 9141.48 | C67: 392.17 | D67: 166.56 | F67: 335.52 | G67: =B67-E67-F67 -> 8805.96 | I67: 9685.2527 | J67: 472.08 | K67: 173.46 | M67: 443.21 | N67: =I67-L67-M67 -> 9242.0427 | O67: 9707.5 | P67: 344.8 | Q67: 109.19 | R67: 0 | S67: 465.38 | T67: =O67-R67-S67 -> 9242.12 | U67: =IF(((((I67-B67)+(2*(O67-I67)))/3)+O67)>0,((((I67-B67)+(2*(O67-I67)))/3)+O67),O67) -> 9903.5891 | V67: =IF(((((J67-C67)+(2*(P67-J67)))/3)+P67)>0,((((J67-C67)+(2*(P67-J67)))/3)+P67),P67) -> 286.58333 | W67: =IF(((((K67-D67)+(2*(Q67-K67)))/3)+Q67)>0,((((K67-D67)+(2*(Q67-K67)))/3)+Q67),Q67) -> 68.643333 | X67: =IF(((((L67-E67)+(2*(R67-L67)))/3)+R67)>0,((((L67-E67)+(2*(R67-L67)))/3)+R67),R67) -> 0 | Y67: =IF(((((M67-F67)+(2*(S67-M67)))/3)+S67)>0,((((M67-F67)+(2*(S67-M67)))/3)+S67),S67) -> 516.05667 | Z67: =IF(((((N67-G67)+(2*(T67-N67)))/3)+T67)>0,((((N67-G67)+(2*(T67-N67)))/3)+T67),T67) -> 9387.5324
A68: =[9]NamesDistrictCollegeCenter!B68 -> Shasta-Tehama-Trinity CCD | B68: 7040.1499 | C68: 148.21 | D68: 34.7 | F68: 627.39 | G68: =B68-E68-F68 -> 6412.7599 | I68: 6089.47 | J68: 135.31 | K68: 32.81 | M68: 701.11 | N68: =I68-L68-M68 -> 5388.36 | O68: 7053.81 | P68: 125.16 | Q68: 19.22 | R68: 0.86 | S68: 729.55357 | T68: =O68-R68-S68 -> 6323.3964 | U68: =IF(((((I68-B68)+(2*(O68-I68)))/3)+O68)>0,((((I68-B68)+(2*(O68-I68)))/3)+O68),O68) -> 7379.81 | V68: =IF(((((J68-C68)+(2*(P68-J68)))/3)+P68)>0,((((J68-C68)+(2*(P68-J68)))/3)+P68),P68) -> 114.09333 | W68: =IF(((((K68-D68)+(2*(Q68-K68)))/3)+Q68)>0,((((K68-D68)+(2*(Q68-K68)))/3)+Q68),Q68) -> 9.53 | X68: =IF(((((L68-E68)+(2*(R68-L68)))/3)+R68)>0,((((L68-E68)+(2*(R68-L68)))/3)+R68),R68) -> 1.4333333 | Y68: =IF(((((M68-F68)+(2*(S68-M68)))/3)+S68)>0,((((M68-F68)+(2*(S68-M68)))/3)+S68),S68) -> 773.08928 | Z68: =IF(((((N68-G68)+(2*(T68-N68)))/3)+T68)>0,((((N68-G68)+(2*(T68-N68)))/3)+T68),T68) -> 6605.2874
A69: =[9]NamesDistrictCollegeCenter!B69 -> Sierra Joint CCD | B69: 12366.82 | C69: 274.82 | D69: 0 | F69: 214.52 | G69: =B69-E69-F69 -> 12152.3 | I69: 14916.48 | J69: 308.75 | K69: 0 | M69: 407.66 | N69: =I69-L69-M69 -> 14508.82 | O69: 12537.92 | P69: 345.66 | Q69: 7.7 | R69: 0 | S69: 423.71 | T69: =O69-R69-S69 -> 12114.21 | U69: =IF(((((I69-B69)+(2*(O69-I69)))/3)+O69)>0,((((I69-B69)+(2*(O69-I69)))/3)+O69),O69) -> 11802.1 | V69: =IF(((((J69-C69)+(2*(P69-J69)))/3)+P69)>0,((((J69-C69)+(2*(P69-J69)))/3)+P69),P69) -> 381.57667 | W69: =IF(((((K69-D69)+(2*(Q69-K69)))/3)+Q69)>0,((((K69-D69)+(2*(Q69-K69)))/3)+Q69),Q69) -> 12.833333 | X69: =IF(((((L69-E69)+(2*(R69-L69)))/3)+R69)>0,((((L69-E69)+(2*(R69-L69)))/3)+R69),R69) -> 0 | Y69: =IF(((((M69-F69)+(2*(S69-M69)))/3)+S69)>0,((((M69-F69)+(2*(S69-M69)))/3)+S69),S69) -> 498.79 | Z69: =IF(((((N69-G69)+(2*(T69-N69)))/3)+T69)>0,((((N69-G69)+(2*(T69-N69)))/3)+T69),T69) -> 11303.31
A70: =[9]NamesDistrictCollegeCenter!B70 -> Siskiyou Joint CCD | B70: 1935.64 | C70: 58.11 | D70: 505.14 | F70: 94.43 | G70: =B70-E70-F70 -> 1841.21 | I70: 1780.34 | J70: 80.46 | K70: 592.54 | M70: 88.75 | N70: =I70-L70-M70 -> 1691.59 | O70: 1421.93 | P70: 102.14 | Q70: 679.83 | R70: 0 | S70: 64.04 | T70: =O70-R70-S70 -> 1357.89 | U70: =IF(((((I70-B70)+(2*(O70-I70)))/3)+O70)>0,((((I70-B70)+(2*(O70-I70)))/3)+O70),O70) -> 1131.2233 | V70: =IF(((((J70-C70)+(2*(P70-J70)))/3)+P70)>0,((((J70-C70)+(2*(P70-J70)))/3)+P70),P70) -> 124.04333 | W70: =IF(((((K70-D70)+(2*(Q70-K70)))/3)+Q70)>0,((((K70-D70)+(2*(Q70-K70)))/3)+Q70),Q70) -> 767.15667 | X70: =IF(((((L70-E70)+(2*(R70-L70)))/3)+R70)>0,((((L70-E70)+(2*(R70-L70)))/3)+R70),R70) -> 0 | Y70: =IF(((((M70-F70)+(2*(S70-M70)))/3)+S70)>0,((((M70-F70)+(2*(S70-M70)))/3)+S70),S70) -> 45.673333 | Z70: =IF(((((N70-G70)+(2*(T70-N70)))/3)+T70)>0,((((N70-G70)+(2*(T70-N70)))/3)+T70),T70) -> 1085.55
A71: =[9]NamesDistrictCollegeCenter!B71 -> Solano CCD | B71: 6447.52 | C71: 37.48 | D71: 0 | E71: 91.04 | F71: 266.87 | G71: =B71-E71-F71 -> 6089.61 | I71: 7907.27 | J71: 79.639884 | K71: 0 | L71: 74.87 | M71: 476.15 | N71: =I71-L71-M71 -> 7356.25 | O71: 6150.89 | P71: 79.639884 | Q71: 0 | R71: 81.77 | S71: 330.38 | T71: =O71-R71-S71 -> 5738.74 | U71: =IF(((((I71-B71)+(2*(O71-I71)))/3)+O71)>0,((((I71-B71)+(2*(O71-I71)))/3)+O71),O71) -> 5466.5533 | V71: =IF(((((J71-C71)+(2*(P71-J71)))/3)+P71)>0,((((J71-C71)+(2*(P71-J71)))/3)+P71),P71) -> 93.693179 | W71: =IF(((((K71-D71)+(2*(Q71-K71)))/3)+Q71)>0,((((K71-D71)+(2*(Q71-K71)))/3)+Q71),Q71) -> 0 | X71: =IF(((((L71-E71)+(2*(R71-L71)))/3)+R71)>0,((((L71-E71)+(2*(R71-L71)))/3)+R71),R71) -> 80.98 | Y71: =IF(((((M71-F71)+(2*(S71-M71)))/3)+S71)>0,((((M71-F71)+(2*(S71-M71)))/3)+S71),S71) -> 302.96 | Z71: =IF(((((N71-G71)+(2*(T71-N71)))/3)+T71)>0,((((N71-G71)+(2*(T71-N71)))/3)+T71),T71) -> 5082.6133
A72: =[9]NamesDistrictCollegeCenter!B72 -> Sonoma County CCD | B72: 13615.21 | C72: 2409.28 | D72: 567.7 | E72: 4.75 | F72: 418.19 | G72: =B72-E72-F72 -> 13192.27 | I72: 16040.47 | J72: 2860.3 | K72: 550.23 | L72: 2.59 | M72: 523.81 | N72: =I72-L72-M72 -> 15514.07 | O72: 16239 | P72: 2574 | Q72: 638 | R72: 10.1 | S72: 508.41 | T72: =O72-R72-S72 -> 15720.49 | U72: =IF(((((I72-B72)+(2*(O72-I72)))/3)+O72)>0,((((I72-B72)+(2*(O72-I72)))/3)+O72),O72) -> 17179.773 | V72: =IF(((((J72-C72)+(2*(P72-J72)))/3)+P72)>0,((((J72-C72)+(2*(P72-J72)))/3)+P72),P72) -> 2533.4733 | W72: =IF(((((K72-D72)+(2*(Q72-K72)))/3)+Q72)>0,((((K72-D72)+(2*(Q72-K72)))/3)+Q72),Q72) -> 690.69 | X72: =IF(((((L72-E72)+(2*(R72-L72)))/3)+R72)>0,((((L72-E72)+(2*(R72-L72)))/3)+R72),R72) -> 14.386667 | Y72: =IF(((((M72-F72)+(2*(S72-M72)))/3)+S72)>0,((((M72-F72)+(2*(S72-M72)))/3)+S72),S72) -> 533.35 | Z72: =IF(((((N72-G72)+(2*(T72-N72)))/3)+T72)>0,((((N72-G72)+(2*(T72-N72)))/3)+T72),T72) -> 16632.037
A73: =[9]NamesDistrictCollegeCenter!B73 -> South Orange County CCD | B73: 24706.37 | C73: 2243.0898 | D73: 415.98 | F73: 593.07 | G73: =B73-E73-F73 -> 24113.3 | I73: 23956.44 | J73: 2042.12 | K73: 977.03 | M73: 693.52 | N73: =I73-L73-M73 -> 23262.92 | O73: 23248.43 | P73: 2104.67 | Q73: 1070.21 | R73: 0 | S73: 750.08 | T73: =O73-R73-S73 -> 22498.35 | U73: =IF(((((I73-B73)+(2*(O73-I73)))/3)+O73)>0,((((I73-B73)+(2*(O73-I73)))/3)+O73),O73) -> 22526.447 | V73: =IF(((((J73-C73)+(2*(P73-J73)))/3)+P73)>0,((((J73-C73)+(2*(P73-J73)))/3)+P73),P73) -> 2079.3801 | W73: =IF(((((K73-D73)+(2*(Q73-K73)))/3)+Q73)>0,((((K73-D73)+(2*(Q73-K73)))/3)+Q73),Q73) -> 1319.3467 | X73: =IF(((((L73-E73)+(2*(R73-L73)))/3)+R73)>0,((((L73-E73)+(2*(R73-L73)))/3)+R73),R73) -> 0 | Y73: =IF(((((M73-F73)+(2*(S73-M73)))/3)+S73)>0,((((M73-F73)+(2*(S73-M73)))/3)+S73),S73) -> 821.27 | Z73: =IF(((((N73-G73)+(2*(T73-N73)))/3)+T73)>0,((((N73-G73)+(2*(T73-N73)))/3)+T73),T73) -> 21705.177
A74: =[9]NamesDistrictCollegeCenter!B74 -> Southwestern CCD | B74: 15625.79 | C74: 212.31 | D74: 38.97 | E74: 28.75 | F74: 154.74 | G74: =B74-E74-F74 -> 15442.3 | I74: 13083.04 | J74: 196.28 | K74: 38.4 | L74: 72.45 | M74: 232.12 | N74: =I74-L74-M74 -> 12778.47 | O74: 14539.77 | P74: 252.74 | Q74: 21.97 | R74: 62.87 | S74: 232.12 | T74: =O74-R74-S74 -> 14244.78 | U74: =IF(((((I74-B74)+(2*(O74-I74)))/3)+O74)>0,((((I74-B74)+(2*(O74-I74)))/3)+O74),O74) -> 14663.34 | V74: =IF(((((J74-C74)+(2*(P74-J74)))/3)+P74)>0,((((J74-C74)+(2*(P74-J74)))/3)+P74),P74) -> 285.03667 | W74: =IF(((((K74-D74)+(2*(Q74-K74)))/3)+Q74)>0,((((K74-D74)+(2*(Q74-K74)))/3)+Q74),Q74) -> 10.826667 | X74: =IF(((((L74-E74)+(2*(R74-L74)))/3)+R74)>0,((((L74-E74)+(2*(R74-L74)))/3)+R74),R74) -> 71.05 | Y74: =IF(((((M74-F74)+(2*(S74-M74)))/3)+S74)>0,((((M74-F74)+(2*(S74-M74)))/3)+S74),S74) -> 257.91333 | Z74: =IF(((((N74-G74)+(2*(T74-N74)))/3)+T74)>0,((((N74-G74)+(2*(T74-N74)))/3)+T74),T74) -> 14334.377
A75: =[9]NamesDistrictCollegeCenter!B75 -> State Center CCD | B75: 26963.42 | C75: 231 | D75: 129.6 | F75: 951.28 | G75: =B75-E75-F75 -> 26012.14 | I75: 31058.822 | J75: 310.1 | K75: 171.51 | M75: 1450.43 | N75: =I75-L75-M75 -> 29608.392 | O75: 29862.79 | P75: 310.1 | Q75: 171.51 | R75: 0 | S75: 1651.08 | T75: =O75-R75-S75 -> 28211.71 | U75: =IF(((((I75-B75)+(2*(O75-I75)))/3)+O75)>0,((((I75-B75)+(2*(O75-I75)))/3)+O75),O75) -> 30430.569 | V75: =IF(((((J75-C75)+(2*(P75-J75)))/3)+P75)>0,((((J75-C75)+(2*(P75-J75)))/3)+P75),P75) -> 336.46667 | W75: =IF(((((K75-D75)+(2*(Q75-K75)))/3)+Q75)>0,((((K75-D75)+(2*(Q75-K75)))/3)+Q75),Q75) -> 185.48 | X75: =IF(((((L75-E75)+(2*(R75-L75)))/3)+R75)>0,((((L75-E75)+(2*(R75-L75)))/3)+R75),R75) -> 0 | Y75: =IF(((((M75-F75)+(2*(S75-M75)))/3)+S75)>0,((((M75-F75)+(2*(S75-M75)))/3)+S75),S75) -> 1951.23 | Z75: =IF(((((N75-G75)+(2*(T75-N75)))/3)+T75)>0,((((N75-G75)+(2*(T75-N75)))/3)+T75),T75) -> 28479.339
A76: =[9]NamesDistrictCollegeCenter!B76 -> Ventura County CCD | B76: 25334.64 | C76: 72.23 | D76: 0 | F76: 592.75 | G76: =B76-E76-F76 -> 24741.89 | I76: 26548.328 | J76: 116.97 | K76: 1.69 | M76: 749.34 | N76: =I76-L76-M76 -> 25798.988 | O76: 24971.89 | P76: 113.95 | Q76: 3.65 | R76: 4.76 | S76: 1568.5 | T76: =O76-R76-S76 -> 23398.63 | U76: =IF(((((I76-B76)+(2*(O76-I76)))/3)+O76)>0,((((I76-B76)+(2*(O76-I76)))/3)+O76),O76) -> 24325.494 | V76: =IF(((((J76-C76)+(2*(P76-J76)))/3)+P76)>0,((((J76-C76)+(2*(P76-J76)))/3)+P76),P76) -> 126.85 | W76: =IF(((((K76-D76)+(2*(Q76-K76)))/3)+Q76)>0,((((K76-D76)+(2*(Q76-K76)))/3)+Q76),Q76) -> 5.52 | X76: =IF(((((L76-E76)+(2*(R76-L76)))/3)+R76)>0,((((L76-E76)+(2*(R76-L76)))/3)+R76),R76) -> 7.9333333 | Y76: =IF(((((M76-F76)+(2*(S76-M76)))/3)+S76)>0,((((M76-F76)+(2*(S76-M76)))/3)+S76),S76) -> 2166.8033 | Z76: =IF(((((N76-G76)+(2*(T76-N76)))/3)+T76)>0,((((N76-G76)+(2*(T76-N76)))/3)+T76),T76) -> 22150.757
A77: =[9]NamesDistrictCollegeCenter!B77 -> Victor Valley CCD | B77: 9420.2099 | C77: 54.72 | D77: 0 | F77: 994.72 | G77: =B77-E77-F77 -> 8425.4899 | I77: 9561.0414 | J77: 79.12 | K77: 0 | M77: 560.21 | N77: =I77-L77-M77 -> 9000.8314 | O77: 9596.02 | P77: 57.68 | Q77: 0 | R77: 0 | S77: 372.01 | T77: =O77-R77-S77 -> 9224.01 | U77: =IF(((((I77-B77)+(2*(O77-I77)))/3)+O77)>0,((((I77-B77)+(2*(O77-I77)))/3)+O77),O77) -> 9666.2829 | V77: =IF(((((J77-C77)+(2*(P77-J77)))/3)+P77)>0,((((J77-C77)+(2*(P77-J77)))/3)+P77),P77) -> 51.52 | W77: =IF(((((K77-D77)+(2*(Q77-K77)))/3)+Q77)>0,((((K77-D77)+(2*(Q77-K77)))/3)+Q77),Q77) -> 0 | X77: =IF(((((L77-E77)+(2*(R77-L77)))/3)+R77)>0,((((L77-E77)+(2*(R77-L77)))/3)+R77),R77) -> 0 | Y77: =IF(((((M77-F77)+(2*(S77-M77)))/3)+S77)>0,((((M77-F77)+(2*(S77-M77)))/3)+S77),S77) -> 101.70667 | Z77: =IF(((((N77-G77)+(2*(T77-N77)))/3)+T77)>0,((((N77-G77)+(2*(T77-N77)))/3)+T77),T77) -> 9564.5762
A78: =[9]NamesDistrictCollegeCenter!B78 -> West Hills CCD | B78: 5148.6799 | C78: 351.55 | D78: 0 | F78: 340.41 | G78: =B78-E78-F78 -> 4808.2699 | I78: 5384.0108 | J78: 363.35 | K78: 0 | L78: 44.49 | M78: 512.37 | N78: =I78-L78-M78 -> 4827.1508 | O78: 5791.4 | P78: 319.88 | Q78: 0 | R78: 148.04 | S78: 316.95987 | T78: =O78-R78-S78 -> 5326.4001 | U78: =IF(((((I78-B78)+(2*(O78-I78)))/3)+O78)>0,((((I78-B78)+(2*(O78-I78)))/3)+O78),O78) -> 6141.4364 | V78: =IF(((((J78-C78)+(2*(P78-J78)))/3)+P78)>0,((((J78-C78)+(2*(P78-J78)))/3)+P78),P78) -> 294.83333 | W78: =IF(((((K78-D78)+(2*(Q78-K78)))/3)+Q78)>0,((((K78-D78)+(2*(Q78-K78)))/3)+Q78),Q78) -> 0 | X78: =IF(((((L78-E78)+(2*(R78-L78)))/3)+R78)>0,((((L78-E78)+(2*(R78-L78)))/3)+R78),R78) -> 231.90333 | Y78: =IF(((((M78-F78)+(2*(S78-M78)))/3)+S78)>0,((((M78-F78)+(2*(S78-M78)))/3)+S78),S78) -> 244.00646 | Z78: =IF(((((N78-G78)+(2*(T78-N78)))/3)+T78)>0,((((N78-G78)+(2*(T78-N78)))/3)+T78),T78) -> 5665.5266
A79: =[9]NamesDistrictCollegeCenter!B79 -> West Kern CCD | B79: 2609.5801 | C79: 31.34 | D79: 0 | E79: 58.7 | F79: 17.57 | G79: =B79-E79-F79 -> 2533.3101 | I79: 2827.0942 | J79: 0.42 | K79: 0 | L79: 44.04 | M79: 17.42 | N79: =I79-L79-M79 -> 2765.6342 | O79: 2909.06 | P79: 0 | Q79: 0 | R79: 50.127583 | S79: 0 | T79: =O79-R79-S79 -> 2858.9324 | U79: =IF(((((I79-B79)+(2*(O79-I79)))/3)+O79)>0,((((I79-B79)+(2*(O79-I79)))/3)+O79),O79) -> 3036.2086 | V79: =IF(((((J79-C79)+(2*(P79-J79)))/3)+P79)>0,((((J79-C79)+(2*(P79-J79)))/3)+P79),P79) -> 0 | W79: =IF(((((K79-D79)+(2*(Q79-K79)))/3)+Q79)>0,((((K79-D79)+(2*(Q79-K79)))/3)+Q79),Q79) -> 0 | X79: =IF(((((L79-E79)+(2*(R79-L79)))/3)+R79)>0,((((L79-E79)+(2*(R79-L79)))/3)+R79),R79) -> 49.299305 | Y79: =IF(((((M79-F79)+(2*(S79-M79)))/3)+S79)>0,((((M79-F79)+(2*(S79-M79)))/3)+S79),S79) -> 0 | Z79: =IF(((((N79-G79)+(2*(T79-N79)))/3)+T79)>0,((((N79-G79)+(2*(T79-N79)))/3)+T79),T79) -> 2998.5726
A80: =[9]NamesDistrictCollegeCenter!B80 -> West Valley-Mission CCD | B80: 11784.29 | C80: 1030.44 | D80: 0 | F80: 293.69 | G80: =B80-E80-F80 -> 11490.6 | I80: 11473.35 | J80: 1198.99 | K80: 0 | L80: 0.87 | M80: 497.63 | N80: =I80-L80-M80 -> 10974.85 | O80: 10022.19 | P80: 1198.99 | Q80: 3.8018211 | R80: 0 | S80: 410.43 | T80: =O80-R80-S80 -> 9611.76 | U80: =IF(((((I80-B80)+(2*(O80-I80)))/3)+O80)>0,((((I80-B80)+(2*(O80-I80)))/3)+O80),O80) -> 8951.1033 | V80: =IF(((((J80-C80)+(2*(P80-J80)))/3)+P80)>0,((((J80-C80)+(2*(P80-J80)))/3)+P80),P80) -> 1255.1733 | W80: =IF(((((K80-D80)+(2*(Q80-K80)))/3)+Q80)>0,((((K80-D80)+(2*(Q80-K80)))/3)+Q80),Q80) -> 6.3363685 | X80: =IF(((((L80-E80)+(2*(R80-L80)))/3)+R80)>0,((((L80-E80)+(2*(R80-L80)))/3)+R80),R80) -> 0 | Y80: =IF(((((M80-F80)+(2*(S80-M80)))/3)+S80)>0,((((M80-F80)+(2*(S80-M80)))/3)+S80),S80) -> 420.27667 | Z80: =IF(((((N80-G80)+(2*(T80-N80)))/3)+T80)>0,((((N80-G80)+(2*(T80-N80)))/3)+T80),T80) -> 8531.1167
A81: =[9]NamesDistrictCollegeCenter!B81 -> Yosemite CCD | B81: 15038.76 | C81: 203.33 | D81: 186.56 | E81: 32.37 | F81: 209.8 | G81: =B81-E81-F81 -> 14796.59 | I81: 16104.27 | J81: 238.45011 | K81: 233.61 | L81: 76.53 | M81: 282.12 | N81: =I81-L81-M81 -> 15745.62 | O81: 15515.44 | P81: 275.23 | Q81: 256.14 | R81: 89.13 | S81: 313.32 | T81: =O81-R81-S81 -> 15112.99 | U81: =IF(((((I81-B81)+(2*(O81-I81)))/3)+O81)>0,((((I81-B81)+(2*(O81-I81)))/3)+O81),O81) -> 15478.057 | V81: =IF(((((J81-C81)+(2*(P81-J81)))/3)+P81)>0,((((J81-C81)+(2*(P81-J81)))/3)+P81),P81) -> 311.45663 | W81: =IF(((((K81-D81)+(2*(Q81-K81)))/3)+Q81)>0,((((K81-D81)+(2*(Q81-K81)))/3)+Q81),Q81) -> 286.84333 | X81: =IF(((((L81-E81)+(2*(R81-L81)))/3)+R81)>0,((((L81-E81)+(2*(R81-L81)))/3)+R81),R81) -> 112.25 | Y81: =IF(((((M81-F81)+(2*(S81-M81)))/3)+S81)>0,((((M81-F81)+(2*(S81-M81)))/3)+S81),S81) -> 358.22667 | Z81: =IF(((((N81-G81)+(2*(T81-N81)))/3)+T81)>0,((((N81-G81)+(2*(T81-N81)))/3)+T81),T81) -> 15007.58
A82: =[9]NamesDistrictCollegeCenter!B82 -> Yuba CCD | B82: 7446.38 | C82: 179.63 | D82: 0 | F82: 339.94 | G82: =B82-E82-F82 -> 7106.44 | I82: 7424.91 | J82: 197.27 | K82: 3.82 | M82: 397.51 | N82: =I82-L82-M82 -> 7027.4 | O82: 7477.98 | P82: 145.92 | Q82: 2.1 | R82: 0 | S82: 211.55792 | T82: =O82-R82-S82 -> 7266.4221 | U82: =IF(((((I82-B82)+(2*(O82-I82)))/3)+O82)>0,((((I82-B82)+(2*(O82-I82)))/3)+O82),O82) -> 7506.2033 | V82: =IF(((((J82-C82)+(2*(P82-J82)))/3)+P82)>0,((((J82-C82)+(2*(P82-J82)))/3)+P82),P82) -> 117.56667 | W82: =IF(((((K82-D82)+(2*(Q82-K82)))/3)+Q82)>0,((((K82-D82)+(2*(Q82-K82)))/3)+Q82),Q82) -> 2.2266667 | X82: =IF(((((L82-E82)+(2*(R82-L82)))/3)+R82)>0,((((L82-E82)+(2*(R82-L82)))/3)+R82),R82) -> 0 | Y82: =IF(((((M82-F82)+(2*(S82-M82)))/3)+S82)>0,((((M82-F82)+(2*(S82-M82)))/3)+S82),S82) -> 106.77986 | Z82: =IF(((((N82-G82)+(2*(T82-N82)))/3)+T82)>0,((((N82-G82)+(2*(T82-N82)))/3)+T82),T82) -> 7399.4235
A83: zzzTotals | B83: =SUM(B11:B82) -> 1055591.8 | C83: =SUM(C11:C82) -> 29256.239 | D83: =SUM(D11:D82) -> 39472.12 | E83: =SUM(E11:E82) -> 2880.32 | F83: =SUM(F11:F82) -> 30057.92 | G83: =SUM(G11:G82) -> 1022653.6 | I83: =SUM(I11:I82) -> 1054297.2 | J83: =SUM(J11:J82) -> 31162.51 | K83: =SUM(K11:K82) -> 40061.78 | L83: =SUM(L11:L82) -> 4142.42 | M83: =SUM(M11:M82) -> 34174.07 | N83: =SUM(N11:N82) -> 1015980.8 | O83: =SUM(O11:O82) -> 1041121 | P83: =SUM(P11:P82) -> 33039.055 | ... Z83: =SUM(Z11:Z82) -> 992071.51
A95: 1
A99: folder
A100: file
A101: tab
A102: column
A103: input date
A104: verification date
A105: notes
A106: notes - verification data
A107: notes - verification data

Sheet 6. Supplemental Allocation
A1: District | B1: Pell Grant | C1: AB 540 | D1: Promise Grant | E1: Supplemental Allocation Total
A2: Rates | B2: ='2. Weighting'!B38 -> 972.79596 | C2: ='2. Weighting'!B38 -> 972.79596 | D2: ='2. Weighting'!B38 -> 972.79596
A3: Points | B3: ='2. Weighting'!B32 -> 1 | C3: ='2. Weighting'!B32 -> 1 | D3: ='2. Weighting'!B34 -> 1
A4: Dollars/Outcome | B4: ='2. Weighting'!B38 -> 972.79596 | C4: ='2. Weighting'!B38 -> 972.79596 | D4: ='2. Weighting'!B38 -> 972.79596
A6: Allan Hancock | B6: ='6a. Supp Counts'!F6*'6. Supplemental Allocation'!B$4 -> 2629467.5 | C6: ='6a. Supp Counts'!G6*'6. Supplemental Allocation'!C$4 -> 658582.86 | D6: ='6a. Supp Counts'!H6*'6. Supplemental Allocation'!D$4 -> 8417603.4 | E6: =SUM(B6:D6) -> 11705654
A7: Antelope | B7: ='6a. Supp Counts'!F7*'6. Supplemental Allocation'!B$4 -> 7795014 | C7: ='6a. Supp Counts'!G7*'6. Supplemental Allocation'!C$4 -> 505853.9 | D7: ='6a. Supp Counts'!H7*'6. Supplemental Allocation'!D$4 -> 13699885 | E7: =SUM(B7:D7) -> 22000753
A8: Barstow | B8: ='6a. Supp Counts'!F8*'6. Supplemental Allocation'!B$4 -> 2007850.9 | C8: ='6a. Supp Counts'!G8*'6. Supplemental Allocation'!C$4 -> 74905.289 | D8: ='6a. Supp Counts'!H8*'6. Supplemental Allocation'!D$4 -> 3002048.3 | E8: =SUM(B8:D8) -> 5084804.5
A9: Butte | B9: ='6a. Supp Counts'!F9*'6. Supplemental Allocation'!B$4 -> 4694713.3 | C9: ='6a. Supp Counts'!G9*'6. Supplemental Allocation'!C$4 -> 292811.58 | D9: ='6a. Supp Counts'!H9*'6. Supplemental Allocation'!D$4 -> 7619910.7 | E9: =SUM(B9:D9) -> 12607436
A10: Cabrillo | B10: ='6a. Supp Counts'!F10*'6. Supplemental Allocation'!B$4 -> 2612929.9 | C10: ='6a. Supp Counts'!G10*'6. Supplemental Allocation'!C$4 -> 491261.96 | D10: ='6a. Supp Counts'!H10*'6. Supplemental Allocation'!D$4 -> 6159744 | E10: =SUM(B10:D10) -> 9263935.9
A11: Cerritos | B11: ='6a. Supp Counts'!F11*'6. Supplemental Allocation'!B$4 -> 9879715.7 | C11: ='6a. Supp Counts'!G11*'6. Supplemental Allocation'!C$4 -> 1519507.3 | D11: ='6a. Supp Counts'!H11*'6. Supplemental Allocation'!D$4 -> 17270047 | E11: =SUM(B11:D11) -> 28669270
A12: Chabot-Las Positas | B12: ='6a. Supp Counts'!F12*'6. Supplemental Allocation'!B$4 -> 4345479.5 | C12: ='6a. Supp Counts'!G12*'6. Supplemental Allocation'!C$4 -> 1078830.7 | D12: ='6a. Supp Counts'!H12*'6. Supplemental Allocation'!D$4 -> 10589857 | E12: =SUM(B12:D12) -> 16014167
A13: Chaffey | B13: ='6a. Supp Counts'!F13*'6. Supplemental Allocation'!B$4 -> 7011913.3 | C13: ='6a. Supp Counts'!G13*'6. Supplemental Allocation'!C$4 -> 1752978.3 | D13: ='6a. Supp Counts'!H13*'6. Supplemental Allocation'!D$4 -> 18258407 | E13: =SUM(B13:D13) -> 27023299
A14: Citrus | B14: ='6a. Supp Counts'!F14*'6. Supplemental Allocation'!B$4 -> 4982660.9 | C14: ='6a. Supp Counts'!G14*'6. Supplemental Allocation'!C$4 -> 530173.8 | D14: ='6a. Supp Counts'!H14*'6. Supplemental Allocation'!D$4 -> 10854457 | E14: =SUM(B14:D14) -> 16367292
A15: Coast | B15: ='6a. Supp Counts'!F15*'6. Supplemental Allocation'!B$4 -> 10145289 | C15: ='6a. Supp Counts'!G15*'6. Supplemental Allocation'!C$4 -> 1365805.5 | D15: ='6a. Supp Counts'!H15*'6. Supplemental Allocation'!D$4 -> 32163553 | E15: =SUM(B15:D15) -> 43674647
A16: Compton | B16: ='6a. Supp Counts'!F16*'6. Supplemental Allocation'!B$4 -> 2023415.6 | C16: ='6a. Supp Counts'!G16*'6. Supplemental Allocation'!C$4 -> -103116.37 | D16: ='6a. Supp Counts'!H16*'6. Supplemental Allocation'!D$4 -> 4782264.9 | E16: =SUM(B16:D16) -> 6702564.1
A17: Contra Costa | B17: ='6a. Supp Counts'!F17*'6. Supplemental Allocation'!B$4 -> 8688040.7 | C17: ='6a. Supp Counts'!G17*'6. Supplemental Allocation'!C$4 -> 209151.13 | D17: ='6a. Supp Counts'!H17*'6. Supplemental Allocation'!D$4 -> 18346932 | E17: =SUM(B17:D17) -> 27244124
... A77: Yuba | B77: ='6a. Supp Counts'!F77*'6. Supplemental Allocation'!B$4 -> 3797795.4 | C77: ='6a. Supp Counts'!G77*'6. Supplemental Allocation'!C$4 -> 328805.03 | D77: ='6a. Supp Counts'!H77*'6. Supplemental Allocation'!D$4 -> 7258030.6 | E77: =SUM(B77:D77) -> 11384631
A78: Statewide Total | B78: =SUM(B6:B77) -> 4.2545912e+08 | C78: =SUM(C6:C77) -> 56416329 | D78: =SUM(D6:D77) -> 9.4933017e+08 | E78: =SUM(E6:E77) -> 1.4312056e+09
E79: ='2. Weighting'!E35 -> 1.4312056e+09

Sheet 6a. Supp Counts
B3: 2017-18 | F3: 2018-19 Estimate
A4: District | B4: 2017-18 Pell Grant | C4: 2017-18 AB540 Headcount | D4: 2017-18 Promise Grant | E4: Supplemental Allocation Total Counts | F4: Estimated 2018-19 Pell Grant | G4: Estimated 2018-19 AB540 Headcount | H4: Estimated 2018-19 Promise Grant | I4: Supplemental Allocation Total Counts
A6: Allan Hancock | B6: 2815 | C6: 766 | D6: 8840 | E6: =SUM(B6:D6) -> 12421 | F6: =B6+'6a1. Supp growth'!H6 -> 2703 | G6: =C6+'6a1. Supp growth'!I6 -> 677 | H6: =D6+'6a1. Supp growth'!J6 -> 8653 | I6: =SUM(F6:H6) -> 12033
A7: Antelope | B7: 7896 | C7: 515 | D7: 13978 | E7: =SUM(B7:D7) -> 22389 | F7: =B7+'6a1. Supp growth'!H7 -> 8013 | G7: =C7+'6a1. Supp growth'!I7 -> 520 | H7: =D7+'6a1. Supp growth'!J7 -> 14083 | I7: =SUM(F7:H7) -> 22616
A8: Barstow | B8: 2130 | C8: 68 | D8: 3333 | E8: =SUM(B8:D8) -> 5531 | F8: =B8+'6a1. Supp growth'!H8 -> 2064 | G8: =C8+'6a1. Supp growth'!I8 -> 77 | H8: =D8+'6a1. Supp growth'!J8 -> 3086 | I8: =SUM(F8:H8) -> 5227
A9: Butte | B9: 5206 | C9: 303 | D9: 8205 | E9: =SUM(B9:D9) -> 13714 | F9: =B9+'6a1. Supp growth'!H9 -> 4826 | G9: =C9+'6a1. Supp growth'!I9 -> 301 | H9: =D9+'6a1. Supp growth'!J9 -> 7833 | I9: =SUM(F9:H9) -> 12960
A10: Cabrillo | B10: 2886 | C10: 513 | D10: 6737 | E10: =SUM(B10:D10) -> 10136 | F10: =B10+'6a1. Supp growth'!H10 -> 2686 | G10: =C10+'6a1. Supp growth'!I10 -> 505 | H10: =D10+'6a1. Supp growth'!J10 -> 6332 | I10: =SUM(F10:H10) -> 9523
A11: Cerritos | B11: 10455 | C11: 1586 | D11: 18362 | E11: =SUM(B11:D11) -> 30403 | F11: =B11+'6a1. Supp growth'!H11 -> 10156 | G11: =C11+'6a1. Supp growth'!I11 -> 1562 | H11: =D11+'6a1. Supp growth'!J11 -> 17753 | I11: =SUM(F11:H11) -> 29471
A12: Chabot-Las Positas | B12: 4787 | C12: 696 | D12: 11272 | E12: =SUM(B12:D12) -> 16755 | F12: =B12+'6a1. Supp growth'!H12 -> 4467 | G12: =C12+'6a1. Supp growth'!I12 -> 1109 | H12: =D12+'6a1. Supp growth'!J12 -> 10886 | I12: =SUM(F12:H12) -> 16462
A13: Chaffey | B13: 8010 | C13: 1343 | D13: 18275 | E13: =SUM(B13:D13) -> 27628 | F13: =B13+'6a1. Supp growth'!H13 -> 7208 | G13: =C13+'6a1. Supp growth'!I13 -> 1802 | H13: =D13+'6a1. Supp growth'!J13 -> 18769 | I13: =SUM(F13:H13) -> 27779
A14: Citrus | B14: 5010 | C14: 501 | D14: 11058 | E14: =SUM(B14:D14) -> 16569 | F14: =B14+'6a1. Supp growth'!H14 -> 5122 | G14: =C14+'6a1. Supp growth'!I14 -> 545 | H14: =D14+'6a1. Supp growth'!J14 -> 11158 | I14: =SUM(F14:H14) -> 16825
A15: Coast | B15: 11222 | C15: 1342 | D15: 32107 | E15: =SUM(B15:D15) -> 44671 | F15: =B15+'6a1. Supp growth'!H15 -> 10429 | G15: =C15+'6a1. Supp growth'!I15 -> 1404 | H15: =D15+'6a1. Supp growth'!J15 -> 33063 | I15: =SUM(F15:H15) -> 44896
A16: Compton | B16: 2459 | C16: 341 | D16: 5230 | E16: =SUM(B16:D16) -> 8030 | F16: =B16+'6a1. Supp growth'!H16 -> 2080 | G16: =C16+'6a1. Supp growth'!I16 -> -106 | H16: =D16+'6a1. Supp growth'!J16 -> 4916 | I16: =SUM(F16:H16) -> 6890
A17: Contra Costa | B17: 8978 | C17: 1245 | D17: 18682 | E17: =SUM(B17:D17) -> 28905 | F17: =B17+'6a1. Supp growth'!H17 -> 8931 | G17: =C17+'6a1. Supp growth'!I17 -> 215 | H17: =D17+'6a1. Supp growth'!J17 -> 18860 | I17: =SUM(F17:H17) -> 28006
... A77: Yuba | B77: 4137 | C77: 360 | D77: 7764 | E77: =SUM(B77:D77) -> 12261 | F77: =B77+'6a1. Supp growth'!H77 -> 3904 | G77: =C77+'6a1. Supp growth'!I77 -> 338 | H77: =D77+'6a1. Supp growth'!J77 -> 7461 | I77: =SUM(F77:H77) -> 11703
A78: Statewide Total | B78: =SUM(B6:B77) -> 448989 | C78: =SUM(C6:C77) -> 60500 | D78: =SUM(D6:D77) -> 989748 | E78: =SUM(E6:E77) -> 1499237 | F78: =SUM(F6:F77) -> 437357 | G78: =SUM(G6:G77) -> 57994 | H78: =SUM(H6:H77) -> 975878 | I78: =SUM(I6:I77) -> 1471229

Sheet 6a1. Supp growth
B3: 2016-17 | E3: 2017-18 | H3: # growth/decline
A4: District | B4: Pell Grant Recipients Totals | C4: 2016-17 AB540 Headcount | D4: California Promise Grant Recipients Totals | E4: Pell Grant Recipients Totals | F4: 2017-18 AB540 Headcount | G4: California Promise Grant Recipients Totals | H4: Pell Grant Recipients Totals | I4: AB 540 | J4: California Promise Grant Recipients Totals
B5: PELL | C5: AB540 | D5: CCPG | E5: PELL | F5: AB540 | G5: CCPG
A6: Allan Hancock | B6: 2927 | C6: 855 | D6: 9027 | E6: 2815 | F6: 766 | G6: 8840 | H6: =E6-B6 -> -112 | I6: =F6-C6 -> -89 | J6: =G6-D6 -> -187
A7: Antelope | B7: 7779 | C7: 510 | D7: 13873 | E7: 7896 | F7: 515 | G7: 13978 | H7: =E7-B7 -> 117 | I7: =F7-C7 -> 5 | J7: =G7-D7 -> 105
A8: Barstow | B8: 2196 | C8: 59 | D8: 3580 | E8: 2130 | F8: 68 | G8: 3333 | H8: =E8-B8 -> -66 | I8: =F8-C8 -> 9 | J8: =G8-D8 -> -247
A9: Butte | B9: 5586 | C9: 305 | D9: 8577 | E9: 5206 | F9: 303 | G9: 8205 | H9: =E9-B9 -> -380 | I9: =F9-C9 -> -2 | J9: =G9-D9 -> -372
A10: Cabrillo | B10: 3086 | C10: 521 | D10: 7142 | E10: 2886 | F10: 513 | G10: 6737 | H10: =E10-B10 -> -200 | I10: =F10-C10 -> -8 | J10: =G10-D10 -> -405
A11: Cerritos | B11: 10754 | C11: 1610 | D11: 18971 | E11: 10455 | F11: 1586 | G11: 18362 | H11: =E11-B11 -> -299 | I11: =F11-C11 -> -24 | J11: =G11-D11 -> -609
A12: Chabot-Las Positas | B12: 5107 | C12: 283 | D12: 11658 | E12: 4787 | F12: 696 | G12: 11272 | H12: =E12-B12 -> -320 | I12: =F12-C12 -> 413 | J12: =G12-D12 -> -386
A13: Chaffey | B13: 8812 | C13: 884 | D13: 17781 | E13: 8010 | F13: 1343 | G13: 18275 | H13: =E13-B13 -> -802 | I13: =F13-C13 -> 459 | J13: =G13-D13 -> 494
A14: Citrus | B14: 4898 | C14: 457 | D14: 10958 | E14: 5010 | F14: 501 | G14: 11058 | H14: =E14-B14 -> 112 | I14: =F14-C14 -> 44 | J14: =G14-D14 -> 100
A15: Coast | B15: 12015 | C15: 1280 | D15: 31151 | E15: 11222 | F15: 1342 | G15: 32107 | H15: =E15-B15 -> -793 | I15: =F15-C15 -> 62 | J15: =G15-D15 -> 956
A16: Compton | B16: 2838 | C16: 788 | D16: 5544 | E16: 2459 | F16: 341 | G16: 5230 | H16: =E16-B16 -> -379 | I16: =F16-C16 -> -447 | J16: =G16-D16 -> -314
A17: Contra Costa | B17: 9025 | C17: 2275 | D17: 18504 | E17: 8978 | F17: 1245 | G17: 18682 | H17: =E17-B17 -> -47 | I17: =F17-C17 -> -1030 | J17: =G17-D17 -> 178
... A77: Yuba | B77: 4370 | C77: 382 | D77: 8067 | E77: 4137 | F77: 360 | G77: 7764 | H77: =E77-B77 -> -233 | I77: =F77-C77 -> -22 | J77: =G77-D77 -> -303
A78: Statewide Total | B78: =SUM(B6:B77) -> 460621 | C78: =SUM(C6:C77) -> 63006 | D78: =SUM(D6:D77) -> 1003618 | E78: =SUM(E6:E77) -> 448989 | F78: =SUM(F6:F77) -> 60500 | G78: =SUM(G6:G77) -> 989748 | H78: =SUM(H6:H77) -> -11632 | I78: =SUM(I6:I77) -> -2506 | J78: =SUM(J6:J77) -> -13870

Sheet 7. Success Allocation
C1: All Students | M1: Pell Grant Students Only | W1: Promise Grant Students Only
A2: District | B2: Associate Degrees for Transfer | C2: Associate Degrees | D2: BA | E2: Credit Certificates | F2: Transfer Level Math and English | G2: Nine or More CTE Units | H2: Transfer | I2: Regional Living Wage | J2: All Students Subtotal | L2: Associate Degrees for Transfer | M2: Associate Degrees | N2: BA | O2: Credit Certificates | P2: Transfer Level Math and English | Q2: Nine or More CTE Units | R2: Transfer | S2: Regional Living Wage | T2: Pell Students Subtotal | V2: Associate Degrees for Transfer | W2: Associate Degrees | X2: BA | Y2: Credit Certificates | Z2: Transfer Level Math and English | AA2: Nine or More CTE Units | AB2: Transfer | AC2: Regional Living Wage | AD2: Promise Grant Students Subtotal | AF2: Student Successs Allocation Total
A3: Rates | B3: ='2. Weighting'!B55 -> 499.77221 | C3: ='2. Weighting'!B55 -> 499.77221 | D3: ='2. Weighting'!B55 -> 499.77221 | E3: ='2. Weighting'!B55 -> 499.77221 | F3: ='2. Weighting'!B55 -> 499.77221 | G3: ='2. Weighting'!B55 -> 499.77221 | H3: ='2. Weighting'!B55 -> 499.77221 | I3: ='2. Weighting'!B55 -> 499.77221 | L3: ='2. Weighting'!B80 -> 124.94305 | M3: ='2. Weighting'!B80 -> 124.94305 | N3: ='2. Weighting'!B80 -> 124.94305 | O3: ='2. Weighting'!B80 -> 124.94305 | P3: ='2. Weighting'!B80 -> 124.94305 | Q3: ='2. Weighting'!B80 -> 124.94305 | R3: ='2. Weighting'!B80 -> 124.94305 | S3: ='2. Weighting'!B80 -> 124.94305 | V3: ='2. Weighting'!B80 -> 124.94305 | W3: ='2. Weighting'!B80 -> 124.94305 | X3: ='2. Weighting'!B80 -> 124.94305 | Y3: ='2. Weighting'!B80 -> 124.94305 | Z3: ='2. Weighting'!B80 -> 124.94305 | AA3: ='2. Weighting'!B80 -> 124.94305 | AB3: ='2. Weighting'!B80 -> 124.94305 | AC3: ='2. Weighting'!B80 -> 124.94305
A4: Points | B4: ='2. Weighting'!B44 -> 4 | C4: ='2. Weighting'!B45 -> 3 | D4: ='2. Weighting'!B46 -> 3 | E4: ='2. Weighting'!B47 -> 2 | F4: ='2. Weighting'!B48 -> 2 | G4: ='2. Weighting'!B50 -> 1 | H4: ='2. Weighting'!B49 -> 1.5 | I4: ='2. Weighting'!B51 -> 1 | L4: ='2. Weighting'!B59 -> 6 | M4: ='2. Weighting'!B60 -> 4.5 | N4: ='2. Weighting'!B61 -> 4.5 | O4: ='2. Weighting'!B62 -> 3 | P4: ='2. Weighting'!B63 -> 3 | Q4: ='2. Weighting'!B65 -> 1.5 | R4: ='2. Weighting'!B64 -> 2.25 | S4: ='2. Weighting'!B66 -> 1.5 | V4: ='2. Weighting'!B69 -> 4 | W4: ='2. Weighting'!B70 -> 3 | X4: ='2. Weighting'!B71 -> 3 | Y4: ='2. Weighting'!B72 -> 2 | Z4: ='2. Weighting'!B73 -> 2 | AA4: ='2. Weighting'!B75 -> 1 | AB4: ='2. Weighting'!B74 -> 1.5 | AC4: ='2. Weighting'!B76 -> 1
A5: Dollars/outcome | B5: =B3*B4 -> 1999.0889 | C5: =C3*C4 -> 1499.3166 | D5: =D3*D4 -> 1499.3166 | E5: =E3*E4 -> 999.54443 | F5: =F3*F4 -> 999.54443 | G5: =G3*G4 -> 499.77221 | H5: =H3*H4 -> 749.65832 | I5: =I3*I4 -> 499.77221 | L5: =L3*L4 -> 749.65832 | M5: =M3*M4 -> 562.24374 | N5: =N3*N4 -> 562.24374 | O5: =O3*O4 -> 374.82916 | P5: =P3*P4 -> 374.82916 | Q5: =Q3*Q4 -> 187.41458 | R5: =R3*R4 -> 281.12187 | S5: =S3*S4 -> 187.41458 | V5: =V3*V4 -> 499.77221 | W5: =W3*W4 -> 374.82916 | X5: =X3*X4 -> 374.82916 | Y5: =Y3*Y4 -> 249.88611 | Z5: =Z3*Z4 -> 249.88611 | AA5: =AA3*AA4 -> 124.94305 | AB5: =AB3*AB4 -> 187.41458 | AC5: =AC3*AC4 -> 124.94305
A6: Allan Hancock | B6: ='7a. Success 3 yr'!B6*'7. Success Allocation'!B$5 -> 543752.17 | C6: ='7a. Success 3 yr'!C6*'7. Success Allocation'!C$5 -> 865105.7 | D6: ='7a. Success 3 yr'!D6*'7. Success Allocation'!D$5 -> 0 | E6: ='7a. Success 3 yr'!E6*'7. Success Allocation'!E$5 -> 243888.84 | F6: ='7a. Success 3 yr'!F6*'7. Success Allocation'!F$5 -> 189913.44 | G6: ='7a. Success 3 yr'!G6*'7. Success Allocation'!G$5 -> 957063.79 | H6: ='7a. Success 3 yr'!H6*'7. Success Allocation'!H$5 -> 648454.45 | I6: ='7a. Success 3 yr'!I6*'7. Success Allocation'!I$5 -> 1111493.4 | J6: =SUM(B6:I6) -> 4559671.8 | L6: ='7a. Success 3 yr'!J6*'7. Success Allocation'!L$5 -> 120694.99 | M6: ='7a. Success 3 yr'!K6*'7. Success Allocation'!M$5 -> 174857.8 | N6: ='7a. Success 3 yr'!L6*'7. Success Allocation'!N$5 -> 0 | O6: ='7a. Success 3 yr'!M6*'7. Success Allocation'!O$5 -> 47228.474 | P6: ='7a. Success 3 yr'!N6*'7. Success Allocation'!P$5 -> 31110.82 | Q6: ='7a. Success 3 yr'!O6*'7. Success Allocation'!Q$5 -> 148619.76 | R6: ='7a. Success 3 yr'!P6*'7. Success Allocation'!R$5 -> 92207.973 | S6: ='7a. Success 3 yr'!Q6*'7. Success Allocation'!S$5 -> 83774.317 | T6: =SUM(L6:S6) -> 698494.14 | V6: ='7a. Success 3 yr'!R6*'7. Success Allocation'!V$5 -> 112448.75 | W6: ='7a. Success 3 yr'!S6*'7. Success Allocation'!W$5 -> 178043.85 | X6: ='7a. Success 3 yr'!T6*'7. Success Allocation'!X$5 -> 0 | Y6: ='7a. Success 3 yr'!U6*'7. Success Allocation'!Y$5 -> 48228.019 | Z6: ='7a. Success 3 yr'!V6*'7. Success Allocation'!Z$5 -> 33984.511 | AA6: ='7a. Success 3 yr'!W6*'7. Success Allocation'!AA$5 -> 170672.21 | AB6: ='7a. Success 3 yr'!X6*'7. Success Allocation'!AB$5 -> 103265.43 | AC6: ='7a. Success 3 yr'!Y6*'7. Success Allocation'!AC$5 -> 117821.3 | AD6: =SUM(V6:AC6) -> 764464.07 | AF6: =SUM(J6,T6,AD6) -> 6022630
A7: Antelope | B7: ='7a. Success 3 yr'!B7*'7. Success Allocation'!B$5 -> 969558.09 | C7: ='7a. Success 3 yr'!C7*'7. Success Allocation'!C$5 -> 1013538 | D7: ='7a. Success 3 yr'!D7*'7. Success Allocation'!D$5 -> 0 | E7: ='7a. Success 3 yr'!E7*'7. Success Allocation'!E$5 -> 253884.28 | F7: ='7a. Success 3 yr'!F7*'7. Success Allocation'!F$5 -> 186914.81 | G7: ='7a. Success 3 yr'!G7*'7. Success Allocation'!G$5 -> 1016036.9 | H7: ='7a. Success 3 yr'!H7*'7. Success Allocation'!H$5 -> 743661.05 | I7: ='7a. Success 3 yr'!I7*'7. Success Allocation'!I$5 -> 573238.73 | J7: =SUM(B7:I7) -> 4756831.9 | L7: ='7a. Success 3 yr'!J7*'7. Success Allocation'!L$5 -> 254883.83 | M7: ='7a. Success 3 yr'!K7*'7. Success Allocation'!M$5 -> 257507.63 | N7: ='7a. Success 3 yr'!L7*'7. Success Allocation'!N$5 -> 0 | O7: ='7a. Success 3 yr'!M7*'7. Success Allocation'!O$5 -> 61471.982 | P7: ='7a. Success 3 yr'!N7*'7. Success Allocation'!P$5 -> 36358.429 | Q7: ='7a. Success 3 yr'!O7*'7. Success Allocation'!Q$5 -> 247012.42 | R7: ='7a. Success 3 yr'!P7*'7. Success Allocation'!R$5 -> 159677.22 | S7: ='7a. Success 3 yr'!Q7*'7. Success Allocation'!S$5 -> 111511.68 | T7: =SUM(L7:S7) -> 1128423.2 | V7: ='7a. Success 3 yr'!R7*'7. Success Allocation'!V$5 -> 207405.47 | W7: ='7a. Success 3 yr'!S7*'7. Success Allocation'!W$5 -> 211403.65 | X7: ='7a. Success 3 yr'!T7*'7. Success Allocation'!X$5 -> 0 | Y7: ='7a. Success 3 yr'!U7*'7. Success Allocation'!Y$5 -> 51726.424 | Z7: ='7a. Success 3 yr'!V7*'7. Success Allocation'!Z$5 -> 34734.169 | AA7: ='7a. Success 3 yr'!W7*'7. Success Allocation'!AA$5 -> 211528.59 | AB7: ='7a. Success 3 yr'!X7*'7. Success Allocation'!AB$5 -> 147682.69 | AC7: ='7a. Success 3 yr'!Y7*'7. Success Allocation'!AC$5 -> 109200.23 | AD7: =SUM(V7:AC7) -> 973681.22 | AF7: =SUM(J7,T7,AD7) -> 6858936.3
A8: Barstow | B8: ='7a. Success 3 yr'!B8*'7. Success Allocation'!B$5 -> 133938.95 | C8: ='7a. Success 3 yr'!C8*'7. Success Allocation'!C$5 -> 377827.79 | D8: ='7a. Success 3 yr'!D8*'7. Success Allocation'!D$5 -> 0 | E8: ='7a. Success 3 yr'!E8*'7. Success Allocation'!E$5 -> 16992.255 | F8: ='7a. Success 3 yr'!F8*'7. Success Allocation'!F$5 -> 56974.032 | G8: ='7a. Success 3 yr'!G8*'7. Success Allocation'!G$5 -> 186914.81 | H8: ='7a. Success 3 yr'!H8*'7. Success Allocation'!H$5 -> 247387.25 | I8: ='7a. Success 3 yr'!I8*'7. Success Allocation'!I$5 -> 257882.46 | J8: =SUM(B8:I8) -> 1277917.6 | L8: ='7a. Success 3 yr'!J8*'7. Success Allocation'!L$5 -> 43480.183 | M8: ='7a. Success 3 yr'!K8*'7. Success Allocation'!M$5 -> 111324.26 | N8: ='7a. Success 3 yr'!L8*'7. Success Allocation'!N$5 -> 0 | O8: ='7a. Success 3 yr'!M8*'7. Success Allocation'!O$5 -> 5997.2666 | P8: ='7a. Success 3 yr'!N8*'7. Success Allocation'!P$5 -> 11994.533 | Q8: ='7a. Success 3 yr'!O8*'7. Success Allocation'!Q$5 -> 50976.766 | R8: ='7a. Success 3 yr'!P8*'7. Success Allocation'!R$5 -> 41887.159 | S8: ='7a. Success 3 yr'!Q8*'7. Success Allocation'!S$5 -> 40294.135 | T8: =SUM(L8:S8) -> 305954.3 | V8: ='7a. Success 3 yr'!R8*'7. Success Allocation'!V$5 -> 31485.649 | W8: ='7a. Success 3 yr'!S8*'7. Success Allocation'!W$5 -> 86210.707 | X8: ='7a. Success 3 yr'!T8*'7. Success Allocation'!X$5 -> 0 | Y8: ='7a. Success 3 yr'!U8*'7. Success Allocation'!Y$5 -> 4248.0638 | Z8: ='7a. Success 3 yr'!V8*'7. Success Allocation'!Z$5 -> 10495.216 | AA8: ='7a. Success 3 yr'!W8*'7. Success Allocation'!AA$5 -> 40981.322 | AB8: ='7a. Success 3 yr'!X8*'7. Success Allocation'!AB$5 -> 41418.622 | AC8: ='7a. Success 3 yr'!Y8*'7. Success Allocation'!AC$5 -> 42230.752 | AD8: =SUM(V8:AC8) -> 257070.33 | AF8: =SUM(J8,T8,AD8) -> 1840942.2
A9: Butte | B9: ='7a. Success 3 yr'!B9*'7. Success Allocation'!B$5 -> 607723.01 | C9: ='7a. Success 3 yr'!C9*'7. Success Allocation'!C$5 -> 1094501.1 | D9: ='7a. Success 3 yr'!D9*'7. Success Allocation'!D$5 -> 0 | E9: ='7a. Success 3 yr'!E9*'7. Success Allocation'!E$5 -> 330849.21 | F9: ='7a. Success 3 yr'!F9*'7. Success Allocation'!F$5 -> 267877.91 | G9: ='7a. Success 3 yr'!G9*'7. Success Allocation'!G$5 -> 1095500.7 | H9: ='7a. Success 3 yr'!H9*'7. Success Allocation'!H$5 -> 900339.64 | I9: ='7a. Success 3 yr'!I9*'7. Success Allocation'!I$5 -> 836618.69 | J9: =SUM(B9:I9) -> 5133410.3 | L9: ='7a. Success 3 yr'!J9*'7. Success Allocation'!L$5 -> 137187.47 | M9: ='7a. Success 3 yr'!K9*'7. Success Allocation'!M$5 -> 276061.68 | N9: ='7a. Success 3 yr'!L9*'7. Success Allocation'!N$5 -> 0 | O9: ='7a. Success 3 yr'!M9*'7. Success Allocation'!O$5 -> 49102.62 | P9: ='7a. Success 3 yr'!N9*'7. Success Allocation'!P$5 -> 50227.107 | Q9: ='7a. Success 3 yr'!O9*'7. Success Allocation'!Q$5 -> 217588.33 | R9: ='7a. Success 3 yr'!P9*'7. Success Allocation'!R$5 -> 173171.07 | S9: ='7a. Success 3 yr'!Q9*'7. Success Allocation'!S$5 -> 146745.62 | T9: =SUM(L9:S9) -> 1050083.9 | V9: ='7a. Success 3 yr'!R9*'7. Success Allocation'!V$5 -> 115447.38 | W9: ='7a. Success 3 yr'!S9*'7. Success Allocation'!W$5 -> 223773.01 | X9: ='7a. Success 3 yr'!T9*'7. Success Allocation'!X$5 -> 0 | Y9: ='7a. Success 3 yr'!U9*'7. Success Allocation'!Y$5 -> 43979.955 | Z9: ='7a. Success 3 yr'!V9*'7. Success Allocation'!Z$5 -> 42480.638 | AA9: ='7a. Success 3 yr'!W9*'7. Success Allocation'!AA$5 -> 196785.31 | AB9: ='7a. Success 3 yr'!X9*'7. Success Allocation'!AB$5 -> 151056.15 | AC9: ='7a. Success 3 yr'!Y9*'7. Success Allocation'!AC$5 -> 134438.73 | AD9: =SUM(V9:AC9) -> 907961.17 | AF9: =SUM(J9,T9,AD9) -> 7091455.4
A10: Cabrillo | B10: ='7a. Success 3 yr'!B10*'7. Success Allocation'!B$5 -> 505769.48 | C10: ='7a. Success 3 yr'!C10*'7. Success Allocation'!C$5 -> 1049521.6 | D10: ='7a. Success 3 yr'!D10*'7. Success Allocation'!D$5 -> 0 | E10: ='7a. Success 3 yr'!E10*'7. Success Allocation'!E$5 -> 58973.121 | F10: ='7a. Success 3 yr'!F10*'7. Success Allocation'!F$5 -> 133938.95 | G10: ='7a. Success 3 yr'!G10*'7. Success Allocation'!G$5 -> 567241.46 | H10: ='7a. Success 3 yr'!H10*'7. Success Allocation'!H$5 -> 761652.85 | I10: ='7a. Success 3 yr'!I10*'7. Success Allocation'!I$5 -> 824624.15 | J10: =SUM(B10:I10) -> 3901721.7 | L10: ='7a. Success 3 yr'!J10*'7. Success Allocation'!L$5 -> 87710.024 | M10: ='7a. Success 3 yr'!K10*'7. Success Allocation'!M$5 -> 200158.77 | N10: ='7a. Success 3 yr'!L10*'7. Success Allocation'!N$5 -> 0 | O10: ='7a. Success 3 yr'!M10*'7. Success Allocation'!O$5 -> 14618.337 | P10: ='7a. Success 3 yr'!N10*'7. Success Allocation'!P$5 -> 17616.971 | Q10: ='7a. Success 3 yr'!O10*'7. Success Allocation'!Q$5 -> 100829.04 | R10: ='7a. Success 3 yr'!P10*'7. Success Allocation'!R$5 -> 108513.04 | S10: ='7a. Success 3 yr'!Q10*'7. Success Allocation'!S$5 -> 74028.759 | T10: =SUM(L10:S10) -> 603474.95 | V10: ='7a. Success 3 yr'!R10*'7. Success Allocation'!V$5 -> 86460.593 | W10: ='7a. Success 3 yr'!S10*'7. Success Allocation'!W$5 -> 181792.14 | X10: ='7a. Success 3 yr'!T10*'7. Success Allocation'!X$5 -> 0 | Y10: ='7a. Success 3 yr'!U10*'7. Success Allocation'!Y$5 -> 12494.305 | Z10: ='7a. Success 3 yr'!V10*'7. Success Allocation'!Z$5 -> 15742.825 | AA10: ='7a. Success 3 yr'!W10*'7. Success Allocation'!AA$5 -> 98455.126 | AB10: ='7a. Success 3 yr'!X10*'7. Success Allocation'!AB$5 -> 109637.53 | AC10: ='7a. Success 3 yr'!Y10*'7. Success Allocation'!AC$5 -> 88334.739 | AD10: =SUM(V10:AC10) -> 592917.26 | AF10: =SUM(J10,T10,AD10) -> 5098113.9
A11: Cerritos | B11: ='7a. Success 3 yr'!B11*'7. Success Allocation'!B$5 -> 1379371.3 | C11: ='7a. Success 3 yr'!C11*'7. Success Allocation'!C$5 -> 1359880.2 | D11: ='7a. Success 3 yr'!D11*'7. Success Allocation'!D$5 -> 0 | E11: ='7a. Success 3 yr'!E11*'7. Success Allocation'!E$5 -> 667695.68 | F11: ='7a. Success 3 yr'!F11*'7. Success Allocation'!F$5 -> 203907.06 | G11: ='7a. Success 3 yr'!G11*'7. Success Allocation'!G$5 -> 1868148.5 | H11: ='7a. Success 3 yr'!H11*'7. Success Allocation'!H$5 -> 1007540.8 | I11: ='7a. Success 3 yr'!I11*'7. Success Allocation'!I$5 -> 1438844.2 | J11: =SUM(B11:I11) -> 7925387.8 | L11: ='7a. Success 3 yr'!J11*'7. Success Allocation'!L$5 -> 374829.16 | M11: ='7a. Success 3 yr'!K11*'7. Success Allocation'!M$5 -> 339032.98 | N11: ='7a. Success 3 yr'!L11*'7. Success Allocation'!N$5 -> 0 | O11: ='7a. Success 3 yr'!M11*'7. Success Allocation'!O$5 -> 121069.82 | P11: ='7a. Success 3 yr'!N11*'7. Success Allocation'!P$5 -> 37857.745 | Q11: ='7a. Success 3 yr'!O11*'7. Success Allocation'!Q$5 -> 366582.92 | R11: ='7a. Success 3 yr'!P11*'7. Success Allocation'!R$5 -> 247387.25 | S11: ='7a. Success 3 yr'!Q11*'7. Success Allocation'!S$5 -> 160801.71 | T11: =SUM(L11:S11) -> 1647561.6 | V11: ='7a. Success 3 yr'!R11*'7. Success Allocation'!V$5 -> 305360.82 | W11: ='7a. Success 3 yr'!S11*'7. Success Allocation'!W$5 -> 287119.14 | X11: ='7a. Success 3 yr'!T11*'7. Success Allocation'!X$5 -> 0 | Y11: ='7a. Success 3 yr'!U11*'7. Success Allocation'!Y$5 -> 110699.55 | Z11: ='7a. Success 3 yr'!V11*'7. Success Allocation'!Z$5 -> 35483.827 | AA11: ='7a. Success 3 yr'!W11*'7. Success Allocation'!AA$5 -> 337096.36 | AB11: ='7a. Success 3 yr'!X11*'7. Success Allocation'!AB$5 -> 206530.87 | AC11: ='7a. Success 3 yr'!Y11*'7. Success Allocation'!AC$5 -> 168423.24 | AD11: =SUM(V11:AC11) -> 1450713.8 | AF11: =SUM(J11,T11,AD11) -> 11023663
A12: Chabot-Las Positas | B12: ='7a. Success 3 yr'!B12*'7. Success Allocation'!B$5 -> 1245432.4 | C12: ='7a. Success 3 yr'!C12*'7. Success Allocation'!C$5 -> 1292410.9 | D12: ='7a. Success 3 yr'!D12*'7. Success Allocation'!D$5 -> 0 | E12: ='7a. Success 3 yr'!E12*'7. Success Allocation'!E$5 -> 269877 | F12: ='7a. Success 3 yr'!F12*'7. Success Allocation'!F$5 -> 469785.88 | G12: ='7a. Success 3 yr'!G12*'7. Success Allocation'!G$5 -> 1358380.9 | H12: ='7a. Success 3 yr'!H12*'7. Success Allocation'!H$5 -> 1566036.2 | I12: ='7a. Success 3 yr'!I12*'7. Success Allocation'!I$5 -> 1276918 | J12: =SUM(B12:I12) -> 7478841.3 | L12: ='7a. Success 3 yr'!J12*'7. Success Allocation'!L$5 -> 204656.72 | M12: ='7a. Success 3 yr'!K12*'7. Success Allocation'!M$5 -> 199596.53 | N12: ='7a. Success 3 yr'!L12*'7. Success Allocation'!N$5 -> 0 | O12: ='7a. Success 3 yr'!M12*'7. Success Allocation'!O$5 -> 34484.283 | P12: ='7a. Success 3 yr'!N12*'7. Success Allocation'!P$5 -> 47228.474 | Q12: ='7a. Success 3 yr'!O12*'7. Success Allocation'!Q$5 -> 146745.62 | R12: ='7a. Success 3 yr'!P12*'7. Success Allocation'!R$5 -> 211965.89 | S12: ='7a. Success 3 yr'!Q12*'7. Success Allocation'!S$5 -> 91833.144 | T12: =SUM(L12:S12) -> 936510.66 | V12: ='7a. Success 3 yr'!R12*'7. Success Allocation'!V$5 -> 195910.71 | W12: ='7a. Success 3 yr'!S12*'7. Success Allocation'!W$5 -> 199034.28 | X12: ='7a. Success 3 yr'!T12*'7. Success Allocation'!X$5 -> 0 | Y12: ='7a. Success 3 yr'!U12*'7. Success Allocation'!Y$5 -> 34234.397 | Z12: ='7a. Success 3 yr'!V12*'7. Success Allocation'!Z$5 -> 48228.019 | AA12: ='7a. Success 3 yr'!W12*'7. Success Allocation'!AA$5 -> 157428.25 | AB12: ='7a. Success 3 yr'!X12*'7. Success Allocation'!AB$5 -> 210279.16 | AC12: ='7a. Success 3 yr'!Y12*'7. Success Allocation'!AC$5 -> 119695.45 | AD12: =SUM(V12:AC12) -> 964810.26 | AF12: =SUM(J12,T12,AD12) -> 9380162.2
A13: Chaffey | B13: ='7a. Success 3 yr'!B13*'7. Success Allocation'!B$5 -> 1711220.1 | C13: ='7a. Success 3 yr'!C13*'7. Success Allocation'!C$5 -> 1292410.9 | D13: ='7a. Success 3 yr'!D13*'7. Success Allocation'!D$5 -> 0 | E13: ='7a. Success 3 yr'!E13*'7. Success Allocation'!E$5 -> 402816.4 | F13: ='7a. Success 3 yr'!F13*'7. Success Allocation'!F$5 -> 262880.18 | G13: ='7a. Success 3 yr'!G13*'7. Success Allocation'!G$5 -> 1190457.4 | H13: ='7a. Success 3 yr'!H13*'7. Success Allocation'!H$5 -> 1059267.2 | I13: ='7a. Success 3 yr'!I13*'7. Success Allocation'!I$5 -> 1389866.5 | J13: =SUM(B13:I13) -> 7308918.7 | L13: ='7a. Success 3 yr'!J13*'7. Success Allocation'!L$5 -> 383075.4 | M13: ='7a. Success 3 yr'!K13*'7. Success Allocation'!M$5 -> 279997.38 | N13: ='7a. Success 3 yr'!L13*'7. Success Allocation'!N$5 -> 0 | O13: ='7a. Success 3 yr'!M13*'7. Success Allocation'!O$5 -> 72716.857 | P13: ='7a. Success 3 yr'!N13*'7. Success Allocation'!P$5 -> 32235.308 | Q13: ='7a. Success 3 yr'!O13*'7. Success Allocation'!Q$5 -> 225272.33 | R13: ='7a. Success 3 yr'!P13*'7. Success Allocation'!R$5 -> 205500.09 | S13: ='7a. Success 3 yr'!Q13*'7. Success Allocation'!S$5 -> 222461.11 | T13: =SUM(L13:S13) -> 1421258.5 | V13: ='7a. Success 3 yr'!R13*'7. Success Allocation'!V$5 -> 339345.33 | W13: ='7a. Success 3 yr'!S13*'7. Success Allocation'!W$5 -> 254883.83 | X13: ='7a. Success 3 yr'!T13*'7. Success Allocation'!X$5 -> 0 | Y13: ='7a. Success 3 yr'!U13*'7. Success Allocation'!Y$5 -> 80213.44 | Z13: ='7a. Success 3 yr'!V13*'7. Success Allocation'!Z$5 -> 35483.827 | AA13: ='7a. Success 3 yr'!W13*'7. Success Allocation'!AA$5 -> 221399.09 | AB13: ='7a. Success 3 yr'!X13*'7. Success Allocation'!AB$5 -> 198846.87 | AC13: ='7a. Success 3 yr'!Y13*'7. Success Allocation'!AC$5 -> 253634.4 | AD13: =SUM(V13:AC13) -> 1383806.8 | AF13: =SUM(J13,T13,AD13) -> 10113984
A14: Citrus | B14: ='7a. Success 3 yr'!B14*'7. Success Allocation'!B$5 -> 1751201.8 | C14: ='7a. Success 3 yr'!C14*'7. Success Allocation'!C$5 -> 842615.95 | D14: ='7a. Success 3 yr'!D14*'7. Success Allocation'!D$5 -> 0 | E14: ='7a. Success 3 yr'!E14*'7. Success Allocation'!E$5 -> 395819.59 | F14: ='7a. Success 3 yr'!F14*'7. Success Allocation'!F$5 -> 323852.39 | G14: ='7a. Success 3 yr'!G14*'7. Success Allocation'!G$5 -> 863606.39 | H14: ='7a. Success 3 yr'!H14*'7. Success Allocation'!H$5 -> 1048772 | I14: ='7a. Success 3 yr'!I14*'7. Success Allocation'!I$5 -> 574738.05 | J14: =SUM(B14:I14) -> 5800606.2 | L14: ='7a. Success 3 yr'!J14*'7. Success Allocation'!L$5 -> 383075.4 | M14: ='7a. Success 3 yr'!K14*'7. Success Allocation'!M$5 -> 167548.63 | N14: ='7a. Success 3 yr'!L14*'7. Success Allocation'!N$5 -> 0 | O14: ='7a. Success 3 yr'!M14*'7. Success Allocation'!O$5 -> 79088.953 | P14: ='7a. Success 3 yr'!N14*'7. Success Allocation'!P$5 -> 45354.328 | Q14: ='7a. Success 3 yr'!O14*'7. Success Allocation'!Q$5 -> 160052.05 | R14: ='7a. Success 3 yr'!P14*'7. Success Allocation'!R$5 -> 182166.97 | S14: ='7a. Success 3 yr'!Q14*'7. Success Allocation'!S$5 -> 69905.638 | T14: =SUM(L14:S14) -> 1087192 | V14: ='7a. Success 3 yr'!R14*'7. Success Allocation'!V$5 -> 335347.16 | W14: ='7a. Success 3 yr'!S14*'7. Success Allocation'!W$5 -> 150306.49 | X14: ='7a. Success 3 yr'!T14*'7. Success Allocation'!X$5 -> 0 | Y14: ='7a. Success 3 yr'!U14*'7. Success Allocation'!Y$5 -> 75465.604 | Z14: ='7a. Success 3 yr'!V14*'7. Success Allocation'!Z$5 -> 44979.499 | AA14: ='7a. Success 3 yr'!W14*'7. Success Allocation'!AA$5 -> 156428.7 | AB14: ='7a. Success 3 yr'!X14*'7. Success Allocation'!AB$5 -> 179543.17 | AC14: ='7a. Success 3 yr'!Y14*'7. Success Allocation'!AC$5 -> 83586.903 | AD14: =SUM(V14:AC14) -> 1025657.5 | AF14: =SUM(J14,T14,AD14) -> 7913455.7
A15: Coast | B15: ='7a. Success 3 yr'!B15*'7. Success Allocation'!B$5 -> 3186547.6 | C15: ='7a. Success 3 yr'!C15*'7. Success Allocation'!C$5 -> 3928209.6 | D15: ='7a. Success 3 yr'!D15*'7. Success Allocation'!D$5 -> 0 | E15: ='7a. Success 3 yr'!E15*'7. Success Allocation'!E$5 -> 850612.31 | F15: ='7a. Success 3 yr'!F15*'7. Success Allocation'!F$5 -> 1145477.9 | G15: ='7a. Success 3 yr'!G15*'7. Success Allocation'!G$5 -> 2786230.1 | H15: ='7a. Success 3 yr'!H15*'7. Success Allocation'!H$5 -> 3701812.8 | I15: ='7a. Success 3 yr'!I15*'7. Success Allocation'!I$5 -> 2000588.2 | J15: =SUM(B15:I15) -> 17599479 | L15: ='7a. Success 3 yr'!J15*'7. Success Allocation'!L$5 -> 610971.53 | M15: ='7a. Success 3 yr'!K15*'7. Success Allocation'!M$5 -> 563930.47 | N15: ='7a. Success 3 yr'!L15*'7. Success Allocation'!N$5 -> 0 | O15: ='7a. Success 3 yr'!M15*'7. Success Allocation'!O$5 -> 121444.65 | P15: ='7a. Success 3 yr'!N15*'7. Success Allocation'!P$5 -> 163800.34 | Q15: ='7a. Success 3 yr'!O15*'7. Success Allocation'!Q$5 -> 376328.48 | R15: ='7a. Success 3 yr'!P15*'7. Success Allocation'!R$5 -> 554372.33 | S15: ='7a. Success 3 yr'!Q15*'7. Success Allocation'!S$5 -> 137937.13 | T15: =SUM(L15:S15) -> 2528784.9 | V15: ='7a. Success 3 yr'!R15*'7. Success Allocation'!V$5 -> 548250.12 | W15: ='7a. Success 3 yr'!S15*'7. Success Allocation'!W$5 -> 585483.15 | X15: ='7a. Success 3 yr'!T15*'7. Success Allocation'!X$5 -> 0 | Y15: ='7a. Success 3 yr'!U15*'7. Success Allocation'!Y$5 -> 137687.24 | Z15: ='7a. Success 3 yr'!V15*'7. Success Allocation'!Z$5 -> 146683.14 | AA15: ='7a. Success 3 yr'!W15*'7. Success Allocation'!AA$5 -> 414436.11 | AB15: ='7a. Success 3 yr'!X15*'7. Success Allocation'!AB$5 -> 527197.21 | AC15: ='7a. Success 3 yr'!Y15*'7. Success Allocation'!AC$5 -> 216776.2 | AD15: =SUM(V15:AC15) -> 2576513.2 | AF15: =SUM(J15,T15,AD15) -> 22704777
A16: Compton | B16: ='7a. Success 3 yr'!B16*'7. Success Allocation'!B$5 -> 0 | C16: ='7a. Success 3 yr'!C16*'7. Success Allocation'!C$5 -> 647704.79 | D16: ='7a. Success 3 yr'!D16*'7. Success Allocation'!D$5 -> 0 | E16: ='7a. Success 3 yr'!E16*'7. Success Allocation'!E$5 -> 47978.133 | F16: ='7a. Success 3 yr'!F16*'7. Success Allocation'!F$5 -> 24988.611 | G16: ='7a. Success 3 yr'!G16*'7. Success Allocation'!G$5 -> 277373.58 | H16: ='7a. Success 3 yr'!H16*'7. Success Allocation'!H$5 -> 366582.92 | I16: ='7a. Success 3 yr'!I16*'7. Success Allocation'!I$5 -> 388323.01 | J16: =SUM(B16:I16) -> 1752951 | L16: ='7a. Success 3 yr'!J16*'7. Success Allocation'!L$5 -> 0 | M16: ='7a. Success 3 yr'!K16*'7. Success Allocation'!M$5 -> 181604.73 | N16: ='7a. Success 3 yr'!L16*'7. Success Allocation'!N$5 -> 0 | O16: ='7a. Success 3 yr'!M16*'7. Success Allocation'!O$5 -> 13493.85 | P16: ='7a. Success 3 yr'!N16*'7. Success Allocation'!P$5 -> 4123.1208 | Q16: ='7a. Success 3 yr'!O16*'7. Success Allocation'!Q$5 -> 58660.764 | R16: ='7a. Success 3 yr'!P16*'7. Success Allocation'!R$5 -> 63814.665 | S16: ='7a. Success 3 yr'!Q16*'7. Success Allocation'!S$5 -> 41043.793 | T16: =SUM(L16:S16) -> 362740.92 | V16: ='7a. Success 3 yr'!R16*'7. Success Allocation'!V$5 -> 0 | W16: ='7a. Success 3 yr'!S16*'7. Success Allocation'!W$5 -> 152930.3 | X16: ='7a. Success 3 yr'!T16*'7. Success Allocation'!X$5 -> 0 | Y16: ='7a. Success 3 yr'!U16*'7. Success Allocation'!Y$5 -> 10495.216 | Z16: ='7a. Success 3 yr'!V16*'7. Success Allocation'!Z$5 -> 4747.836 | AA16: ='7a. Success 3 yr'!W16*'7. Success Allocation'!AA$5 -> 52476.082 | AB16: ='7a. Success 3 yr'!X16*'7. Success Allocation'!AB$5 -> 56036.959 | AC16: ='7a. Success 3 yr'!Y16*'7. Success Allocation'!AC$5 -> 45854.101 | AD16: =SUM(V16:AC16) -> 322540.49 | AF16: =SUM(J16,T16,AD16) -> 2438232.5
A17: Contra Costa | B17: ='7a. Success 3 yr'!B17*'7. Success Allocation'!B$5 -> 2842704.4 | C17: ='7a. Success 3 yr'!C17*'7. Success Allocation'!C$5 -> 2244477 | D17: ='7a. Success 3 yr'!D17*'7. Success Allocation'!D$5 -> 0 | E17: ='7a. Success 3 yr'!E17*'7. Success Allocation'!E$5 -> 595728.48 | F17: ='7a. Success 3 yr'!F17*'7. Success Allocation'!F$5 -> 901589.07 | G17: ='7a. Success 3 yr'!G17*'7. Success Allocation'!G$5 -> 2201996.4 | H17: ='7a. Success 3 yr'!H17*'7. Success Allocation'!H$5 -> 2725757.7 | I17: ='7a. Success 3 yr'!I17*'7. Success Allocation'!I$5 -> 1249930.3 | J17: =SUM(B17:I17) -> 12762183 | L17: ='7a. Success 3 yr'!J17*'7. Success Allocation'!L$5 -> 419059 | M17: ='7a. Success 3 yr'!K17*'7. Success Allocation'!M$5 -> 377827.79 | N17: ='7a. Success 3 yr'!L17*'7. Success Allocation'!N$5 -> 0 | O17: ='7a. Success 3 yr'!M17*'7. Success Allocation'!O$5 -> 70842.711 | P17: ='7a. Success 3 yr'!N17*'7. Success Allocation'!P$5 -> 77214.807 | Q17: ='7a. Success 3 yr'!O17*'7. Success Allocation'!Q$5 -> 305485.77 | R17: ='7a. Success 3 yr'!P17*'7. Success Allocation'!R$5 -> 327225.86 | S17: ='7a. Success 3 yr'!Q17*'7. Success Allocation'!S$5 -> 94644.363 | T17: =SUM(L17:S17) -> 1672300.3 | V17: ='7a. Success 3 yr'!R17*'7. Success Allocation'!V$5 -> 399817.77 | W17: ='7a. Success 3 yr'!S17*'7. Success Allocation'!W$5 -> 363959.11 | X17: ='7a. Success 3 yr'!T17*'7. Success Allocation'!X$5 -> 0 | Y17: ='7a. Success 3 yr'!U17*'7. Success Allocation'!Y$5 -> 65969.932 | Z17: ='7a. Success 3 yr'!V17*'7. Success Allocation'!Z$5 -> 84461.504 | AA17: ='7a. Success 3 yr'!W17*'7. Success Allocation'!AA$5 -> 304486.22 | AB17: ='7a. Success 3 yr'!X17*'7. Success Allocation'!AB$5 -> 342031.61 | AC17: ='7a. Success 3 yr'!Y17*'7. Success Allocation'!AC$5 -> 123193.85 | AD17: =SUM(V17:AC17) -> 1683920 | AF17: =SUM(J17,T17,AD17) -> 16118404
... A77: Yuba | B77: ='7a. Success 3 yr'!B77*'7. Success Allocation'!B$5 -> 477782.24 | C77: ='7a. Success 3 yr'!C77*'7. Success Allocation'!C$5 -> 931075.63 | D77: ='7a. Success 3 yr'!D77*'7. Success Allocation'!D$5 -> 0 | E77: ='7a. Success 3 yr'!E77*'7. Success Allocation'!E$5 -> 98954.898 | F77: ='7a. Success 3 yr'!F77*'7. Success Allocation'!F$5 -> 104952.16 | G77: ='7a. Success 3 yr'!G77*'7. Success Allocation'!G$5 -> 682189.07 | H77: ='7a. Success 3 yr'!H77*'7. Success Allocation'!H$5 -> 588481.78 | I77: ='7a. Success 3 yr'!I77*'7. Success Allocation'!I$5 -> 876100.69 | J77: =SUM(B77:I77) -> 3759536.5 | L77: ='7a. Success 3 yr'!J77*'7. Success Allocation'!L$5 -> 118446.01 | M77: ='7a. Success 3 yr'!K77*'7. Success Allocation'!M$5 -> 226021.98 | N77: ='7a. Success 3 yr'!L77*'7. Success Allocation'!N$5 -> 0 | O77: ='7a. Success 3 yr'!M77*'7. Success Allocation'!O$5 -> 17242.141 | P77: ='7a. Success 3 yr'!N77*'7. Success Allocation'!P$5 -> 17991.8 | Q77: ='7a. Success 3 yr'!O77*'7. Success Allocation'!Q$5 -> 148619.76 | R77: ='7a. Success 3 yr'!P77*'7. Success Allocation'!R$5 -> 108513.04 | S77: ='7a. Success 3 yr'!Q77*'7. Success Allocation'!S$5 -> 149556.84 | T77: =SUM(L77:S77) -> 786391.58 | V77: ='7a. Success 3 yr'!R77*'7. Success Allocation'!V$5 -> 102953.08 | W77: ='7a. Success 3 yr'!S77*'7. Success Allocation'!W$5 -> 199783.94 | X77: ='7a. Success 3 yr'!T77*'7. Success Allocation'!X$5 -> 0 | Y77: ='7a. Success 3 yr'!U77*'7. Success Allocation'!Y$5 -> 19491.116 | Z77: ='7a. Success 3 yr'!V77*'7. Success Allocation'!Z$5 -> 17492.027 | AA77: ='7a. Success 3 yr'!W77*'7. Success Allocation'!AA$5 -> 141060.71 | AB77: ='7a. Success 3 yr'!X77*'7. Success Allocation'!AB$5 -> 99704.557 | AC77: ='7a. Success 3 yr'!Y77*'7. Success Allocation'!AC$5 -> 150681.32 | AD77: =SUM(V77:AC77) -> 731166.75 | AF77: =SUM(J77,T77,AD77) -> 5277094.8
A78: Statewide Total | B78: =SUM(B6:B77) -> 87939919 | C78: =SUM(C6:C77) -> 92690753 | D78: =SUM(D6:D77) -> 158927.56 | E78: =SUM(E6:E77) -> 20964445 | F78: =SUM(F6:F77) -> 25223504 | G78: =SUM(G6:G77) -> 93206518 | H78: =SUM(H6:H77) -> 94817534 | I78: =SUM(I6:I77) -> 94294522 | J78: =SUM(J6:J77) -> 5.0929612e+08 | L78: =SUM(L6:L77) -> 18057770 | M78: =SUM(M6:M77) -> 18829543 | N78: =SUM(N6:N77) -> 28112.187 | O78: =SUM(O6:O77) -> 3608855.2 | P78: =SUM(P6:P77) -> 3414693.7 | Q78: =SUM(Q6:Q77) -> 15649680 | R78: =SUM(R6:R77) -> 15118734 | S78: =SUM(S6:S77) -> 9491798.8 | T78: =SUM(T6:T77) -> 84199186 | V78: =SUM(V6:V77) -> 16304569 | W78: =SUM(W6:W77) -> 17372582 | X78: =SUM(X6:X77) -> 31485.649 | Y78: =SUM(Y6:Y77) -> 3521644.9 | Z78: =SUM(Z6:Z77) -> 3339477.9 | AA78: =SUM(AA6:AA77) -> 15524424 | AB78: =SUM(AB6:AB77) -> 14917451 | AC78: =SUM(AC6:AC77) -> 11277610 | AD78: =SUM(AD6:AD77) -> 82289244 | AF78: =SUM(AF6:AF77) -> 6.7578455e+08
AF79: ='2. Weighting'!B8 -> 7.1560281e+08

Sheet 7a. Success 3 yr
B1: 3 year average (2016-17, 2017-18, 2018-19 projected)
B2: All Students | J2: Pell Grant Students Only | R2: Promise Grant Students Only
A3: District | B3: Associate Degrees for Transfer | C3: Associate Degrees | D3: BA | E3: Credit Certificates | F3: Transfer Level Math and English | G3: Nine or More CTE Units | H3: Transfer | I3: Regional Living Wage | J3: Associate Degrees for Transfer | K3: Associate Degrees | L3: BA | M3: Credit Certificates | N3: Transfer Level Math and English | O3: Nine or More CTE Units | P3: Transfer | Q3: Regional Living Wage | R3: Associate Degrees for Transfer | S3: Associate Degrees | T3: BA | U3: Credit Certificates | V3: Transfer Level Math and English | W3: Nine or More CTE Units | X3: Transfer | Y3: Regional Living Wage
A6: Allan Hancock | B6: =AVERAGE('7b. Success proj 1819'!B4,'7c. Success counts 1718'!B4,'7d Success counts 1617'!B4) -> 272 | C6: =AVERAGE('7b. Success proj 1819'!C4,'7c. Success counts 1718'!C4,'7d Success counts 1617'!C4) -> 577 | D6: =AVERAGE('7b. Success proj 1819'!D4,'7c. Success counts 1718'!D4,'7d Success counts 1617'!D4) -> 0 | E6: =AVERAGE('7b. Success proj 1819'!E4,'7c. Success counts 1718'!E4,'7d Success counts 1617'!E4) -> 244 | F6: =AVERAGE('7b. Success proj 1819'!F4,'7c. Success counts 1718'!F4,'7d Success counts 1617'!F4) -> 190 | G6: =AVERAGE('7b. Success proj 1819'!G4,'7c. Success counts 1718'!G4,'7d Success counts 1617'!G4) -> 1915 | H6: =AVERAGE('7b. Success proj 1819'!H4,'7c. Success counts 1718'!H4,'7d Success counts 1617'!H4) -> 865 | I6: =AVERAGE('7b. Success proj 1819'!I4,'7c. Success counts 1718'!I4,'7d Success counts 1617'!I4) -> 2224 | ... Y6: =AVERAGE('7b. Success proj 1819'!Y4,'7c. Success counts 1718'!Y4,'7d Success counts 1617'!Y4) -> 943
A7: Antelope | B7: =AVERAGE('7b. Success proj 1819'!B5,'7c. Success counts 1718'!B5,'7d Success counts 1617'!B5) -> 485 | C7: =AVERAGE('7b. Success proj 1819'!C5,'7c. Success counts 1718'!C5,'7d Success counts 1617'!C5) -> 676 | D7: =AVERAGE('7b. Success proj 1819'!D5,'7c. Success counts 1718'!D5,'7d Success counts 1617'!D5) -> 0 | E7: =AVERAGE('7b. Success proj 1819'!E5,'7c. Success counts 1718'!E5,'7d Success counts 1617'!E5) -> 254 | F7: =AVERAGE('7b. Success proj 1819'!F5,'7c. Success counts 1718'!F5,'7d Success counts 1617'!F5) -> 187 | G7: =AVERAGE('7b. Success proj 1819'!G5,'7c. Success counts 1718'!G5,'7d Success counts 1617'!G5) -> 2033 | H7: =AVERAGE('7b. Success proj 1819'!H5,'7c. Success counts 1718'!H5,'7d Success counts 1617'!H5) -> 992 | I7: =AVERAGE('7b. Success proj 1819'!I5,'7c. Success counts 1718'!I5,'7d Success counts 1617'!I5) -> 1147 | ... Y7: =AVERAGE('7b. Success proj 1819'!Y5,'7c. Success counts 1718'!Y5,'7d Success counts 1617'!Y5) -> 874
A8: Barstow | B8: =AVERAGE('7b. Success proj 1819'!B6,'7c. Success counts 1718'!B6,'7d Success counts 1617'!B6) -> 67 | C8: =AVERAGE('7b. Success proj 1819'!C6,'7c. Success counts 1718'!C6,'7d Success counts 1617'!C6) -> 252 | D8: =AVERAGE('7b. Success proj 1819'!D6,'7c. Success counts 1718'!D6,'7d Success counts 1617'!D6) -> 0 | E8: =AVERAGE('7b. Success proj 1819'!E6,'7c. Success counts 1718'!E6,'7d Success counts 1617'!E6) -> 17 | F8: =AVERAGE('7b. Success proj 1819'!F6,'7c. Success counts 1718'!F6,'7d Success counts 1617'!F6) -> 57 | G8: =AVERAGE('7b. Success proj 1819'!G6,'7c. Success counts 1718'!G6,'7d Success counts 1617'!G6) -> 374 | H8: =AVERAGE('7b. Success proj 1819'!H6,'7c. Success counts 1718'!H6,'7d Success counts 1617'!H6) -> 330 | I8: =AVERAGE('7b. Success proj 1819'!I6,'7c. Success counts 1718'!I6,'7d Success counts 1617'!I6) -> 516 | ... Y8: =AVERAGE('7b. Success proj 1819'!Y6,'7c. Success counts 1718'!Y6,'7d Success counts 1617'!Y6) -> 338
A9: Butte | B9: =AVERAGE('7b. Success proj 1819'!B7,'7c. Success counts 1718'!B7,'7d Success counts 1617'!B7) -> 304 | C9: =AVERAGE('7b. Success proj 1819'!C7,'7c. Success counts 1718'!C7,'7d Success counts 1617'!C7) -> 730 | D9: =AVERAGE('7b. Success proj 1819'!D7,'7c. Success counts 1718'!D7,'7d Success counts 1617'!D7) -> 0 | E9: =AVERAGE('7b. Success proj 1819'!E7,'7c. Success counts 1718'!E7,'7d Success counts 1617'!E7) -> 331 | F9: =AVERAGE('7b. Success proj 1819'!F7,'7c. Success counts 1718'!F7,'7d Success counts 1617'!F7) -> 268 | G9: =AVERAGE('7b. Success proj 1819'!G7,'7c. Success counts 1718'!G7,'7d Success counts 1617'!G7) -> 2192 | H9: =AVERAGE('7b. Success proj 1819'!H7,'7c. Success counts 1718'!H7,'7d Success counts 1617'!H7) -> 1201 | I9: =AVERAGE('7b. Success proj 1819'!I7,'7c. Success counts 1718'!I7,'7d Success counts 1617'!I7) -> 1674 | ... Y9: =AVERAGE('7b. Success proj 1819'!Y7,'7c. Success counts 1718'!Y7,'7d Success counts 1617'!Y7) -> 1076
A10: Cabrillo | B10: =AVERAGE('7b. Success proj 1819'!B8,'7c. Success counts 1718'!B8,'7d Success counts 1617'!B8) -> 253 | C10: =AVERAGE('7b. Success proj 1819'!C8,'7c. Success counts 1718'!C8,'7d Success counts 1617'!C8) -> 700 | D10: =AVERAGE('7b. Success proj 1819'!D8,'7c. Success counts 1718'!D8,'7d Success counts 1617'!D8) -> 0 | E10: =AVERAGE('7b. Success proj 1819'!E8,'7c. Success counts 1718'!E8,'7d Success counts 1617'!E8) -> 59 | F10: =AVERAGE('7b. Success proj 1819'!F8,'7c. Success counts 1718'!F8,'7d Success counts 1617'!F8) -> 134 | G10: =AVERAGE('7b. Success proj 1819'!G8,'7c. Success counts 1718'!G8,'7d Success counts 1617'!G8) -> 1135 | H10: =AVERAGE('7b. Success proj 1819'!H8,'7c. Success counts 1718'!H8,'7d Success counts 1617'!H8) -> 1016 | I10: =AVERAGE('7b. Success proj 1819'!I8,'7c. Success counts 1718'!I8,'7d Success counts 1617'!I8) -> 1650 | ... Y10: =AVERAGE('7b. Success proj 1819'!Y8,'7c. Success counts 1718'!Y8,'7d Success counts 1617'!Y8) -> 707
A11: Cerritos | B11: =AVERAGE('7b. Success proj 1819'!B9,'7c. Success counts 1718'!B9,'7d Success counts 1617'!B9) -> 690 | C11: =AVERAGE('7b. Success proj 1819'!C9,'7c. Success counts 1718'!C9,'7d Success counts 1617'!C9) -> 907 | D11: =AVERAGE('7b. Success proj 1819'!D9,'7c. Success counts 1718'!D9,'7d Success counts 1617'!D9) -> 0 | E11: =AVERAGE('7b. Success proj 1819'!E9,'7c. Success counts 1718'!E9,'7d Success counts 1617'!E9) -> 668 | F11: =AVERAGE('7b. Success proj 1819'!F9,'7c. Success counts 1718'!F9,'7d Success counts 1617'!F9) -> 204 | G11: =AVERAGE('7b. Success proj 1819'!G9,'7c. Success counts 1718'!G9,'7d Success counts 1617'!G9) -> 3738 | H11: =AVERAGE('7b. Success proj 1819'!H9,'7c. Success counts 1718'!H9,'7d Success counts 1617'!H9) -> 1344 | I11: =AVERAGE('7b. Success proj 1819'!I9,'7c. Success counts 1718'!I9,'7d Success counts 1617'!I9) -> 2879 | ... Y11: =AVERAGE('7b. Success proj 1819'!Y9,'7c. Success counts 1718'!Y9,'7d Success counts 1617'!Y9) -> 1348
A12: Chabot-Las Positas | B12: =AVERAGE('7b. Success proj 1819'!B10,'7c. Success counts 1718'!B10,'7d Success counts 1617'!B10) -> 623 | C12: =AVERAGE('7b. Success proj 1819'!C10,'7c. Success counts 1718'!C10,'7d Success counts 1617'!C10) -> 862 | D12: =AVERAGE('7b. Success proj 1819'!D10,'7c. Success counts 1718'!D10,'7d Success counts 1617'!D10) -> 0 | E12: =AVERAGE('7b. Success proj 1819'!E10,'7c. Success counts 1718'!E10,'7d Success counts 1617'!E10) -> 270 | F12: =AVERAGE('7b. Success proj 1819'!F10,'7c. Success counts 1718'!F10,'7d Success counts 1617'!F10) -> 470 | G12: =AVERAGE('7b. Success proj 1819'!G10,'7c. Success counts 1718'!G10,'7d Success counts 1617'!G10) -> 2718 | H12: =AVERAGE('7b. Success proj 1819'!H10,'7c. Success counts 1718'!H10,'7d Success counts 1617'!H10) -> 2089 | I12: =AVERAGE('7b. Success proj 1819'!I10,'7c. Success counts 1718'!I10,'7d Success counts 1617'!I10) -> 2555 | ... Y12: =AVERAGE('7b. Success proj 1819'!Y10,'7c. Success counts 1718'!Y10,'7d Success counts 1617'!Y10) -> 958
A13: Chaffey | B13: =AVERAGE('7b. Success proj 1819'!B11,'7c. Success counts 1718'!B11,'7d Success counts 1617'!B11) -> 856 | C13: =AVERAGE('7b. Success proj 1819'!C11,'7c. Success counts 1718'!C11,'7d Success counts 1617'!C11) -> 862 | D13: =AVERAGE('7b. Success proj 1819'!D11,'7c. Success counts 1718'!D11,'7d Success counts 1617'!D11) -> 0 | E13: =AVERAGE('7b. Success proj 1819'!E11,'7c. Success counts 1718'!E11,'7d Success counts 1617'!E11) -> 403 | F13: =AVERAGE('7b. Success proj 1819'!F11,'7c. Success counts 1718'!F11,'7d Success counts 1617'!F11) -> 263 | G13: =AVERAGE('7b. Success proj 1819'!G11,'7c. Success counts 1718'!G11,'7d Success counts 1617'!G11) -> 2382 | H13: =AVERAGE('7b. Success proj 1819'!H11,'7c. Success counts 1718'!H11,'7d Success counts 1617'!H11) -> 1413 | I13: =AVERAGE('7b. Success proj 1819'!I11,'7c. Success counts 1718'!I11,'7d Success counts 1617'!I11) -> 2781 | ... Y13: =AVERAGE('7b. Success proj 1819'!Y11,'7c. Success counts 1718'!Y11,'7d Success counts 1617'!Y11) -> 2030
A14: Citrus | B14: =AVERAGE('7b. Success proj 1819'!B12,'7c. Success counts 1718'!B12,'7d Success counts 1617'!B12) -> 876 | C14: =AVERAGE('7b. Success proj 1819'!C12,'7c. Success counts 1718'!C12,'7d Success counts 1617'!C12) -> 562 | D14: =AVERAGE('7b. Success proj 1819'!D12,'7c. Success counts 1718'!D12,'7d Success counts 1617'!D12) -> 0 | E14: =AVERAGE('7b. Success proj 1819'!E12,'7c. Success counts 1718'!E12,'7d Success counts 1617'!E12) -> 396 | F14: =AVERAGE('7b. Success proj 1819'!F12,'7c. Success counts 1718'!F12,'7d Success counts 1617'!F12) -> 324 | G14: =AVERAGE('7b. Success proj 1819'!G12,'7c. Success counts 1718'!G12,'7d Success counts 1617'!G12) -> 1728 | H14: =AVERAGE('7b. Success proj 1819'!H12,'7c. Success counts 1718'!H12,'7d Success counts 1617'!H12) -> 1399 | I14: =AVERAGE('7b. Success proj 1819'!I12,'7c. Success counts 1718'!I12,'7d Success counts 1617'!I12) -> 1150 | ... Y14: =AVERAGE('7b. Success proj 1819'!Y12,'7c. Success counts 1718'!Y12,'7d Success counts 1617'!Y12) -> 669
