Workbook

Sheet READ ME
B1: Blue indicates raw data
B2: Indicates projected estimates
B3: Rate Assumptions
B4: Allocation Calculations

Sheet 2019-20 Rates
C1: Calculated with data available as of October 10, 2019
A2: EdCode | B2: 84750.4(b)(2) | C2: 2019-20 TCR by DOF at Budget Act | E2: 7430429651
A4: Budget Act 2019 | B4: Provision 2(a)(1) | C4: Growth | E4: 24727000 | F4: UNCLEAR WHERE THESE COME FROM
A5: EdCode | B5: 84750.4(b)(2) | C5: Hold Harmless - DOF | E5: 1.2230507e+08 | F5: UNCLEAR WHERE THESE COME FROM | G5: =22214518+121403827 -> 143618345
A6: EdCode | B6: 84750.4(b)(1) | C6: Cost of CDCP FTES | E6: 216366451 | F6: ="Calculated as " & TEXT('Base Allocation'!AB80, "###,###,###") & " using $5,313 growth at COLA (2.71%, 3.26%)" -> Calculated as 222,214,518 using $5,313 growth at COLA (2.71%, 3.26%)
A7: EdCode | B7: 84750.4(b)(1) | C7: Cost of Noncredit FTES | E7: 110682048 | F7: ="Calculated as " & TEXT('Base Allocation'!AA80, "###,###,###") & " using $3,259 growth at COLA (2.71%, 3.26%)" -> Calculated as 121,403,827 using $3,259 growth at COLA (2.71%, 3.26%)
C8: subtotal | E8: =SUM(E4:E7) -> 4.7408057e+08
C10: Funds Available for Distribution | E10: =E2-E8 -> 6.9563491e+09
A12: EdCode | B12: 84750.4(b)(2)(A) | C12: Base Allocation | D12: 0.7 | E12: =ROUND(D12*E10,0) -> 4869444357
A13: EdCode | B13: 84750.4(b)(2)(B) | C13: Supplemental Allocation | D13: 0.2 | E13: =ROUND(D13*E10,0) -> 1391269816
A14: EdCode | B14: 84750.4(b)(2)(C)(i) | C14: Student Success Allocation | D14: 0.1 | E14: =ROUND(D14*E10,0) -> 695634908
C15: =C10 -> Funds Available for Distribution | E15: =SUM(E12:E14) -> 6956349081
C17: =C12 -> Base Allocation | E17: =E12 -> 4869444357
C19: Cost of Basic Allocation | E19: 620217582 | F19: ="Calculated as " & TEXT('Base Allocation'!$AD$77, "$###,###,###,###") -> Calculated as $628,729,878
A20: EdCode | B20: 84750.4(d)(3) | C20: Cost of Incarcerated Students | E20: 25634535 | F20: ="Calculated as " & TEXT('Base Allocation'!W80, "###,###,###") & " using $5,313 growth at COLA (2.71%, 3.26%)" -> Calculated as 28,276,764 using $5,313 growth at COLA (2.71%, 3.26%)
A21: EdCode | B21: 84750.4(d)(3) | C21: Cost of Special Admit Students | E21: 205252980 | F21: ="Calculated as " & TEXT('Base Allocation'!X80, "###,###,###") & " using $5,313 growth at COLA (2.71%, 3.26%)" -> Calculated as 202,119,426 using $5,313 growth at COLA (2.71%, 3.26%)
C22: subtotal | E22: =SUM(E19:E21) -> 851105097 | F22: =TEXT(SUM('Base Allocation'!$AD$77, 'Base Allocation'!W80, 'Base Allocation'!X80), "$###,###,###,###") -> $859,126,069
C24: Funds for New Credit FTES Rate | E24: =E17-E22 -> 4018339260
C25: 3 year average Credit FTES | E25: 1007459.6 | F25: ="Calculated as "& TEXT('Base Allocation'!$Z$77, "###,###,###,###") -> Calculated as 1,003,322 | G25: 2018-19 | H25: dif | I25: %dif
A26: EdCode | B26: 84750.4(d)(1)(C)(ii) | C26: New Credit FTES Rate | E26: =E24/E25 -> 3988.5862 | G26: 3727 | H26: =E26-G26 -> 261.58618 | I26: =H26/G26 -> 0.070186793
C28: Supplemental Allocation | E28: =E13 -> 1391269816
A29: EdCode | B29: 84750.4(b)(2)(C)(i)(ii) | C29: Total Point Count | E29: =G53 -> 1496683 | F29: ="Calculated as " & TEXT(SUM('Supplemental Allocation'!K76, 'Supplemental Allocation'!L76, 'Supplemental Allocation'!M76), "###,###,###,###") -> Calculated as 1,471,229
C30: New Supplemental Allocation Point Value | E30: =E28/E29 -> 929.5688 | G30: 919 | H30: =E30-G30 -> 10.568797 | I30: =H30/G30 -> 0.011500323
C32: =C14 -> Student Success Allocation | E32: =E14 -> 695634908
C34: Main Component | D34: 0.75 | E34: =ROUND(D34*E32,0) -> 521726181
C35: Equity Component | D35: 0.25 | E35: =ROUND(D35*E32,0) -> 173908727
E36: =SUM(E34:E35) -> 695634908
C38: Main Component | E38: =E34 -> 521726181
C39: Point Count for Main Component | E39: =G72 -> 910614.17 | F39: ="Calculated as " & TEXT('Success Allocation'!$DA$80, "###,###,###,###") -> Calculated as 1,019,057 | G39: ='Success Allocation'!$DA$80 -> 1019056.5
C40: New Main Component Point Value | E40: =IF(E39>0,(E38/E39),0) -> 572.93879 | G40: 440 | H40: =E40-G40 -> 132.93879 | I40: =H40/G40 -> 0.30213362
C42: Equity Component | E42: =E35 -> 173908727
C43: Point Count for Equity Component | E43: =G89+G100 -> 1204471.3 | F43: ="Calculated as " & TEXT('Success Allocation'!$DI$80+'Success Allocation'!$DQ$80, "###,###,###,###") -> Calculated as 1,430,928
C44: New Equity Component Point Value | E44: =IF(E43>0,(E42/E43),0) -> 144.38595 | G44: 111 | H44: =E44-G44 -> 33.385951 | I44: =H44/G44 -> 0.30077433
C46: Supplemental
E48: Points | F48: Total Counts1 | G48: Total Points | H48: Total Dollars
C49: Metrics | E49: (a) | F49: (b) | G49: (c) = (a) * (b) | H49: =CONCATENATE("(d) = (c) * $",TEXT(E55,"#,###")) -> (d) = (c) * $930
C50: AB 540 Students | E50: 1 | F50: ='[1]720| Supplemental Data'!B83 -> 59199 | G50: =F50*E50 -> 59199 | H50: =G50*$E$55 -> 55029543
C51: Pell Grant Recipients | E51: 1 | F51: ='[1]720| Supplemental Data'!C83 -> 448958 | G51: =F51*E51 -> 448958 | H51: =G51*$E$55 -> 4.1733735e+08
C52: Promise Grant Recipients | E52: 1 | F52: ='[1]720| Supplemental Data'!D83 -> 988526 | G52: =F52*E52 -> 988526 | H52: =G52*$E$55 -> 9.1890292e+08
C53: Total | E53: =SUM(E50:E52) -> 3 | F53: =SUM(F50:F52) -> 1496683 | G53: =SUM(G50:G52) -> 1496683 | H53: =SUM(H50:H52) -> 1391269816
C55: Supplemental Rate Per Point | E55: =E30 -> 929.5688
C57: =C28 -> Supplemental Allocation | E57: =E28 -> 1391269816
C58: Goal seek to zero | E58: =E57-H53 -> 0
C60: Student Success
E62: Points | F62: Total Counts1 | G62: Total Points | H62: Total Dollars
C63: All Students | E63: (a) | F63: (b) | G63: (c) = (a) * (b) | H63: =CONCATENATE("(d) = (c) * $",TEXT(E74,"#,###")) -> (d) = (c) * $573
C64: Associate Degrees for Transfers | E64: 4 | F64: 41335.333 | G64: =F64*E64 -> 165341.33 | H64: =$E$74*G64 -> 94730464
C65: Associate Degrees | E65: 3 | F65: 61562.667 | G65: =F65*E65 -> 184688 | H65: =$E$74*G65 -> 1.0581492e+08
C66: Baccalaureate Degrees | E66: 3 | F66: 70.666667 | G66: =F66*E66 -> 212 | H66: =$E$74*G66 -> 121463.02
C67: Credit Certificates | E67: 2 | F67: 20245.667 | G67: =F67*E67 -> 40491.333 | H67: =$E$74*G67 -> 23199056
C68: Transfer Level Math and English | E68: 2 | F68: 24095.667 | G68: =F68*E68 -> 48191.333 | H68: =$E$74*G68 -> 27610684
C69: Transfers | E69: 1.5 | F69: 68005 | G69: =F69*E69 -> 102007.5 | H69: =$E$74*G69 -> 58444054
C70: Nine or More CTE Units | E70: 1 | F70: 185323.33 | G70: =F70*E70 -> 185323.33 | H70: =$E$74*G70 -> 1.0617893e+08
C71: Regional Living Wage | E71: 1 | F71: 184359.33 | G71: =F71*E71 -> 184359.33 | H71: =$E$74*G71 -> 1.0562661e+08
C72: Total | E72: =SUM(E64:E71) -> 17.5 | F72: =SUM(F64:F71) -> 584997.67 | G72: =SUM(G64:G71) -> 910614.17 | H72: =SUM(H64:H71) -> 5.2172618e+08
C74: Student Success Main Component Rate per Point | E74: =E40 -> 572.93879
C76: =C38 -> Main Component | E76: =E38 -> 521726181
C77: Goal seek to zero | E77: =E76-H72 -> 0
E79: Points | F79: Total Counts1 | G79: Total Points | H79: Total Dollars
C80: Pell Grant Recipients | E80: (a) | F80: (b) | G80: (c) = (a) * (b) | H80: =CONCATENATE("(d) = (c) * $",TEXT(E102,"#,###")) -> (d) = (c) * $144
C81: Associate Degrees for Transfers PELL GRANT | E81: 6 | F81: 22725.333 | G81: =F81*E81 -> 136352 | H81: =$E$102*G81 -> 19687313
C82: Associate Degrees PELL GRANT | E82: 4.5 | F82: 33490.333 | G82: =F82*E82 -> 150706.5 | H82: =$E$102*G82 -> 21759901
C83: Baccalaureate Degrees PELL GRANT | E83: 4.5 | F83: 33.333333 | G83: =F83*E83 -> 150 | H83: =$E$102*G83 -> 21657.893
C84: Credit Certificates PELL GRANT | E84: 3 | F84: 9376.6667 | G84: =F84*E84 -> 28130 | H84: =$E$102*G84 -> 4061576.8
C85: Transfer Level Math and English PELL GRANT | E85: 3 | F85: 8522.6667 | G85: =F85*E85 -> 25568 | H85: =$E$102*G85 -> 3691660
C86: Transfers PELL GRANT | E86: 2.25 | F86: 32186.333 | G86: =F86*E86 -> 72419.25 | H86: =$E$102*G86 -> 10456322
C87: Nine or More CTE Units PELL GRANT | E87: 1.5 | F87: 83658.333 | G87: =F87*E87 -> 125487.5 | H87: =$E$102*G87 -> 18118632
C88: Regional Living Wage PELL GRANT | E88: 1.5 | F88: 49276 | G88: =F88*E88 -> 73914 | H88: =$E$102*G88 -> 10672143
C89: Total | E89: =SUM(E81:E88) -> 26.25 | F89: =SUM(F81:F88) -> 239269 | G89: =SUM(G81:G88) -> 612727.25 | H89: =SUM(H81:H88) -> 88469207
C91: Promise Grant Recipients
C92: Associate Degrees for Transfers PROMISE GRANT | E92: 4 | F92: 30664.333 | G92: =F92*E92 -> 122657.33 | H92: =G92*$E$102 -> 17709996
C93: Associate Degrees PROMISE GRANT | E93: 3 | F93: 46101.333 | G93: =F93*E93 -> 138304 | H93: =G93*$E$102 -> 19969155
C94: Baccalaureate Degrees PROMISE GRANT | E94: 3 | F94: 56 | G94: =F94*E94 -> 168 | H94: =G94*$E$102 -> 24256.84
C95: Credit Certificates PROMISE GRANT | E95: 2 | F95: 13667 | G95: =F95*E95 -> 27334 | H95: =G95*$E$102 -> 3946645.6
C96: Transfer Level Math and English PROMISE GRANT | E96: 2 | F96: 12595 | G96: =F96*E96 -> 25190 | H96: =G96*$E$102 -> 3637082.1
C97: Transfers PROMISE GRANT | E97: 1.5 | F97: 44228 | G97: =F97*E97 -> 66342 | H97: =G97*$E$102 -> 9578852.8
C98: Nine or More CTE Units PROMISE GRANT | E98: 1 | F98: 123803 | G98: =F98*E98 -> 123803 | H98: =G98*$E$102 -> 17875414
C99: Regional Living Wage PROMISE GRANT | E99: 1 | F99: 87945.667 | G99: =F99*E99 -> 87945.667 | H99: =G99*$E$102 -> 12698119
C100: Total | E100: =SUM(E92:E99) -> 17.5 | F100: =SUM(F92:F99) -> 359060.33 | G100: =SUM(G92:G99) -> 591744 | H100: =SUM(H92:H99) -> 85439520
C102: Student Success Equity Rate per Point | E102: =E44 -> 144.38595
C104: =C42 -> Equity Component | E104: =E42 -> 173908727
C105: Goal seek to zero | E105: =E104-H100-H89 -> 0

Sheet Rate Assumptions
A1: Count | B1: Rate | C1: Notes
A2: Credit FTES | B2: ='2019-20 Rates'!E26 -> 3988.5862 | C2: Need to verify
A3: Noncredit FTES | B3: 3456.4415 | C3: Used value from 2017-18 grown at COLA
A4: CDCP FTES | B4: 5634.5606 | C4: Used value from 2017-18 grown at COLA
A5: Special Admits and Students in Correctional Facilities FTES | B5: =B4 -> 5634.5606 | C5: Used value from 2017-18 grown at COLA
A6: Pell Grant Recipients | B6: ='2019-20 Rates'!$E$30*'2019-20 Rates'!E51 -> 929.5688 | C6: Need to verify
A7: AB 540 Students | B7: ='2019-20 Rates'!$E$30*'2019-20 Rates'!E50 -> 929.5688 | C7: Need to verify
A8: Promise Grant Recipients | B8: ='2019-20 Rates'!$E$30*'2019-20 Rates'!E52 -> 929.5688 | C8: Need to verify
A9: Associate Degrees for Transfers | B9: ='2019-20 Rates'!$E$74*'2019-20 Rates'!E64 -> 2291.7552 | C9: Need to verify
A10: Associate Degrees | B10: ='2019-20 Rates'!$E$74*'2019-20 Rates'!E65 -> 1718.8164 | C10: Need to verify
A11: Baccalaureate Degrees | B11: ='2019-20 Rates'!$E$74*'2019-20 Rates'!E66 -> 1718.8164 | C11: Need to verify
A12: Credit Certificates | B12: ='2019-20 Rates'!$E$74*'2019-20 Rates'!E67 -> 1145.8776 | C12: Need to verify
A13: Transfer Level Math and English | B13: ='2019-20 Rates'!$E$74*'2019-20 Rates'!E68 -> 1145.8776 | C13: Need to verify
A14: Transfers | B14: ='2019-20 Rates'!$E$74*'2019-20 Rates'!E69 -> 859.40819 | C14: Need to verify
A15: Nine or More CTE Units | B15: ='2019-20 Rates'!$E$74*'2019-20 Rates'!E70 -> 572.93879 | C15: Need to verify
A16: Regional Living Wage | B16: ='2019-20 Rates'!$E$74*'2019-20 Rates'!E71 -> 572.93879 | C16: Need to verify
A17: Associate Degrees for Transfers PELL GRANT | B17: ='2019-20 Rates'!$E$102*'2019-20 Rates'!E81 -> 866.31571 | C17: Need to verify
A18: Associate Degrees PELL GRANT | B18: ='2019-20 Rates'!$E$102*'2019-20 Rates'!E82 -> 649.73678 | C18: Need to verify
A19: Baccalaureate Degrees PELL GRANT | B19: ='2019-20 Rates'!$E$102*'2019-20 Rates'!E83 -> 649.73678 | C19: Need to verify
A20: Credit Certificates PELL GRANT | B20: ='2019-20 Rates'!$E$102*'2019-20 Rates'!E84 -> 433.15785 | C20: Need to verify
A21: Transfer Level Math and English PELL GRANT | B21: ='2019-20 Rates'!$E$102*'2019-20 Rates'!E85 -> 433.15785 | C21: Need to verify
A22: Transfers PELL GRANT | B22: ='2019-20 Rates'!$E$102*'2019-20 Rates'!E86 -> 324.86839 | C22: Need to verify
A23: Nine or More CTE Units PELL GRANT | B23: ='2019-20 Rates'!$E$102*'2019-20 Rates'!E87 -> 216.57893 | C23: Need to verify
A24: Regional Living Wage PELL GRANT | B24: ='2019-20 Rates'!$E$102*'2019-20 Rates'!E88 -> 216.57893 | C24: Need to verify
A25: Associate Degrees for Transfers PROMISE GRANT | B25: ='2019-20 Rates'!$E$102*'2019-20 Rates'!E92 -> 577.5438 | C25: Need to verify
A26: Associate Degrees PROMISE GRANT | B26: ='2019-20 Rates'!$E$102*'2019-20 Rates'!E93 -> 433.15785 | C26: Need to verify
A27: Baccalaureate Degrees PROMISE GRANT | B27: ='2019-20 Rates'!$E$102*'2019-20 Rates'!E94 -> 433.15785 | C27: Need to verify
A28: Credit Certificates PROMISE GRANT | B28: ='2019-20 Rates'!$E$102*'2019-20 Rates'!E95 -> 288.7719 | C28: Need to verify
A29: Transfer Level Math and English PROMISE GRANT | B29: ='2019-20 Rates'!$E$102*'2019-20 Rates'!E96 -> 288.7719 | C29: Need to verify
A30: Transfers PROMISE GRANT | B30: ='2019-20 Rates'!$E$102*'2019-20 Rates'!E97 -> 216.57893 | C30: Need to verify
A31: Nine or More CTE Units PROMISE GRANT | B31: ='2019-20 Rates'!$E$102*'2019-20 Rates'!E98 -> 144.38595 | C31: Need to verify
A32: Regional Living Wage PROMISE GRANT | B32: ='2019-20 Rates'!$E$102*'2019-20 Rates'!E99 -> 144.38595 | C32: Need to verify
A33: 2017-18 COLA | B33: 0.0271 | C33: Need to verify
A34: 2018-19 COLA | B34: 0.0326 | C34: Need to verify

Sheet CALCULATIONS >>>

Sheet District Specific SCFF
A1: District | B1: Base Allocation | C1: Supplemental Allocation | D1: Success Allocation | E1: 2019-20 Total Computational Revenue (SCFF) | F1: 2017-18 Total Computational Revenue (Realized) | G1: 2017-18 COLA | H1: 2018-19 COLA | I1: 2019-20 Minimum (2017-18 Total Computational Revenue Plus 17-18 COLA plus 18-19 COLA) | J1: 2019-20 Minimum Larger Than 2019-20 Total Computation Revenue (SCFF) | K1: Hold Harmless | L1: Basic Aid Districts | M1: Hold Harmless for Non-Basic Aid Districts | N1: 2019-20 SCFF
A2: Allan Hancock | B2: =INDEX('Base Allocation'!$A$2:$AI$77,MATCH('District Specific SCFF'!$A2,'Base Allocation'!$A$2:$A$77,0),MATCH('District Specific SCFF'!B$1,'Base Allocation'!$A$2:$AI$2,0)) -> 44716892 | C2: =INDEX('Supplemental Allocation'!$A$2:$Q$76,MATCH('District Specific SCFF'!$A2,'Supplemental Allocation'!$A$2:$A$76,0),MATCH('District Specific SCFF'!C$1,'Supplemental Allocation'!$A$2:$Q$2,0)) -> 11185501 | D2: =INDEX('Success Allocation'!$A$3:$EP$76,MATCH('District Specific SCFF'!$A2,'Success Allocation'!$A$3:$A$76,0),MATCH('District Specific SCFF'!D$1,'Success Allocation'!$A$3:$EP$3,0)) -> 6696154 | E2: =SUM(B2:D2) -> 62598547 | F2: 58423221 | G2: =INDEX('Rate Assumptions'!$A$1:$C$34,MATCH('District Specific SCFF'!G$1,'Rate Assumptions'!$A$1:$A$34,0),2) -> 0.0271 | H2: =INDEX('Rate Assumptions'!$A$1:$C$34,MATCH('District Specific SCFF'!H$1,'Rate Assumptions'!$A$1:$A$34,0),2) -> 0.0326 | I2: =F2*(1+G2)*(1+H2) -> 61962702 | J2: =IF(I2>E2,"Y","") | K2: =IF(J2="",0,I2-E2) -> 0 | M2: =IF(L2="x",0,K2) -> 0 | N2: =M2+I2 -> 61962702
A3: Antelope | B3: =INDEX('Base Allocation'!$A$2:$AI$77,MATCH('District Specific SCFF'!$A3,'Base Allocation'!$A$2:$A$77,0),MATCH('District Specific SCFF'!B$1,'Base Allocation'!$A$2:$AI$2,0)) -> 51379024 | C3: =INDEX('Supplemental Allocation'!$A$2:$Q$76,MATCH('District Specific SCFF'!$A3,'Supplemental Allocation'!$A$2:$A$76,0),MATCH('District Specific SCFF'!C$1,'Supplemental Allocation'!$A$2:$Q$2,0)) -> 21023128 | D3: =INDEX('Success Allocation'!$A$3:$EP$76,MATCH('District Specific SCFF'!$A3,'Success Allocation'!$A$3:$A$76,0),MATCH('District Specific SCFF'!D$1,'Success Allocation'!$A$3:$EP$3,0)) -> 8031644.8 | E3: =SUM(B3:D3) -> 80433796 | F3: 62613062 | G3: =INDEX('Rate Assumptions'!$A$1:$C$34,MATCH('District Specific SCFF'!G$1,'Rate Assumptions'!$A$1:$A$34,0),2) -> 0.0271 | H3: =INDEX('Rate Assumptions'!$A$1:$C$34,MATCH('District Specific SCFF'!H$1,'Rate Assumptions'!$A$1:$A$34,0),2) -> 0.0326 | I3: =F3*(1+G3)*(1+H3) -> 66406378 | J3: =IF(I3>E3,"Y","") | K3: =IF(J3="",0,I3-E3) -> 0 | M3: =IF(L3="x",0,K3) -> 0 | N3: =M3+I3 -> 66406378
A4: Barstow | B4: =INDEX('Base Allocation'!$A$2:$AI$77,MATCH('District Specific SCFF'!$A4,'Base Allocation'!$A$2:$A$77,0),MATCH('District Specific SCFF'!B$1,'Base Allocation'!$A$2:$AI$2,0)) -> 15360163 | C4: =INDEX('Supplemental Allocation'!$A$2:$Q$76,MATCH('District Specific SCFF'!$A4,'Supplemental Allocation'!$A$2:$A$76,0),MATCH('District Specific SCFF'!C$1,'Supplemental Allocation'!$A$2:$Q$2,0)) -> 4858856.1 | D4: =INDEX('Success Allocation'!$A$3:$EP$76,MATCH('District Specific SCFF'!$A4,'Success Allocation'!$A$3:$A$76,0),MATCH('District Specific SCFF'!D$1,'Success Allocation'!$A$3:$EP$3,0)) -> 2240168.5 | E4: =SUM(B4:D4) -> 22459188 | F4: 18681460 | G4: =INDEX('Rate Assumptions'!$A$1:$C$34,MATCH('District Specific SCFF'!G$1,'Rate Assumptions'!$A$1:$A$34,0),2) -> 0.0271 | H4: =INDEX('Rate Assumptions'!$A$1:$C$34,MATCH('District Specific SCFF'!H$1,'Rate Assumptions'!$A$1:$A$34,0),2) -> 0.0326 | I4: =F4*(1+G4)*(1+H4) -> 19813247 | J4: =IF(I4>E4,"Y","") | K4: =IF(J4="",0,I4-E4) -> 0 | M4: =IF(L4="x",0,K4) -> 0 | N4: =M4+I4 -> 19813247
A5: Butte | B5: =INDEX('Base Allocation'!$A$2:$AI$77,MATCH('District Specific SCFF'!$A5,'Base Allocation'!$A$2:$A$77,0),MATCH('District Specific SCFF'!B$1,'Base Allocation'!$A$2:$AI$2,0)) -> 48029964 | C5: =INDEX('Supplemental Allocation'!$A$2:$Q$76,MATCH('District Specific SCFF'!$A5,'Supplemental Allocation'!$A$2:$A$76,0),MATCH('District Specific SCFF'!C$1,'Supplemental Allocation'!$A$2:$Q$2,0)) -> 12047212 | D5: =INDEX('Success Allocation'!$A$3:$EP$76,MATCH('District Specific SCFF'!$A5,'Success Allocation'!$A$3:$A$76,0),MATCH('District Specific SCFF'!D$1,'Success Allocation'!$A$3:$EP$3,0)) -> 8115842.2 | E5: =SUM(B5:D5) -> 68193017 | F5: 58869732 | G5: =INDEX('Rate Assumptions'!$A$1:$C$34,MATCH('District Specific SCFF'!G$1,'Rate Assumptions'!$A$1:$A$34,0),2) -> 0.0271 | H5: =INDEX('Rate Assumptions'!$A$1:$C$34,MATCH('District Specific SCFF'!H$1,'Rate Assumptions'!$A$1:$A$34,0),2) -> 0.0326 | I5: =F5*(1+G5)*(1+H5) -> 62436264 | J5: =IF(I5>E5,"Y","") | K5: =IF(J5="",0,I5-E5) -> 0 | M5: =IF(L5="x",0,K5) -> 0 | N5: =M5+I5 -> 62436264
A6: Cabrillo | B6: =INDEX('Base Allocation'!$A$2:$AI$77,MATCH('District Specific SCFF'!$A6,'Base Allocation'!$A$2:$A$77,0),MATCH('District Specific SCFF'!B$1,'Base Allocation'!$A$2:$AI$2,0)) -> 47678619 | C6: =INDEX('Supplemental Allocation'!$A$2:$Q$76,MATCH('District Specific SCFF'!$A6,'Supplemental Allocation'!$A$2:$A$76,0),MATCH('District Specific SCFF'!C$1,'Supplemental Allocation'!$A$2:$Q$2,0)) -> 8852283.7 | D6: =INDEX('Success Allocation'!$A$3:$EP$76,MATCH('District Specific SCFF'!$A6,'Success Allocation'!$A$3:$A$76,0),MATCH('District Specific SCFF'!D$1,'Success Allocation'!$A$3:$EP$3,0)) -> 6160625.2 | E6: =SUM(B6:D6) -> 62691528 | F6: 61066687 | G6: =INDEX('Rate Assumptions'!$A$1:$C$34,MATCH('District Specific SCFF'!G$1,'Rate Assumptions'!$A$1:$A$34,0),2) -> 0.0271 | H6: =INDEX('Rate Assumptions'!$A$1:$C$34,MATCH('District Specific SCFF'!H$1,'Rate Assumptions'!$A$1:$A$34,0),2) -> 0.0326 | I6: =F6*(1+G6)*(1+H6) -> 64766318 | J6: =IF(I6>E6,"Y","") -> Y | K6: =IF(J6="",0,I6-E6) -> 2074789.8 | M6: =IF(L6="x",0,K6) -> 2074789.8 | N6: =M6+I6 -> 66841108
A7: Cerritos | B7: =INDEX('Base Allocation'!$A$2:$AI$77,MATCH('District Specific SCFF'!$A7,'Base Allocation'!$A$2:$A$77,0),MATCH('District Specific SCFF'!B$1,'Base Allocation'!$A$2:$AI$2,0)) -> 71743529 | C7: =INDEX('Supplemental Allocation'!$A$2:$Q$76,MATCH('District Specific SCFF'!$A7,'Supplemental Allocation'!$A$2:$A$76,0),MATCH('District Specific SCFF'!C$1,'Supplemental Allocation'!$A$2:$Q$2,0)) -> 27395322 | D7: =INDEX('Success Allocation'!$A$3:$EP$76,MATCH('District Specific SCFF'!$A7,'Success Allocation'!$A$3:$A$76,0),MATCH('District Specific SCFF'!D$1,'Success Allocation'!$A$3:$EP$3,0)) -> 13540953 | E7: =SUM(B7:D7) -> 1.126798e+08 | F7: 93447643 | G7: =INDEX('Rate Assumptions'!$A$1:$C$34,MATCH('District Specific SCFF'!G$1,'Rate Assumptions'!$A$1:$A$34,0),2) -> 0.0271 | H7: =INDEX('Rate Assumptions'!$A$1:$C$34,MATCH('District Specific SCFF'!H$1,'Rate Assumptions'!$A$1:$A$34,0),2) -> 0.0326 | I7: =F7*(1+G7)*(1+H7) -> 99109025 | J7: =IF(I7>E7,"Y","") | K7: =IF(J7="",0,I7-E7) -> 0 | M7: =IF(L7="x",0,K7) -> 0 | N7: =M7+I7 -> 99109025
A8: Chabot-Las Positas | B8: =INDEX('Base Allocation'!$A$2:$AI$77,MATCH('District Specific SCFF'!$A8,'Base Allocation'!$A$2:$A$77,0),MATCH('District Specific SCFF'!B$1,'Base Allocation'!$A$2:$AI$2,0)) -> 74184208 | C8: =INDEX('Supplemental Allocation'!$A$2:$Q$76,MATCH('District Specific SCFF'!$A8,'Supplemental Allocation'!$A$2:$A$76,0),MATCH('District Specific SCFF'!C$1,'Supplemental Allocation'!$A$2:$Q$2,0)) -> 15302562 | D8: =INDEX('Success Allocation'!$A$3:$EP$76,MATCH('District Specific SCFF'!$A8,'Success Allocation'!$A$3:$A$76,0),MATCH('District Specific SCFF'!D$1,'Success Allocation'!$A$3:$EP$3,0)) -> 11525159 | E8: =SUM(B8:D8) -> 1.0101193e+08 | F8: 107679794 | G8: =INDEX('Rate Assumptions'!$A$1:$C$34,MATCH('District Specific SCFF'!G$1,'Rate Assumptions'!$A$1:$A$34,0),2) -> 0.0271 | H8: =INDEX('Rate Assumptions'!$A$1:$C$34,MATCH('District Specific SCFF'!H$1,'Rate Assumptions'!$A$1:$A$34,0),2) -> 0.0326 | I8: =F8*(1+G8)*(1+H8) -> 1.1420341e+08 | J8: =IF(I8>E8,"Y","") -> Y | K8: =IF(J8="",0,I8-E8) -> 13191480 | M8: =IF(L8="x",0,K8) -> 13191480 | N8: =M8+I8 -> 1.2739489e+08
A9: Chaffey | B9: =INDEX('Base Allocation'!$A$2:$AI$77,MATCH('District Specific SCFF'!$A9,'Base Allocation'!$A$2:$A$77,0),MATCH('District Specific SCFF'!B$1,'Base Allocation'!$A$2:$AI$2,0)) -> 74314293 | C9: =INDEX('Supplemental Allocation'!$A$2:$Q$76,MATCH('District Specific SCFF'!$A9,'Supplemental Allocation'!$A$2:$A$76,0),MATCH('District Specific SCFF'!C$1,'Supplemental Allocation'!$A$2:$Q$2,0)) -> 25822492 | D9: =INDEX('Success Allocation'!$A$3:$EP$76,MATCH('District Specific SCFF'!$A9,'Success Allocation'!$A$3:$A$76,0),MATCH('District Specific SCFF'!D$1,'Success Allocation'!$A$3:$EP$3,0)) -> 12928519 | E9: =SUM(B9:D9) -> 1.130653e+08 | F9: 93669819 | G9: =INDEX('Rate Assumptions'!$A$1:$C$34,MATCH('District Specific SCFF'!G$1,'Rate Assumptions'!$A$1:$A$34,0),2) -> 0.0271 | H9: =INDEX('Rate Assumptions'!$A$1:$C$34,MATCH('District Specific SCFF'!H$1,'Rate Assumptions'!$A$1:$A$34,0),2) -> 0.0326 | I9: =F9*(1+G9)*(1+H9) -> 99344661 | J9: =IF(I9>E9,"Y","") | K9: =IF(J9="",0,I9-E9) -> 0 | M9: =IF(L9="x",0,K9) -> 0 | N9: =M9+I9 -> 99344661
A10: Citrus | B10: =INDEX('Base Allocation'!$A$2:$AI$77,MATCH('District Specific SCFF'!$A10,'Base Allocation'!$A$2:$A$77,0),MATCH('District Specific SCFF'!B$1,'Base Allocation'!$A$2:$AI$2,0)) -> 52374517 | C10: =INDEX('Supplemental Allocation'!$A$2:$Q$76,MATCH('District Specific SCFF'!$A10,'Supplemental Allocation'!$A$2:$A$76,0),MATCH('District Specific SCFF'!C$1,'Supplemental Allocation'!$A$2:$Q$2,0)) -> 15639995 | D10: =INDEX('Success Allocation'!$A$3:$EP$76,MATCH('District Specific SCFF'!$A10,'Success Allocation'!$A$3:$A$76,0),MATCH('District Specific SCFF'!D$1,'Success Allocation'!$A$3:$EP$3,0)) -> 9994418.3 | E10: =SUM(B10:D10) -> 78008930 | F10: 68139191 | G10: =INDEX('Rate Assumptions'!$A$1:$C$34,MATCH('District Specific SCFF'!G$1,'Rate Assumptions'!$A$1:$A$34,0),2) -> 0.0271 | H10: =INDEX('Rate Assumptions'!$A$1:$C$34,MATCH('District Specific SCFF'!H$1,'Rate Assumptions'!$A$1:$A$34,0),2) -> 0.0326 | I10: =F10*(1+G10)*(1+H10) -> 72267299 | J10: =IF(I10>E10,"Y","") | K10: =IF(J10="",0,I10-E10) -> 0 | M10: =IF(L10="x",0,K10) -> 0 | N10: =M10+I10 -> 72267299
A11: Coast | B11: =INDEX('Base Allocation'!$A$2:$AI$77,MATCH('District Specific SCFF'!$A11,'Base Allocation'!$A$2:$A$77,0),MATCH('District Specific SCFF'!B$1,'Base Allocation'!$A$2:$AI$2,0)) -> 1.3933535e+08 | C11: =INDEX('Supplemental Allocation'!$A$2:$Q$76,MATCH('District Specific SCFF'!$A11,'Supplemental Allocation'!$A$2:$A$76,0),MATCH('District Specific SCFF'!C$1,'Supplemental Allocation'!$A$2:$Q$2,0)) -> 41733921 | D11: =INDEX('Success Allocation'!$A$3:$EP$76,MATCH('District Specific SCFF'!$A11,'Success Allocation'!$A$3:$A$76,0),MATCH('District Specific SCFF'!D$1,'Success Allocation'!$A$3:$EP$3,0)) -> 26702605 | E11: =SUM(B11:D11) -> 2.0777187e+08 | F11: 184284255 | G11: =INDEX('Rate Assumptions'!$A$1:$C$34,MATCH('District Specific SCFF'!G$1,'Rate Assumptions'!$A$1:$A$34,0),2) -> 0.0271 | H11: =INDEX('Rate Assumptions'!$A$1:$C$34,MATCH('District Specific SCFF'!H$1,'Rate Assumptions'!$A$1:$A$34,0),2) -> 0.0326 | I11: =F11*(1+G11)*(1+H11) -> 1.9544883e+08 | J11: =IF(I11>E11,"Y","") | K11: =IF(J11="",0,I11-E11) -> 0 | M11: =IF(L11="x",0,K11) -> 0 | N11: =M11+I11 -> 1.9544883e+08
A12: Compton | B12: =INDEX('Base Allocation'!$A$2:$AI$77,MATCH('District Specific SCFF'!$A12,'Base Allocation'!$A$2:$A$77,0),MATCH('District Specific SCFF'!B$1,'Base Allocation'!$A$2:$AI$2,0)) -> 28723234 | C12: =INDEX('Supplemental Allocation'!$A$2:$Q$76,MATCH('District Specific SCFF'!$A12,'Supplemental Allocation'!$A$2:$A$76,0),MATCH('District Specific SCFF'!C$1,'Supplemental Allocation'!$A$2:$Q$2,0)) -> 6404729 | D12: =INDEX('Success Allocation'!$A$3:$EP$76,MATCH('District Specific SCFF'!$A12,'Success Allocation'!$A$3:$A$76,0),MATCH('District Specific SCFF'!D$1,'Success Allocation'!$A$3:$EP$3,0)) -> 2952104.9 | E12: =SUM(B12:D12) -> 38080068 | F12: 35475170 | G12: =INDEX('Rate Assumptions'!$A$1:$C$34,MATCH('District Specific SCFF'!G$1,'Rate Assumptions'!$A$1:$A$34,0),2) -> 0.0271 | H12: =INDEX('Rate Assumptions'!$A$1:$C$34,MATCH('District Specific SCFF'!H$1,'Rate Assumptions'!$A$1:$A$34,0),2) -> 0.0326 | I12: =F12*(1+G12)*(1+H12) -> 37624379 | J12: =IF(I12>E12,"Y","") | K12: =IF(J12="",0,I12-E12) -> 0 | M12: =IF(L12="x",0,K12) -> 0 | N12: =M12+I12 -> 37624379
A13: Contra Costa | B13: =INDEX('Base Allocation'!$A$2:$AI$77,MATCH('District Specific SCFF'!$A13,'Base Allocation'!$A$2:$A$77,0),MATCH('District Specific SCFF'!B$1,'Base Allocation'!$A$2:$AI$2,0)) -> 1.2211645e+08 | C13: =INDEX('Supplemental Allocation'!$A$2:$Q$76,MATCH('District Specific SCFF'!$A13,'Supplemental Allocation'!$A$2:$A$76,0),MATCH('District Specific SCFF'!C$1,'Supplemental Allocation'!$A$2:$Q$2,0)) -> 26033504 | D13: =INDEX('Success Allocation'!$A$3:$EP$76,MATCH('District Specific SCFF'!$A13,'Success Allocation'!$A$3:$A$76,0),MATCH('District Specific SCFF'!D$1,'Success Allocation'!$A$3:$EP$3,0)) -> 19911652 | E13: =SUM(B13:D13) -> 1.680616e+08 | F13: 170246475 | G13: =INDEX('Rate Assumptions'!$A$1:$C$34,MATCH('District Specific SCFF'!G$1,'Rate Assumptions'!$A$1:$A$34,0),2) -> 0.0271 | H13: =INDEX('Rate Assumptions'!$A$1:$C$34,MATCH('District Specific SCFF'!H$1,'Rate Assumptions'!$A$1:$A$34,0),2) -> 0.0326 | I13: =F13*(1+G13)*(1+H13) -> 1.805606e+08 | J13: =IF(I13>E13,"Y","") -> Y | K13: =IF(J13="",0,I13-E13) -> 12498994 | M13: =IF(L13="x",0,K13) -> 12498994 | N13: =M13+I13 -> 1.9305959e+08
... A29: Los Rios | B29: =INDEX('Base Allocation'!$A$2:$AI$77,MATCH('District Specific SCFF'!$A29,'Base Allocation'!$A$2:$A$77,0),MATCH('District Specific SCFF'!B$1,'Base Allocation'!$A$2:$AI$2,0)) -> 2.2943937e+08 | C29: =INDEX('Supplemental Allocation'!$A$2:$Q$76,MATCH('District Specific SCFF'!$A29,'Supplemental Allocation'!$A$2:$A$76,0),MATCH('District Specific SCFF'!C$1,'Supplemental Allocation'!$A$2:$Q$2,0)) -> 66255946 | D29: =INDEX('Success Allocation'!$A$3:$EP$76,MATCH('District Specific SCFF'!$A29,'Success Allocation'!$A$3:$A$76,0),MATCH('District Specific SCFF'!D$1,'Success Allocation'!$A$3:$EP$3,0)) -> 36722101 | E29: =SUM(B29:D29) -> 3.3241742e+08 | F29: 303959995 | G29: =INDEX('Rate Assumptions'!$A$1:$C$34,MATCH('District Specific SCFF'!G$1,'Rate Assumptions'!$A$1:$A$34,0),2) -> 0.0271 | H29: =INDEX('Rate Assumptions'!$A$1:$C$34,MATCH('District Specific SCFF'!H$1,'Rate Assumptions'!$A$1:$A$34,0),2) -> 0.0326 | I29: =F29*(1+G29)*(1+H29) -> 3.2237494e+08 | J29: =IF(I29>E29,"Y","") | K29: =IF(J29="",0,I29-E29) -> 0 | M29: =IF(L29="x",0,K29) -> 0 | N29: =M29+I29 -> 3.2237494e+08
A30: Marin | B30: =INDEX('Base Allocation'!$A$2:$AI$77,MATCH('District Specific SCFF'!$A30,'Base Allocation'!$A$2:$A$77,0),MATCH('District Specific SCFF'!B$1,'Base Allocation'!$A$2:$AI$2,0)) -> 17663150 | C30: =INDEX('Supplemental Allocation'!$A$2:$Q$76,MATCH('District Specific SCFF'!$A30,'Supplemental Allocation'!$A$2:$A$76,0),MATCH('District Specific SCFF'!C$1,'Supplemental Allocation'!$A$2:$Q$2,0)) -> 2930930.4 | D30: =INDEX('Success Allocation'!$A$3:$EP$76,MATCH('District Specific SCFF'!$A30,'Success Allocation'!$A$3:$A$76,0),MATCH('District Specific SCFF'!D$1,'Success Allocation'!$A$3:$EP$3,0)) -> 1872784.4 | E30: =SUM(B30:D30) -> 22466865 | F30: 25606935 | G30: =INDEX('Rate Assumptions'!$A$1:$C$34,MATCH('District Specific SCFF'!G$1,'Rate Assumptions'!$A$1:$A$34,0),2) -> 0.0271 | H30: =INDEX('Rate Assumptions'!$A$1:$C$34,MATCH('District Specific SCFF'!H$1,'Rate Assumptions'!$A$1:$A$34,0),2) -> 0.0326 | I30: =F30*(1+G30)*(1+H30) -> 27158292 | J30: =IF(I30>E30,"Y","") -> Y | K30: =IF(J30="",0,I30-E30) -> 4691426.5 | L30: x | M30: =IF(L30="x",0,K30) -> 0 | N30: =M30+I30 -> 27158292
A31: Mendocino | B31: =INDEX('Base Allocation'!$A$2:$AI$77,MATCH('District Specific SCFF'!$A31,'Base Allocation'!$A$2:$A$77,0),MATCH('District Specific SCFF'!B$1,'Base Allocation'!$A$2:$AI$2,0)) -> 18063757 | C31: =INDEX('Supplemental Allocation'!$A$2:$Q$76,MATCH('District Specific SCFF'!$A31,'Supplemental Allocation'!$A$2:$A$76,0),MATCH('District Specific SCFF'!C$1,'Supplemental Allocation'!$A$2:$Q$2,0)) -> 3806584.2 | D31: =INDEX('Success Allocation'!$A$3:$EP$76,MATCH('District Specific SCFF'!$A31,'Success Allocation'!$A$3:$A$76,0),MATCH('District Specific SCFF'!D$1,'Success Allocation'!$A$3:$EP$3,0)) -> 2224095.4 | E31: =SUM(B31:D31) -> 24094437 | F31: 22434165 | G31: =INDEX('Rate Assumptions'!$A$1:$C$34,MATCH('District Specific SCFF'!G$1,'Rate Assumptions'!$A$1:$A$34,0),2) -> 0.0271 | H31: =INDEX('Rate Assumptions'!$A$1:$C$34,MATCH('District Specific SCFF'!H$1,'Rate Assumptions'!$A$1:$A$34,0),2) -> 0.0326 | I31: =F31*(1+G31)*(1+H31) -> 23793304 | J31: =IF(I31>E31,"Y","") | K31: =IF(J31="",0,I31-E31) -> 0 | M31: =IF(L31="x",0,K31) -> 0 | N31: =M31+I31 -> 23793304
A32: Merced | B32: =INDEX('Base Allocation'!$A$2:$AI$77,MATCH('District Specific SCFF'!$A32,'Base Allocation'!$A$2:$A$77,0),MATCH('District Specific SCFF'!B$1,'Base Allocation'!$A$2:$AI$2,0)) -> 46378425 | C32: =INDEX('Supplemental Allocation'!$A$2:$Q$76,MATCH('District Specific SCFF'!$A32,'Supplemental Allocation'!$A$2:$A$76,0),MATCH('District Specific SCFF'!C$1,'Supplemental Allocation'!$A$2:$Q$2,0)) -> 13281679 | D32: =INDEX('Success Allocation'!$A$3:$EP$76,MATCH('District Specific SCFF'!$A32,'Success Allocation'!$A$3:$A$76,0),MATCH('District Specific SCFF'!D$1,'Success Allocation'!$A$3:$EP$3,0)) -> 7814570.1 | E32: =SUM(B32:D32) -> 67474674 | F32: 56496411 | G32: =INDEX('Rate Assumptions'!$A$1:$C$34,MATCH('District Specific SCFF'!G$1,'Rate Assumptions'!$A$1:$A$34,0),2) -> 0.0271 | H32: =INDEX('Rate Assumptions'!$A$1:$C$34,MATCH('District Specific SCFF'!H$1,'Rate Assumptions'!$A$1:$A$34,0),2) -> 0.0326 | I32: =F32*(1+G32)*(1+H32) -> 59919159 | J32: =IF(I32>E32,"Y","") | K32: =IF(J32="",0,I32-E32) -> 0 | M32: =IF(L32="x",0,K32) -> 0 | N32: =M32+I32 -> 59919159
A33: MiraCosta | B33: =INDEX('Base Allocation'!$A$2:$AI$77,MATCH('District Specific SCFF'!$A33,'Base Allocation'!$A$2:$A$77,0),MATCH('District Specific SCFF'!B$1,'Base Allocation'!$A$2:$AI$2,0)) -> 46762627 | C33: =INDEX('Supplemental Allocation'!$A$2:$Q$76,MATCH('District Specific SCFF'!$A33,'Supplemental Allocation'!$A$2:$A$76,0),MATCH('District Specific SCFF'!C$1,'Supplemental Allocation'!$A$2:$Q$2,0)) -> 13171990 | D33: =INDEX('Success Allocation'!$A$3:$EP$76,MATCH('District Specific SCFF'!$A33,'Success Allocation'!$A$3:$A$76,0),MATCH('District Specific SCFF'!D$1,'Success Allocation'!$A$3:$EP$3,0)) -> 9640643.5 | E33: =SUM(B33:D33) -> 69575261 | F33: 63540067 | G33: =INDEX('Rate Assumptions'!$A$1:$C$34,MATCH('District Specific SCFF'!G$1,'Rate Assumptions'!$A$1:$A$34,0),2) -> 0.0271 | H33: =INDEX('Rate Assumptions'!$A$1:$C$34,MATCH('District Specific SCFF'!H$1,'Rate Assumptions'!$A$1:$A$34,0),2) -> 0.0326 | I33: =F33*(1+G33)*(1+H33) -> 67389544 | J33: =IF(I33>E33,"Y","") | K33: =IF(J33="",0,I33-E33) -> 0 | L33: x | M33: =IF(L33="x",0,K33) -> 0 | N33: =M33+I33 -> 67389544
A34: Monterey | B34: =INDEX('Base Allocation'!$A$2:$AI$77,MATCH('District Specific SCFF'!$A34,'Base Allocation'!$A$2:$A$77,0),MATCH('District Specific SCFF'!B$1,'Base Allocation'!$A$2:$AI$2,0)) -> 29413762 | C34: =INDEX('Supplemental Allocation'!$A$2:$Q$76,MATCH('District Specific SCFF'!$A34,'Supplemental Allocation'!$A$2:$A$76,0),MATCH('District Specific SCFF'!C$1,'Supplemental Allocation'!$A$2:$Q$2,0)) -> 7029399.2 | D34: =INDEX('Success Allocation'!$A$3:$EP$76,MATCH('District Specific SCFF'!$A34,'Success Allocation'!$A$3:$A$76,0),MATCH('District Specific SCFF'!D$1,'Success Allocation'!$A$3:$EP$3,0)) -> 5189495.9 | E34: =SUM(B34:D34) -> 41632657 | F34: 38888873 | G34: =INDEX('Rate Assumptions'!$A$1:$C$34,MATCH('District Specific SCFF'!G$1,'Rate Assumptions'!$A$1:$A$34,0),2) -> 0.0271 | H34: =INDEX('Rate Assumptions'!$A$1:$C$34,MATCH('District Specific SCFF'!H$1,'Rate Assumptions'!$A$1:$A$34,0),2) -> 0.0326 | I34: =F34*(1+G34)*(1+H34) -> 41244895 | J34: =IF(I34>E34,"Y","") | K34: =IF(J34="",0,I34-E34) -> 0 | M34: =IF(L34="x",0,K34) -> 0 | N34: =M34+I34 -> 41244895
A35: Mt. San Antonio | B35: =INDEX('Base Allocation'!$A$2:$AI$77,MATCH('District Specific SCFF'!$A35,'Base Allocation'!$A$2:$A$77,0),MATCH('District Specific SCFF'!B$1,'Base Allocation'!$A$2:$AI$2,0)) -> 1.5032963e+08 | C35: =INDEX('Supplemental Allocation'!$A$2:$Q$76,MATCH('District Specific SCFF'!$A35,'Supplemental Allocation'!$A$2:$A$76,0),MATCH('District Specific SCFF'!C$1,'Supplemental Allocation'!$A$2:$Q$2,0)) -> 35875778 | D35: =INDEX('Success Allocation'!$A$3:$EP$76,MATCH('District Specific SCFF'!$A35,'Success Allocation'!$A$3:$A$76,0),MATCH('District Specific SCFF'!D$1,'Success Allocation'!$A$3:$EP$3,0)) -> 17248770 | E35: =SUM(B35:D35) -> 2.0345418e+08 | F35: 176424297 | G35: =INDEX('Rate Assumptions'!$A$1:$C$34,MATCH('District Specific SCFF'!G$1,'Rate Assumptions'!$A$1:$A$34,0),2) -> 0.0271 | H35: =INDEX('Rate Assumptions'!$A$1:$C$34,MATCH('District Specific SCFF'!H$1,'Rate Assumptions'!$A$1:$A$34,0),2) -> 0.0326 | I35: =F35*(1+G35)*(1+H35) -> 1.8711269e+08 | J35: =IF(I35>E35,"Y","") | K35: =IF(J35="",0,I35-E35) -> 0 | M35: =IF(L35="x",0,K35) -> 0 | N35: =M35+I35 -> 1.8711269e+08
A36: Mt. San Jacinto | B36: =INDEX('Base Allocation'!$A$2:$AI$77,MATCH('District Specific SCFF'!$A36,'Base Allocation'!$A$2:$A$77,0),MATCH('District Specific SCFF'!B$1,'Base Allocation'!$A$2:$AI$2,0)) -> 53879645 | C36: =INDEX('Supplemental Allocation'!$A$2:$Q$76,MATCH('District Specific SCFF'!$A36,'Supplemental Allocation'!$A$2:$A$76,0),MATCH('District Specific SCFF'!C$1,'Supplemental Allocation'!$A$2:$Q$2,0)) -> 20307360 | D36: =INDEX('Success Allocation'!$A$3:$EP$76,MATCH('District Specific SCFF'!$A36,'Success Allocation'!$A$3:$A$76,0),MATCH('District Specific SCFF'!D$1,'Success Allocation'!$A$3:$EP$3,0)) -> 9458392.4 | E36: =SUM(B36:D36) -> 83645397 | F36: 71517436 | G36: =INDEX('Rate Assumptions'!$A$1:$C$34,MATCH('District Specific SCFF'!G$1,'Rate Assumptions'!$A$1:$A$34,0),2) -> 0.0271 | H36: =INDEX('Rate Assumptions'!$A$1:$C$34,MATCH('District Specific SCFF'!H$1,'Rate Assumptions'!$A$1:$A$34,0),2) -> 0.0326 | I36: =F36*(1+G36)*(1+H36) -> 75850210 | J36: =IF(I36>E36,"Y","") | K36: =IF(J36="",0,I36-E36) -> 0 | M36: =IF(L36="x",0,K36) -> 0 | N36: =M36+I36 -> 75850210
A37: Napa | B37: =INDEX('Base Allocation'!$A$2:$AI$77,MATCH('District Specific SCFF'!$A37,'Base Allocation'!$A$2:$A$77,0),MATCH('District Specific SCFF'!B$1,'Base Allocation'!$A$2:$AI$2,0)) -> 24652417 | C37: =INDEX('Supplemental Allocation'!$A$2:$Q$76,MATCH('District Specific SCFF'!$A37,'Supplemental Allocation'!$A$2:$A$76,0),MATCH('District Specific SCFF'!C$1,'Supplemental Allocation'!$A$2:$Q$2,0)) -> 5168402.5 | D37: =INDEX('Success Allocation'!$A$3:$EP$76,MATCH('District Specific SCFF'!$A37,'Success Allocation'!$A$3:$A$76,0),MATCH('District Specific SCFF'!D$1,'Success Allocation'!$A$3:$EP$3,0)) -> 3610585.1 | E37: =SUM(B37:D37) -> 33431405 | F37: 31620290 | G37: =INDEX('Rate Assumptions'!$A$1:$C$34,MATCH('District Specific SCFF'!G$1,'Rate Assumptions'!$A$1:$A$34,0),2) -> 0.0271 | H37: =INDEX('Rate Assumptions'!$A$1:$C$34,MATCH('District Specific SCFF'!H$1,'Rate Assumptions'!$A$1:$A$34,0),2) -> 0.0326 | I37: =F37*(1+G37)*(1+H37) -> 33535957 | J37: =IF(I37>E37,"Y","") -> Y | K37: =IF(J37="",0,I37-E37) -> 104551.55 | M37: =IF(L37="x",0,K37) -> 104551.55 | N37: =M37+I37 -> 33640508
A38: North Orange | B38: =INDEX('Base Allocation'!$A$2:$AI$77,MATCH('District Specific SCFF'!$A38,'Base Allocation'!$A$2:$A$77,0),MATCH('District Specific SCFF'!B$1,'Base Allocation'!$A$2:$AI$2,0)) -> 1.3949899e+08 | C38: =INDEX('Supplemental Allocation'!$A$2:$Q$76,MATCH('District Specific SCFF'!$A38,'Supplemental Allocation'!$A$2:$A$76,0),MATCH('District Specific SCFF'!C$1,'Supplemental Allocation'!$A$2:$Q$2,0)) -> 34860689 | D38: =INDEX('Success Allocation'!$A$3:$EP$76,MATCH('District Specific SCFF'!$A38,'Success Allocation'!$A$3:$A$76,0),MATCH('District Specific SCFF'!D$1,'Success Allocation'!$A$3:$EP$3,0)) -> 21025588 | E38: =SUM(B38:D38) -> 1.9538527e+08 | F38: 202056270 | G38: =INDEX('Rate Assumptions'!$A$1:$C$34,MATCH('District Specific SCFF'!G$1,'Rate Assumptions'!$A$1:$A$34,0),2) -> 0.0271 | H38: =INDEX('Rate Assumptions'!$A$1:$C$34,MATCH('District Specific SCFF'!H$1,'Rate Assumptions'!$A$1:$A$34,0),2) -> 0.0326 | I38: =F38*(1+G38)*(1+H38) -> 2.1429754e+08 | J38: =IF(I38>E38,"Y","") -> Y | K38: =IF(J38="",0,I38-E38) -> 18912273 | M38: =IF(L38="x",0,K38) -> 18912273 | N38: =M38+I38 -> 2.3320981e+08
A39: Ohlone | B39: =INDEX('Base Allocation'!$A$2:$AI$77,MATCH('District Specific SCFF'!$A39,'Base Allocation'!$A$2:$A$77,0),MATCH('District Specific SCFF'!B$1,'Base Allocation'!$A$2:$AI$2,0)) -> 34039372 | C39: =INDEX('Supplemental Allocation'!$A$2:$Q$76,MATCH('District Specific SCFF'!$A39,'Supplemental Allocation'!$A$2:$A$76,0),MATCH('District Specific SCFF'!C$1,'Supplemental Allocation'!$A$2:$Q$2,0)) -> 4701759 | D39: =INDEX('Success Allocation'!$A$3:$EP$76,MATCH('District Specific SCFF'!$A39,'Success Allocation'!$A$3:$A$76,0),MATCH('District Specific SCFF'!D$1,'Success Allocation'!$A$3:$EP$3,0)) -> 4914244.1 | E39: =SUM(B39:D39) -> 43655375 | F39: 48764473 | G39: =INDEX('Rate Assumptions'!$A$1:$C$34,MATCH('District Specific SCFF'!G$1,'Rate Assumptions'!$A$1:$A$34,0),2) -> 0.0271 | H39: =INDEX('Rate Assumptions'!$A$1:$C$34,MATCH('District Specific SCFF'!H$1,'Rate Assumptions'!$A$1:$A$34,0),2) -> 0.0326 | I39: =F39*(1+G39)*(1+H39) -> 51718793 | J39: =IF(I39>E39,"Y","") -> Y | K39: =IF(J39="",0,I39-E39) -> 8063418.4 | M39: =IF(L39="x",0,K39) -> 8063418.4 | N39: =M39+I39 -> 59782212
A40: Palo Verde | B40: =INDEX('Base Allocation'!$A$2:$AI$77,MATCH('District Specific SCFF'!$A40,'Base Allocation'!$A$2:$A$77,0),MATCH('District Specific SCFF'!B$1,'Base Allocation'!$A$2:$AI$2,0)) -> 14539576 | C40: =INDEX('Supplemental Allocation'!$A$2:$Q$76,MATCH('District Specific SCFF'!$A40,'Supplemental Allocation'!$A$2:$A$76,0),MATCH('District Specific SCFF'!C$1,'Supplemental Allocation'!$A$2:$Q$2,0)) -> 3393855.7 | D40: =INDEX('Success Allocation'!$A$3:$EP$76,MATCH('District Specific SCFF'!$A40,'Success Allocation'!$A$3:$A$76,0),MATCH('District Specific SCFF'!D$1,'Success Allocation'!$A$3:$EP$3,0)) -> 1241113.4 | E40: =SUM(B40:D40) -> 19174545 | F40: 16636774 | G40: =INDEX('Rate Assumptions'!$A$1:$C$34,MATCH('District Specific SCFF'!G$1,'Rate Assumptions'!$A$1:$A$34,0),2) -> 0.0271 | H40: =INDEX('Rate Assumptions'!$A$1:$C$34,MATCH('District Specific SCFF'!H$1,'Rate Assumptions'!$A$1:$A$34,0),2) -> 0.0326 | I40: =F40*(1+G40)*(1+H40) -> 17644687 | J40: =IF(I40>E40,"Y","") | K40: =IF(J40="",0,I40-E40) -> 0 | M40: =IF(L40="x",0,K40) -> 0 | N40: =M40+I40 -> 17644687
A41: Palomar | B41: =INDEX('Base Allocation'!$A$2:$AI$77,MATCH('District Specific SCFF'!$A41,'Base Allocation'!$A$2:$A$77,0),MATCH('District Specific SCFF'!B$1,'Base Allocation'!$A$2:$AI$2,0)) -> 80483849 | C41: =INDEX('Supplemental Allocation'!$A$2:$Q$76,MATCH('District Specific SCFF'!$A41,'Supplemental Allocation'!$A$2:$A$76,0),MATCH('District Specific SCFF'!C$1,'Supplemental Allocation'!$A$2:$Q$2,0)) -> 19782154 | D41: =INDEX('Success Allocation'!$A$3:$EP$76,MATCH('District Specific SCFF'!$A41,'Success Allocation'!$A$3:$A$76,0),MATCH('District Specific SCFF'!D$1,'Success Allocation'!$A$3:$EP$3,0)) -> 12323100 | E41: =SUM(B41:D41) -> 1.125891e+08 | F41: 108548444 | G41: =INDEX('Rate Assumptions'!$A$1:$C$34,MATCH('District Specific SCFF'!G$1,'Rate Assumptions'!$A$1:$A$34,0),2) -> 0.0271 | H41: =INDEX('Rate Assumptions'!$A$1:$C$34,MATCH('District Specific SCFF'!H$1,'Rate Assumptions'!$A$1:$A$34,0),2) -> 0.0326 | I41: =F41*(1+G41)*(1+H41) -> 1.1512468e+08 | J41: =IF(I41>E41,"Y","") -> Y | K41: =IF(J41="",0,I41-E41) -> 2535581.5 | M41: =IF(L41="x",0,K41) -> 2535581.5 | N41: =M41+I41 -> 1.1766027e+08
A42: Pasadena | B42: =INDEX('Base Allocation'!$A$2:$AI$77,MATCH('District Specific SCFF'!$A42,'Base Allocation'!$A$2:$A$77,0),MATCH('District Specific SCFF'!B$1,'Base Allocation'!$A$2:$AI$2,0)) -> 1.0513312e+08 | C42: =INDEX('Supplemental Allocation'!$A$2:$Q$76,MATCH('District Specific SCFF'!$A42,'Supplemental Allocation'!$A$2:$A$76,0),MATCH('District Specific SCFF'!C$1,'Supplemental Allocation'!$A$2:$Q$2,0)) -> 28181737 | D42: =INDEX('Success Allocation'!$A$3:$EP$76,MATCH('District Specific SCFF'!$A42,'Success Allocation'!$A$3:$A$76,0),MATCH('District Specific SCFF'!D$1,'Success Allocation'!$A$3:$EP$3,0)) -> 18242406 | E42: =SUM(B42:D42) -> 1.5155727e+08 | F42: 134464486 | G42: =INDEX('Rate Assumptions'!$A$1:$C$34,MATCH('District Specific SCFF'!G$1,'Rate Assumptions'!$A$1:$A$34,0),2) -> 0.0271 | H42: =INDEX('Rate Assumptions'!$A$1:$C$34,MATCH('District Specific SCFF'!H$1,'Rate Assumptions'!$A$1:$A$34,0),2) -> 0.0326 | I42: =F42*(1+G42)*(1+H42) -> 1.4261081e+08 | J42: =IF(I42>E42,"Y","") | K42: =IF(J42="",0,I42-E42) -> 0 | M42: =IF(L42="x",0,K42) -> 0 | N42: =M42+I42 -> 1.4261081e+08
A43: Peralta | B43: =INDEX('Base Allocation'!$A$2:$AI$77,MATCH('District Specific SCFF'!$A43,'Base Allocation'!$A$2:$A$77,0),MATCH('District Specific SCFF'!B$1,'Base Allocation'!$A$2:$AI$2,0)) -> 88635367 | C43: =INDEX('Supplemental Allocation'!$A$2:$Q$76,MATCH('District Specific SCFF'!$A43,'Supplemental Allocation'!$A$2:$A$76,0),MATCH('District Specific SCFF'!C$1,'Supplemental Allocation'!$A$2:$Q$2,0)) -> 21486983 | D43: =INDEX('Success Allocation'!$A$3:$EP$76,MATCH('District Specific SCFF'!$A43,'Success Allocation'!$A$3:$A$76,0),MATCH('District Specific SCFF'!D$1,'Success Allocation'!$A$3:$EP$3,0)) -> 10982378 | E43: =SUM(B43:D43) -> 1.2110473e+08 | F43: 114674531 | G43: =INDEX('Rate Assumptions'!$A$1:$C$34,MATCH('District Specific SCFF'!G$1,'Rate Assumptions'!$A$1:$A$34,0),2) -> 0.0271 | H43: =INDEX('Rate Assumptions'!$A$1:$C$34,MATCH('District Specific SCFF'!H$1,'Rate Assumptions'!$A$1:$A$34,0),2) -> 0.0326 | I43: =F43*(1+G43)*(1+H43) -> 1.2162191e+08 | J43: =IF(I43>E43,"Y","") -> Y | K43: =IF(J43="",0,I43-E43) -> 517183.75 | M43: =IF(L43="x",0,K43) -> 517183.75 | N43: =M43+I43 -> 1.2213909e+08
A44: Rancho Santiago | B44: =INDEX('Base Allocation'!$A$2:$AI$77,MATCH('District Specific SCFF'!$A44,'Base Allocation'!$A$2:$A$77,0),MATCH('District Specific SCFF'!B$1,'Base Allocation'!$A$2:$AI$2,0)) -> 1.3747475e+08 | C44: =INDEX('Supplemental Allocation'!$A$2:$Q$76,MATCH('District Specific SCFF'!$A44,'Supplemental Allocation'!$A$2:$A$76,0),MATCH('District Specific SCFF'!C$1,'Supplemental Allocation'!$A$2:$Q$2,0)) -> 25960068 | D44: =INDEX('Success Allocation'!$A$3:$EP$76,MATCH('District Specific SCFF'!$A44,'Success Allocation'!$A$3:$A$76,0),MATCH('District Specific SCFF'!D$1,'Success Allocation'!$A$3:$EP$3,0)) -> 18254490 | E44: =SUM(B44:D44) -> 1.8168931e+08 | F44: 164850888 | G44: =INDEX('Rate Assumptions'!$A$1:$C$34,MATCH('District Specific SCFF'!G$1,'Rate Assumptions'!$A$1:$A$34,0),2) -> 0.0271 | H44: =INDEX('Rate Assumptions'!$A$1:$C$34,MATCH('District Specific SCFF'!H$1,'Rate Assumptions'!$A$1:$A$34,0),2) -> 0.0326 | I44: =F44*(1+G44)*(1+H44) -> 1.7483813e+08 | J44: =IF(I44>E44,"Y","") | K44: =IF(J44="",0,I44-E44) -> 0 | M44: =IF(L44="x",0,K44) -> 0 | N44: =M44+I44 -> 1.7483813e+08
A45: Redwoods | B45: =INDEX('Base Allocation'!$A$2:$AI$77,MATCH('District Specific SCFF'!$A45,'Base Allocation'!$A$2:$A$77,0),MATCH('District Specific SCFF'!B$1,'Base Allocation'!$A$2:$AI$2,0)) -> 21372499 | C45: =INDEX('Supplemental Allocation'!$A$2:$Q$76,MATCH('District Specific SCFF'!$A45,'Supplemental Allocation'!$A$2:$A$76,0),MATCH('District Specific SCFF'!C$1,'Supplemental Allocation'!$A$2:$Q$2,0)) -> 5192571.3 | D45: =INDEX('Success Allocation'!$A$3:$EP$76,MATCH('District Specific SCFF'!$A45,'Success Allocation'!$A$3:$A$76,0),MATCH('District Specific SCFF'!D$1,'Success Allocation'!$A$3:$EP$3,0)) -> 3212567.6 | E45: =SUM(B45:D45) -> 29777638 | F45: 26897607 | G45: =INDEX('Rate Assumptions'!$A$1:$C$34,MATCH('District Specific SCFF'!G$1,'Rate Assumptions'!$A$1:$A$34,0),2) -> 0.0271 | H45: =INDEX('Rate Assumptions'!$A$1:$C$34,MATCH('District Specific SCFF'!H$1,'Rate Assumptions'!$A$1:$A$34,0),2) -> 0.0326 | I45: =F45*(1+G45)*(1+H45) -> 28527157 | J45: =IF(I45>E45,"Y","") | K45: =IF(J45="",0,I45-E45) -> 0 | M45: =IF(L45="x",0,K45) -> 0 | N45: =M45+I45 -> 28527157
... A51: San Joaquin Delta | B51: =INDEX('Base Allocation'!$A$2:$AI$77,MATCH('District Specific SCFF'!$A51,'Base Allocation'!$A$2:$A$77,0),MATCH('District Specific SCFF'!B$1,'Base Allocation'!$A$2:$AI$2,0)) -> 68761467 | C51: =INDEX('Supplemental Allocation'!$A$2:$Q$76,MATCH('District Specific SCFF'!$A51,'Supplemental Allocation'!$A$2:$A$76,0),MATCH('District Specific SCFF'!C$1,'Supplemental Allocation'!$A$2:$Q$2,0)) -> 20877186 | D51: =INDEX('Success Allocation'!$A$3:$EP$76,MATCH('District Specific SCFF'!$A51,'Success Allocation'!$A$3:$A$76,0),MATCH('District Specific SCFF'!D$1,'Success Allocation'!$A$3:$EP$3,0)) -> 12389409 | E51: =SUM(B51:D51) -> 1.0202806e+08 | F51: 90280054 | G51: =INDEX('Rate Assumptions'!$A$1:$C$34,MATCH('District Specific SCFF'!G$1,'Rate Assumptions'!$A$1:$A$34,0),2) -> 0.0271 | H51: =INDEX('Rate Assumptions'!$A$1:$C$34,MATCH('District Specific SCFF'!H$1,'Rate Assumptions'!$A$1:$A$34,0),2) -> 0.0326 | I51: =F51*(1+G51)*(1+H51) -> 95749532 | J51: =IF(I51>E51,"Y","") | K51: =IF(J51="",0,I51-E51) -> 0 | M51: =IF(L51="x",0,K51) -> 0 | N51: =M51+I51 -> 95749532
A52: San Jose | B52: =INDEX('Base Allocation'!$A$2:$AI$77,MATCH('District Specific SCFF'!$A52,'Base Allocation'!$A$2:$A$77,0),MATCH('District Specific SCFF'!B$1,'Base Allocation'!$A$2:$AI$2,0)) -> 57509202 | C52: =INDEX('Supplemental Allocation'!$A$2:$Q$76,MATCH('District Specific SCFF'!$A52,'Supplemental Allocation'!$A$2:$A$76,0),MATCH('District Specific SCFF'!C$1,'Supplemental Allocation'!$A$2:$Q$2,0)) -> 15935598 | D52: =INDEX('Success Allocation'!$A$3:$EP$76,MATCH('District Specific SCFF'!$A52,'Success Allocation'!$A$3:$A$76,0),MATCH('District Specific SCFF'!D$1,'Success Allocation'!$A$3:$EP$3,0)) -> 8263072.7 | E52: =SUM(B52:D52) -> 81707872 | F52: 70622433 | G52: =INDEX('Rate Assumptions'!$A$1:$C$34,MATCH('District Specific SCFF'!G$1,'Rate Assumptions'!$A$1:$A$34,0),2) -> 0.0271 | H52: =INDEX('Rate Assumptions'!$A$1:$C$34,MATCH('District Specific SCFF'!H$1,'Rate Assumptions'!$A$1:$A$34,0),2) -> 0.0326 | I52: =F52*(1+G52)*(1+H52) -> 74900984 | J52: =IF(I52>E52,"Y","") | K52: =IF(J52="",0,I52-E52) -> 0 | L52: x | M52: =IF(L52="x",0,K52) -> 0 | N52: =M52+I52 -> 74900984
A53: San Luis Obispo | B53: =INDEX('Base Allocation'!$A$2:$AI$77,MATCH('District Specific SCFF'!$A53,'Base Allocation'!$A$2:$A$77,0),MATCH('District Specific SCFF'!B$1,'Base Allocation'!$A$2:$AI$2,0)) -> 38498095 | C53: =INDEX('Supplemental Allocation'!$A$2:$Q$76,MATCH('District Specific SCFF'!$A53,'Supplemental Allocation'!$A$2:$A$76,0),MATCH('District Specific SCFF'!C$1,'Supplemental Allocation'!$A$2:$Q$2,0)) -> 7995221.2 | D53: =INDEX('Success Allocation'!$A$3:$EP$76,MATCH('District Specific SCFF'!$A53,'Success Allocation'!$A$3:$A$76,0),MATCH('District Specific SCFF'!D$1,'Success Allocation'!$A$3:$EP$3,0)) -> 6017921.3 | E53: =SUM(B53:D53) -> 52511237 | F53: 49069768 | G53: =INDEX('Rate Assumptions'!$A$1:$C$34,MATCH('District Specific SCFF'!G$1,'Rate Assumptions'!$A$1:$A$34,0),2) -> 0.0271 | H53: =INDEX('Rate Assumptions'!$A$1:$C$34,MATCH('District Specific SCFF'!H$1,'Rate Assumptions'!$A$1:$A$34,0),2) -> 0.0326 | I53: =F53*(1+G53)*(1+H53) -> 52042584 | J53: =IF(I53>E53,"Y","") | K53: =IF(J53="",0,I53-E53) -> 0 | M53: =IF(L53="x",0,K53) -> 0 | N53: =M53+I53 -> 52042584
A54: San Mateo | B54: =INDEX('Base Allocation'!$A$2:$AI$77,MATCH('District Specific SCFF'!$A54,'Base Allocation'!$A$2:$A$77,0),MATCH('District Specific SCFF'!B$1,'Base Allocation'!$A$2:$AI$2,0)) -> 74755545 | C54: =INDEX('Supplemental Allocation'!$A$2:$Q$76,MATCH('District Specific SCFF'!$A54,'Supplemental Allocation'!$A$2:$A$76,0),MATCH('District Specific SCFF'!C$1,'Supplemental Allocation'!$A$2:$Q$2,0)) -> 13788294 | D54: =INDEX('Success Allocation'!$A$3:$EP$76,MATCH('District Specific SCFF'!$A54,'Success Allocation'!$A$3:$A$76,0),MATCH('District Specific SCFF'!D$1,'Success Allocation'!$A$3:$EP$3,0)) -> 11450122 | E54: =SUM(B54:D54) -> 99993961 | F54: 98289606 | G54: =INDEX('Rate Assumptions'!$A$1:$C$34,MATCH('District Specific SCFF'!G$1,'Rate Assumptions'!$A$1:$A$34,0),2) -> 0.0271 | H54: =INDEX('Rate Assumptions'!$A$1:$C$34,MATCH('District Specific SCFF'!H$1,'Rate Assumptions'!$A$1:$A$34,0),2) -> 0.0326 | I54: =F54*(1+G54)*(1+H54) -> 1.0424433e+08 | J54: =IF(I54>E54,"Y","") -> Y | K54: =IF(J54="",0,I54-E54) -> 4250369.3 | L54: x | M54: =IF(L54="x",0,K54) -> 0 | N54: =M54+I54 -> 1.0424433e+08
A55: Santa Barbara | B55: =INDEX('Base Allocation'!$A$2:$AI$77,MATCH('District Specific SCFF'!$A55,'Base Allocation'!$A$2:$A$77,0),MATCH('District Specific SCFF'!B$1,'Base Allocation'!$A$2:$AI$2,0)) -> 57719268 | C55: =INDEX('Supplemental Allocation'!$A$2:$Q$76,MATCH('District Specific SCFF'!$A55,'Supplemental Allocation'!$A$2:$A$76,0),MATCH('District Specific SCFF'!C$1,'Supplemental Allocation'!$A$2:$Q$2,0)) -> 12488757 | D55: =INDEX('Success Allocation'!$A$3:$EP$76,MATCH('District Specific SCFF'!$A55,'Success Allocation'!$A$3:$A$76,0),MATCH('District Specific SCFF'!D$1,'Success Allocation'!$A$3:$EP$3,0)) -> 8504950.7 | E55: =SUM(B55:D55) -> 78712975 | F55: 72610515 | G55: =INDEX('Rate Assumptions'!$A$1:$C$34,MATCH('District Specific SCFF'!G$1,'Rate Assumptions'!$A$1:$A$34,0),2) -> 0.0271 | H55: =INDEX('Rate Assumptions'!$A$1:$C$34,MATCH('District Specific SCFF'!H$1,'Rate Assumptions'!$A$1:$A$34,0),2) -> 0.0326 | I55: =F55*(1+G55)*(1+H55) -> 77009511 | J55: =IF(I55>E55,"Y","") | K55: =IF(J55="",0,I55-E55) -> 0 | M55: =IF(L55="x",0,K55) -> 0 | N55: =M55+I55 -> 77009511
A56: Santa Clarita | B56: =INDEX('Base Allocation'!$A$2:$AI$77,MATCH('District Specific SCFF'!$A56,'Base Allocation'!$A$2:$A$77,0),MATCH('District Specific SCFF'!B$1,'Base Allocation'!$A$2:$AI$2,0)) -> 72979666 | C56: =INDEX('Supplemental Allocation'!$A$2:$Q$76,MATCH('District Specific SCFF'!$A56,'Supplemental Allocation'!$A$2:$A$76,0),MATCH('District Specific SCFF'!C$1,'Supplemental Allocation'!$A$2:$Q$2,0)) -> 13614465 | D56: =INDEX('Success Allocation'!$A$3:$EP$76,MATCH('District Specific SCFF'!$A56,'Success Allocation'!$A$3:$A$76,0),MATCH('District Specific SCFF'!D$1,'Success Allocation'!$A$3:$EP$3,0)) -> 13564937 | E56: =SUM(B56:D56) -> 1.0015907e+08 | F56: 94448588 | G56: =INDEX('Rate Assumptions'!$A$1:$C$34,MATCH('District Specific SCFF'!G$1,'Rate Assumptions'!$A$1:$A$34,0),2) -> 0.0271 | H56: =INDEX('Rate Assumptions'!$A$1:$C$34,MATCH('District Specific SCFF'!H$1,'Rate Assumptions'!$A$1:$A$34,0),2) -> 0.0326 | I56: =F56*(1+G56)*(1+H56) -> 1.0017061e+08 | J56: =IF(I56>E56,"Y","") -> Y | K56: =IF(J56="",0,I56-E56) -> 11542.655 | M56: =IF(L56="x",0,K56) -> 11542.655 | N56: =M56+I56 -> 1.0018215e+08
A57: Santa Monica | B57: =INDEX('Base Allocation'!$A$2:$AI$77,MATCH('District Specific SCFF'!$A57,'Base Allocation'!$A$2:$A$77,0),MATCH('District Specific SCFF'!B$1,'Base Allocation'!$A$2:$AI$2,0)) -> 86857394 | C57: =INDEX('Supplemental Allocation'!$A$2:$Q$76,MATCH('District Specific SCFF'!$A57,'Supplemental Allocation'!$A$2:$A$76,0),MATCH('District Specific SCFF'!C$1,'Supplemental Allocation'!$A$2:$Q$2,0)) -> 26195249 | D57: =INDEX('Success Allocation'!$A$3:$EP$76,MATCH('District Specific SCFF'!$A57,'Success Allocation'!$A$3:$A$76,0),MATCH('District Specific SCFF'!D$1,'Success Allocation'!$A$3:$EP$3,0)) -> 15569122 | E57: =SUM(B57:D57) -> 1.2862177e+08 | F57: 129918589 | G57: =INDEX('Rate Assumptions'!$A$1:$C$34,MATCH('District Specific SCFF'!G$1,'Rate Assumptions'!$A$1:$A$34,0),2) -> 0.0271 | H57: =INDEX('Rate Assumptions'!$A$1:$C$34,MATCH('District Specific SCFF'!H$1,'Rate Assumptions'!$A$1:$A$34,0),2) -> 0.0326 | I57: =F57*(1+G57)*(1+H57) -> 1.3778951e+08 | J57: =IF(I57>E57,"Y","") -> Y | K57: =IF(J57="",0,I57-E57) -> 9167741 | M57: =IF(L57="x",0,K57) -> 9167741 | N57: =M57+I57 -> 1.4695725e+08
A58: Sequoias | B58: =INDEX('Base Allocation'!$A$2:$AI$77,MATCH('District Specific SCFF'!$A58,'Base Allocation'!$A$2:$A$77,0),MATCH('District Specific SCFF'!B$1,'Base Allocation'!$A$2:$AI$2,0)) -> 49432270 | C58: =INDEX('Supplemental Allocation'!$A$2:$Q$76,MATCH('District Specific SCFF'!$A58,'Supplemental Allocation'!$A$2:$A$76,0),MATCH('District Specific SCFF'!C$1,'Supplemental Allocation'!$A$2:$Q$2,0)) -> 15945823 | D58: =INDEX('Success Allocation'!$A$3:$EP$76,MATCH('District Specific SCFF'!$A58,'Success Allocation'!$A$3:$A$76,0),MATCH('District Specific SCFF'!D$1,'Success Allocation'!$A$3:$EP$3,0)) -> 8290263.6 | E58: =SUM(B58:D58) -> 73668356 | F58: 61392655 | G58: =INDEX('Rate Assumptions'!$A$1:$C$34,MATCH('District Specific SCFF'!G$1,'Rate Assumptions'!$A$1:$A$34,0),2) -> 0.0271 | H58: =INDEX('Rate Assumptions'!$A$1:$C$34,MATCH('District Specific SCFF'!H$1,'Rate Assumptions'!$A$1:$A$34,0),2) -> 0.0326 | I58: =F58*(1+G58)*(1+H58) -> 65112034 | J58: =IF(I58>E58,"Y","") | K58: =IF(J58="",0,I58-E58) -> 0 | M58: =IF(L58="x",0,K58) -> 0 | N58: =M58+I58 -> 65112034
A59: Shasta Tehama | B59: =INDEX('Base Allocation'!$A$2:$AI$77,MATCH('District Specific SCFF'!$A59,'Base Allocation'!$A$2:$A$77,0),MATCH('District Specific SCFF'!B$1,'Base Allocation'!$A$2:$AI$2,0)) -> 33210665 | C59: =INDEX('Supplemental Allocation'!$A$2:$Q$76,MATCH('District Specific SCFF'!$A59,'Supplemental Allocation'!$A$2:$A$76,0),MATCH('District Specific SCFF'!C$1,'Supplemental Allocation'!$A$2:$Q$2,0)) -> 12161549 | D59: =INDEX('Success Allocation'!$A$3:$EP$76,MATCH('District Specific SCFF'!$A59,'Success Allocation'!$A$3:$A$76,0),MATCH('District Specific SCFF'!D$1,'Success Allocation'!$A$3:$EP$3,0)) -> 6562690.4 | E59: =SUM(B59:D59) -> 51934904 | F59: 41789199 | G59: =INDEX('Rate Assumptions'!$A$1:$C$34,MATCH('District Specific SCFF'!G$1,'Rate Assumptions'!$A$1:$A$34,0),2) -> 0.0271 | H59: =INDEX('Rate Assumptions'!$A$1:$C$34,MATCH('District Specific SCFF'!H$1,'Rate Assumptions'!$A$1:$A$34,0),2) -> 0.0326 | I59: =F59*(1+G59)*(1+H59) -> 44320933 | J59: =IF(I59>E59,"Y","") | K59: =IF(J59="",0,I59-E59) -> 0 | M59: =IF(L59="x",0,K59) -> 0 | N59: =M59+I59 -> 44320933
A60: Sierra | B60: =INDEX('Base Allocation'!$A$2:$AI$77,MATCH('District Specific SCFF'!$A60,'Base Allocation'!$A$2:$A$77,0),MATCH('District Specific SCFF'!B$1,'Base Allocation'!$A$2:$AI$2,0)) -> 61536862 | C60: =INDEX('Supplemental Allocation'!$A$2:$Q$76,MATCH('District Specific SCFF'!$A60,'Supplemental Allocation'!$A$2:$A$76,0),MATCH('District Specific SCFF'!C$1,'Supplemental Allocation'!$A$2:$Q$2,0)) -> 16685760 | D60: =INDEX('Success Allocation'!$A$3:$EP$76,MATCH('District Specific SCFF'!$A60,'Success Allocation'!$A$3:$A$76,0),MATCH('District Specific SCFF'!D$1,'Success Allocation'!$A$3:$EP$3,0)) -> 12048574 | E60: =SUM(B60:D60) -> 90271196 | F60: 86569715 | G60: =INDEX('Rate Assumptions'!$A$1:$C$34,MATCH('District Specific SCFF'!G$1,'Rate Assumptions'!$A$1:$A$34,0),2) -> 0.0271 | H60: =INDEX('Rate Assumptions'!$A$1:$C$34,MATCH('District Specific SCFF'!H$1,'Rate Assumptions'!$A$1:$A$34,0),2) -> 0.0326 | I60: =F60*(1+G60)*(1+H60) -> 91814408 | J60: =IF(I60>E60,"Y","") -> Y | K60: =IF(J60="",0,I60-E60) -> 1543212.1 | M60: =IF(L60="x",0,K60) -> 1543212.1 | N60: =M60+I60 -> 93357620
A61: Siskiyous | B61: =INDEX('Base Allocation'!$A$2:$AI$77,MATCH('District Specific SCFF'!$A61,'Base Allocation'!$A$2:$A$77,0),MATCH('District Specific SCFF'!B$1,'Base Allocation'!$A$2:$AI$2,0)) -> 15838522 | C61: =INDEX('Supplemental Allocation'!$A$2:$Q$76,MATCH('District Specific SCFF'!$A61,'Supplemental Allocation'!$A$2:$A$76,0),MATCH('District Specific SCFF'!C$1,'Supplemental Allocation'!$A$2:$Q$2,0)) -> 1979052 | D61: =INDEX('Success Allocation'!$A$3:$EP$76,MATCH('District Specific SCFF'!$A61,'Success Allocation'!$A$3:$A$76,0),MATCH('District Specific SCFF'!D$1,'Success Allocation'!$A$3:$EP$3,0)) -> 1788939.4 | E61: =SUM(B61:D61) -> 19606513 | F61: 18150995 | G61: =INDEX('Rate Assumptions'!$A$1:$C$34,MATCH('District Specific SCFF'!G$1,'Rate Assumptions'!$A$1:$A$34,0),2) -> 0.0271 | H61: =INDEX('Rate Assumptions'!$A$1:$C$34,MATCH('District Specific SCFF'!H$1,'Rate Assumptions'!$A$1:$A$34,0),2) -> 0.0326 | I61: =F61*(1+G61)*(1+H61) -> 19250645 | J61: =IF(I61>E61,"Y","") | K61: =IF(J61="",0,I61-E61) -> 0 | M61: =IF(L61="x",0,K61) -> 0 | N61: =M61+I61 -> 19250645
A62: Solano | B62: =INDEX('Base Allocation'!$A$2:$AI$77,MATCH('District Specific SCFF'!$A62,'Base Allocation'!$A$2:$A$77,0),MATCH('District Specific SCFF'!B$1,'Base Allocation'!$A$2:$AI$2,0)) -> 33397293 | C62: =INDEX('Supplemental Allocation'!$A$2:$Q$76,MATCH('District Specific SCFF'!$A62,'Supplemental Allocation'!$A$2:$A$76,0),MATCH('District Specific SCFF'!C$1,'Supplemental Allocation'!$A$2:$Q$2,0)) -> 7168834.6 | D62: =INDEX('Success Allocation'!$A$3:$EP$76,MATCH('District Specific SCFF'!$A62,'Success Allocation'!$A$3:$A$76,0),MATCH('District Specific SCFF'!D$1,'Success Allocation'!$A$3:$EP$3,0)) -> 4740194.2 | E62: =SUM(B62:D62) -> 45306322 | F62: 48526065 | G62: =INDEX('Rate Assumptions'!$A$1:$C$34,MATCH('District Specific SCFF'!G$1,'Rate Assumptions'!$A$1:$A$34,0),2) -> 0.0271 | H62: =INDEX('Rate Assumptions'!$A$1:$C$34,MATCH('District Specific SCFF'!H$1,'Rate Assumptions'!$A$1:$A$34,0),2) -> 0.0326 | I62: =F62*(1+G62)*(1+H62) -> 51465942 | J62: =IF(I62>E62,"Y","") -> Y | K62: =IF(J62="",0,I62-E62) -> 6159620.1 | M62: =IF(L62="x",0,K62) -> 6159620.1 | N62: =M62+I62 -> 57625562
A63: Sonoma | B63: =INDEX('Base Allocation'!$A$2:$AI$77,MATCH('District Specific SCFF'!$A63,'Base Allocation'!$A$2:$A$77,0),MATCH('District Specific SCFF'!B$1,'Base Allocation'!$A$2:$AI$2,0)) -> 89151389 | C63: =INDEX('Supplemental Allocation'!$A$2:$Q$76,MATCH('District Specific SCFF'!$A63,'Supplemental Allocation'!$A$2:$A$76,0),MATCH('District Specific SCFF'!C$1,'Supplemental Allocation'!$A$2:$Q$2,0)) -> 14494766 | D63: =INDEX('Success Allocation'!$A$3:$EP$76,MATCH('District Specific SCFF'!$A63,'Success Allocation'!$A$3:$A$76,0),MATCH('District Specific SCFF'!D$1,'Success Allocation'!$A$3:$EP$3,0)) -> 11811947 | E63: =SUM(B63:D63) -> 1.154581e+08 | F63: 106270424 | G63: =INDEX('Rate Assumptions'!$A$1:$C$34,MATCH('District Specific SCFF'!G$1,'Rate Assumptions'!$A$1:$A$34,0),2) -> 0.0271 | H63: =INDEX('Rate Assumptions'!$A$1:$C$34,MATCH('District Specific SCFF'!H$1,'Rate Assumptions'!$A$1:$A$34,0),2) -> 0.0326 | I63: =F63*(1+G63)*(1+H63) -> 1.1270865e+08 | J63: =IF(I63>E63,"Y","") | K63: =IF(J63="",0,I63-E63) -> 0 | M63: =IF(L63="x",0,K63) -> 0 | N63: =M63+I63 -> 1.1270865e+08
A64: South Orange County | B64: =INDEX('Base Allocation'!$A$2:$AI$77,MATCH('District Specific SCFF'!$A64,'Base Allocation'!$A$2:$A$77,0),MATCH('District Specific SCFF'!B$1,'Base Allocation'!$A$2:$AI$2,0)) -> 1.1838673e+08 | C64: =INDEX('Supplemental Allocation'!$A$2:$Q$76,MATCH('District Specific SCFF'!$A64,'Supplemental Allocation'!$A$2:$A$76,0),MATCH('District Specific SCFF'!C$1,'Supplemental Allocation'!$A$2:$Q$2,0)) -> 18666671 | D64: =INDEX('Success Allocation'!$A$3:$EP$76,MATCH('District Specific SCFF'!$A64,'Success Allocation'!$A$3:$A$76,0),MATCH('District Specific SCFF'!D$1,'Success Allocation'!$A$3:$EP$3,0)) -> 19749448 | E64: =SUM(B64:D64) -> 1.5680285e+08 | F64: 152673419 | G64: =INDEX('Rate Assumptions'!$A$1:$C$34,MATCH('District Specific SCFF'!G$1,'Rate Assumptions'!$A$1:$A$34,0),2) -> 0.0271 | H64: =INDEX('Rate Assumptions'!$A$1:$C$34,MATCH('District Specific SCFF'!H$1,'Rate Assumptions'!$A$1:$A$34,0),2) -> 0.0326 | I64: =F64*(1+G64)*(1+H64) -> 1.619229e+08 | J64: =IF(I64>E64,"Y","") -> Y | K64: =IF(J64="",0,I64-E64) -> 5120056.7 | L64: x | M64: =IF(L64="x",0,K64) -> 0 | N64: =M64+I64 -> 1.619229e+08
A65: Southwestern | B65: =INDEX('Base Allocation'!$A$2:$AI$77,MATCH('District Specific SCFF'!$A65,'Base Allocation'!$A$2:$A$77,0),MATCH('District Specific SCFF'!B$1,'Base Allocation'!$A$2:$AI$2,0)) -> 67325391 | C65: =INDEX('Supplemental Allocation'!$A$2:$Q$76,MATCH('District Specific SCFF'!$A65,'Supplemental Allocation'!$A$2:$A$76,0),MATCH('District Specific SCFF'!C$1,'Supplemental Allocation'!$A$2:$Q$2,0)) -> 20436570 | D65: =INDEX('Success Allocation'!$A$3:$EP$76,MATCH('District Specific SCFF'!$A65,'Success Allocation'!$A$3:$A$76,0),MATCH('District Specific SCFF'!D$1,'Success Allocation'!$A$3:$EP$3,0)) -> 9551040.7 | E65: =SUM(B65:D65) -> 97313001 | F65: 92612800 | G65: =INDEX('Rate Assumptions'!$A$1:$C$34,MATCH('District Specific SCFF'!G$1,'Rate Assumptions'!$A$1:$A$34,0),2) -> 0.0271 | H65: =INDEX('Rate Assumptions'!$A$1:$C$34,MATCH('District Specific SCFF'!H$1,'Rate Assumptions'!$A$1:$A$34,0),2) -> 0.0326 | I65: =F65*(1+G65)*(1+H65) -> 98223604 | J65: =IF(I65>E65,"Y","") -> Y | K65: =IF(J65="",0,I65-E65) -> 910602.42 | M65: =IF(L65="x",0,K65) -> 910602.42 | N65: =M65+I65 -> 99134206
A66: State Center | B66: =INDEX('Base Allocation'!$A$2:$AI$77,MATCH('District Specific SCFF'!$A66,'Base Allocation'!$A$2:$A$77,0),MATCH('District Specific SCFF'!B$1,'Base Allocation'!$A$2:$AI$2,0)) -> 1.4344766e+08 | C66: =INDEX('Supplemental Allocation'!$A$2:$Q$76,MATCH('District Specific SCFF'!$A66,'Supplemental Allocation'!$A$2:$A$76,0),MATCH('District Specific SCFF'!C$1,'Supplemental Allocation'!$A$2:$Q$2,0)) -> 47775188 | D66: =INDEX('Success Allocation'!$A$3:$EP$76,MATCH('District Specific SCFF'!$A66,'Success Allocation'!$A$3:$A$76,0),MATCH('District Specific SCFF'!D$1,'Success Allocation'!$A$3:$EP$3,0)) -> 27683385 | E66: =SUM(B66:D66) -> 2.1890624e+08 | F66: 181156108 | G66: =INDEX('Rate Assumptions'!$A$1:$C$34,MATCH('District Specific SCFF'!G$1,'Rate Assumptions'!$A$1:$A$34,0),2) -> 0.0271 | H66: =INDEX('Rate Assumptions'!$A$1:$C$34,MATCH('District Specific SCFF'!H$1,'Rate Assumptions'!$A$1:$A$34,0),2) -> 0.0326 | I66: =F66*(1+G66)*(1+H66) -> 1.9213117e+08 | J66: =IF(I66>E66,"Y","") | K66: =IF(J66="",0,I66-E66) -> 0 | M66: =IF(L66="x",0,K66) -> 0 | N66: =M66+I66 -> 1.9213117e+08
A67: Ventura | B67: =INDEX('Base Allocation'!$A$2:$AI$77,MATCH('District Specific SCFF'!$A67,'Base Allocation'!$A$2:$A$77,0),MATCH('District Specific SCFF'!B$1,'Base Allocation'!$A$2:$AI$2,0)) -> 1.2106789e+08 | C67: =INDEX('Supplemental Allocation'!$A$2:$Q$76,MATCH('District Specific SCFF'!$A67,'Supplemental Allocation'!$A$2:$A$76,0),MATCH('District Specific SCFF'!C$1,'Supplemental Allocation'!$A$2:$Q$2,0)) -> 29932115 | D67: =INDEX('Success Allocation'!$A$3:$EP$76,MATCH('District Specific SCFF'!$A67,'Success Allocation'!$A$3:$A$76,0),MATCH('District Specific SCFF'!D$1,'Success Allocation'!$A$3:$EP$3,0)) -> 23814743 | E67: =SUM(B67:D67) -> 1.7481475e+08 | F67: 153823885 | G67: =INDEX('Rate Assumptions'!$A$1:$C$34,MATCH('District Specific SCFF'!G$1,'Rate Assumptions'!$A$1:$A$34,0),2) -> 0.0271 | H67: =INDEX('Rate Assumptions'!$A$1:$C$34,MATCH('District Specific SCFF'!H$1,'Rate Assumptions'!$A$1:$A$34,0),2) -> 0.0326 | I67: =F67*(1+G67)*(1+H67) -> 1.6314307e+08 | J67: =IF(I67>E67,"Y","") | K67: =IF(J67="",0,I67-E67) -> 0 | M67: =IF(L67="x",0,K67) -> 0 | N67: =M67+I67 -> 1.6314307e+08
A68: Victor Valley | B68: =INDEX('Base Allocation'!$A$2:$AI$77,MATCH('District Specific SCFF'!$A68,'Base Allocation'!$A$2:$A$77,0),MATCH('District Specific SCFF'!B$1,'Base Allocation'!$A$2:$AI$2,0)) -> 41743457 | C68: =INDEX('Supplemental Allocation'!$A$2:$Q$76,MATCH('District Specific SCFF'!$A68,'Supplemental Allocation'!$A$2:$A$76,0),MATCH('District Specific SCFF'!C$1,'Supplemental Allocation'!$A$2:$Q$2,0)) -> 17114291 | D68: =INDEX('Success Allocation'!$A$3:$EP$76,MATCH('District Specific SCFF'!$A68,'Success Allocation'!$A$3:$A$76,0),MATCH('District Specific SCFF'!D$1,'Success Allocation'!$A$3:$EP$3,0)) -> 6569004.5 | E68: =SUM(B68:D68) -> 65426753 | F68: 54747776 | G68: =INDEX('Rate Assumptions'!$A$1:$C$34,MATCH('District Specific SCFF'!G$1,'Rate Assumptions'!$A$1:$A$34,0),2) -> 0.0271 | H68: =INDEX('Rate Assumptions'!$A$1:$C$34,MATCH('District Specific SCFF'!H$1,'Rate Assumptions'!$A$1:$A$34,0),2) -> 0.0326 | I68: =F68*(1+G68)*(1+H68) -> 58064586 | J68: =IF(I68>E68,"Y","") | K68: =IF(J68="",0,I68-E68) -> 0 | M68: =IF(L68="x",0,K68) -> 0 | N68: =M68+I68 -> 58064586
A69: West Hills | B69: =INDEX('Base Allocation'!$A$2:$AI$77,MATCH('District Specific SCFF'!$A69,'Base Allocation'!$A$2:$A$77,0),MATCH('District Specific SCFF'!B$1,'Base Allocation'!$A$2:$AI$2,0)) -> 33160619 | C69: =INDEX('Supplemental Allocation'!$A$2:$Q$76,MATCH('District Specific SCFF'!$A69,'Supplemental Allocation'!$A$2:$A$76,0),MATCH('District Specific SCFF'!C$1,'Supplemental Allocation'!$A$2:$Q$2,0)) -> 8860649.8 | D69: =INDEX('Success Allocation'!$A$3:$EP$76,MATCH('District Specific SCFF'!$A69,'Success Allocation'!$A$3:$A$76,0),MATCH('District Specific SCFF'!D$1,'Success Allocation'!$A$3:$EP$3,0)) -> 5180397.2 | E69: =SUM(B69:D69) -> 47201666 | F69: 37644442 | G69: =INDEX('Rate Assumptions'!$A$1:$C$34,MATCH('District Specific SCFF'!G$1,'Rate Assumptions'!$A$1:$A$34,0),2) -> 0.0271 | H69: =INDEX('Rate Assumptions'!$A$1:$C$34,MATCH('District Specific SCFF'!H$1,'Rate Assumptions'!$A$1:$A$34,0),2) -> 0.0326 | I69: =F69*(1+G69)*(1+H69) -> 39925073 | J69: =IF(I69>E69,"Y","") | K69: =IF(J69="",0,I69-E69) -> 0 | M69: =IF(L69="x",0,K69) -> 0 | N69: =M69+I69 -> 39925073
A70: West Kern | B70: =INDEX('Base Allocation'!$A$2:$AI$77,MATCH('District Specific SCFF'!$A70,'Base Allocation'!$A$2:$A$77,0),MATCH('District Specific SCFF'!B$1,'Base Allocation'!$A$2:$AI$2,0)) -> 17059177 | C70: =INDEX('Supplemental Allocation'!$A$2:$Q$76,MATCH('District Specific SCFF'!$A70,'Supplemental Allocation'!$A$2:$A$76,0),MATCH('District Specific SCFF'!C$1,'Supplemental Allocation'!$A$2:$Q$2,0)) -> 4768687.9 | D70: =INDEX('Success Allocation'!$A$3:$EP$76,MATCH('District Specific SCFF'!$A70,'Success Allocation'!$A$3:$A$76,0),MATCH('District Specific SCFF'!D$1,'Success Allocation'!$A$3:$EP$3,0)) -> 4971930.2 | E70: =SUM(B70:D70) -> 26799795 | F70: 24502556 | G70: =INDEX('Rate Assumptions'!$A$1:$C$34,MATCH('District Specific SCFF'!G$1,'Rate Assumptions'!$A$1:$A$34,0),2) -> 0.0271 | H70: =INDEX('Rate Assumptions'!$A$1:$C$34,MATCH('District Specific SCFF'!H$1,'Rate Assumptions'!$A$1:$A$34,0),2) -> 0.0326 | I70: =F70*(1+G70)*(1+H70) -> 25987006 | J70: =IF(I70>E70,"Y","") | K70: =IF(J70="",0,I70-E70) -> 0 | M70: =IF(L70="x",0,K70) -> 0 | N70: =M70+I70 -> 25987006
A71: West Valley-Mission2 | B71: =INDEX('Base Allocation'!$A$2:$AI$77,MATCH('District Specific SCFF'!$A71,'Base Allocation'!$A$2:$A$77,0),MATCH('District Specific SCFF'!B$1,'Base Allocation'!$A$2:$AI$2,0)) -> 53545640 | C71: =INDEX('Supplemental Allocation'!$A$2:$Q$76,MATCH('District Specific SCFF'!$A71,'Supplemental Allocation'!$A$2:$A$76,0),MATCH('District Specific SCFF'!C$1,'Supplemental Allocation'!$A$2:$Q$2,0)) -> 7280382.8 | D71: =INDEX('Success Allocation'!$A$3:$EP$76,MATCH('District Specific SCFF'!$A71,'Success Allocation'!$A$3:$A$76,0),MATCH('District Specific SCFF'!D$1,'Success Allocation'!$A$3:$EP$3,0)) -> 7847252.6 | E71: =SUM(B71:D71) -> 68673275 | F71: 73379536 | G71: =INDEX('Rate Assumptions'!$A$1:$C$34,MATCH('District Specific SCFF'!G$1,'Rate Assumptions'!$A$1:$A$34,0),2) -> 0.0271 | H71: =INDEX('Rate Assumptions'!$A$1:$C$34,MATCH('District Specific SCFF'!H$1,'Rate Assumptions'!$A$1:$A$34,0),2) -> 0.0326 | I71: =F71*(1+G71)*(1+H71) -> 77825122 | J71: =IF(I71>E71,"Y","") -> Y | K71: =IF(J71="",0,I71-E71) -> 9151847 | L71: x | M71: =IF(L71="x",0,K71) -> 0 | N71: =M71+I71 -> 77825122
A72: Yosemite | B72: =INDEX('Base Allocation'!$A$2:$AI$77,MATCH('District Specific SCFF'!$A72,'Base Allocation'!$A$2:$A$77,0),MATCH('District Specific SCFF'!B$1,'Base Allocation'!$A$2:$AI$2,0)) -> 75089324 | C72: =INDEX('Supplemental Allocation'!$A$2:$Q$76,MATCH('District Specific SCFF'!$A72,'Supplemental Allocation'!$A$2:$A$76,0),MATCH('District Specific SCFF'!C$1,'Supplemental Allocation'!$A$2:$Q$2,0)) -> 26171080 | D72: =INDEX('Success Allocation'!$A$3:$EP$76,MATCH('District Specific SCFF'!$A72,'Success Allocation'!$A$3:$A$76,0),MATCH('District Specific SCFF'!D$1,'Success Allocation'!$A$3:$EP$3,0)) -> 12082902 | E72: =SUM(B72:D72) -> 1.1334331e+08 | F72: 95628458 | G72: =INDEX('Rate Assumptions'!$A$1:$C$34,MATCH('District Specific SCFF'!G$1,'Rate Assumptions'!$A$1:$A$34,0),2) -> 0.0271 | H72: =INDEX('Rate Assumptions'!$A$1:$C$34,MATCH('District Specific SCFF'!H$1,'Rate Assumptions'!$A$1:$A$34,0),2) -> 0.0326 | I72: =F72*(1+G72)*(1+H72) -> 1.0142196e+08 | J72: =IF(I72>E72,"Y","") | K72: =IF(J72="",0,I72-E72) -> 0 | M72: =IF(L72="x",0,K72) -> 0 | N72: =M72+I72 -> 1.0142196e+08
A73: Yuba | B73: =INDEX('Base Allocation'!$A$2:$AI$77,MATCH('District Specific SCFF'!$A73,'Base Allocation'!$A$2:$A$77,0),MATCH('District Specific SCFF'!B$1,'Base Allocation'!$A$2:$AI$2,0)) -> 39976061 | C73: =INDEX('Supplemental Allocation'!$A$2:$Q$76,MATCH('District Specific SCFF'!$A73,'Supplemental Allocation'!$A$2:$A$76,0),MATCH('District Specific SCFF'!C$1,'Supplemental Allocation'!$A$2:$Q$2,0)) -> 10878744 | D73: =INDEX('Success Allocation'!$A$3:$EP$76,MATCH('District Specific SCFF'!$A73,'Success Allocation'!$A$3:$A$76,0),MATCH('District Specific SCFF'!D$1,'Success Allocation'!$A$3:$EP$3,0)) -> 6098543.5 | E73: =SUM(B73:D73) -> 56953348 | F73: 49580375 | G73: =INDEX('Rate Assumptions'!$A$1:$C$34,MATCH('District Specific SCFF'!G$1,'Rate Assumptions'!$A$1:$A$34,0),2) -> 0.0271 | H73: =INDEX('Rate Assumptions'!$A$1:$C$34,MATCH('District Specific SCFF'!H$1,'Rate Assumptions'!$A$1:$A$34,0),2) -> 0.0326 | I73: =F73*(1+G73)*(1+H73) -> 52584126 | J73: =IF(I73>E73,"Y","") | K73: =IF(J73="",0,I73-E73) -> 0 | M73: =IF(L73="x",0,K73) -> 0 | N73: =M73+I73 -> 52584126
A74: Total | B74: =SUM(B2:B73) -> 5.2045806e+09 | C74: =SUM(C2:C73) -> 1.3676086e+09 | D74: =SUM(D2:D73) -> 8.2198644e+08 | E74: =SUM(E2:E73) -> 7.3941757e+09 | F74: =SUM(F2:F73) -> 6766922198 | I74: =SUM(I2:I73) -> 7.1768858e+09 | K74: =SUM(K2:K73) -> 1.2897928e+08 | M74: =SUM(M2:M73) -> 1.0576558e+08 | N74: =SUM(N2:N73) -> 7.2826513e+09

Sheet Base Allocation
B1: 2016-17 | H1: 2017-18 | N1: 2018-19 | T1: 2019-20 Projection | Z1: Model Inputs | AE1: Rates
A2: FTES Data | B2: FTES | E2: Inmates in Correctional Facilities Education FTES | F2: Special Admit FTES | G2: Excluding Inmates and Special Admit | H2: FTES | K2: Inmates in Correctional Facilities Education FTES | L2: Special Admit FTES | M2: Excluding Inmates and Special Admit | N2: FTES | Q2: Inmates in Correctional Facilities Education FTES | R2: Special Admit FTES | S2: Excluding Inmates and Special Admit | T2: FTES | W2: Inmates in Correctional Facilities Education FTES | X2: Special Admit FTES | Y2: Excluding Inmates and Special Admit | Z2: 3-Year Average Credit FTES (Excluding Inmates and Special Admits) | AA2: Noncredit FTES | AB2: CDCP FTES | AC2: Special Admits and Students in Correctional Facilities FTES | AD2: Basic Allocation DOF | AE2: Credit FTES | AF2: Noncredit FTES | AG2: CDCP FTES | AH2: Special Admits and Students in Correctional Facilities FTES | AI2: Base Allocation
B3: Credit | C3: Noncredit | D3: CDCP | E3: Credit | F3: Credit | G3: Credit | H3: Credit | I3: Noncredit | J3: CDCP | K3: Credit | L3: Credit | M3: Credit | N3: Credit | O3: Noncredit | P3: CDCP | Q3: Credit | R3: Credit | S3: Credit | T3: Credit | U3: Noncredit | V3: CDCP | W3: Credit | X3: Credit | Y3: Credit
A4: District
A5: Allan Hancock | B5: 9202.61 | C5: 499.92 | D5: 319.04 | E5: 106.5 | F5: 425.76 | G5: =B5-E5-F5 -> 8670.35 | H5: 7860.16 | I5: 431.7 | J5: 261.7 | K5: 83.47 | L5: 436.82 | M5: =H5-K5-L5 -> 7339.87 | N5: 8984.08 | O5: 401.82 | P5: 255.44 | Q5: 73.67 | R5: 420.1 | S5: =N5-Q5-R5 -> 8490.31 | T5: =IF((H5-B5)*(1/3)+(N5-H5)*(2/3) + N5>0,N5+(H5-B5)*(1/3)+(N5-H5)*(2/3),N5) -> 9285.8767 | U5: =IF((I5-C5)*(1/3)+(O5-I5)*(2/3) + O5>0,O5+(I5-C5)*(1/3)+(O5-I5)*(2/3),O5) -> 359.16 | V5: =IF((J5-D5)*(1/3)+(P5-J5)*(2/3) + P5>0,P5+(J5-D5)*(1/3)+(P5-J5)*(2/3),P5) -> 232.15333 | W5: =IF((K5-E5)*(1/3)+(Q5-K5)*(2/3) + Q5>0,Q5+(K5-E5)*(1/3)+(Q5-K5)*(2/3),Q5) -> 59.46 | X5: =IF((L5-F5)*(1/3)+(R5-L5)*(2/3) + R5>0,R5+(L5-F5)*(1/3)+(R5-L5)*(2/3),R5) -> 412.64 | Y5: =T5-W5-X5 -> 8813.7767 | Z5: =AVERAGE(Y5,S5,M5) -> 8214.6522 | AA5: =U5 -> 359.16 | AB5: =V5 -> 232.15333 | AC5: =SUM(W5:X5) -> 472.1 | AD5: 6742470.1 | AE5: =INDEX('Rate Assumptions'!$A:$B,MATCH('Base Allocation'!AE$2,'Rate Assumptions'!$A:$A,0),2) -> 3988.5862 | AF5: =INDEX('Rate Assumptions'!$A:$B,MATCH('Base Allocation'!AF$2,'Rate Assumptions'!$A:$A,0),2) -> 3456.4415 | AG5: =INDEX('Rate Assumptions'!$A:$B,MATCH('Base Allocation'!AG$2,'Rate Assumptions'!$A:$A,0),2) -> 5634.5606 | AH5: =INDEX('Rate Assumptions'!$A:$B,MATCH('Base Allocation'!AH$2,'Rate Assumptions'!$A:$A,0),2) -> 5634.5606 | AI5: =AD5+SUMPRODUCT(Z5:AC5,AE5:AH5) -> 44716892
A6: Antelope | B6: 10523.45 | C6: 4.5 | D6: 39.28 | E6: 8.68 | F6: 302.6 | G6: =B6-E6-F6 -> 10212.17 | H6: 10527.04 | I6: 7.919966 | J6: 80.880058 | K6: 1.79 | L6: 308.01 | M6: =H6-K6-L6 -> 10217.24 | N6: 10968.8 | O6: 7.61 | P6: 55.1 | Q6: 11.01 | R6: 341.84 | S6: =N6-Q6-R6 -> 10615.95 | T6: =IF((H6-B6)*(1/3)+(N6-H6)*(2/3) + N6>0,N6+(H6-B6)*(1/3)+(N6-H6)*(2/3),N6) -> 11264.503 | U6: =IF((I6-C6)*(1/3)+(O6-I6)*(2/3) + O6>0,O6+(I6-C6)*(1/3)+(O6-I6)*(2/3),O6) -> 8.5433447 | V6: =IF((J6-D6)*(1/3)+(P6-J6)*(2/3) + P6>0,P6+(J6-D6)*(1/3)+(P6-J6)*(2/3),P6) -> 51.779981 | W6: =IF((K6-E6)*(1/3)+(Q6-K6)*(2/3) + Q6>0,Q6+(K6-E6)*(1/3)+(Q6-K6)*(2/3),Q6) -> 14.86 | X6: =IF((L6-F6)*(1/3)+(R6-L6)*(2/3) + R6>0,R6+(L6-F6)*(1/3)+(R6-L6)*(2/3),R6) -> 366.19667 | Y6: =T6-W6-X6 -> 10883.447 | Z6: =AVERAGE(Y6,S6,M6) -> 10572.212 | AA6: =U6 -> 8.5433447 | AB6: =V6 -> 51.779981 | AC6: =SUM(W6:X6) -> 381.05667 | AD6: 6742470.1 | AE6: =INDEX('Rate Assumptions'!$A:$B,MATCH('Base Allocation'!AE$2,'Rate Assumptions'!$A:$A,0),2) -> 3988.5862 | AF6: =INDEX('Rate Assumptions'!$A:$B,MATCH('Base Allocation'!AF$2,'Rate Assumptions'!$A:$A,0),2) -> 3456.4415 | AG6: =INDEX('Rate Assumptions'!$A:$B,MATCH('Base Allocation'!AG$2,'Rate Assumptions'!$A:$A,0),2) -> 5634.5606 | AH6: =INDEX('Rate Assumptions'!$A:$B,MATCH('Base Allocation'!AH$2,'Rate Assumptions'!$A:$A,0),2) -> 5634.5606 | AI6: =AD6+SUMPRODUCT(Z6:AC6,AE6:AH6) -> 51379024
A7: Barstow | B7: 2565.1499 | C7: 17.72 | D7: 0 | F7: 39.21 | G7: =B7-E7-F7 -> 2525.9399 | H7: 2320.71 | I7: 29.82 | J7: 0 | L7: 43.74 | M7: =H7-K7-L7 -> 2276.97 | N7: 2552.27 | O7: 29.84 | P7: 0 | Q7: 0 | R7: 0 | S7: =N7-Q7-R7 -> 2552.27 | T7: =IF((H7-B7)*(1/3)+(N7-H7)*(2/3) + N7>0,N7+(H7-B7)*(1/3)+(N7-H7)*(2/3),N7) -> 2625.1634 | U7: =IF((I7-C7)*(1/3)+(O7-I7)*(2/3) + O7>0,O7+(I7-C7)*(1/3)+(O7-I7)*(2/3),O7) -> 33.886667 | V7: =IF((J7-D7)*(1/3)+(P7-J7)*(2/3) + P7>0,P7+(J7-D7)*(1/3)+(P7-J7)*(2/3),P7) -> 0 | W7: =IF((K7-E7)*(1/3)+(Q7-K7)*(2/3) + Q7>0,Q7+(K7-E7)*(1/3)+(Q7-K7)*(2/3),Q7) -> 0 | X7: =IF((L7-F7)*(1/3)+(R7-L7)*(2/3) + R7>0,R7+(L7-F7)*(1/3)+(R7-L7)*(2/3),R7) -> 0 | Y7: =T7-W7-X7 -> 2625.1634 | Z7: =AVERAGE(Y7,S7,M7) -> 2484.8011 | AA7: =U7 -> 33.886667 | AB7: =V7 -> 0 | AC7: =SUM(W7:X7) -> 0 | AD7: 5332192.5 | AE7: =INDEX('Rate Assumptions'!$A:$B,MATCH('Base Allocation'!AE$2,'Rate Assumptions'!$A:$A,0),2) -> 3988.5862 | AF7: =INDEX('Rate Assumptions'!$A:$B,MATCH('Base Allocation'!AF$2,'Rate Assumptions'!$A:$A,0),2) -> 3456.4415 | AG7: =INDEX('Rate Assumptions'!$A:$B,MATCH('Base Allocation'!AG$2,'Rate Assumptions'!$A:$A,0),2) -> 5634.5606 | AH7: =INDEX('Rate Assumptions'!$A:$B,MATCH('Base Allocation'!AH$2,'Rate Assumptions'!$A:$A,0),2) -> 5634.5606 | AI7: =AD7+SUMPRODUCT(Z7:AC7,AE7:AH7) -> 15360163
A8: Butte | B8: 8717.92 | C8: 1245.24 | D8: 23.44 | F8: 172.12 | G8: =B8-E8-F8 -> 8545.8 | H8: 9162.4001 | I8: 1195.77 | J8: 25.05 | L8: 185.72 | M8: =H8-K8-L8 -> 8976.6801 | N8: 9162.4 | O8: 1195.77 | P8: 25.05 | Q8: 0 | R8: 185.72 | S8: =N8-Q8-R8 -> 8976.68 | T8: =IF((H8-B8)*(1/3)+(N8-H8)*(2/3) + N8>0,N8+(H8-B8)*(1/3)+(N8-H8)*(2/3),N8) -> 9310.56 | U8: =IF((I8-C8)*(1/3)+(O8-I8)*(2/3) + O8>0,O8+(I8-C8)*(1/3)+(O8-I8)*(2/3),O8) -> 1179.28 | V8: =IF((J8-D8)*(1/3)+(P8-J8)*(2/3) + P8>0,P8+(J8-D8)*(1/3)+(P8-J8)*(2/3),P8) -> 25.586667 | W8: =IF((K8-E8)*(1/3)+(Q8-K8)*(2/3) + Q8>0,Q8+(K8-E8)*(1/3)+(Q8-K8)*(2/3),Q8) -> 0 | X8: =IF((L8-F8)*(1/3)+(R8-L8)*(2/3) + R8>0,R8+(L8-F8)*(1/3)+(R8-L8)*(2/3),R8) -> 190.25333 | Y8: =T8-W8-X8 -> 9120.3066 | Z8: =AVERAGE(Y8,S8,M8) -> 9024.5556 | AA8: =U8 -> 1179.28 | AB8: =V8 -> 25.586667 | AC8: =SUM(W8:X8) -> 190.25333 | AD8: 6742470.1 | AE8: =INDEX('Rate Assumptions'!$A:$B,MATCH('Base Allocation'!AE$2,'Rate Assumptions'!$A:$A,0),2) -> 3988.5862 | AF8: =INDEX('Rate Assumptions'!$A:$B,MATCH('Base Allocation'!AF$2,'Rate Assumptions'!$A:$A,0),2) -> 3456.4415 | AG8: =INDEX('Rate Assumptions'!$A:$B,MATCH('Base Allocation'!AG$2,'Rate Assumptions'!$A:$A,0),2) -> 5634.5606 | AH8: =INDEX('Rate Assumptions'!$A:$B,MATCH('Base Allocation'!AH$2,'Rate Assumptions'!$A:$A,0),2) -> 5634.5606 | AI8: =AD8+SUMPRODUCT(Z8:AC8,AE8:AH8) -> 48029964
A9: Cabrillo | B9: 10208.64 | C9: 181.86 | D9: 2.96 | F9: 300.29 | G9: =B9-E9-F9 -> 9908.35 | H9: 8791.82 | I9: 136.63 | J9: 15 | L9: 285.12 | M9: =H9-K9-L9 -> 8506.7 | N9: 9763.41 | O9: 481.52 | P9: 55.93 | Q9: 0 | R9: 234.9 | S9: =N9-Q9-R9 -> 9528.51 | T9: =IF((H9-B9)*(1/3)+(N9-H9)*(2/3) + N9>0,N9+(H9-B9)*(1/3)+(N9-H9)*(2/3),N9) -> 9938.8633 | U9: =IF((I9-C9)*(1/3)+(O9-I9)*(2/3) + O9>0,O9+(I9-C9)*(1/3)+(O9-I9)*(2/3),O9) -> 696.37 | V9: =IF((J9-D9)*(1/3)+(P9-J9)*(2/3) + P9>0,P9+(J9-D9)*(1/3)+(P9-J9)*(2/3),P9) -> 87.23 | W9: =IF((K9-E9)*(1/3)+(Q9-K9)*(2/3) + Q9>0,Q9+(K9-E9)*(1/3)+(Q9-K9)*(2/3),Q9) -> 0 | X9: =IF((L9-F9)*(1/3)+(R9-L9)*(2/3) + R9>0,R9+(L9-F9)*(1/3)+(R9-L9)*(2/3),R9) -> 196.36333 | Y9: =T9-W9-X9 -> 9742.5 | Z9: =AVERAGE(Y9,S9,M9) -> 9259.2367 | AA9: =U9 -> 696.37 | AB9: =V9 -> 87.23 | AC9: =SUM(W9:X9) -> 196.36333 | AD9: 6742470.1 | AE9: =INDEX('Rate Assumptions'!$A:$B,MATCH('Base Allocation'!AE$2,'Rate Assumptions'!$A:$A,0),2) -> 3988.5862 | AF9: =INDEX('Rate Assumptions'!$A:$B,MATCH('Base Allocation'!AF$2,'Rate Assumptions'!$A:$A,0),2) -> 3456.4415 | AG9: =INDEX('Rate Assumptions'!$A:$B,MATCH('Base Allocation'!AG$2,'Rate Assumptions'!$A:$A,0),2) -> 5634.5606 | AH9: =INDEX('Rate Assumptions'!$A:$B,MATCH('Base Allocation'!AH$2,'Rate Assumptions'!$A:$A,0),2) -> 5634.5606 | AI9: =AD9+SUMPRODUCT(Z9:AC9,AE9:AH9) -> 47678619
A10: Cerritos | B10: 16303.43 | C10: 138.5 | D10: 279.76 | F10: 81.08 | G10: =B10-E10-F10 -> 16222.35 | H10: 16254.43 | I10: 273.91 | J10: 249.77 | L10: 91 | M10: =H10-K10-L10 -> 16163.43 | N10: 15924.63 | O10: 273.91 | P10: 249.77 | Q10: 0 | R10: 106.49 | S10: =N10-Q10-R10 -> 15818.14 | T10: =IF((H10-B10)*(1/3)+(N10-H10)*(2/3) + N10>0,N10+(H10-B10)*(1/3)+(N10-H10)*(2/3),N10) -> 15688.43 | U10: =IF((I10-C10)*(1/3)+(O10-I10)*(2/3) + O10>0,O10+(I10-C10)*(1/3)+(O10-I10)*(2/3),O10) -> 319.04667 | V10: =IF((J10-D10)*(1/3)+(P10-J10)*(2/3) + P10>0,P10+(J10-D10)*(1/3)+(P10-J10)*(2/3),P10) -> 239.77333 | W10: =IF((K10-E10)*(1/3)+(Q10-K10)*(2/3) + Q10>0,Q10+(K10-E10)*(1/3)+(Q10-K10)*(2/3),Q10) -> 0 | X10: =IF((L10-F10)*(1/3)+(R10-L10)*(2/3) + R10>0,R10+(L10-F10)*(1/3)+(R10-L10)*(2/3),R10) -> 120.12333 | Y10: =T10-W10-X10 -> 15568.307 | Z10: =AVERAGE(Y10,S10,M10) -> 15849.959 | AA10: =U10 -> 319.04667 | AB10: =V10 -> 239.77333 | AC10: =SUM(W10:X10) -> 120.12333 | AD10: 5393976.1 | AE10: =INDEX('Rate Assumptions'!$A:$B,MATCH('Base Allocation'!AE$2,'Rate Assumptions'!$A:$A,0),2) -> 3988.5862 | AF10: =INDEX('Rate Assumptions'!$A:$B,MATCH('Base Allocation'!AF$2,'Rate Assumptions'!$A:$A,0),2) -> 3456.4415 | AG10: =INDEX('Rate Assumptions'!$A:$B,MATCH('Base Allocation'!AG$2,'Rate Assumptions'!$A:$A,0),2) -> 5634.5606 | AH10: =INDEX('Rate Assumptions'!$A:$B,MATCH('Base Allocation'!AH$2,'Rate Assumptions'!$A:$A,0),2) -> 5634.5606 | AI10: =AD10+SUMPRODUCT(Z10:AC10,AE10:AH10) -> 71743529
A11: Chabot-Las Positas | B11: 15460.45 | C11: 164.83 | D11: 0 | F11: 212.72 | G11: =B11-E11-F11 -> 15247.73 | H11: 18651.603 | I11: 171.55 | J11: 0 | L11: 278.6 | M11: =H11-K11-L11 -> 18373.003 | N11: 15239.66 | O11: 179.03 | P11: 0 | Q11: 0 | R11: 366.03 | S11: =N11-Q11-R11 -> 14873.63 | T11: =IF((H11-B11)*(1/3)+(N11-H11)*(2/3) + N11>0,N11+(H11-B11)*(1/3)+(N11-H11)*(2/3),N11) -> 14028.749 | U11: =IF((I11-C11)*(1/3)+(O11-I11)*(2/3) + O11>0,O11+(I11-C11)*(1/3)+(O11-I11)*(2/3),O11) -> 186.25667 | V11: =IF((J11-D11)*(1/3)+(P11-J11)*(2/3) + P11>0,P11+(J11-D11)*(1/3)+(P11-J11)*(2/3),P11) -> 0 | W11: =IF((K11-E11)*(1/3)+(Q11-K11)*(2/3) + Q11>0,Q11+(K11-E11)*(1/3)+(Q11-K11)*(2/3),Q11) -> 0 | X11: =IF((L11-F11)*(1/3)+(R11-L11)*(2/3) + R11>0,R11+(L11-F11)*(1/3)+(R11-L11)*(2/3),R11) -> 446.27667 | Y11: =T11-W11-X11 -> 13582.472 | Z11: =AVERAGE(Y11,S11,M11) -> 15609.702 | AA11: =U11 -> 186.25667 | AB11: =V11 -> 0 | AC11: =SUM(W11:X11) -> 446.27667 | AD11: 8765209.6 | AE11: =INDEX('Rate Assumptions'!$A:$B,MATCH('Base Allocation'!AE$2,'Rate Assumptions'!$A:$A,0),2) -> 3988.5862 | AF11: =INDEX('Rate Assumptions'!$A:$B,MATCH('Base Allocation'!AF$2,'Rate Assumptions'!$A:$A,0),2) -> 3456.4415 | AG11: =INDEX('Rate Assumptions'!$A:$B,MATCH('Base Allocation'!AG$2,'Rate Assumptions'!$A:$A,0),2) -> 5634.5606 | AH11: =INDEX('Rate Assumptions'!$A:$B,MATCH('Base Allocation'!AH$2,'Rate Assumptions'!$A:$A,0),2) -> 5634.5606 | AI11: =AD11+SUMPRODUCT(Z11:AC11,AE11:AH11) -> 74184208
A12: Chaffey | B12: 16000.02 | C12: 385.28 | D12: 0 | F12: 131.12 | G12: =B12-E12-F12 -> 15868.9 | H12: 14222.03 | I12: 404.9 | J12: 0 | K12: 59.64 | L12: 182.02 | M12: =H12-K12-L12 -> 13980.37 | N12: 16545.68 | O12: 370.29 | P12: 0 | Q12: 47.26 | R12: 240.26 | S12: =N12-Q12-R12 -> 16258.16 | T12: =IF((H12-B12)*(1/3)+(N12-H12)*(2/3) + N12>0,N12+(H12-B12)*(1/3)+(N12-H12)*(2/3),N12) -> 17502.117 | U12: =IF((I12-C12)*(1/3)+(O12-I12)*(2/3) + O12>0,O12+(I12-C12)*(1/3)+(O12-I12)*(2/3),O12) -> 353.75667 | V12: =IF((J12-D12)*(1/3)+(P12-J12)*(2/3) + P12>0,P12+(J12-D12)*(1/3)+(P12-J12)*(2/3),P12) -> 0 | W12: =IF((K12-E12)*(1/3)+(Q12-K12)*(2/3) + Q12>0,Q12+(K12-E12)*(1/3)+(Q12-K12)*(2/3),Q12) -> 58.886667 | X12: =IF((L12-F12)*(1/3)+(R12-L12)*(2/3) + R12>0,R12+(L12-F12)*(1/3)+(R12-L12)*(2/3),R12) -> 296.05333 | Y12: =T12-W12-X12 -> 17147.177 | Z12: =AVERAGE(Y12,S12,M12) -> 15795.236 | AA12: =U12 -> 353.75667 | AB12: =V12 -> 0 | AC12: =SUM(W12:X12) -> 354.94 | AD12: 8090964.1 | AE12: =INDEX('Rate Assumptions'!$A:$B,MATCH('Base Allocation'!AE$2,'Rate Assumptions'!$A:$A,0),2) -> 3988.5862 | AF12: =INDEX('Rate Assumptions'!$A:$B,MATCH('Base Allocation'!AF$2,'Rate Assumptions'!$A:$A,0),2) -> 3456.4415 | AG12: =INDEX('Rate Assumptions'!$A:$B,MATCH('Base Allocation'!AG$2,'Rate Assumptions'!$A:$A,0),2) -> 5634.5606 | AH12: =INDEX('Rate Assumptions'!$A:$B,MATCH('Base Allocation'!AH$2,'Rate Assumptions'!$A:$A,0),2) -> 5634.5606 | AI12: =AD12+SUMPRODUCT(Z12:AC12,AE12:AH12) -> 74314293
A13: Citrus | B13: 11468.25 | C13: 219.1 | D13: 113.84 | F13: 129.29 | G13: =B13-E13-F13 -> 11338.96 | H13: 11617.945 | I13: 295.13 | J13: 99.64 | L13: 208.13 | M13: =H13-K13-L13 -> 11409.815 | N13: 11053.78 | O13: 295.13 | P13: 99.64 | Q13: 0 | R13: 289.74 | S13: =N13-Q13-R13 -> 10764.04 | T13: =IF((H13-B13)*(1/3)+(N13-H13)*(2/3) + N13>0,N13+(H13-B13)*(1/3)+(N13-H13)*(2/3),N13) -> 10727.568 | U13: =IF((I13-C13)*(1/3)+(O13-I13)*(2/3) + O13>0,O13+(I13-C13)*(1/3)+(O13-I13)*(2/3),O13) -> 320.47333 | V13: =IF((J13-D13)*(1/3)+(P13-J13)*(2/3) + P13>0,P13+(J13-D13)*(1/3)+(P13-J13)*(2/3),P13) -> 94.906667 | W13: =IF((K13-E13)*(1/3)+(Q13-K13)*(2/3) + Q13>0,Q13+(K13-E13)*(1/3)+(Q13-K13)*(2/3),Q13) -> 0 | X13: =IF((L13-F13)*(1/3)+(R13-L13)*(2/3) + R13>0,R13+(L13-F13)*(1/3)+(R13-L13)*(2/3),R13) -> 370.42667 | Y13: =T13-W13-X13 -> 10357.142 | Z13: =AVERAGE(Y13,S13,M13) -> 10843.666 | AA13: =U13 -> 320.47333 | AB13: =V13 -> 94.906667 | AC13: =SUM(W13:X13) -> 370.42667 | AD13: 5393976.1 | AE13: =INDEX('Rate Assumptions'!$A:$B,MATCH('Base Allocation'!AE$2,'Rate Assumptions'!$A:$A,0),2) -> 3988.5862 | AF13: =INDEX('Rate Assumptions'!$A:$B,MATCH('Base Allocation'!AF$2,'Rate Assumptions'!$A:$A,0),2) -> 3456.4415 | AG13: =INDEX('Rate Assumptions'!$A:$B,MATCH('Base Allocation'!AG$2,'Rate Assumptions'!$A:$A,0),2) -> 5634.5606 | AH13: =INDEX('Rate Assumptions'!$A:$B,MATCH('Base Allocation'!AH$2,'Rate Assumptions'!$A:$A,0),2) -> 5634.5606 | AI13: =AD13+SUMPRODUCT(Z13:AC13,AE13:AH13) -> 52374517
A14: Coast | B14: 29983.06 | C14: 309.27 | D14: 0 | F14: 78.42 | G14: =B14-E14-F14 -> 29904.64 | H14: 32276.79 | I14: 349.01011 | J14: 0 | K14: 201.08 | L14: 187.33 | M14: =H14-K14-L14 -> 31888.38 | N14: 30455.94 | O14: 47.38 | P14: 313.09 | Q14: 0 | R14: 174.29 | S14: =N14-Q14-R14 -> 30281.65 | T14: =IF((H14-B14)*(1/3)+(N14-H14)*(2/3) + N14>0,N14+(H14-B14)*(1/3)+(N14-H14)*(2/3),N14) -> 30006.617 | U14: =IF((I14-C14)*(1/3)+(O14-I14)*(2/3) + O14>0,O14+(I14-C14)*(1/3)+(O14-I14)*(2/3),O14) -> 47.38 | V14: =IF((J14-D14)*(1/3)+(P14-J14)*(2/3) + P14>0,P14+(J14-D14)*(1/3)+(P14-J14)*(2/3),P14) -> 521.81667 | W14: =IF((K14-E14)*(1/3)+(Q14-K14)*(2/3) + Q14>0,Q14+(K14-E14)*(1/3)+(Q14-K14)*(2/3),Q14) -> 0 | X14: =IF((L14-F14)*(1/3)+(R14-L14)*(2/3) + R14>0,R14+(L14-F14)*(1/3)+(R14-L14)*(2/3),R14) -> 201.9 | Y14: =T14-W14-X14 -> 29804.717 | Z14: =AVERAGE(Y14,S14,M14) -> 30658.249 | AA14: =U14 -> 47.38 | AB14: =V14 -> 521.81667 | AC14: =SUM(W14:X14) -> 201.9 | AD14: 12810690 | AE14: =INDEX('Rate Assumptions'!$A:$B,MATCH('Base Allocation'!AE$2,'Rate Assumptions'!$A:$A,0),2) -> 3988.5862 | AF14: =INDEX('Rate Assumptions'!$A:$B,MATCH('Base Allocation'!AF$2,'Rate Assumptions'!$A:$A,0),2) -> 3456.4415 | AG14: =INDEX('Rate Assumptions'!$A:$B,MATCH('Base Allocation'!AG$2,'Rate Assumptions'!$A:$A,0),2) -> 5634.5606 | AH14: =INDEX('Rate Assumptions'!$A:$B,MATCH('Base Allocation'!AH$2,'Rate Assumptions'!$A:$A,0),2) -> 5634.5606 | AI14: =AD14+SUMPRODUCT(Z14:AC14,AE14:AH14) -> 1.3933535e+08
A15: Compton | B15: 5088.51 | C15: 21.28 | D15: 0 | F15: 195.16 | G15: =B15-E15-F15 -> 4893.35 | H15: 5961.6899 | I15: 18.52 | J15: 0 | L15: 245.21 | M15: =H15-K15-L15 -> 5716.4799 | N15: 5961.69 | O15: 18.52 | P15: 0 | Q15: 0 | R15: 241.07041 | S15: =N15-Q15-R15 -> 5720.6196 | T15: =IF((H15-B15)*(1/3)+(N15-H15)*(2/3) + N15>0,N15+(H15-B15)*(1/3)+(N15-H15)*(2/3),N15) -> 6252.75 | U15: =IF((I15-C15)*(1/3)+(O15-I15)*(2/3) + O15>0,O15+(I15-C15)*(1/3)+(O15-I15)*(2/3),O15) -> 17.6 | V15: =IF((J15-D15)*(1/3)+(P15-J15)*(2/3) + P15>0,P15+(J15-D15)*(1/3)+(P15-J15)*(2/3),P15) -> 0 | W15: =IF((K15-E15)*(1/3)+(Q15-K15)*(2/3) + Q15>0,Q15+(K15-E15)*(1/3)+(Q15-K15)*(2/3),Q15) -> 0 | X15: =IF((L15-F15)*(1/3)+(R15-L15)*(2/3) + R15>0,R15+(L15-F15)*(1/3)+(R15-L15)*(2/3),R15) -> 254.99402 | Y15: =T15-W15-X15 -> 5997.756 | Z15: =AVERAGE(Y15,S15,M15) -> 5811.6185 | AA15: =U15 -> 17.6 | AB15: =V15 -> 0 | AC15: =SUM(W15:X15) -> 254.99402 | AD15: 4045480 | AE15: =INDEX('Rate Assumptions'!$A:$B,MATCH('Base Allocation'!AE$2,'Rate Assumptions'!$A:$A,0),2) -> 3988.5862 | AF15: =INDEX('Rate Assumptions'!$A:$B,MATCH('Base Allocation'!AF$2,'Rate Assumptions'!$A:$A,0),2) -> 3456.4415 | AG15: =INDEX('Rate Assumptions'!$A:$B,MATCH('Base Allocation'!AG$2,'Rate Assumptions'!$A:$A,0),2) -> 5634.5606 | AH15: =INDEX('Rate Assumptions'!$A:$B,MATCH('Base Allocation'!AH$2,'Rate Assumptions'!$A:$A,0),2) -> 5634.5606 | AI15: =AD15+SUMPRODUCT(Z15:AC15,AE15:AH15) -> 28723234
A16: Contra Costa | B16: 23962.51 | C16: 153.79 | D16: 0 | F16: 583.12 | G16: =B16-E16-F16 -> 23379.39 | H16: 29269.36 | I16: 148.56 | J16: 0 | L16: 1002.35 | M16: =H16-K16-L16 -> 28267.01 | N16: 25136.88 | O16: 153.55 | P16: 0 | Q16: 0 | R16: 895.81 | S16: =N16-Q16-R16 -> 24241.07 | T16: =IF((H16-B16)*(1/3)+(N16-H16)*(2/3) + N16>0,N16+(H16-B16)*(1/3)+(N16-H16)*(2/3),N16) -> 24150.843 | U16: =IF((I16-C16)*(1/3)+(O16-I16)*(2/3) + O16>0,O16+(I16-C16)*(1/3)+(O16-I16)*(2/3),O16) -> 155.13333 | V16: =IF((J16-D16)*(1/3)+(P16-J16)*(2/3) + P16>0,P16+(J16-D16)*(1/3)+(P16-J16)*(2/3),P16) -> 0 | W16: =IF((K16-E16)*(1/3)+(Q16-K16)*(2/3) + Q16>0,Q16+(K16-E16)*(1/3)+(Q16-K16)*(2/3),Q16) -> 0 | X16: =IF((L16-F16)*(1/3)+(R16-L16)*(2/3) + R16>0,R16+(L16-F16)*(1/3)+(R16-L16)*(2/3),R16) -> 964.52667 | Y16: =T16-W16-X16 -> 23186.317 | Z16: =AVERAGE(Y16,S16,M16) -> 25231.466 | AA16: =U16 -> 155.13333 | AB16: =V16 -> 0 | AC16: =SUM(W16:X16) -> 964.52667 | AD16: 15507678 | AE16: =INDEX('Rate Assumptions'!$A:$B,MATCH('Base Allocation'!AE$2,'Rate Assumptions'!$A:$A,0),2) -> 3988.5862 | AF16: =INDEX('Rate Assumptions'!$A:$B,MATCH('Base Allocation'!AF$2,'Rate Assumptions'!$A:$A,0),2) -> 3456.4415 | AG16: =INDEX('Rate Assumptions'!$A:$B,MATCH('Base Allocation'!AG$2,'Rate Assumptions'!$A:$A,0),2) -> 5634.5606 | AH16: =INDEX('Rate Assumptions'!$A:$B,MATCH('Base Allocation'!AH$2,'Rate Assumptions'!$A:$A,0),2) -> 5634.5606 | AI16: =AD16+SUMPRODUCT(Z16:AC16,AE16:AH16) -> 1.2211645e+08
A17: Copper Mountain | B17: 1318.93 | C17: 91.78 | D17: 3.13 | F17: 3.38 | G17: =B17-E17-F17 -> 1315.55 | H17: 1431.83 | I17: 87.31 | J17: 2.98 | L17: 3.64 | M17: =H17-K17-L17 -> 1428.19 | N17: 1452.68 | O17: 66.606677 | P17: 1.44 | Q17: 0 | R17: 0 | S17: =N17-Q17-R17 -> 1452.68 | T17: =IF((H17-B17)*(1/3)+(N17-H17)*(2/3) + N17>0,N17+(H17-B17)*(1/3)+(N17-H17)*(2/3),N17) -> 1504.2133 | U17: =IF((I17-C17)*(1/3)+(O17-I17)*(2/3) + O17>0,O17+(I17-C17)*(1/3)+(O17-I17)*(2/3),O17) -> 51.314461 | V17: =IF((J17-D17)*(1/3)+(P17-J17)*(2/3) + P17>0,P17+(J17-D17)*(1/3)+(P17-J17)*(2/3),P17) -> 0.36333333 | W17: =IF((K17-E17)*(1/3)+(Q17-K17)*(2/3) + Q17>0,Q17+(K17-E17)*(1/3)+(Q17-K17)*(2/3),Q17) -> 0 | X17: =IF((L17-F17)*(1/3)+(R17-L17)*(2/3) + R17>0,R17+(L17-F17)*(1/3)+(R17-L17)*(2/3),R17) -> 0 | Y17: =T17-W17-X17 -> 1504.2133 | Z17: =AVERAGE(Y17,S17,M17) -> 1461.6944 | AA17: =U17 -> 51.314461 | AB17: =V17 -> 0.36333333 | AC17: =SUM(W17:X17) -> 0 | AD17: 5332192.5 | AE17: =INDEX('Rate Assumptions'!$A:$B,MATCH('Base Allocation'!AE$2,'Rate Assumptions'!$A:$A,0),2) -> 3988.5862 | AF17: =INDEX('Rate Assumptions'!$A:$B,MATCH('Base Allocation'!AF$2,'Rate Assumptions'!$A:$A,0),2) -> 3456.4415 | AG17: =INDEX('Rate Assumptions'!$A:$B,MATCH('Base Allocation'!AG$2,'Rate Assumptions'!$A:$A,0),2) -> 5634.5606 | AH17: =INDEX('Rate Assumptions'!$A:$B,MATCH('Base Allocation'!AH$2,'Rate Assumptions'!$A:$A,0),2) -> 5634.5606 | AI17: =AD17+SUMPRODUCT(Z17:AC17,AE17:AH17) -> 11341699
A18: Desert | B18: 7758.61 | C18: 40.67 | D18: 738.4 | F18: 45.02 | G18: =B18-E18-F18 -> 7713.59 | H18: 9398.6091 | I18: 59.72 | J18: 668.2 | L18: 298.45 | M18: =H18-K18-L18 -> 9100.1591 | N18: 8637.27 | O18: 303.9 | P18: 1465.7436 | Q18: 0 | R18: 0 | S18: =N18-Q18-R18 -> 8637.27 | T18: =IF((H18-B18)*(1/3)+(N18-H18)*(2/3) + N18>0,N18+(H18-B18)*(1/3)+(N18-H18)*(2/3),N18) -> 8676.377 | U18: =IF((I18-C18)*(1/3)+(O18-I18)*(2/3) + O18>0,O18+(I18-C18)*(1/3)+(O18-I18)*(2/3),O18) -> 473.03667 | V18: =IF((J18-D18)*(1/3)+(P18-J18)*(2/3) + P18>0,P18+(J18-D18)*(1/3)+(P18-J18)*(2/3),P18) -> 1974.0394 | W18: =IF((K18-E18)*(1/3)+(Q18-K18)*(2/3) + Q18>0,Q18+(K18-E18)*(1/3)+(Q18-K18)*(2/3),Q18) -> 0 | X18: =IF((L18-F18)*(1/3)+(R18-L18)*(2/3) + R18>0,R18+(L18-F18)*(1/3)+(R18-L18)*(2/3),R18) -> 0 | Y18: =T18-W18-X18 -> 8676.377 | Z18: =AVERAGE(Y18,S18,M18) -> 8804.602 | AA18: =U18 -> 473.03667 | AB18: =V18 -> 1974.0394 | AC18: =SUM(W18:X18) -> 0 | AD18: 6742470.1 | AE18: =INDEX('Rate Assumptions'!$A:$B,MATCH('Base Allocation'!AE$2,'Rate Assumptions'!$A:$A,0),2) -> 3988.5862 | AF18: =INDEX('Rate Assumptions'!$A:$B,MATCH('Base Allocation'!AF$2,'Rate Assumptions'!$A:$A,0),2) -> 3456.4415 | AG18: =INDEX('Rate Assumptions'!$A:$B,MATCH('Base Allocation'!AG$2,'Rate Assumptions'!$A:$A,0),2) -> 5634.5606 | AH18: =INDEX('Rate Assumptions'!$A:$B,MATCH('Base Allocation'!AH$2,'Rate Assumptions'!$A:$A,0),2) -> 5634.5606 | AI18: =AD18+SUMPRODUCT(Z18:AC18,AE18:AH18) -> 54618252
A19: El Camino | B19: 17898.23 | C19: 30.3 | D19: 0 | F19: 233.94 | G19: =B19-E19-F19 -> 17664.29 | H19: 19587.66 | I19: 55.19 | J19: 0 | L19: 360.76 | M19: =H19-K19-L19 -> 19226.9 | N19: 18479.54 | O19: 55.19 | P19: 0 | Q19: 0 | R19: 541.31 | S19: =N19-Q19-R19 -> 17938.23 | T19: =IF((H19-B19)*(1/3)+(N19-H19)*(2/3) + N19>0,N19+(H19-B19)*(1/3)+(N19-H19)*(2/3),N19) -> 18303.937 | U19: =IF((I19-C19)*(1/3)+(O19-I19)*(2/3) + O19>0,O19+(I19-C19)*(1/3)+(O19-I19)*(2/3),O19) -> 63.486667 | V19: =IF((J19-D19)*(1/3)+(P19-J19)*(2/3) + P19>0,P19+(J19-D19)*(1/3)+(P19-J19)*(2/3),P19) -> 0 | W19: =IF((K19-E19)*(1/3)+(Q19-K19)*(2/3) + Q19>0,Q19+(K19-E19)*(1/3)+(Q19-K19)*(2/3),Q19) -> 0 | X19: =IF((L19-F19)*(1/3)+(R19-L19)*(2/3) + R19>0,R19+(L19-F19)*(1/3)+(R19-L19)*(2/3),R19) -> 703.95 | Y19: =T19-W19-X19 -> 17599.987 | Z19: =AVERAGE(Y19,S19,M19) -> 18255.039 | AA19: =U19 -> 63.486667 | AB19: =V19 -> 0 | AC19: =SUM(W19:X19) -> 703.95 | AD19: 10787950 | AE19: =INDEX('Rate Assumptions'!$A:$B,MATCH('Base Allocation'!AE$2,'Rate Assumptions'!$A:$A,0),2) -> 3988.5862 | AF19: =INDEX('Rate Assumptions'!$A:$B,MATCH('Base Allocation'!AF$2,'Rate Assumptions'!$A:$A,0),2) -> 3456.4415 | AG19: =INDEX('Rate Assumptions'!$A:$B,MATCH('Base Allocation'!AG$2,'Rate Assumptions'!$A:$A,0),2) -> 5634.5606 | AH19: =INDEX('Rate Assumptions'!$A:$B,MATCH('Base Allocation'!AH$2,'Rate Assumptions'!$A:$A,0),2) -> 5634.5606 | AI19: =AD19+SUMPRODUCT(Z19:AC19,AE19:AH19) -> 87785633
A20: Feather River | B20: 1580.29 | C20: 33.3 | D20: 0 | E20: 273.92 | F20: 116.74 | G20: =B20-E20-F20 -> 1189.63 | H20: 1599.3681 | I20: 39.2 | J20: 0 | K20: 301.23 | L20: 92.89 | M20: =H20-K20-L20 -> 1205.2481 | N20: 1603.11 | O20: 37.07 | P20: 0 | Q20: 257.66215 | R20: 0 | S20: =N20-Q20-R20 -> 1345.4479 | T20: =IF((H20-B20)*(1/3)+(N20-H20)*(2/3) + N20>0,N20+(H20-B20)*(1/3)+(N20-H20)*(2/3),N20) -> 1611.964 | U20: =IF((I20-C20)*(1/3)+(O20-I20)*(2/3) + O20>0,O20+(I20-C20)*(1/3)+(O20-I20)*(2/3),O20) -> 37.616667 | V20: =IF((J20-D20)*(1/3)+(P20-J20)*(2/3) + P20>0,P20+(J20-D20)*(1/3)+(P20-J20)*(2/3),P20) -> 0 | W20: =IF((K20-E20)*(1/3)+(Q20-K20)*(2/3) + Q20>0,Q20+(K20-E20)*(1/3)+(Q20-K20)*(2/3),Q20) -> 237.72024 | X20: =IF((L20-F20)*(1/3)+(R20-L20)*(2/3) + R20>0,R20+(L20-F20)*(1/3)+(R20-L20)*(2/3),R20) -> 0 | Y20: =T20-W20-X20 -> 1374.2437 | Z20: =AVERAGE(Y20,S20,M20) -> 1308.3132 | AA20: =U20 -> 37.616667 | AB20: =V20 -> 0 | AC20: =SUM(W20:X20) -> 237.72024 | AD20: 5332192.5 | AE20: =INDEX('Rate Assumptions'!$A:$B,MATCH('Base Allocation'!AE$2,'Rate Assumptions'!$A:$A,0),2) -> 3988.5862 | AF20: =INDEX('Rate Assumptions'!$A:$B,MATCH('Base Allocation'!AF$2,'Rate Assumptions'!$A:$A,0),2) -> 3456.4415 | AG20: =INDEX('Rate Assumptions'!$A:$B,MATCH('Base Allocation'!AG$2,'Rate Assumptions'!$A:$A,0),2) -> 5634.5606 | AH20: =INDEX('Rate Assumptions'!$A:$B,MATCH('Base Allocation'!AH$2,'Rate Assumptions'!$A:$A,0),2) -> 5634.5606 | AI20: =AD20+SUMPRODUCT(Z20:AC20,AE20:AH20) -> 12019982
A21: Foothill-De Anza3 | B21: 25518.78 | C21: 264.29 | D21: 184.45 | F21: 693.85 | G21: =B21-E21-F21 -> 24824.93 | H21: 23961.87 | I21: 238.57 | J21: 283.28 | L21: 575.87 | M21: =H21-K21-L21 -> 23386 | N21: 22677.1 | O21: 238.57 | P21: 283.28 | Q21: 0 | R21: 755 | S21: =N21-Q21-R21 -> 21922.1 | T21: =IF((H21-B21)*(1/3)+(N21-H21)*(2/3) + N21>0,N21+(H21-B21)*(1/3)+(N21-H21)*(2/3),N21) -> 21301.617 | U21: =IF((I21-C21)*(1/3)+(O21-I21)*(2/3) + O21>0,O21+(I21-C21)*(1/3)+(O21-I21)*(2/3),O21) -> 229.99667 | V21: =IF((J21-D21)*(1/3)+(P21-J21)*(2/3) + P21>0,P21+(J21-D21)*(1/3)+(P21-J21)*(2/3),P21) -> 316.22333 | W21: =IF((K21-E21)*(1/3)+(Q21-K21)*(2/3) + Q21>0,Q21+(K21-E21)*(1/3)+(Q21-K21)*(2/3),Q21) -> 0 | X21: =IF((L21-F21)*(1/3)+(R21-L21)*(2/3) + R21>0,R21+(L21-F21)*(1/3)+(R21-L21)*(2/3),R21) -> 835.09333 | Y21: =T21-W21-X21 -> 20466.523 | Z21: =AVERAGE(Y21,S21,M21) -> 21924.874 | AA21: =U21 -> 229.99667 | AB21: =V21 -> 316.22333 | AC21: =SUM(W21:X21) -> 835.09333 | AD21: 10787952 | AE21: =INDEX('Rate Assumptions'!$A:$B,MATCH('Base Allocation'!AE$2,'Rate Assumptions'!$A:$A,0),2) -> 3988.5862 | AF21: =INDEX('Rate Assumptions'!$A:$B,MATCH('Base Allocation'!AF$2,'Rate Assumptions'!$A:$A,0),2) -> 3456.4415 | AG21: =INDEX('Rate Assumptions'!$A:$B,MATCH('Base Allocation'!AG$2,'Rate Assumptions'!$A:$A,0),2) -> 5634.5606 | AH21: =INDEX('Rate Assumptions'!$A:$B,MATCH('Base Allocation'!AH$2,'Rate Assumptions'!$A:$A,0),2) -> 5634.5606 | AI21: =AD21+SUMPRODUCT(Z21:AC21,AE21:AH21) -> 1.0551934e+08
A22: Gavilan | B22: 4751.6037 | C22: 454.979 | D22: 114.54 | E22: 0.54 | F22: 189.99 | G22: =B22-E22-F22 -> 4561.0737 | H22: 4106.62 | I22: 481.47 | J22: 117.69 | K22: 0.44 | L22: 187.71 | M22: =H22-K22-L22 -> 3918.47 | N22: 4934.71 | O22: 292.22 | P22: 117.74 | Q22: 0 | R22: 220.04 | S22: =N22-Q22-R22 -> 4714.67 | T22: =IF((H22-B22)*(1/3)+(N22-H22)*(2/3) + N22>0,N22+(H22-B22)*(1/3)+(N22-H22)*(2/3),N22) -> 5271.7754 | U22: =IF((I22-C22)*(1/3)+(O22-I22)*(2/3) + O22>0,O22+(I22-C22)*(1/3)+(O22-I22)*(2/3),O22) -> 174.88367 | V22: =IF((J22-D22)*(1/3)+(P22-J22)*(2/3) + P22>0,P22+(J22-D22)*(1/3)+(P22-J22)*(2/3),P22) -> 118.82333 | W22: =IF((K22-E22)*(1/3)+(Q22-K22)*(2/3) + Q22>0,Q22+(K22-E22)*(1/3)+(Q22-K22)*(2/3),Q22) -> 0 | X22: =IF((L22-F22)*(1/3)+(R22-L22)*(2/3) + R22>0,R22+(L22-F22)*(1/3)+(R22-L22)*(2/3),R22) -> 240.83333 | Y22: =T22-W22-X22 -> 5030.9421 | Z22: =AVERAGE(Y22,S22,M22) -> 4554.694 | AA22: =U22 -> 174.88367 | AB22: =V22 -> 118.82333 | AC22: =SUM(W22:X22) -> 240.83333 | AD22: 5332192.5 | AE22: =INDEX('Rate Assumptions'!$A:$B,MATCH('Base Allocation'!AE$2,'Rate Assumptions'!$A:$A,0),2) -> 3988.5862 | AF22: =INDEX('Rate Assumptions'!$A:$B,MATCH('Base Allocation'!AF$2,'Rate Assumptions'!$A:$A,0),2) -> 3456.4415 | AG22: =INDEX('Rate Assumptions'!$A:$B,MATCH('Base Allocation'!AG$2,'Rate Assumptions'!$A:$A,0),2) -> 5634.5606 | AH22: =INDEX('Rate Assumptions'!$A:$B,MATCH('Base Allocation'!AH$2,'Rate Assumptions'!$A:$A,0),2) -> 5634.5606 | AI22: =AD22+SUMPRODUCT(Z22:AC22,AE22:AH22) -> 26129965
A23: Glendale | B23: 12449.54 | C23: 243.85 | D23: 2847.21 | F23: 230.88 | G23: =B23-E23-F23 -> 12218.66 | H23: 11026.53 | I23: 272.56 | J23: 2656.3 | L23: 282.49 | M23: =H23-K23-L23 -> 10744.04 | N23: 11143.41 | O23: 183.49377 | P23: 2536.14 | Q23: 0 | R23: 299.6 | S23: =N23-Q23-R23 -> 10843.81 | T23: =IF((H23-B23)*(1/3)+(N23-H23)*(2/3) + N23>0,N23+(H23-B23)*(1/3)+(N23-H23)*(2/3),N23) -> 10746.993 | U23: =IF((I23-C23)*(1/3)+(O23-I23)*(2/3) + O23>0,O23+(I23-C23)*(1/3)+(O23-I23)*(2/3),O23) -> 133.68628 | V23: =IF((J23-D23)*(1/3)+(P23-J23)*(2/3) + P23>0,P23+(J23-D23)*(1/3)+(P23-J23)*(2/3),P23) -> 2392.3967 | W23: =IF((K23-E23)*(1/3)+(Q23-K23)*(2/3) + Q23>0,Q23+(K23-E23)*(1/3)+(Q23-K23)*(2/3),Q23) -> 0 | X23: =IF((L23-F23)*(1/3)+(R23-L23)*(2/3) + R23>0,R23+(L23-F23)*(1/3)+(R23-L23)*(2/3),R23) -> 328.21 | Y23: =T23-W23-X23 -> 10418.783 | Z23: =AVERAGE(Y23,S23,M23) -> 10668.878 | AA23: =U23 -> 133.68628 | AB23: =V23 -> 2392.3967 | AC23: =SUM(W23:X23) -> 328.21 | AD23: 6742470.1 | AE23: =INDEX('Rate Assumptions'!$A:$B,MATCH('Base Allocation'!AE$2,'Rate Assumptions'!$A:$A,0),2) -> 3988.5862 | AF23: =INDEX('Rate Assumptions'!$A:$B,MATCH('Base Allocation'!AF$2,'Rate Assumptions'!$A:$A,0),2) -> 3456.4415 | AG23: =INDEX('Rate Assumptions'!$A:$B,MATCH('Base Allocation'!AG$2,'Rate Assumptions'!$A:$A,0),2) -> 5634.5606 | AH23: =INDEX('Rate Assumptions'!$A:$B,MATCH('Base Allocation'!AH$2,'Rate Assumptions'!$A:$A,0),2) -> 5634.5606 | AI23: =AD23+SUMPRODUCT(Z23:AC23,AE23:AH23) -> 65087710
A24: Grossmont-Cuyamaca | B24: 19064.97 | C24: 20.18 | D24: 0 | F24: 317.76 | G24: =B24-E24-F24 -> 18747.21 | H24: 17160.77 | I24: 19.71 | J24: 0 | L24: 334.9 | M24: =H24-K24-L24 -> 16825.87 | N24: 17730.4 | O24: 17.02 | P24: 0 | Q24: 5.42 | R24: 298.79 | S24: =N24-Q24-R24 -> 17426.19 | T24: =IF((H24-B24)*(1/3)+(N24-H24)*(2/3) + N24>0,N24+(H24-B24)*(1/3)+(N24-H24)*(2/3),N24) -> 17475.42 | U24: =IF((I24-C24)*(1/3)+(O24-I24)*(2/3) + O24>0,O24+(I24-C24)*(1/3)+(O24-I24)*(2/3),O24) -> 15.07 | V24: =IF((J24-D24)*(1/3)+(P24-J24)*(2/3) + P24>0,P24+(J24-D24)*(1/3)+(P24-J24)*(2/3),P24) -> 0 | W24: =IF((K24-E24)*(1/3)+(Q24-K24)*(2/3) + Q24>0,Q24+(K24-E24)*(1/3)+(Q24-K24)*(2/3),Q24) -> 9.0333333 | X24: =IF((L24-F24)*(1/3)+(R24-L24)*(2/3) + R24>0,R24+(L24-F24)*(1/3)+(R24-L24)*(2/3),R24) -> 280.43 | Y24: =T24-W24-X24 -> 17185.957 | Z24: =AVERAGE(Y24,S24,M24) -> 17146.006 | AA24: =U24 -> 15.07 | AB24: =V24 -> 0 | AC24: =SUM(W24:X24) -> 289.46333 | AD24: 8765209.6 | AE24: =INDEX('Rate Assumptions'!$A:$B,MATCH('Base Allocation'!AE$2,'Rate Assumptions'!$A:$A,0),2) -> 3988.5862 | AF24: =INDEX('Rate Assumptions'!$A:$B,MATCH('Base Allocation'!AF$2,'Rate Assumptions'!$A:$A,0),2) -> 3456.4415 | AG24: =INDEX('Rate Assumptions'!$A:$B,MATCH('Base Allocation'!AG$2,'Rate Assumptions'!$A:$A,0),2) -> 5634.5606 | AH24: =INDEX('Rate Assumptions'!$A:$B,MATCH('Base Allocation'!AH$2,'Rate Assumptions'!$A:$A,0),2) -> 5634.5606 | AI24: =AD24+SUMPRODUCT(Z24:AC24,AE24:AH24) -> 78836618
A25: Hartnell | B25: 7340.3599 | C25: 4.43 | D25: 0 | F25: 33.53 | G25: =B25-E25-F25 -> 7306.8299 | H25: 7356.0899 | I25: 2.91 | J25: 0 | K25: 65.25 | L25: 48.47 | M25: =H25-K25-L25 -> 7242.3699 | N25: 7327.45 | O25: 14.44 | P25: 12.24 | Q25: 77.93 | R25: 50.386017 | S25: =N25-Q25-R25 -> 7199.134 | T25: =IF((H25-B25)*(1/3)+(N25-H25)*(2/3) + N25>0,N25+(H25-B25)*(1/3)+(N25-H25)*(2/3),N25) -> 7313.6001 | U25: =IF((I25-C25)*(1/3)+(O25-I25)*(2/3) + O25>0,O25+(I25-C25)*(1/3)+(O25-I25)*(2/3),O25) -> 21.62 | V25: =IF((J25-D25)*(1/3)+(P25-J25)*(2/3) + P25>0,P25+(J25-D25)*(1/3)+(P25-J25)*(2/3),P25) -> 20.4 | W25: =IF((K25-E25)*(1/3)+(Q25-K25)*(2/3) + Q25>0,Q25+(K25-E25)*(1/3)+(Q25-K25)*(2/3),Q25) -> 108.13333 | X25: =IF((L25-F25)*(1/3)+(R25-L25)*(2/3) + R25>0,R25+(L25-F25)*(1/3)+(R25-L25)*(2/3),R25) -> 56.643361 | Y25: =T25-W25-X25 -> 7148.8234 | Z25: =AVERAGE(Y25,S25,M25) -> 7196.7758 | AA25: =U25 -> 21.62 | AB25: =V25 -> 20.4 | AC25: =SUM(W25:X25) -> 164.77669 | AD25: 4382603.3 | AE25: =INDEX('Rate Assumptions'!$A:$B,MATCH('Base Allocation'!AE$2,'Rate Assumptions'!$A:$A,0),2) -> 3988.5862 | AF25: =INDEX('Rate Assumptions'!$A:$B,MATCH('Base Allocation'!AF$2,'Rate Assumptions'!$A:$A,0),2) -> 3456.4415 | AG25: =INDEX('Rate Assumptions'!$A:$B,MATCH('Base Allocation'!AG$2,'Rate Assumptions'!$A:$A,0),2) -> 5634.5606 | AH25: =INDEX('Rate Assumptions'!$A:$B,MATCH('Base Allocation'!AH$2,'Rate Assumptions'!$A:$A,0),2) -> 5634.5606 | AI25: =AD25+SUMPRODUCT(Z25:AC25,AE25:AH25) -> 34205681
A26: Imperial | B26: 6799.88 | C26: 38.44 | D26: 15.96 | E26: 55.11 | F26: 21.49 | G26: =B26-E26-F26 -> 6723.28 | H26: 7347.2481 | I26: 24.1 | J26: 24.22 | K26: 167.75 | L26: 61.2 | M26: =H26-K26-L26 -> 7118.2981 | N26: 7403.73 | O26: 31.87 | P26: 14.4 | Q26: 219.04 | R26: 1.9395992 | S26: =N26-Q26-R26 -> 7182.7504 | T26: =IF((H26-B26)*(1/3)+(N26-H26)*(2/3) + N26>0,N26+(H26-B26)*(1/3)+(N26-H26)*(2/3),N26) -> 7623.8406 | U26: =IF((I26-C26)*(1/3)+(O26-I26)*(2/3) + O26>0,O26+(I26-C26)*(1/3)+(O26-I26)*(2/3),O26) -> 32.27 | V26: =IF((J26-D26)*(1/3)+(P26-J26)*(2/3) + P26>0,P26+(J26-D26)*(1/3)+(P26-J26)*(2/3),P26) -> 10.606667 | W26: =IF((K26-E26)*(1/3)+(Q26-K26)*(2/3) + Q26>0,Q26+(K26-E26)*(1/3)+(Q26-K26)*(2/3),Q26) -> 290.78 | X26: =IF((L26-F26)*(1/3)+(R26-L26)*(2/3) + R26>0,R26+(L26-F26)*(1/3)+(R26-L26)*(2/3),R26) -> 1.9395992 | Y26: =T26-W26-X26 -> 7331.121 | Z26: =AVERAGE(Y26,S26,M26) -> 7210.7232 | AA26: =U26 -> 32.27 | AB26: =V26 -> 10.606667 | AC26: =SUM(W26:X26) -> 292.7196 | AD26: 4045480 | AE26: =INDEX('Rate Assumptions'!$A:$B,MATCH('Base Allocation'!AE$2,'Rate Assumptions'!$A:$A,0),2) -> 3988.5862 | AF26: =INDEX('Rate Assumptions'!$A:$B,MATCH('Base Allocation'!AF$2,'Rate Assumptions'!$A:$A,0),2) -> 3456.4415 | AG26: =INDEX('Rate Assumptions'!$A:$B,MATCH('Base Allocation'!AG$2,'Rate Assumptions'!$A:$A,0),2) -> 5634.5606 | AH26: =INDEX('Rate Assumptions'!$A:$B,MATCH('Base Allocation'!AH$2,'Rate Assumptions'!$A:$A,0),2) -> 5634.5606 | AI26: =AD26+SUMPRODUCT(Z26:AC26,AE26:AH26) -> 34626720
A27: Kern | B27: 21647.56 | C27: 74.24 | D27: 0 | E27: 3.88 | F27: 1141.01 | G27: =B27-E27-F27 -> 20502.67 | H27: 22475.839 | I27: 26.64 | J27: 29.99 | K27: 476.99 | L27: 1325.59 | M27: =H27-K27-L27 -> 20673.259 | N27: 23271.77 | O27: 65.88 | P27: 40.97 | Q27: 735.11 | R27: 556.4372 | S27: =N27-Q27-R27 -> 21980.223 | T27: =IF((H27-B27)*(1/3)+(N27-H27)*(2/3) + N27>0,N27+(H27-B27)*(1/3)+(N27-H27)*(2/3),N27) -> 24078.484 | U27: =IF((I27-C27)*(1/3)+(O27-I27)*(2/3) + O27>0,O27+(I27-C27)*(1/3)+(O27-I27)*(2/3),O27) -> 76.173333 | V27: =IF((J27-D27)*(1/3)+(P27-J27)*(2/3) + P27>0,P27+(J27-D27)*(1/3)+(P27-J27)*(2/3),P27) -> 58.286667 | W27: =IF((K27-E27)*(1/3)+(Q27-K27)*(2/3) + Q27>0,Q27+(K27-E27)*(1/3)+(Q27-K27)*(2/3),Q27) -> 1064.8933 | X27: =IF((L27-F27)*(1/3)+(R27-L27)*(2/3) + R27>0,R27+(L27-F27)*(1/3)+(R27-L27)*(2/3),R27) -> 105.19533 | Y27: =T27-W27-X27 -> 22908.395 | Z27: =AVERAGE(Y27,S27,M27) -> 21853.959 | AA27: =U27 -> 76.173333 | AB27: =V27 -> 58.286667 | AC27: =SUM(W27:X27) -> 1170.0887 | AD27: 17024735 | AE27: =INDEX('Rate Assumptions'!$A:$B,MATCH('Base Allocation'!AE$2,'Rate Assumptions'!$A:$A,0),2) -> 3988.5862 | AF27: =INDEX('Rate Assumptions'!$A:$B,MATCH('Base Allocation'!AF$2,'Rate Assumptions'!$A:$A,0),2) -> 3456.4415 | AG27: =INDEX('Rate Assumptions'!$A:$B,MATCH('Base Allocation'!AG$2,'Rate Assumptions'!$A:$A,0),2) -> 5634.5606 | AH27: =INDEX('Rate Assumptions'!$A:$B,MATCH('Base Allocation'!AH$2,'Rate Assumptions'!$A:$A,0),2) -> 5634.5606 | AI27: =AD27+SUMPRODUCT(Z27:AC27,AE27:AH27) -> 1.1137578e+08
A28: Lake Tahoe | B28: 1663.3 | C28: 56.419921 | D28: 14.09 | E28: 690.1 | F28: 30.88 | G28: =B28-E28-F28 -> 942.32 | H28: 1628.82 | I28: 40.14 | J28: 9.87 | K28: 741.25 | L28: 41.54 | M28: =H28-K28-L28 -> 846.03 | N28: 1834.13 | O28: 52.89 | P28: 5.98 | Q28: 132.84987 | R28: 0 | S28: =N28-Q28-R28 -> 1701.2801 | T28: =IF((H28-B28)*(1/3)+(N28-H28)*(2/3) + N28>0,N28+(H28-B28)*(1/3)+(N28-H28)*(2/3),N28) -> 1959.51 | U28: =IF((I28-C28)*(1/3)+(O28-I28)*(2/3) + O28>0,O28+(I28-C28)*(1/3)+(O28-I28)*(2/3),O28) -> 55.96336 | V28: =IF((J28-D28)*(1/3)+(P28-J28)*(2/3) + P28>0,P28+(J28-D28)*(1/3)+(P28-J28)*(2/3),P28) -> 1.98 | W28: =IF((K28-E28)*(1/3)+(Q28-K28)*(2/3) + Q28>0,Q28+(K28-E28)*(1/3)+(Q28-K28)*(2/3),Q28) -> 132.84987 | X28: =IF((L28-F28)*(1/3)+(R28-L28)*(2/3) + R28>0,R28+(L28-F28)*(1/3)+(R28-L28)*(2/3),R28) -> 0 | Y28: =T28-W28-X28 -> 1826.6601 | Z28: =AVERAGE(Y28,S28,M28) -> 1457.9901 | AA28: =U28 -> 55.96336 | AB28: =V28 -> 1.98 | AC28: =SUM(W28:X28) -> 132.84987 | AD28: 5332192.5 | AE28: =INDEX('Rate Assumptions'!$A:$B,MATCH('Base Allocation'!AE$2,'Rate Assumptions'!$A:$A,0),2) -> 3988.5862 | AF28: =INDEX('Rate Assumptions'!$A:$B,MATCH('Base Allocation'!AF$2,'Rate Assumptions'!$A:$A,0),2) -> 3456.4415 | AG28: =INDEX('Rate Assumptions'!$A:$B,MATCH('Base Allocation'!AG$2,'Rate Assumptions'!$A:$A,0),2) -> 5634.5606 | AH28: =INDEX('Rate Assumptions'!$A:$B,MATCH('Base Allocation'!AH$2,'Rate Assumptions'!$A:$A,0),2) -> 5634.5606 | AI28: =AD28+SUMPRODUCT(Z28:AC28,AE28:AH28) -> 12100653
A29: Lassen | B29: 1570.5699 | C29: 23.93 | D29: 1.62 | E29: 497 | F29: 35.5 | G29: =B29-E29-F29 -> 1038.0699 | H29: 1341.9 | I29: 12.96 | J29: 2.6 | K29: 613.04 | L29: 88.43 | M29: =H29-K29-L29 -> 640.43 | N29: 1581.71 | O29: 10.28 | P29: 2.05 | Q29: 761.86122 | R29: 0 | S29: =N29-Q29-R29 -> 819.84878 | T29: =IF((H29-B29)*(1/3)+(N29-H29)*(2/3) + N29>0,N29+(H29-B29)*(1/3)+(N29-H29)*(2/3),N29) -> 1665.36 | U29: =IF((I29-C29)*(1/3)+(O29-I29)*(2/3) + O29>0,O29+(I29-C29)*(1/3)+(O29-I29)*(2/3),O29) -> 4.8366667 | V29: =IF((J29-D29)*(1/3)+(P29-J29)*(2/3) + P29>0,P29+(J29-D29)*(1/3)+(P29-J29)*(2/3),P29) -> 2.01 | W29: =IF((K29-E29)*(1/3)+(Q29-K29)*(2/3) + Q29>0,Q29+(K29-E29)*(1/3)+(Q29-K29)*(2/3),Q29) -> 899.75536 | X29: =IF((L29-F29)*(1/3)+(R29-L29)*(2/3) + R29>0,R29+(L29-F29)*(1/3)+(R29-L29)*(2/3),R29) -> 0 | Y29: =T29-W29-X29 -> 765.60466 | Z29: =AVERAGE(Y29,S29,M29) -> 741.96115 | AA29: =U29 -> 4.8366667 | AB29: =V29 -> 2.01 | AC29: =SUM(W29:X29) -> 899.75536 | AD29: 5332192.5 | AE29: =INDEX('Rate Assumptions'!$A:$B,MATCH('Base Allocation'!AE$2,'Rate Assumptions'!$A:$A,0),2) -> 3988.5862 | AF29: =INDEX('Rate Assumptions'!$A:$B,MATCH('Base Allocation'!AF$2,'Rate Assumptions'!$A:$A,0),2) -> 3456.4415 | AG29: =INDEX('Rate Assumptions'!$A:$B,MATCH('Base Allocation'!AG$2,'Rate Assumptions'!$A:$A,0),2) -> 5634.5606 | AH29: =INDEX('Rate Assumptions'!$A:$B,MATCH('Base Allocation'!AH$2,'Rate Assumptions'!$A:$A,0),2) -> 5634.5606 | AI29: =AD29+SUMPRODUCT(Z29:AC29,AE29:AH29) -> 13389338
A30: Long Beach | B30: 20580.63 | C30: 108.52 | D30: 386.81 | F30: 105.44 | G30: =B30-E30-F30 -> 20475.19 | H30: 18388.58 | I30: 100.53 | J30: 407.61 | L30: 76.14 | M30: =H30-K30-L30 -> 18312.44 | N30: 18747.16 | O30: 60.89 | P30: 395.54 | Q30: 0 | R30: 157.24 | S30: =N30-Q30-R30 -> 18589.92 | T30: =IF((H30-B30)*(1/3)+(N30-H30)*(2/3) + N30>0,N30+(H30-B30)*(1/3)+(N30-H30)*(2/3),N30) -> 18255.53 | U30: =IF((I30-C30)*(1/3)+(O30-I30)*(2/3) + O30>0,O30+(I30-C30)*(1/3)+(O30-I30)*(2/3),O30) -> 31.8 | V30: =IF((J30-D30)*(1/3)+(P30-J30)*(2/3) + P30>0,P30+(J30-D30)*(1/3)+(P30-J30)*(2/3),P30) -> 394.42667 | W30: =IF((K30-E30)*(1/3)+(Q30-K30)*(2/3) + Q30>0,Q30+(K30-E30)*(1/3)+(Q30-K30)*(2/3),Q30) -> 0 | X30: =IF((L30-F30)*(1/3)+(R30-L30)*(2/3) + R30>0,R30+(L30-F30)*(1/3)+(R30-L30)*(2/3),R30) -> 201.54 | Y30: =T30-W30-X30 -> 18053.99 | Z30: =AVERAGE(Y30,S30,M30) -> 18318.783 | AA30: =U30 -> 31.8 | AB30: =V30 -> 394.42667 | AC30: =SUM(W30:X30) -> 201.54 | AD30: 8090964.1 | AE30: =INDEX('Rate Assumptions'!$A:$B,MATCH('Base Allocation'!AE$2,'Rate Assumptions'!$A:$A,0),2) -> 3988.5862 | AF30: =INDEX('Rate Assumptions'!$A:$B,MATCH('Base Allocation'!AF$2,'Rate Assumptions'!$A:$A,0),2) -> 3456.4415 | AG30: =INDEX('Rate Assumptions'!$A:$B,MATCH('Base Allocation'!AG$2,'Rate Assumptions'!$A:$A,0),2) -> 5634.5606 | AH30: =INDEX('Rate Assumptions'!$A:$B,MATCH('Base Allocation'!AH$2,'Rate Assumptions'!$A:$A,0),2) -> 5634.5606 | AI30: =AD30+SUMPRODUCT(Z30:AC30,AE30:AH30) -> 84624935
A31: Los Angeles | B31: 101333.93 | C31: 2226.65 | D31: 4423.7 | E31: =41.86+13.74 -> 55.6 | F31: 5149.4 | G31: =B31-E31-F31 -> 96128.932 | H31: 93053.62 | I31: 2917.27 | J31: 4074.59 | K31: 27.63 | L31: 5496.54 | M31: =H31-K31-L31 -> 87529.45 | N31: 90768.6 | O31: 2719.16 | P31: 4512.28 | Q31: 20 | R31: 5496.54 | S31: =N31-Q31-R31 -> 85252.06 | T31: =IF((H31-B31)*(1/3)+(N31-H31)*(2/3) + N31>0,N31+(H31-B31)*(1/3)+(N31-H31)*(2/3),N31) -> 86485.149 | U31: =IF((I31-C31)*(1/3)+(O31-I31)*(2/3) + O31>0,O31+(I31-C31)*(1/3)+(O31-I31)*(2/3),O31) -> 2817.2933 | V31: =IF((J31-D31)*(1/3)+(P31-J31)*(2/3) + P31>0,P31+(J31-D31)*(1/3)+(P31-J31)*(2/3),P31) -> 4687.7033 | W31: =IF((K31-E31)*(1/3)+(Q31-K31)*(2/3) + Q31>0,Q31+(K31-E31)*(1/3)+(Q31-K31)*(2/3),Q31) -> 5.59 | X31: =IF((L31-F31)*(1/3)+(R31-L31)*(2/3) + R31>0,R31+(L31-F31)*(1/3)+(R31-L31)*(2/3),R31) -> 5612.2533 | Y31: =T31-W31-X31 -> 80867.306 | Z31: =AVERAGE(Y31,S31,M31) -> 84549.605 | AA31: =U31 -> 2817.2933 | AB31: =V31 -> 4687.7033 | AC31: =SUM(W31:X31) -> 5617.8433 | AD31: 40454814 | AE31: =INDEX('Rate Assumptions'!$A:$B,MATCH('Base Allocation'!AE$2,'Rate Assumptions'!$A:$A,0),2) -> 3988.5862 | AF31: =INDEX('Rate Assumptions'!$A:$B,MATCH('Base Allocation'!AF$2,'Rate Assumptions'!$A:$A,0),2) -> 3456.4415 | AG31: =INDEX('Rate Assumptions'!$A:$B,MATCH('Base Allocation'!AG$2,'Rate Assumptions'!$A:$A,0),2) -> 5634.5606 | AH31: =INDEX('Rate Assumptions'!$A:$B,MATCH('Base Allocation'!AH$2,'Rate Assumptions'!$A:$A,0),2) -> 5634.5606 | AI31: =AD31+SUMPRODUCT(Z31:AC31,AE31:AH31) -> 4.4549324e+08
A32: Los Rios | B32: 52402.09 | C32: 237.67 | D32: 0 | F32: 358.34 | G32: =B32-E32-F32 -> 52043.75 | H32: 44183.24 | I32: 129.82 | J32: 0 | K32: 60.8 | L32: 449.12 | M32: =H32-K32-L32 -> 43673.32 | N32: 52019.38 | O32: 240.84 | P32: 0 | Q32: 93.53 | R32: 545.43 | S32: =N32-Q32-R32 -> 51380.42 | T32: =IF((H32-B32)*(1/3)+(N32-H32)*(2/3) + N32>0,N32+(H32-B32)*(1/3)+(N32-H32)*(2/3),N32) -> 54503.857 | U32: =IF((I32-C32)*(1/3)+(O32-I32)*(2/3) + O32>0,O32+(I32-C32)*(1/3)+(O32-I32)*(2/3),O32) -> 278.90333 | V32: =IF((J32-D32)*(1/3)+(P32-J32)*(2/3) + P32>0,P32+(J32-D32)*(1/3)+(P32-J32)*(2/3),P32) -> 0 | W32: =IF((K32-E32)*(1/3)+(Q32-K32)*(2/3) + Q32>0,Q32+(K32-E32)*(1/3)+(Q32-K32)*(2/3),Q32) -> 135.61667 | X32: =IF((L32-F32)*(1/3)+(R32-L32)*(2/3) + R32>0,R32+(L32-F32)*(1/3)+(R32-L32)*(2/3),R32) -> 639.89667 | Y32: =T32-W32-X32 -> 53728.343 | Z32: =AVERAGE(Y32,S32,M32) -> 49594.028 | AA32: =U32 -> 278.90333 | AB32: =V32 -> 0 | AC32: =SUM(W32:X32) -> 775.51333 | AD32: 26295631 | AE32: =INDEX('Rate Assumptions'!$A:$B,MATCH('Base Allocation'!AE$2,'Rate Assumptions'!$A:$A,0),2) -> 3988.5862 | AF32: =INDEX('Rate Assumptions'!$A:$B,MATCH('Base Allocation'!AF$2,'Rate Assumptions'!$A:$A,0),2) -> 3456.4415 | AG32: =INDEX('Rate Assumptions'!$A:$B,MATCH('Base Allocation'!AG$2,'Rate Assumptions'!$A:$A,0),2) -> 5634.5606 | AH32: =INDEX('Rate Assumptions'!$A:$B,MATCH('Base Allocation'!AH$2,'Rate Assumptions'!$A:$A,0),2) -> 5634.5606 | AI32: =AD32+SUMPRODUCT(Z32:AC32,AE32:AH32) -> 2.2943937e+08
A33: Marin | B33: 3452.66 | C33: 270.67 | D33: 0 | F33: 150.64 | G33: =B33-E33-F33 -> 3302.02 | H33: 3439.73 | I33: 284.79 | J33: 0 | L33: 201.12 | M33: =H33-K33-L33 -> 3238.61 | N33: 3090.03 | O33: 284.79 | P33: 0 | Q33: 0 | R33: 156.55 | S33: =N33-Q33-R33 -> 2933.48 | T33: =IF((H33-B33)*(1/3)+(N33-H33)*(2/3) + N33>0,N33+(H33-B33)*(1/3)+(N33-H33)*(2/3),N33) -> 2852.5867 | U33: =IF((I33-C33)*(1/3)+(O33-I33)*(2/3) + O33>0,O33+(I33-C33)*(1/3)+(O33-I33)*(2/3),O33) -> 289.49667 | V33: =IF((J33-D33)*(1/3)+(P33-J33)*(2/3) + P33>0,P33+(J33-D33)*(1/3)+(P33-J33)*(2/3),P33) -> 0 | W33: =IF((K33-E33)*(1/3)+(Q33-K33)*(2/3) + Q33>0,Q33+(K33-E33)*(1/3)+(Q33-K33)*(2/3),Q33) -> 0 | X33: =IF((L33-F33)*(1/3)+(R33-L33)*(2/3) + R33>0,R33+(L33-F33)*(1/3)+(R33-L33)*(2/3),R33) -> 143.66333 | Y33: =T33-W33-X33 -> 2708.9233 | Z33: =AVERAGE(Y33,S33,M33) -> 2960.3378 | AA33: =U33 -> 289.49667 | AB33: =V33 -> 0 | AC33: =SUM(W33:X33) -> 143.66333 | AD33: 4045480 | AE33: =INDEX('Rate Assumptions'!$A:$B,MATCH('Base Allocation'!AE$2,'Rate Assumptions'!$A:$A,0),2) -> 3988.5862 | AF33: =INDEX('Rate Assumptions'!$A:$B,MATCH('Base Allocation'!AF$2,'Rate Assumptions'!$A:$A,0),2) -> 3456.4415 | AG33: =INDEX('Rate Assumptions'!$A:$B,MATCH('Base Allocation'!AG$2,'Rate Assumptions'!$A:$A,0),2) -> 5634.5606 | AH33: =INDEX('Rate Assumptions'!$A:$B,MATCH('Base Allocation'!AH$2,'Rate Assumptions'!$A:$A,0),2) -> 5634.5606 | AI33: =AD33+SUMPRODUCT(Z33:AC33,AE33:AH33) -> 17663150
A34: Mendocino | B34: 2983.31 | C34: 42.12 | D34: 39.6 | F34: 398.58 | G34: =B34-E34-F34 -> 2584.73 | H34: 2369.96 | I34: 36.4 | J34: 49.79 | L34: 205.79 | M34: =H34-K34-L34 -> 2164.17 | N34: 2803.41 | O34: 31.98 | P34: 56.25 | Q34: 0 | R34: 288.98 | S34: =N34-Q34-R34 -> 2514.43 | T34: =IF((H34-B34)*(1/3)+(N34-H34)*(2/3) + N34>0,N34+(H34-B34)*(1/3)+(N34-H34)*(2/3),N34) -> 2887.9267 | U34: =IF((I34-C34)*(1/3)+(O34-I34)*(2/3) + O34>0,O34+(I34-C34)*(1/3)+(O34-I34)*(2/3),O34) -> 27.126667 | V34: =IF((J34-D34)*(1/3)+(P34-J34)*(2/3) + P34>0,P34+(J34-D34)*(1/3)+(P34-J34)*(2/3),P34) -> 63.953333 | W34: =IF((K34-E34)*(1/3)+(Q34-K34)*(2/3) + Q34>0,Q34+(K34-E34)*(1/3)+(Q34-K34)*(2/3),Q34) -> 0 | X34: =IF((L34-F34)*(1/3)+(R34-L34)*(2/3) + R34>0,R34+(L34-F34)*(1/3)+(R34-L34)*(2/3),R34) -> 280.17667 | Y34: =T34-W34-X34 -> 2607.75 | Z34: =AVERAGE(Y34,S34,M34) -> 2428.7833 | AA34: =U34 -> 27.126667 | AB34: =V34 -> 63.953333 | AC34: =SUM(W34:X34) -> 280.17667 | AD34: 6343562.3 | AE34: =INDEX('Rate Assumptions'!$A:$B,MATCH('Base Allocation'!AE$2,'Rate Assumptions'!$A:$A,0),2) -> 3988.5862 | AF34: =INDEX('Rate Assumptions'!$A:$B,MATCH('Base Allocation'!AF$2,'Rate Assumptions'!$A:$A,0),2) -> 3456.4415 | AG34: =INDEX('Rate Assumptions'!$A:$B,MATCH('Base Allocation'!AG$2,'Rate Assumptions'!$A:$A,0),2) -> 5634.5606 | AH34: =INDEX('Rate Assumptions'!$A:$B,MATCH('Base Allocation'!AH$2,'Rate Assumptions'!$A:$A,0),2) -> 5634.5606 | AI34: =AD34+SUMPRODUCT(Z34:AC34,AE34:AH34) -> 18063757
A35: Merced | B35: 8760.98 | C35: 228.53 | D35: 560.37 | E35: 45.26 | F35: 357.36 | G35: =B35-E35-F35 -> 8358.36 | H35: 8379.03 | I35: 183.32 | J35: 690.09 | K35: 75 | L35: 519.14 | M35: =H35-K35-L35 -> 7784.89 | N35: 8971.49 | O35: 365.7 | P35: 663.84 | Q35: 147.21 | R35: 72.941232 | S35: =N35-Q35-R35 -> 8751.3388 | T35: =IF((H35-B35)*(1/3)+(N35-H35)*(2/3) + N35>0,N35+(H35-B35)*(1/3)+(N35-H35)*(2/3),N35) -> 9239.1467 | U35: =IF((I35-C35)*(1/3)+(O35-I35)*(2/3) + O35>0,O35+(I35-C35)*(1/3)+(O35-I35)*(2/3),O35) -> 472.21667 | V35: =IF((J35-D35)*(1/3)+(P35-J35)*(2/3) + P35>0,P35+(J35-D35)*(1/3)+(P35-J35)*(2/3),P35) -> 689.58 | W35: =IF((K35-E35)*(1/3)+(Q35-K35)*(2/3) + Q35>0,Q35+(K35-E35)*(1/3)+(Q35-K35)*(2/3),Q35) -> 205.26333 | X35: =IF((L35-F35)*(1/3)+(R35-L35)*(2/3) + R35>0,R35+(L35-F35)*(1/3)+(R35-L35)*(2/3),R35) -> 72.941232 | Y35: =T35-W35-X35 -> 8960.9421 | Z35: =AVERAGE(Y35,S35,M35) -> 8499.057 | AA35: =U35 -> 472.21667 | AB35: =V35 -> 689.58 | AC35: =SUM(W35:X35) -> 278.20457 | AD35: 5393974 | AE35: =INDEX('Rate Assumptions'!$A:$B,MATCH('Base Allocation'!AE$2,'Rate Assumptions'!$A:$A,0),2) -> 3988.5862 | AF35: =INDEX('Rate Assumptions'!$A:$B,MATCH('Base Allocation'!AF$2,'Rate Assumptions'!$A:$A,0),2) -> 3456.4415 | AG35: =INDEX('Rate Assumptions'!$A:$B,MATCH('Base Allocation'!AG$2,'Rate Assumptions'!$A:$A,0),2) -> 5634.5606 | AH35: =INDEX('Rate Assumptions'!$A:$B,MATCH('Base Allocation'!AH$2,'Rate Assumptions'!$A:$A,0),2) -> 5634.5606 | AI35: =AD35+SUMPRODUCT(Z35:AC35,AE35:AH35) -> 46378425
A36: MiraCosta | B36: 10299.25 | C36: 782.45 | D36: 0 | F36: 151.13 | G36: =B36-E36-F36 -> 10148.12 | H36: 10274.23 | I36: 759.88 | J36: 0 | L36: 150.49 | M36: =H36-K36-L36 -> 10123.74 | N36: 9249.71 | O36: 759.88 | P36: 0 | Q36: 0 | R36: 122.55 | S36: =N36-Q36-R36 -> 9127.16 | T36: =IF((H36-B36)*(1/3)+(N36-H36)*(2/3) + N36>0,N36+(H36-B36)*(1/3)+(N36-H36)*(2/3),N36) -> 8558.3567 | U36: =IF((I36-C36)*(1/3)+(O36-I36)*(2/3) + O36>0,O36+(I36-C36)*(1/3)+(O36-I36)*(2/3),O36) -> 752.35667 | V36: =IF((J36-D36)*(1/3)+(P36-J36)*(2/3) + P36>0,P36+(J36-D36)*(1/3)+(P36-J36)*(2/3),P36) -> 0 | W36: =IF((K36-E36)*(1/3)+(Q36-K36)*(2/3) + Q36>0,Q36+(K36-E36)*(1/3)+(Q36-K36)*(2/3),Q36) -> 0 | X36: =IF((L36-F36)*(1/3)+(R36-L36)*(2/3) + R36>0,R36+(L36-F36)*(1/3)+(R36-L36)*(2/3),R36) -> 103.71 | Y36: =T36-W36-X36 -> 8454.6467 | Z36: =AVERAGE(Y36,S36,M36) -> 9235.1822 | AA36: =U36 -> 752.35667 | AB36: =V36 -> 0 | AC36: =SUM(W36:X36) -> 103.71 | AD36: 6742470.1 | AE36: =INDEX('Rate Assumptions'!$A:$B,MATCH('Base Allocation'!AE$2,'Rate Assumptions'!$A:$A,0),2) -> 3988.5862 | AF36: =INDEX('Rate Assumptions'!$A:$B,MATCH('Base Allocation'!AF$2,'Rate Assumptions'!$A:$A,0),2) -> 3456.4415 | AG36: =INDEX('Rate Assumptions'!$A:$B,MATCH('Base Allocation'!AG$2,'Rate Assumptions'!$A:$A,0),2) -> 5634.5606 | AH36: =INDEX('Rate Assumptions'!$A:$B,MATCH('Base Allocation'!AH$2,'Rate Assumptions'!$A:$A,0),2) -> 5634.5606 | AI36: =AD36+SUMPRODUCT(Z36:AC36,AE36:AH36) -> 46762627
A37: Monterey | B37: 6258.5701 | C37: 355.9 | D37: 82.58 | F37: 120.21 | G37: =B37-E37-F37 -> 6138.3601 | H37: 5956.3 | I37: 230.02 | J37: 87.89 | L37: 140.1 | M37: =H37-K37-L37 -> 5816.2 | N37: 5968.8 | O37: 293.83 | P37: 37.24 | Q37: 0 | R37: 149.9 | S37: =N37-Q37-R37 -> 5818.9 | T37: =IF((H37-B37)*(1/3)+(N37-H37)*(2/3) + N37>0,N37+(H37-B37)*(1/3)+(N37-H37)*(2/3),N37) -> 5876.3766 | U37: =IF((I37-C37)*(1/3)+(O37-I37)*(2/3) + O37>0,O37+(I37-C37)*(1/3)+(O37-I37)*(2/3),O37) -> 294.41 | V37: =IF((J37-D37)*(1/3)+(P37-J37)*(2/3) + P37>0,P37+(J37-D37)*(1/3)+(P37-J37)*(2/3),P37) -> 5.2433333 | W37: =IF((K37-E37)*(1/3)+(Q37-K37)*(2/3) + Q37>0,Q37+(K37-E37)*(1/3)+(Q37-K37)*(2/3),Q37) -> 0 | X37: =IF((L37-F37)*(1/3)+(R37-L37)*(2/3) + R37>0,R37+(L37-F37)*(1/3)+(R37-L37)*(2/3),R37) -> 163.06333 | Y37: =T37-W37-X37 -> 5713.3133 | Z37: =AVERAGE(Y37,S37,M37) -> 5782.8044 | AA37: =U37 -> 294.41 | AB37: =V37 -> 5.2433333 | AC37: =SUM(W37:X37) -> 163.06333 | AD37: 4382603.3 | AE37: =INDEX('Rate Assumptions'!$A:$B,MATCH('Base Allocation'!AE$2,'Rate Assumptions'!$A:$A,0),2) -> 3988.5862 | AF37: =INDEX('Rate Assumptions'!$A:$B,MATCH('Base Allocation'!AF$2,'Rate Assumptions'!$A:$A,0),2) -> 3456.4415 | AG37: =INDEX('Rate Assumptions'!$A:$B,MATCH('Base Allocation'!AG$2,'Rate Assumptions'!$A:$A,0),2) -> 5634.5606 | AH37: =INDEX('Rate Assumptions'!$A:$B,MATCH('Base Allocation'!AH$2,'Rate Assumptions'!$A:$A,0),2) -> 5634.5606 | AI37: =AD37+SUMPRODUCT(Z37:AC37,AE37:AH37) -> 29413762
A38: Mt. San Antonio | B38: 24240.05 | C38: 1697.18 | D38: 5080.4 | F38: 24.49 | G38: =B38-E38-F38 -> 24215.56 | H38: 24977.135 | I38: 1557.81 | J38: 6169.37 | L38: 108.69 | M38: =H38-K38-L38 -> 24868.445 | N38: 24957.29 | O38: 1636.03 | P38: 6299.98 | Q38: 0 | R38: 57.306977 | S38: =N38-Q38-R38 -> 24899.983 | T38: =IF((H38-B38)*(1/3)+(N38-H38)*(2/3) + N38>0,N38+(H38-B38)*(1/3)+(N38-H38)*(2/3),N38) -> 25189.755 | U38: =IF((I38-C38)*(1/3)+(O38-I38)*(2/3) + O38>0,O38+(I38-C38)*(1/3)+(O38-I38)*(2/3),O38) -> 1641.72 | V38: =IF((J38-D38)*(1/3)+(P38-J38)*(2/3) + P38>0,P38+(J38-D38)*(1/3)+(P38-J38)*(2/3),P38) -> 6750.0433 | W38: =IF((K38-E38)*(1/3)+(Q38-K38)*(2/3) + Q38>0,Q38+(K38-E38)*(1/3)+(Q38-K38)*(2/3),Q38) -> 0 | X38: =IF((L38-F38)*(1/3)+(R38-L38)*(2/3) + R38>0,R38+(L38-F38)*(1/3)+(R38-L38)*(2/3),R38) -> 51.118295 | Y38: =T38-W38-X38 -> 25138.637 | Z38: =AVERAGE(Y38,S38,M38) -> 24969.022 | AA38: =U38 -> 1641.72 | AB38: =V38 -> 6750.0433 | AC38: =SUM(W38:X38) -> 51.118295 | AD38: 6742470.1 | AE38: =INDEX('Rate Assumptions'!$A:$B,MATCH('Base Allocation'!AE$2,'Rate Assumptions'!$A:$A,0),2) -> 3988.5862 | AF38: =INDEX('Rate Assumptions'!$A:$B,MATCH('Base Allocation'!AF$2,'Rate Assumptions'!$A:$A,0),2) -> 3456.4415 | AG38: =INDEX('Rate Assumptions'!$A:$B,MATCH('Base Allocation'!AG$2,'Rate Assumptions'!$A:$A,0),2) -> 5634.5606 | AH38: =INDEX('Rate Assumptions'!$A:$B,MATCH('Base Allocation'!AH$2,'Rate Assumptions'!$A:$A,0),2) -> 5634.5606 | AI38: =AD38+SUMPRODUCT(Z38:AC38,AE38:AH38) -> 1.5032963e+08
A39: Mt. San Jacinto | B39: 11828.49 | C39: 320.34 | D39: 271.38 | F39: 100.61 | G39: =B39-E39-F39 -> 11727.88 | H39: 10195.46 | I39: 367.36 | J39: 242.17 | L39: 79.69 | M39: =H39-K39-L39 -> 10115.77 | N39: 11454.47 | O39: 274.04 | P39: 260.8 | Q39: 0 | R39: 141.21 | S39: =N39-Q39-R39 -> 11313.26 | T39: =IF((H39-B39)*(1/3)+(N39-H39)*(2/3) + N39>0,N39+(H39-B39)*(1/3)+(N39-H39)*(2/3),N39) -> 11749.467 | U39: =IF((I39-C39)*(1/3)+(O39-I39)*(2/3) + O39>0,O39+(I39-C39)*(1/3)+(O39-I39)*(2/3),O39) -> 227.5 | V39: =IF((J39-D39)*(1/3)+(P39-J39)*(2/3) + P39>0,P39+(J39-D39)*(1/3)+(P39-J39)*(2/3),P39) -> 263.48333 | W39: =IF((K39-E39)*(1/3)+(Q39-K39)*(2/3) + Q39>0,Q39+(K39-E39)*(1/3)+(Q39-K39)*(2/3),Q39) -> 0 | X39: =IF((L39-F39)*(1/3)+(R39-L39)*(2/3) + R39>0,R39+(L39-F39)*(1/3)+(R39-L39)*(2/3),R39) -> 175.25 | Y39: =T39-W39-X39 -> 11574.217 | Z39: =AVERAGE(Y39,S39,M39) -> 11001.082 | AA39: =U39 -> 227.5 | AB39: =V39 -> 263.48333 | AC39: =SUM(W39:X39) -> 175.25 | AD39: 6742470.1 | AE39: =INDEX('Rate Assumptions'!$A:$B,MATCH('Base Allocation'!AE$2,'Rate Assumptions'!$A:$A,0),2) -> 3988.5862 | AF39: =INDEX('Rate Assumptions'!$A:$B,MATCH('Base Allocation'!AF$2,'Rate Assumptions'!$A:$A,0),2) -> 3456.4415 | AG39: =INDEX('Rate Assumptions'!$A:$B,MATCH('Base Allocation'!AG$2,'Rate Assumptions'!$A:$A,0),2) -> 5634.5606 | AH39: =INDEX('Rate Assumptions'!$A:$B,MATCH('Base Allocation'!AH$2,'Rate Assumptions'!$A:$A,0),2) -> 5634.5606 | AI39: =AD39+SUMPRODUCT(Z39:AC39,AE39:AH39) -> 53879645
A40: Napa | B40: 4841 | C40: 453.46 | D40: 11.99 | F40: 129.39 | G40: =B40-E40-F40 -> 4711.61 | H40: 4749.63 | I40: 418.75 | J40: 5.77 | L40: 185.77 | M40: =H40-K40-L40 -> 4563.86 | N40: 4597.67 | O40: 418.75 | P40: 5.77 | Q40: 0 | R40: 143.47 | S40: =N40-Q40-R40 -> 4454.2 | T40: =IF((H40-B40)*(1/3)+(N40-H40)*(2/3) + N40>0,N40+(H40-B40)*(1/3)+(N40-H40)*(2/3),N40) -> 4465.9067 | U40: =IF((I40-C40)*(1/3)+(O40-I40)*(2/3) + O40>0,O40+(I40-C40)*(1/3)+(O40-I40)*(2/3),O40) -> 407.18 | V40: =IF((J40-D40)*(1/3)+(P40-J40)*(2/3) + P40>0,P40+(J40-D40)*(1/3)+(P40-J40)*(2/3),P40) -> 3.6966667 | W40: =IF((K40-E40)*(1/3)+(Q40-K40)*(2/3) + Q40>0,Q40+(K40-E40)*(1/3)+(Q40-K40)*(2/3),Q40) -> 0 | X40: =IF((L40-F40)*(1/3)+(R40-L40)*(2/3) + R40>0,R40+(L40-F40)*(1/3)+(R40-L40)*(2/3),R40) -> 134.06333 | Y40: =T40-W40-X40 -> 4331.8433 | Z40: =AVERAGE(Y40,S40,M40) -> 4449.9678 | AA40: =U40 -> 407.18 | AB40: =V40 -> 3.6966667 | AC40: =SUM(W40:X40) -> 134.06333 | AD40: 4719726.5 | AE40: =INDEX('Rate Assumptions'!$A:$B,MATCH('Base Allocation'!AE$2,'Rate Assumptions'!$A:$A,0),2) -> 3988.5862 | AF40: =INDEX('Rate Assumptions'!$A:$B,MATCH('Base Allocation'!AF$2,'Rate Assumptions'!$A:$A,0),2) -> 3456.4415 | AG40: =INDEX('Rate Assumptions'!$A:$B,MATCH('Base Allocation'!AG$2,'Rate Assumptions'!$A:$A,0),2) -> 5634.5606 | AH40: =INDEX('Rate Assumptions'!$A:$B,MATCH('Base Allocation'!AH$2,'Rate Assumptions'!$A:$A,0),2) -> 5634.5606 | AI40: =AD40+SUMPRODUCT(Z40:AC40,AE40:AH40) -> 24652417
A41: North Orange | B41: 32051.03 | C41: 2631.79 | D41: 2565.56 | F41: 263.71 | G41: =B41-E41-F41 -> 31787.32 | H41: 27208.32 | I41: 2573.57 | J41: 2664.91 | L41: 251.8 | M41: =H41-K41-L41 -> 26956.52 | N41: 28054.18 | O41: 4039.74 | P41: 1066.14 | Q41: 0 | R41: 504.2 | S41: =N41-Q41-R41 -> 27549.98 | T41: =IF((H41-B41)*(1/3)+(N41-H41)*(2/3) + N41>0,N41+(H41-B41)*(1/3)+(N41-H41)*(2/3),N41) -> 27003.85 | U41: =IF((I41-C41)*(1/3)+(O41-I41)*(2/3) + O41>0,O41+(I41-C41)*(1/3)+(O41-I41)*(2/3),O41) -> 4997.78 | V41: =IF((J41-D41)*(1/3)+(P41-J41)*(2/3) + P41>0,P41+(J41-D41)*(1/3)+(P41-J41)*(2/3),P41) -> 33.41 | W41: =IF((K41-E41)*(1/3)+(Q41-K41)*(2/3) + Q41>0,Q41+(K41-E41)*(1/3)+(Q41-K41)*(2/3),Q41) -> 0 | X41: =IF((L41-F41)*(1/3)+(R41-L41)*(2/3) + R41>0,R41+(L41-F41)*(1/3)+(R41-L41)*(2/3),R41) -> 668.49667 | Y41: =T41-W41-X41 -> 26335.353 | Z41: =AVERAGE(Y41,S41,M41) -> 26947.284 | AA41: =U41 -> 4997.78 | AB41: =V41 -> 33.41 | AC41: =SUM(W41:X41) -> 668.49667 | AD41: 10787952 | AE41: =INDEX('Rate Assumptions'!$A:$B,MATCH('Base Allocation'!AE$2,'Rate Assumptions'!$A:$A,0),2) -> 3988.5862 | AF41: =INDEX('Rate Assumptions'!$A:$B,MATCH('Base Allocation'!AF$2,'Rate Assumptions'!$A:$A,0),2) -> 3456.4415 | AG41: =INDEX('Rate Assumptions'!$A:$B,MATCH('Base Allocation'!AG$2,'Rate Assumptions'!$A:$A,0),2) -> 5634.5606 | AH41: =INDEX('Rate Assumptions'!$A:$B,MATCH('Base Allocation'!AH$2,'Rate Assumptions'!$A:$A,0),2) -> 5634.5606 | AI41: =AD41+SUMPRODUCT(Z41:AC41,AE41:AH41) -> 1.3949899e+08
A42: Ohlone | B42: 8239.9999 | C42: 0 | D42: 0 | F42: 1307.92 | G42: =B42-E42-F42 -> 6932.0799 | H42: 6833.46 | I42: 0 | J42: 0 | L42: 943.95 | M42: =H42-K42-L42 -> 5889.51 | N42: 7850.49 | O42: 0.03 | P42: 1.48 | Q42: 0 | R42: 492.6 | S42: =N42-Q42-R42 -> 7357.89 | T42: =IF((H42-B42)*(1/3)+(N42-H42)*(2/3) + N42>0,N42+(H42-B42)*(1/3)+(N42-H42)*(2/3),N42) -> 8059.6634 | U42: =IF((I42-C42)*(1/3)+(O42-I42)*(2/3) + O42>0,O42+(I42-C42)*(1/3)+(O42-I42)*(2/3),O42) -> 0.05 | V42: =IF((J42-D42)*(1/3)+(P42-J42)*(2/3) + P42>0,P42+(J42-D42)*(1/3)+(P42-J42)*(2/3),P42) -> 2.4666667 | W42: =IF((K42-E42)*(1/3)+(Q42-K42)*(2/3) + Q42>0,Q42+(K42-E42)*(1/3)+(Q42-K42)*(2/3),Q42) -> 0 | X42: =IF((L42-F42)*(1/3)+(R42-L42)*(2/3) + R42>0,R42+(L42-F42)*(1/3)+(R42-L42)*(2/3),R42) -> 70.376667 | Y42: =T42-W42-X42 -> 7989.2867 | Z42: =AVERAGE(Y42,S42,M42) -> 7078.8956 | AA42: =U42 -> 0.05 | AB42: =V42 -> 2.4666667 | AC42: =SUM(W42:X42) -> 70.376667 | AD42: 5393974 | AE42: =INDEX('Rate Assumptions'!$A:$B,MATCH('Base Allocation'!AE$2,'Rate Assumptions'!$A:$A,0),2) -> 3988.5862 | AF42: =INDEX('Rate Assumptions'!$A:$B,MATCH('Base Allocation'!AF$2,'Rate Assumptions'!$A:$A,0),2) -> 3456.4415 | AG42: =INDEX('Rate Assumptions'!$A:$B,MATCH('Base Allocation'!AG$2,'Rate Assumptions'!$A:$A,0),2) -> 5634.5606 | AH42: =INDEX('Rate Assumptions'!$A:$B,MATCH('Base Allocation'!AH$2,'Rate Assumptions'!$A:$A,0),2) -> 5634.5606 | AI42: =AD42+SUMPRODUCT(Z42:AC42,AE42:AH42) -> 34039372
A43: Palo Verde | B43: 1957.93 | C43: 21.96 | D43: 115.11 | E43: 890.02 | F43: 58.77 | G43: =B43-E43-F43 -> 1009.14 | H43: 2051.5483 | I43: 12.51 | J43: 101.02 | K43: 816.79 | L43: 50.25 | M43: =H43-K43-L43 -> 1184.5083 | N43: 2067.14 | O43: 23.48 | P43: 6.02 | Q43: 723.94755 | R43: 0 | S43: =N43-Q43-R43 -> 1343.1924 | T43: =IF((H43-B43)*(1/3)+(N43-H43)*(2/3) + N43>0,N43+(H43-B43)*(1/3)+(N43-H43)*(2/3),N43) -> 2108.7406 | U43: =IF((I43-C43)*(1/3)+(O43-I43)*(2/3) + O43>0,O43+(I43-C43)*(1/3)+(O43-I43)*(2/3),O43) -> 27.643333 | V43: =IF((J43-D43)*(1/3)+(P43-J43)*(2/3) + P43>0,P43+(J43-D43)*(1/3)+(P43-J43)*(2/3),P43) -> 6.02 | W43: =IF((K43-E43)*(1/3)+(Q43-K43)*(2/3) + Q43>0,Q43+(K43-E43)*(1/3)+(Q43-K43)*(2/3),Q43) -> 637.64259 | X43: =IF((L43-F43)*(1/3)+(R43-L43)*(2/3) + R43>0,R43+(L43-F43)*(1/3)+(R43-L43)*(2/3),R43) -> 0 | Y43: =T43-W43-X43 -> 1471.098 | Z43: =AVERAGE(Y43,S43,M43) -> 1332.9329 | AA43: =U43 -> 27.643333 | AB43: =V43 -> 6.02 | AC43: =SUM(W43:X43) -> 637.64259 | AD43: 5500755.2 | AE43: =INDEX('Rate Assumptions'!$A:$B,MATCH('Base Allocation'!AE$2,'Rate Assumptions'!$A:$A,0),2) -> 3988.5862 | AF43: =INDEX('Rate Assumptions'!$A:$B,MATCH('Base Allocation'!AF$2,'Rate Assumptions'!$A:$A,0),2) -> 3456.4415 | AG43: =INDEX('Rate Assumptions'!$A:$B,MATCH('Base Allocation'!AG$2,'Rate Assumptions'!$A:$A,0),2) -> 5634.5606 | AH43: =INDEX('Rate Assumptions'!$A:$B,MATCH('Base Allocation'!AH$2,'Rate Assumptions'!$A:$A,0),2) -> 5634.5606 | AI43: =AD43+SUMPRODUCT(Z43:AC43,AE43:AH43) -> 14539576
A44: Palomar | B44: 17424.79 | C44: 289.81 | D44: 504.25 | F44: 453.88 | G44: =B44-E44-F44 -> 16970.91 | H44: 18449.84 | I44: 276.86 | J44: 422.24 | K44: 1.52 | L44: 522.44 | M44: =H44-K44-L44 -> 17925.88 | N44: 17225.78 | O44: 276.86 | P44: 422.24 | Q44: 13.22 | R44: 495 | S44: =N44-Q44-R44 -> 16717.56 | T44: =IF((H44-B44)*(1/3)+(N44-H44)*(2/3) + N44>0,N44+(H44-B44)*(1/3)+(N44-H44)*(2/3),N44) -> 16751.423 | U44: =IF((I44-C44)*(1/3)+(O44-I44)*(2/3) + O44>0,O44+(I44-C44)*(1/3)+(O44-I44)*(2/3),O44) -> 272.54333 | V44: =IF((J44-D44)*(1/3)+(P44-J44)*(2/3) + P44>0,P44+(J44-D44)*(1/3)+(P44-J44)*(2/3),P44) -> 394.90333 | W44: =IF((K44-E44)*(1/3)+(Q44-K44)*(2/3) + Q44>0,Q44+(K44-E44)*(1/3)+(Q44-K44)*(2/3),Q44) -> 21.526667 | X44: =IF((L44-F44)*(1/3)+(R44-L44)*(2/3) + R44>0,R44+(L44-F44)*(1/3)+(R44-L44)*(2/3),R44) -> 499.56 | Y44: =T44-W44-X44 -> 16230.337 | Z44: =AVERAGE(Y44,S44,M44) -> 16957.926 | AA44: =U44 -> 272.54333 | AB44: =V44 -> 394.90333 | AC44: =SUM(W44:X44) -> 521.08667 | AD44: 6742470.1 | AE44: =INDEX('Rate Assumptions'!$A:$B,MATCH('Base Allocation'!AE$2,'Rate Assumptions'!$A:$A,0),2) -> 3988.5862 | AF44: =INDEX('Rate Assumptions'!$A:$B,MATCH('Base Allocation'!AF$2,'Rate Assumptions'!$A:$A,0),2) -> 3456.4415 | AG44: =INDEX('Rate Assumptions'!$A:$B,MATCH('Base Allocation'!AG$2,'Rate Assumptions'!$A:$A,0),2) -> 5634.5606 | AH44: =INDEX('Rate Assumptions'!$A:$B,MATCH('Base Allocation'!AH$2,'Rate Assumptions'!$A:$A,0),2) -> 5634.5606 | AI44: =AD44+SUMPRODUCT(Z44:AC44,AE44:AH44) -> 80483849
A45: Pasadena | B45: 22765.3 | C45: 166.57 | D45: 1056.35 | F45: 252.26 | G45: =B45-E45-F45 -> 22513.04 | H45: 22801.97 | I45: 152.77 | J45: 1033.81 | L45: 206.91 | M45: =H45-K45-L45 -> 22595.06 | N45: 22816.07 | O45: 147.35621 | P45: 943.76 | Q45: 0 | R45: 264.18 | S45: =N45-Q45-R45 -> 22551.89 | T45: =IF((H45-B45)*(1/3)+(N45-H45)*(2/3) + N45>0,N45+(H45-B45)*(1/3)+(N45-H45)*(2/3),N45) -> 22837.693 | U45: =IF((I45-C45)*(1/3)+(O45-I45)*(2/3) + O45>0,O45+(I45-C45)*(1/3)+(O45-I45)*(2/3),O45) -> 139.14701 | V45: =IF((J45-D45)*(1/3)+(P45-J45)*(2/3) + P45>0,P45+(J45-D45)*(1/3)+(P45-J45)*(2/3),P45) -> 876.21333 | W45: =IF((K45-E45)*(1/3)+(Q45-K45)*(2/3) + Q45>0,Q45+(K45-E45)*(1/3)+(Q45-K45)*(2/3),Q45) -> 0 | X45: =IF((L45-F45)*(1/3)+(R45-L45)*(2/3) + R45>0,R45+(L45-F45)*(1/3)+(R45-L45)*(2/3),R45) -> 287.24333 | Y45: =T45-W45-X45 -> 22550.45 | Z45: =AVERAGE(Y45,S45,M45) -> 22565.8 | AA45: =U45 -> 139.14701 | AB45: =V45 -> 876.21333 | AC45: =SUM(W45:X45) -> 287.24333 | AD45: 8090964.1 | AE45: =INDEX('Rate Assumptions'!$A:$B,MATCH('Base Allocation'!AE$2,'Rate Assumptions'!$A:$A,0),2) -> 3988.5862 | AF45: =INDEX('Rate Assumptions'!$A:$B,MATCH('Base Allocation'!AF$2,'Rate Assumptions'!$A:$A,0),2) -> 3456.4415 | AG45: =INDEX('Rate Assumptions'!$A:$B,MATCH('Base Allocation'!AG$2,'Rate Assumptions'!$A:$A,0),2) -> 5634.5606 | AH45: =INDEX('Rate Assumptions'!$A:$B,MATCH('Base Allocation'!AH$2,'Rate Assumptions'!$A:$A,0),2) -> 5634.5606 | AI45: =AD45+SUMPRODUCT(Z45:AC45,AE45:AH45) -> 1.0513312e+08
A46: Peralta | B46: 15624.75 | C46: 143.57 | D46: 0 | F46: 1093.24 | G46: =B46-E46-F46 -> 14531.51 | H46: 18684.53 | I46: 117.31 | J46: 0 | L46: 0 | M46: =H46-K46-L46 -> 18684.53 | N46: 16601.38 | O46: 117.31 | P46: 0 | Q46: 0 | R46: 881.32 | S46: =N46-Q46-R46 -> 15720.06 | T46: =IF((H46-B46)*(1/3)+(N46-H46)*(2/3) + N46>0,N46+(H46-B46)*(1/3)+(N46-H46)*(2/3),N46) -> 16232.54 | U46: =IF((I46-C46)*(1/3)+(O46-I46)*(2/3) + O46>0,O46+(I46-C46)*(1/3)+(O46-I46)*(2/3),O46) -> 108.55667 | V46: =IF((J46-D46)*(1/3)+(P46-J46)*(2/3) + P46>0,P46+(J46-D46)*(1/3)+(P46-J46)*(2/3),P46) -> 0 | W46: =IF((K46-E46)*(1/3)+(Q46-K46)*(2/3) + Q46>0,Q46+(K46-E46)*(1/3)+(Q46-K46)*(2/3),Q46) -> 0 | X46: =IF((L46-F46)*(1/3)+(R46-L46)*(2/3) + R46>0,R46+(L46-F46)*(1/3)+(R46-L46)*(2/3),R46) -> 1104.4533 | Y46: =T46-W46-X46 -> 15128.087 | Z46: =AVERAGE(Y46,S46,M46) -> 16510.892 | AA46: =U46 -> 108.55667 | AB46: =V46 -> 0 | AC46: =SUM(W46:X46) -> 1104.4533 | AD46: 16181921 | AE46: =INDEX('Rate Assumptions'!$A:$B,MATCH('Base Allocation'!AE$2,'Rate Assumptions'!$A:$A,0),2) -> 3988.5862 | AF46: =INDEX('Rate Assumptions'!$A:$B,MATCH('Base Allocation'!AF$2,'Rate Assumptions'!$A:$A,0),2) -> 3456.4415 | AG46: =INDEX('Rate Assumptions'!$A:$B,MATCH('Base Allocation'!AG$2,'Rate Assumptions'!$A:$A,0),2) -> 5634.5606 | AH46: =INDEX('Rate Assumptions'!$A:$B,MATCH('Base Allocation'!AH$2,'Rate Assumptions'!$A:$A,0),2) -> 5634.5606 | AI46: =AD46+SUMPRODUCT(Z46:AC46,AE46:AH46) -> 88635367
A47: Rancho Santiago | B47: 21499.15 | C47: 854.66 | D47: 5163.5 | E47: 6.72 | F47: 1944.53 | G47: =B47-E47-F47 -> 19547.9 | H47: 23301.943 | I47: 1092.28 | J47: 4981.71 | L47: 2196.94 | M47: =H47-K47-L47 -> 21105.003 | N47: 21492.12 | O47: 1092.28 | P47: 4981.71 | Q47: 0 | R47: 2583.27 | S47: =N47-Q47-R47 -> 18908.85 | T47: =IF((H47-B47)*(1/3)+(N47-H47)*(2/3) + N47>0,N47+(H47-B47)*(1/3)+(N47-H47)*(2/3),N47) -> 20886.502 | U47: =IF((I47-C47)*(1/3)+(O47-I47)*(2/3) + O47>0,O47+(I47-C47)*(1/3)+(O47-I47)*(2/3),O47) -> 1171.4867 | V47: =IF((J47-D47)*(1/3)+(P47-J47)*(2/3) + P47>0,P47+(J47-D47)*(1/3)+(P47-J47)*(2/3),P47) -> 4921.1133 | W47: =IF((K47-E47)*(1/3)+(Q47-K47)*(2/3) + Q47>0,Q47+(K47-E47)*(1/3)+(Q47-K47)*(2/3),Q47) -> 0 | X47: =IF((L47-F47)*(1/3)+(R47-L47)*(2/3) + R47>0,R47+(L47-F47)*(1/3)+(R47-L47)*(2/3),R47) -> 2924.96 | Y47: =T47-W47-X47 -> 17961.542 | Z47: =AVERAGE(Y47,S47,M47) -> 19325.132 | AA47: =U47 -> 1171.4867 | AB47: =V47 -> 4921.1133 | AC47: =SUM(W47:X47) -> 2924.96 | AD47: 12136444 | AE47: =INDEX('Rate Assumptions'!$A:$B,MATCH('Base Allocation'!AE$2,'Rate Assumptions'!$A:$A,0),2) -> 3988.5862 | AF47: =INDEX('Rate Assumptions'!$A:$B,MATCH('Base Allocation'!AF$2,'Rate Assumptions'!$A:$A,0),2) -> 3456.4415 | AG47: =INDEX('Rate Assumptions'!$A:$B,MATCH('Base Allocation'!AG$2,'Rate Assumptions'!$A:$A,0),2) -> 5634.5606 | AH47: =INDEX('Rate Assumptions'!$A:$B,MATCH('Base Allocation'!AH$2,'Rate Assumptions'!$A:$A,0),2) -> 5634.5606 | AI47: =AD47+SUMPRODUCT(Z47:AC47,AE47:AH47) -> 1.3747475e+08
A48: Redwoods | B48: 3900.86 | C48: 31.84 | D48: 85.85 | F48: 209.78 | G48: =B48-E48-F48 -> 3691.08 | H48: 3477.45 | I48: 87 | J48: 83.5 | L48: 165.43 | M48: =H48-K48-L48 -> 3312.02 | N48: 3470.29 | O48: 89.19 | P48: 65.18 | Q48: 116.57 | R48: 190.75 | S48: =N48-Q48-R48 -> 3162.97 | T48: =IF((H48-B48)*(1/3)+(N48-H48)*(2/3) + N48>0,N48+(H48-B48)*(1/3)+(N48-H48)*(2/3),N48) -> 3324.38 | U48: =IF((I48-C48)*(1/3)+(O48-I48)*(2/3) + O48>0,O48+(I48-C48)*(1/3)+(O48-I48)*(2/3),O48) -> 109.03667 | V48: =IF((J48-D48)*(1/3)+(P48-J48)*(2/3) + P48>0,P48+(J48-D48)*(1/3)+(P48-J48)*(2/3),P48) -> 52.183333 | W48: =IF((K48-E48)*(1/3)+(Q48-K48)*(2/3) + Q48>0,Q48+(K48-E48)*(1/3)+(Q48-K48)*(2/3),Q48) -> 194.28333 | X48: =IF((L48-F48)*(1/3)+(R48-L48)*(2/3) + R48>0,R48+(L48-F48)*(1/3)+(R48-L48)*(2/3),R48) -> 192.84667 | Y48: =T48-W48-X48 -> 2937.25 | Z48: =AVERAGE(Y48,S48,M48) -> 3137.4133 | AA48: =U48 -> 109.03667 | AB48: =V48 -> 52.183333 | AC48: =SUM(W48:X48) -> 387.13 | AD48: 6006439 | AE48: =INDEX('Rate Assumptions'!$A:$B,MATCH('Base Allocation'!AE$2,'Rate Assumptions'!$A:$A,0),2) -> 3988.5862 | AF48: =INDEX('Rate Assumptions'!$A:$B,MATCH('Base Allocation'!AF$2,'Rate Assumptions'!$A:$A,0),2) -> 3456.4415 | AG48: =INDEX('Rate Assumptions'!$A:$B,MATCH('Base Allocation'!AG$2,'Rate Assumptions'!$A:$A,0),2) -> 5634.5606 | AH48: =INDEX('Rate Assumptions'!$A:$B,MATCH('Base Allocation'!AH$2,'Rate Assumptions'!$A:$A,0),2) -> 5634.5606 | AI48: =AD48+SUMPRODUCT(Z48:AC48,AE48:AH48) -> 21372499
A49: Rio Hondo | B49: 11122.72 | C49: 462.45 | D49: 34.29 | F49: 197.97 | G49: =B49-E49-F49 -> 10924.75 | H49: 12782.115 | I49: 452.83 | J49: 36.49 | L49: 442.48 | M49: =H49-K49-L49 -> 12339.635 | N49: 12504.11 | O49: 452.83 | P49: 36.49 | Q49: 0 | R49: 360.98 | S49: =N49-Q49-R49 -> 12143.13 | T49: =IF((H49-B49)*(1/3)+(N49-H49)*(2/3) + N49>0,N49+(H49-B49)*(1/3)+(N49-H49)*(2/3),N49) -> 12871.905 | U49: =IF((I49-C49)*(1/3)+(O49-I49)*(2/3) + O49>0,O49+(I49-C49)*(1/3)+(O49-I49)*(2/3),O49) -> 449.62333 | V49: =IF((J49-D49)*(1/3)+(P49-J49)*(2/3) + P49>0,P49+(J49-D49)*(1/3)+(P49-J49)*(2/3),P49) -> 37.223333 | W49: =IF((K49-E49)*(1/3)+(Q49-K49)*(2/3) + Q49>0,Q49+(K49-E49)*(1/3)+(Q49-K49)*(2/3),Q49) -> 0 | X49: =IF((L49-F49)*(1/3)+(R49-L49)*(2/3) + R49>0,R49+(L49-F49)*(1/3)+(R49-L49)*(2/3),R49) -> 388.15 | Y49: =T49-W49-X49 -> 12483.755 | Z49: =AVERAGE(Y49,S49,M49) -> 12322.173 | AA49: =U49 -> 449.62333 | AB49: =V49 -> 37.223333 | AC49: =SUM(W49:X49) -> 388.15 | AD49: 5393976.1 | AE49: =INDEX('Rate Assumptions'!$A:$B,MATCH('Base Allocation'!AE$2,'Rate Assumptions'!$A:$A,0),2) -> 3988.5862 | AF49: =INDEX('Rate Assumptions'!$A:$B,MATCH('Base Allocation'!AF$2,'Rate Assumptions'!$A:$A,0),2) -> 3456.4415 | AG49: =INDEX('Rate Assumptions'!$A:$B,MATCH('Base Allocation'!AG$2,'Rate Assumptions'!$A:$A,0),2) -> 5634.5606 | AH49: =INDEX('Rate Assumptions'!$A:$B,MATCH('Base Allocation'!AH$2,'Rate Assumptions'!$A:$A,0),2) -> 5634.5606 | AI49: =AD49+SUMPRODUCT(Z49:AC49,AE49:AH49) -> 58492915
A50: Riverside | B50: 29578.89 | C50: 73.45 | D50: 0 | F50: 712.52 | G50: =B50-E50-F50 -> 28866.37 | H50: 30445.289 | I50: 82.07 | J50: 0 | K50: 34.91 | L50: 802.83 | M50: =H50-K50-L50 -> 29607.549 | N50: 29802.73 | O50: 145.31 | P50: 0 | Q50: 83 | R50: 850 | S50: =N50-Q50-R50 -> 28869.73 | T50: =IF((H50-B50)*(1/3)+(N50-H50)*(2/3) + N50>0,N50+(H50-B50)*(1/3)+(N50-H50)*(2/3),N50) -> 29663.157 | U50: =IF((I50-C50)*(1/3)+(O50-I50)*(2/3) + O50>0,O50+(I50-C50)*(1/3)+(O50-I50)*(2/3),O50) -> 190.34333 | V50: =IF((J50-D50)*(1/3)+(P50-J50)*(2/3) + P50>0,P50+(J50-D50)*(1/3)+(P50-J50)*(2/3),P50) -> 0 | W50: =IF((K50-E50)*(1/3)+(Q50-K50)*(2/3) + Q50>0,Q50+(K50-E50)*(1/3)+(Q50-K50)*(2/3),Q50) -> 126.69667 | X50: =IF((L50-F50)*(1/3)+(R50-L50)*(2/3) + R50>0,R50+(L50-F50)*(1/3)+(R50-L50)*(2/3),R50) -> 911.55 | Y50: =T50-W50-X50 -> 28624.91 | Z50: =AVERAGE(Y50,S50,M50) -> 29034.063 | AA50: =U50 -> 190.34333 | AB50: =V50 -> 0 | AC50: =SUM(W50:X50) -> 1038.2467 | AD50: 12810690 | AE50: =INDEX('Rate Assumptions'!$A:$B,MATCH('Base Allocation'!AE$2,'Rate Assumptions'!$A:$A,0),2) -> 3988.5862 | AF50: =INDEX('Rate Assumptions'!$A:$B,MATCH('Base Allocation'!AF$2,'Rate Assumptions'!$A:$A,0),2) -> 3456.4415 | AG50: =INDEX('Rate Assumptions'!$A:$B,MATCH('Base Allocation'!AG$2,'Rate Assumptions'!$A:$A,0),2) -> 5634.5606 | AH50: =INDEX('Rate Assumptions'!$A:$B,MATCH('Base Allocation'!AH$2,'Rate Assumptions'!$A:$A,0),2) -> 5634.5606 | AI50: =AD50+SUMPRODUCT(Z50:AC50,AE50:AH50) -> 1.3512353e+08
A51: San Bernardino | B51: 14114.1 | C51: 139.13 | D51: 0 | F51: 117.7 | G51: =B51-E51-F51 -> 13996.4 | H51: 15066.39 | I51: 162.56999 | J51: 75.200007 | L51: 229.32 | M51: =H51-K51-L51 -> 14837.07 | N51: 15138.77 | O51: 294.24 | P51: 46.34 | Q51: 0 | R51: 348.40757 | S51: =N51-Q51-R51 -> 14790.362 | T51: =IF((H51-B51)*(1/3)+(N51-H51)*(2/3) + N51>0,N51+(H51-B51)*(1/3)+(N51-H51)*(2/3),N51) -> 15504.453 | U51: =IF((I51-C51)*(1/3)+(O51-I51)*(2/3) + O51>0,O51+(I51-C51)*(1/3)+(O51-I51)*(2/3),O51) -> 389.83334 | V51: =IF((J51-D51)*(1/3)+(P51-J51)*(2/3) + P51>0,P51+(J51-D51)*(1/3)+(P51-J51)*(2/3),P51) -> 52.166664 | W51: =IF((K51-E51)*(1/3)+(Q51-K51)*(2/3) + Q51>0,Q51+(K51-E51)*(1/3)+(Q51-K51)*(2/3),Q51) -> 0 | X51: =IF((L51-F51)*(1/3)+(R51-L51)*(2/3) + R51>0,R51+(L51-F51)*(1/3)+(R51-L51)*(2/3),R51) -> 465.00595 | Y51: =T51-W51-X51 -> 15039.447 | Z51: =AVERAGE(Y51,S51,M51) -> 14888.96 | AA51: =U51 -> 389.83334 | AB51: =V51 -> 52.166664 | AC51: =SUM(W51:X51) -> 465.00595 | AD51: 8765209.6 | AE51: =INDEX('Rate Assumptions'!$A:$B,MATCH('Base Allocation'!AE$2,'Rate Assumptions'!$A:$A,0),2) -> 3988.5862 | AF51: =INDEX('Rate Assumptions'!$A:$B,MATCH('Base Allocation'!AF$2,'Rate Assumptions'!$A:$A,0),2) -> 3456.4415 | AG51: =INDEX('Rate Assumptions'!$A:$B,MATCH('Base Allocation'!AG$2,'Rate Assumptions'!$A:$A,0),2) -> 5634.5606 | AH51: =INDEX('Rate Assumptions'!$A:$B,MATCH('Base Allocation'!AH$2,'Rate Assumptions'!$A:$A,0),2) -> 5634.5606 | AI51: =AD51+SUMPRODUCT(Z51:AC51,AE51:AH51) -> 72412586
A52: San Diego | B52: 34927.69 | C52: 2061.91 | D52: 6532.08 | F52: 630.18 | G52: =B52-E52-F52 -> 34297.51 | H52: 35115.99 | I52: 2049.9 | J52: 6114.81 | L52: 864.16 | M52: =H52-K52-L52 -> 34251.83 | N52: 32509.53 | O52: 2049.9 | P52: 6114.81 | Q52: 0 | R52: 992.19 | S52: =N52-Q52-R52 -> 31517.34 | T52: =IF((H52-B52)*(1/3)+(N52-H52)*(2/3) + N52>0,N52+(H52-B52)*(1/3)+(N52-H52)*(2/3),N52) -> 30834.657 | U52: =IF((I52-C52)*(1/3)+(O52-I52)*(2/3) + O52>0,O52+(I52-C52)*(1/3)+(O52-I52)*(2/3),O52) -> 2045.8967 | V52: =IF((J52-D52)*(1/3)+(P52-J52)*(2/3) + P52>0,P52+(J52-D52)*(1/3)+(P52-J52)*(2/3),P52) -> 5975.72 | W52: =IF((K52-E52)*(1/3)+(Q52-K52)*(2/3) + Q52>0,Q52+(K52-E52)*(1/3)+(Q52-K52)*(2/3),Q52) -> 0 | X52: =IF((L52-F52)*(1/3)+(R52-L52)*(2/3) + R52>0,R52+(L52-F52)*(1/3)+(R52-L52)*(2/3),R52) -> 1155.5367 | Y52: =T52-W52-X52 -> 29679.12 | Z52: =AVERAGE(Y52,S52,M52) -> 31816.097 | AA52: =U52 -> 2045.8967 | AB52: =V52 -> 5975.72 | AC52: =SUM(W52:X52) -> 1155.5367 | AD52: 20901658 | AE52: =INDEX('Rate Assumptions'!$A:$B,MATCH('Base Allocation'!AE$2,'Rate Assumptions'!$A:$A,0),2) -> 3988.5862 | AF52: =INDEX('Rate Assumptions'!$A:$B,MATCH('Base Allocation'!AF$2,'Rate Assumptions'!$A:$A,0),2) -> 3456.4415 | AG52: =INDEX('Rate Assumptions'!$A:$B,MATCH('Base Allocation'!AG$2,'Rate Assumptions'!$A:$A,0),2) -> 5634.5606 | AH52: =INDEX('Rate Assumptions'!$A:$B,MATCH('Base Allocation'!AH$2,'Rate Assumptions'!$A:$A,0),2) -> 5634.5606 | AI52: =AD52+SUMPRODUCT(Z52:AC52,AE52:AH52) -> 1.9505592e+08
A53: San Francisco | B53: 14108.98 | C53: 1699.39 | D53: 4713.15 | E53: 3.59 | F53: 203.6 | G53: =B53-E53-F53 -> 13901.79 | H53: 16031.34 | I53: 1734.96 | J53: 4542.28 | K53: 7.68 | L53: 305.15 | M53: =H53-K53-L53 -> 15718.51 | N53: 16460.46 | O53: 1695.9583 | P53: 4177.63 | Q53: 19.91 | R53: 271.84 | S53: =N53-Q53-R53 -> 16168.71 | T53: =IF((H53-B53)*(1/3)+(N53-H53)*(2/3) + N53>0,N53+(H53-B53)*(1/3)+(N53-H53)*(2/3),N53) -> 17387.327 | U53: =IF((I53-C53)*(1/3)+(O53-I53)*(2/3) + O53>0,O53+(I53-C53)*(1/3)+(O53-I53)*(2/3),O53) -> 1681.8138 | V53: =IF((J53-D53)*(1/3)+(P53-J53)*(2/3) + P53>0,P53+(J53-D53)*(1/3)+(P53-J53)*(2/3),P53) -> 3877.5733 | W53: =IF((K53-E53)*(1/3)+(Q53-K53)*(2/3) + Q53>0,Q53+(K53-E53)*(1/3)+(Q53-K53)*(2/3),Q53) -> 29.426667 | X53: =IF((L53-F53)*(1/3)+(R53-L53)*(2/3) + R53>0,R53+(L53-F53)*(1/3)+(R53-L53)*(2/3),R53) -> 283.48333 | Y53: =T53-W53-X53 -> 17074.417 | Z53: =AVERAGE(Y53,S53,M53) -> 16320.546 | AA53: =U53 -> 1681.8138 | AB53: =V53 -> 3877.5733 | AC53: =SUM(W53:X53) -> 312.91 | AD53: 13653502 | AE53: =INDEX('Rate Assumptions'!$A:$B,MATCH('Base Allocation'!AE$2,'Rate Assumptions'!$A:$A,0),2) -> 3988.5862 | AF53: =INDEX('Rate Assumptions'!$A:$B,MATCH('Base Allocation'!AF$2,'Rate Assumptions'!$A:$A,0),2) -> 3456.4415 | AG53: =INDEX('Rate Assumptions'!$A:$B,MATCH('Base Allocation'!AG$2,'Rate Assumptions'!$A:$A,0),2) -> 5634.5606 | AH53: =INDEX('Rate Assumptions'!$A:$B,MATCH('Base Allocation'!AH$2,'Rate Assumptions'!$A:$A,0),2) -> 5634.5606 | AI53: =AD53+SUMPRODUCT(Z53:AC53,AE53:AH53) -> 1.0817403e+08
A54: San Joaquin Delta | B54: 13337.72 | C54: 175.49 | D54: 0 | F54: 425.5 | G54: =B54-E54-F54 -> 12912.22 | H54: 15729.64 | I54: 170.36 | J54: 0 | K54: 20.09 | L54: 481.3 | M54: =H54-K54-L54 -> 15228.25 | N54: 14732.93 | O54: 170.36 | P54: 0 | Q54: 13.44 | R54: 528.42 | S54: =N54-Q54-R54 -> 14191.07 | T54: =IF((H54-B54)*(1/3)+(N54-H54)*(2/3) + N54>0,N54+(H54-B54)*(1/3)+(N54-H54)*(2/3),N54) -> 14865.763 | U54: =IF((I54-C54)*(1/3)+(O54-I54)*(2/3) + O54>0,O54+(I54-C54)*(1/3)+(O54-I54)*(2/3),O54) -> 168.65 | V54: =IF((J54-D54)*(1/3)+(P54-J54)*(2/3) + P54>0,P54+(J54-D54)*(1/3)+(P54-J54)*(2/3),P54) -> 0 | W54: =IF((K54-E54)*(1/3)+(Q54-K54)*(2/3) + Q54>0,Q54+(K54-E54)*(1/3)+(Q54-K54)*(2/3),Q54) -> 15.703333 | X54: =IF((L54-F54)*(1/3)+(R54-L54)*(2/3) + R54>0,R54+(L54-F54)*(1/3)+(R54-L54)*(2/3),R54) -> 578.43333 | Y54: =T54-W54-X54 -> 14271.627 | Z54: =AVERAGE(Y54,S54,M54) -> 14563.649 | AA54: =U54 -> 168.65 | AB54: =V54 -> 0 | AC54: =SUM(W54:X54) -> 594.13667 | AD54: 6742470.1 | AE54: =INDEX('Rate Assumptions'!$A:$B,MATCH('Base Allocation'!AE$2,'Rate Assumptions'!$A:$A,0),2) -> 3988.5862 | AF54: =INDEX('Rate Assumptions'!$A:$B,MATCH('Base Allocation'!AF$2,'Rate Assumptions'!$A:$A,0),2) -> 3456.4415 | AG54: =INDEX('Rate Assumptions'!$A:$B,MATCH('Base Allocation'!AG$2,'Rate Assumptions'!$A:$A,0),2) -> 5634.5606 | AH54: =INDEX('Rate Assumptions'!$A:$B,MATCH('Base Allocation'!AH$2,'Rate Assumptions'!$A:$A,0),2) -> 5634.5606 | AI54: =AD54+SUMPRODUCT(Z54:AC54,AE54:AH54) -> 68761467
A55: San Jose | B55: 11234.88 | C55: 116.72 | D55: 0 | F55: 193.38 | G55: =B55-E55-F55 -> 11041.5 | H55: 11715.93 | I55: 197.11002 | J55: 0 | L55: 308.31 | M55: =H55-K55-L55 -> 11407.62 | N55: 12055.63 | O55: 213.42 | P55: 0 | Q55: 0 | R55: 262.19 | S55: =N55-Q55-R55 -> 11793.44 | T55: =IF((H55-B55)*(1/3)+(N55-H55)*(2/3) + N55>0,N55+(H55-B55)*(1/3)+(N55-H55)*(2/3),N55) -> 12442.447 | U55: =IF((I55-C55)*(1/3)+(O55-I55)*(2/3) + O55>0,O55+(I55-C55)*(1/3)+(O55-I55)*(2/3),O55) -> 251.08999 | V55: =IF((J55-D55)*(1/3)+(P55-J55)*(2/3) + P55>0,P55+(J55-D55)*(1/3)+(P55-J55)*(2/3),P55) -> 0 | W55: =IF((K55-E55)*(1/3)+(Q55-K55)*(2/3) + Q55>0,Q55+(K55-E55)*(1/3)+(Q55-K55)*(2/3),Q55) -> 0 | X55: =IF((L55-F55)*(1/3)+(R55-L55)*(2/3) + R55>0,R55+(L55-F55)*(1/3)+(R55-L55)*(2/3),R55) -> 269.75333 | Y55: =T55-W55-X55 -> 12172.693 | Z55: =AVERAGE(Y55,S55,M55) -> 11791.251 | AA55: =U55 -> 251.08999 | AB55: =V55 -> 0 | AC55: =SUM(W55:X55) -> 269.75333 | AD55: 8090961 | AE55: =INDEX('Rate Assumptions'!$A:$B,MATCH('Base Allocation'!AE$2,'Rate Assumptions'!$A:$A,0),2) -> 3988.5862 | AF55: =INDEX('Rate Assumptions'!$A:$B,MATCH('Base Allocation'!AF$2,'Rate Assumptions'!$A:$A,0),2) -> 3456.4415 | AG55: =INDEX('Rate Assumptions'!$A:$B,MATCH('Base Allocation'!AG$2,'Rate Assumptions'!$A:$A,0),2) -> 5634.5606 | AH55: =INDEX('Rate Assumptions'!$A:$B,MATCH('Base Allocation'!AH$2,'Rate Assumptions'!$A:$A,0),2) -> 5634.5606 | AI55: =AD55+SUMPRODUCT(Z55:AC55,AE55:AH55) -> 57509202
A56: San Luis Obispo | B56: 6739.42 | C56: 149.56 | D56: 239.43 | E56: 20.8 | F56: 562.09 | G56: =B56-E56-F56 -> 6156.53 | H56: 7933.11 | I56: 337.21 | J56: 161.71 | K56: 39.18 | L56: 769.85 | M56: =H56-K56-L56 -> 7124.08 | N56: 6801.35 | O56: 370.1 | P56: 217.1 | Q56: 110.22 | R56: 772.89 | S56: =N56-Q56-R56 -> 5918.24 | T56: =IF((H56-B56)*(1/3)+(N56-H56)*(2/3) + N56>0,N56+(H56-B56)*(1/3)+(N56-H56)*(2/3),N56) -> 6444.74 | U56: =IF((I56-C56)*(1/3)+(O56-I56)*(2/3) + O56>0,O56+(I56-C56)*(1/3)+(O56-I56)*(2/3),O56) -> 454.57667 | V56: =IF((J56-D56)*(1/3)+(P56-J56)*(2/3) + P56>0,P56+(J56-D56)*(1/3)+(P56-J56)*(2/3),P56) -> 228.12 | W56: =IF((K56-E56)*(1/3)+(Q56-K56)*(2/3) + Q56>0,Q56+(K56-E56)*(1/3)+(Q56-K56)*(2/3),Q56) -> 163.70667 | X56: =IF((L56-F56)*(1/3)+(R56-L56)*(2/3) + R56>0,R56+(L56-F56)*(1/3)+(R56-L56)*(2/3),R56) -> 844.17 | Y56: =T56-W56-X56 -> 5436.8633 | Z56: =AVERAGE(Y56,S56,M56) -> 6159.7278 | AA56: =U56 -> 454.57667 | AB56: =V56 -> 228.12 | AC56: =SUM(W56:X56) -> 1007.8767 | AD56: 5393974 | AE56: =INDEX('Rate Assumptions'!$A:$B,MATCH('Base Allocation'!AE$2,'Rate Assumptions'!$A:$A,0),2) -> 3988.5862 | AF56: =INDEX('Rate Assumptions'!$A:$B,MATCH('Base Allocation'!AF$2,'Rate Assumptions'!$A:$A,0),2) -> 3456.4415 | AG56: =INDEX('Rate Assumptions'!$A:$B,MATCH('Base Allocation'!AG$2,'Rate Assumptions'!$A:$A,0),2) -> 5634.5606 | AH56: =INDEX('Rate Assumptions'!$A:$B,MATCH('Base Allocation'!AH$2,'Rate Assumptions'!$A:$A,0),2) -> 5634.5606 | AI56: =AD56+SUMPRODUCT(Z56:AC56,AE56:AH56) -> 38498095
A57: San Mateo | B57: 16348.83 | C57: 57.88 | D57: 0 | E57: 4.6 | F57: 563.44 | G57: =B57-E57-F57 -> 15780.79 | H57: 15681 | I57: 41.48 | J57: 0 | L57: 847.58 | M57: =H57-K57-L57 -> 14833.42 | N57: 15232.02 | O57: 41.48 | P57: 0 | Q57: 3.26 | R57: 851.36 | S57: =N57-Q57-R57 -> 14377.4 | T57: =IF((H57-B57)*(1/3)+(N57-H57)*(2/3) + N57>0,N57+(H57-B57)*(1/3)+(N57-H57)*(2/3),N57) -> 14710.09 | U57: =IF((I57-C57)*(1/3)+(O57-I57)*(2/3) + O57>0,O57+(I57-C57)*(1/3)+(O57-I57)*(2/3),O57) -> 36.013333 | V57: =IF((J57-D57)*(1/3)+(P57-J57)*(2/3) + P57>0,P57+(J57-D57)*(1/3)+(P57-J57)*(2/3),P57) -> 0 | W57: =IF((K57-E57)*(1/3)+(Q57-K57)*(2/3) + Q57>0,Q57+(K57-E57)*(1/3)+(Q57-K57)*(2/3),Q57) -> 3.9 | X57: =IF((L57-F57)*(1/3)+(R57-L57)*(2/3) + R57>0,R57+(L57-F57)*(1/3)+(R57-L57)*(2/3),R57) -> 948.59333 | Y57: =T57-W57-X57 -> 13757.597 | Z57: =AVERAGE(Y57,S57,M57) -> 14322.806 | AA57: =U57 -> 36.013333 | AB57: =V57 -> 0 | AC57: =SUM(W57:X57) -> 952.49333 | AD57: 12136441 | AE57: =INDEX('Rate Assumptions'!$A:$B,MATCH('Base Allocation'!AE$2,'Rate Assumptions'!$A:$A,0),2) -> 3988.5862 | AF57: =INDEX('Rate Assumptions'!$A:$B,MATCH('Base Allocation'!AF$2,'Rate Assumptions'!$A:$A,0),2) -> 3456.4415 | AG57: =INDEX('Rate Assumptions'!$A:$B,MATCH('Base Allocation'!AG$2,'Rate Assumptions'!$A:$A,0),2) -> 5634.5606 | AH57: =INDEX('Rate Assumptions'!$A:$B,MATCH('Base Allocation'!AH$2,'Rate Assumptions'!$A:$A,0),2) -> 5634.5606 | AI57: =AD57+SUMPRODUCT(Z57:AC57,AE57:AH57) -> 74755545
A58: Santa Barbara | B58: 11805.67 | C58: 2.74 | D58: 571.46 | F58: 709.7 | G58: =B58-E58-F58 -> 11095.97 | H58: 11660.82 | I58: 294.71 | J58: 489.98 | K58: 3.25 | L58: 726.33 | M58: =H58-K58-L58 -> 10931.24 | N58: 11437.29 | O58: 698.44 | P58: 413.72 | Q58: 4.05 | R58: 357.25 | S58: =N58-Q58-R58 -> 11075.99 | T58: =IF((H58-B58)*(1/3)+(N58-H58)*(2/3) + N58>0,N58+(H58-B58)*(1/3)+(N58-H58)*(2/3),N58) -> 11239.987 | U58: =IF((I58-C58)*(1/3)+(O58-I58)*(2/3) + O58>0,O58+(I58-C58)*(1/3)+(O58-I58)*(2/3),O58) -> 1064.9167 | V58: =IF((J58-D58)*(1/3)+(P58-J58)*(2/3) + P58>0,P58+(J58-D58)*(1/3)+(P58-J58)*(2/3),P58) -> 335.72 | W58: =IF((K58-E58)*(1/3)+(Q58-K58)*(2/3) + Q58>0,Q58+(K58-E58)*(1/3)+(Q58-K58)*(2/3),Q58) -> 5.6666667 | X58: =IF((L58-F58)*(1/3)+(R58-L58)*(2/3) + R58>0,R58+(L58-F58)*(1/3)+(R58-L58)*(2/3),R58) -> 116.74 | Y58: =T58-W58-X58 -> 11117.58 | Z58: =AVERAGE(Y58,S58,M58) -> 11041.603 | AA58: =U58 -> 1064.9167 | AB58: =V58 -> 335.72 | AC58: =SUM(W58:X58) -> 122.40667 | AD58: 7416716.6 | AE58: =INDEX('Rate Assumptions'!$A:$B,MATCH('Base Allocation'!AE$2,'Rate Assumptions'!$A:$A,0),2) -> 3988.5862 | AF58: =INDEX('Rate Assumptions'!$A:$B,MATCH('Base Allocation'!AF$2,'Rate Assumptions'!$A:$A,0),2) -> 3456.4415 | AG58: =INDEX('Rate Assumptions'!$A:$B,MATCH('Base Allocation'!AG$2,'Rate Assumptions'!$A:$A,0),2) -> 5634.5606 | AH58: =INDEX('Rate Assumptions'!$A:$B,MATCH('Base Allocation'!AH$2,'Rate Assumptions'!$A:$A,0),2) -> 5634.5606 | AI58: =AD58+SUMPRODUCT(Z58:AC58,AE58:AH58) -> 57719268
A59: Santa Clarita | B59: 16098.7 | C59: 221.52 | D59: 123.86 | E59: 2.39 | F59: 675.23 | G59: =B59-E59-F59 -> 15421.08 | H59: 16308.519 | I59: 237.74 | J59: 167 | K59: 27.8 | L59: 983.67 | M59: =H59-K59-L59 -> 15297.049 | N59: 15732.13 | O59: 237.74 | P59: 167 | Q59: 22.73 | R59: 840.5 | S59: =N59-Q59-R59 -> 14868.9 | T59: =IF((H59-B59)*(1/3)+(N59-H59)*(2/3) + N59>0,N59+(H59-B59)*(1/3)+(N59-H59)*(2/3),N59) -> 15417.81 | U59: =IF((I59-C59)*(1/3)+(O59-I59)*(2/3) + O59>0,O59+(I59-C59)*(1/3)+(O59-I59)*(2/3),O59) -> 243.14667 | V59: =IF((J59-D59)*(1/3)+(P59-J59)*(2/3) + P59>0,P59+(J59-D59)*(1/3)+(P59-J59)*(2/3),P59) -> 181.38 | W59: =IF((K59-E59)*(1/3)+(Q59-K59)*(2/3) + Q59>0,Q59+(K59-E59)*(1/3)+(Q59-K59)*(2/3),Q59) -> 27.82 | X59: =IF((L59-F59)*(1/3)+(R59-L59)*(2/3) + R59>0,R59+(L59-F59)*(1/3)+(R59-L59)*(2/3),R59) -> 847.86667 | Y59: =T59-W59-X59 -> 14542.124 | Z59: =AVERAGE(Y59,S59,M59) -> 14902.691 | AA59: =U59 -> 243.14667 | AB59: =V59 -> 181.38 | AC59: =SUM(W59:X59) -> 875.68667 | AD59: 6742470.1 | AE59: =INDEX('Rate Assumptions'!$A:$B,MATCH('Base Allocation'!AE$2,'Rate Assumptions'!$A:$A,0),2) -> 3988.5862 | AF59: =INDEX('Rate Assumptions'!$A:$B,MATCH('Base Allocation'!AF$2,'Rate Assumptions'!$A:$A,0),2) -> 3456.4415 | AG59: =INDEX('Rate Assumptions'!$A:$B,MATCH('Base Allocation'!AG$2,'Rate Assumptions'!$A:$A,0),2) -> 5634.5606 | AH59: =INDEX('Rate Assumptions'!$A:$B,MATCH('Base Allocation'!AH$2,'Rate Assumptions'!$A:$A,0),2) -> 5634.5606 | AI59: =AD59+SUMPRODUCT(Z59:AC59,AE59:AH59) -> 72979666
A60: Santa Monica | B60: 22257.88 | C60: 584.5 | D60: 167.47 | F60: 247.18 | G60: =B60-E60-F60 -> 22010.7 | H60: 17871.4 | I60: 599.81 | J60: 157.57 | L60: 273.43 | M60: =H60-K60-L60 -> 17597.97 | N60: 19636.32 | O60: 622.78 | P60: 119.98 | Q60: 0 | R60: 263.9 | S60: =N60-Q60-R60 -> 19372.42 | T60: =IF((H60-B60)*(1/3)+(N60-H60)*(2/3) + N60>0,N60+(H60-B60)*(1/3)+(N60-H60)*(2/3),N60) -> 19350.773 | U60: =IF((I60-C60)*(1/3)+(O60-I60)*(2/3) + O60>0,O60+(I60-C60)*(1/3)+(O60-I60)*(2/3),O60) -> 643.19667 | V60: =IF((J60-D60)*(1/3)+(P60-J60)*(2/3) + P60>0,P60+(J60-D60)*(1/3)+(P60-J60)*(2/3),P60) -> 91.62 | W60: =IF((K60-E60)*(1/3)+(Q60-K60)*(2/3) + Q60>0,Q60+(K60-E60)*(1/3)+(Q60-K60)*(2/3),Q60) -> 0 | X60: =IF((L60-F60)*(1/3)+(R60-L60)*(2/3) + R60>0,R60+(L60-F60)*(1/3)+(R60-L60)*(2/3),R60) -> 266.29667 | Y60: =T60-W60-X60 -> 19084.477 | Z60: =AVERAGE(Y60,S60,M60) -> 18684.956 | AA60: =U60 -> 643.19667 | AB60: =V60 -> 91.62 | AC60: =SUM(W60:X60) -> 266.29667 | AD60: 8090964.1 | AE60: =INDEX('Rate Assumptions'!$A:$B,MATCH('Base Allocation'!AE$2,'Rate Assumptions'!$A:$A,0),2) -> 3988.5862 | AF60: =INDEX('Rate Assumptions'!$A:$B,MATCH('Base Allocation'!AF$2,'Rate Assumptions'!$A:$A,0),2) -> 3456.4415 | AG60: =INDEX('Rate Assumptions'!$A:$B,MATCH('Base Allocation'!AG$2,'Rate Assumptions'!$A:$A,0),2) -> 5634.5606 | AH60: =INDEX('Rate Assumptions'!$A:$B,MATCH('Base Allocation'!AH$2,'Rate Assumptions'!$A:$A,0),2) -> 5634.5606 | AI60: =AD60+SUMPRODUCT(Z60:AC60,AE60:AH60) -> 86857394
A61: Sequoias | B61: 9141.48 | C61: 392.17 | D61: 166.56 | F61: 335.52 | G61: =B61-E61-F61 -> 8805.96 | H61: 9685.2527 | I61: 472.08 | J61: 173.46 | L61: 443.21 | M61: =H61-K61-L61 -> 9242.0427 | N61: 9707.5 | O61: 344.8 | P61: 109.19 | Q61: 0 | R61: 465.38 | S61: =N61-Q61-R61 -> 9242.12 | T61: =IF((H61-B61)*(1/3)+(N61-H61)*(2/3) + N61>0,N61+(H61-B61)*(1/3)+(N61-H61)*(2/3),N61) -> 9903.5891 | U61: =IF((I61-C61)*(1/3)+(O61-I61)*(2/3) + O61>0,O61+(I61-C61)*(1/3)+(O61-I61)*(2/3),O61) -> 286.58333 | V61: =IF((J61-D61)*(1/3)+(P61-J61)*(2/3) + P61>0,P61+(J61-D61)*(1/3)+(P61-J61)*(2/3),P61) -> 68.643333 | W61: =IF((K61-E61)*(1/3)+(Q61-K61)*(2/3) + Q61>0,Q61+(K61-E61)*(1/3)+(Q61-K61)*(2/3),Q61) -> 0 | X61: =IF((L61-F61)*(1/3)+(R61-L61)*(2/3) + R61>0,R61+(L61-F61)*(1/3)+(R61-L61)*(2/3),R61) -> 516.05667 | Y61: =T61-W61-X61 -> 9387.5324 | Z61: =AVERAGE(Y61,S61,M61) -> 9290.565 | AA61: =U61 -> 286.58333 | AB61: =V61 -> 68.643333 | AC61: =SUM(W61:X61) -> 516.05667 | AD61: 8090964.1 | AE61: =INDEX('Rate Assumptions'!$A:$B,MATCH('Base Allocation'!AE$2,'Rate Assumptions'!$A:$A,0),2) -> 3988.5862 | AF61: =INDEX('Rate Assumptions'!$A:$B,MATCH('Base Allocation'!AF$2,'Rate Assumptions'!$A:$A,0),2) -> 3456.4415 | AG61: =INDEX('Rate Assumptions'!$A:$B,MATCH('Base Allocation'!AG$2,'Rate Assumptions'!$A:$A,0),2) -> 5634.5606 | AH61: =INDEX('Rate Assumptions'!$A:$B,MATCH('Base Allocation'!AH$2,'Rate Assumptions'!$A:$A,0),2) -> 5634.5606 | AI61: =AD61+SUMPRODUCT(Z61:AC61,AE61:AH61) -> 49432270
A62: Shasta Tehama | B62: 7040.1499 | C62: 148.21 | D62: 34.7 | F62: 627.39 | G62: =B62-E62-F62 -> 6412.7599 | H62: 6089.47 | I62: 135.31 | J62: 32.81 | L62: 701.11 | M62: =H62-K62-L62 -> 5388.36 | N62: 7053.81 | O62: 125.16 | P62: 19.22 | Q62: 0.86 | R62: 729.55357 | S62: =N62-Q62-R62 -> 6323.3964 | T62: =IF((H62-B62)*(1/3)+(N62-H62)*(2/3) + N62>0,N62+(H62-B62)*(1/3)+(N62-H62)*(2/3),N62) -> 7379.81 | U62: =IF((I62-C62)*(1/3)+(O62-I62)*(2/3) + O62>0,O62+(I62-C62)*(1/3)+(O62-I62)*(2/3),O62) -> 114.09333 | V62: =IF((J62-D62)*(1/3)+(P62-J62)*(2/3) + P62>0,P62+(J62-D62)*(1/3)+(P62-J62)*(2/3),P62) -> 9.53 | W62: =IF((K62-E62)*(1/3)+(Q62-K62)*(2/3) + Q62>0,Q62+(K62-E62)*(1/3)+(Q62-K62)*(2/3),Q62) -> 1.4333333 | X62: =IF((L62-F62)*(1/3)+(R62-L62)*(2/3) + R62>0,R62+(L62-F62)*(1/3)+(R62-L62)*(2/3),R62) -> 773.08928 | Y62: =T62-W62-X62 -> 6605.2874 | Z62: =AVERAGE(Y62,S62,M62) -> 6105.6813 | AA62: =U62 -> 114.09333 | AB62: =V62 -> 9.53 | AC62: =SUM(W62:X62) -> 774.52261 | AD62: 4045480 | AE62: =INDEX('Rate Assumptions'!$A:$B,MATCH('Base Allocation'!AE$2,'Rate Assumptions'!$A:$A,0),2) -> 3988.5862 | AF62: =INDEX('Rate Assumptions'!$A:$B,MATCH('Base Allocation'!AF$2,'Rate Assumptions'!$A:$A,0),2) -> 3456.4415 | AG62: =INDEX('Rate Assumptions'!$A:$B,MATCH('Base Allocation'!AG$2,'Rate Assumptions'!$A:$A,0),2) -> 5634.5606 | AH62: =INDEX('Rate Assumptions'!$A:$B,MATCH('Base Allocation'!AH$2,'Rate Assumptions'!$A:$A,0),2) -> 5634.5606 | AI62: =AD62+SUMPRODUCT(Z62:AC62,AE62:AH62) -> 33210665
A63: Sierra | B63: 12366.82 | C63: 274.82 | D63: 0 | F63: 214.52 | G63: =B63-E63-F63 -> 12152.3 | H63: 14916.48 | I63: 308.75 | J63: 0 | L63: 407.66 | M63: =H63-K63-L63 -> 14508.82 | N63: 12537.92 | O63: 345.66 | P63: 7.7 | Q63: 0 | R63: 423.71 | S63: =N63-Q63-R63 -> 12114.21 | T63: =IF((H63-B63)*(1/3)+(N63-H63)*(2/3) + N63>0,N63+(H63-B63)*(1/3)+(N63-H63)*(2/3),N63) -> 11802.1 | U63: =IF((I63-C63)*(1/3)+(O63-I63)*(2/3) + O63>0,O63+(I63-C63)*(1/3)+(O63-I63)*(2/3),O63) -> 381.57667 | V63: =IF((J63-D63)*(1/3)+(P63-J63)*(2/3) + P63>0,P63+(J63-D63)*(1/3)+(P63-J63)*(2/3),P63) -> 12.833333 | W63: =IF((K63-E63)*(1/3)+(Q63-K63)*(2/3) + Q63>0,Q63+(K63-E63)*(1/3)+(Q63-K63)*(2/3),Q63) -> 0 | X63: =IF((L63-F63)*(1/3)+(R63-L63)*(2/3) + R63>0,R63+(L63-F63)*(1/3)+(R63-L63)*(2/3),R63) -> 498.79 | Y63: =T63-W63-X63 -> 11303.31 | Z63: =AVERAGE(Y63,S63,M63) -> 12642.113 | AA63: =U63 -> 381.57667 | AB63: =V63 -> 12.833333 | AC63: =SUM(W63:X63) -> 498.79 | AD63: 6911032.8 | AE63: =INDEX('Rate Assumptions'!$A:$B,MATCH('Base Allocation'!AE$2,'Rate Assumptions'!$A:$A,0),2) -> 3988.5862 | AF63: =INDEX('Rate Assumptions'!$A:$B,MATCH('Base Allocation'!AF$2,'Rate Assumptions'!$A:$A,0),2) -> 3456.4415 | AG63: =INDEX('Rate Assumptions'!$A:$B,MATCH('Base Allocation'!AG$2,'Rate Assumptions'!$A:$A,0),2) -> 5634.5606 | AH63: =INDEX('Rate Assumptions'!$A:$B,MATCH('Base Allocation'!AH$2,'Rate Assumptions'!$A:$A,0),2) -> 5634.5606 | AI63: =AD63+SUMPRODUCT(Z63:AC63,AE63:AH63) -> 61536862
A64: Siskiyous | B64: 1935.64 | C64: 58.11 | D64: 505.14 | F64: 94.43 | G64: =B64-E64-F64 -> 1841.21 | H64: 1780.34 | I64: 80.46 | J64: 592.54 | L64: 88.75 | M64: =H64-K64-L64 -> 1691.59 | N64: 1421.93 | O64: 102.14 | P64: 679.83 | Q64: 0 | R64: 64.04 | S64: =N64-Q64-R64 -> 1357.89 | T64: =IF((H64-B64)*(1/3)+(N64-H64)*(2/3) + N64>0,N64+(H64-B64)*(1/3)+(N64-H64)*(2/3),N64) -> 1131.2233 | U64: =IF((I64-C64)*(1/3)+(O64-I64)*(2/3) + O64>0,O64+(I64-C64)*(1/3)+(O64-I64)*(2/3),O64) -> 124.04333 | V64: =IF((J64-D64)*(1/3)+(P64-J64)*(2/3) + P64>0,P64+(J64-D64)*(1/3)+(P64-J64)*(2/3),P64) -> 767.15667 | W64: =IF((K64-E64)*(1/3)+(Q64-K64)*(2/3) + Q64>0,Q64+(K64-E64)*(1/3)+(Q64-K64)*(2/3),Q64) -> 0 | X64: =IF((L64-F64)*(1/3)+(R64-L64)*(2/3) + R64>0,R64+(L64-F64)*(1/3)+(R64-L64)*(2/3),R64) -> 45.673333 | Y64: =T64-W64-X64 -> 1085.55 | Z64: =AVERAGE(Y64,S64,M64) -> 1378.3433 | AA64: =U64 -> 124.04333 | AB64: =V64 -> 767.15667 | AC64: =SUM(W64:X64) -> 45.673333 | AD64: 5332192.5 | AE64: =INDEX('Rate Assumptions'!$A:$B,MATCH('Base Allocation'!AE$2,'Rate Assumptions'!$A:$A,0),2) -> 3988.5862 | AF64: =INDEX('Rate Assumptions'!$A:$B,MATCH('Base Allocation'!AF$2,'Rate Assumptions'!$A:$A,0),2) -> 3456.4415 | AG64: =INDEX('Rate Assumptions'!$A:$B,MATCH('Base Allocation'!AG$2,'Rate Assumptions'!$A:$A,0),2) -> 5634.5606 | AH64: =INDEX('Rate Assumptions'!$A:$B,MATCH('Base Allocation'!AH$2,'Rate Assumptions'!$A:$A,0),2) -> 5634.5606 | AI64: =AD64+SUMPRODUCT(Z64:AC64,AE64:AH64) -> 15838522
A65: Solano | B65: 6447.52 | C65: 37.48 | D65: 0 | E65: 91.04 | F65: 266.87 | G65: =B65-E65-F65 -> 6089.61 | H65: 7907.27 | I65: 79.639884 | J65: 0 | K65: 74.87 | L65: 476.15 | M65: =H65-K65-L65 -> 7356.25 | N65: 6150.89 | O65: 79.639884 | P65: 0 | Q65: 81.77 | R65: 330.38 | S65: =N65-Q65-R65 -> 5738.74 | T65: =IF((H65-B65)*(1/3)+(N65-H65)*(2/3) + N65>0,N65+(H65-B65)*(1/3)+(N65-H65)*(2/3),N65) -> 5466.5533 | U65: =IF((I65-C65)*(1/3)+(O65-I65)*(2/3) + O65>0,O65+(I65-C65)*(1/3)+(O65-I65)*(2/3),O65) -> 93.693179 | V65: =IF((J65-D65)*(1/3)+(P65-J65)*(2/3) + P65>0,P65+(J65-D65)*(1/3)+(P65-J65)*(2/3),P65) -> 0 | W65: =IF((K65-E65)*(1/3)+(Q65-K65)*(2/3) + Q65>0,Q65+(K65-E65)*(1/3)+(Q65-K65)*(2/3),Q65) -> 80.98 | X65: =IF((L65-F65)*(1/3)+(R65-L65)*(2/3) + R65>0,R65+(L65-F65)*(1/3)+(R65-L65)*(2/3),R65) -> 302.96 | Y65: =T65-W65-X65 -> 5082.6133 | Z65: =AVERAGE(Y65,S65,M65) -> 6059.2011 | AA65: =U65 -> 93.693179 | AB65: =V65 -> 0 | AC65: =SUM(W65:X65) -> 383.94 | AD65: 6742469.1 | AE65: =INDEX('Rate Assumptions'!$A:$B,MATCH('Base Allocation'!AE$2,'Rate Assumptions'!$A:$A,0),2) -> 3988.5862 | AF65: =INDEX('Rate Assumptions'!$A:$B,MATCH('Base Allocation'!AF$2,'Rate Assumptions'!$A:$A,0),2) -> 3456.4415 | AG65: =INDEX('Rate Assumptions'!$A:$B,MATCH('Base Allocation'!AG$2,'Rate Assumptions'!$A:$A,0),2) -> 5634.5606 | AH65: =INDEX('Rate Assumptions'!$A:$B,MATCH('Base Allocation'!AH$2,'Rate Assumptions'!$A:$A,0),2) -> 5634.5606 | AI65: =AD65+SUMPRODUCT(Z65:AC65,AE65:AH65) -> 33397293
A66: Sonoma | B66: 13615.21 | C66: 2409.28 | D66: 567.7 | E66: 4.75 | F66: 418.19 | G66: =B66-E66-F66 -> 13192.27 | H66: 16040.47 | I66: 2860.3 | J66: 550.23 | K66: 2.59 | L66: 523.81 | M66: =H66-K66-L66 -> 15514.07 | N66: 16239 | O66: 2574 | P66: 638 | Q66: 10.1 | R66: 508.41 | S66: =N66-Q66-R66 -> 15720.49 | T66: =IF((H66-B66)*(1/3)+(N66-H66)*(2/3) + N66>0,N66+(H66-B66)*(1/3)+(N66-H66)*(2/3),N66) -> 17179.773 | U66: =IF((I66-C66)*(1/3)+(O66-I66)*(2/3) + O66>0,O66+(I66-C66)*(1/3)+(O66-I66)*(2/3),O66) -> 2533.4733 | V66: =IF((J66-D66)*(1/3)+(P66-J66)*(2/3) + P66>0,P66+(J66-D66)*(1/3)+(P66-J66)*(2/3),P66) -> 690.69 | W66: =IF((K66-E66)*(1/3)+(Q66-K66)*(2/3) + Q66>0,Q66+(K66-E66)*(1/3)+(Q66-K66)*(2/3),Q66) -> 14.386667 | X66: =IF((L66-F66)*(1/3)+(R66-L66)*(2/3) + R66>0,R66+(L66-F66)*(1/3)+(R66-L66)*(2/3),R66) -> 533.35 | Y66: =T66-W66-X66 -> 16632.037 | Z66: =AVERAGE(Y66,S66,M66) -> 15955.532 | AA66: =U66 -> 2533.4733 | AB66: =V66 -> 690.69 | AC66: =SUM(W66:X66) -> 547.73667 | AD66: 9776581.4 | AE66: =INDEX('Rate Assumptions'!$A:$B,MATCH('Base Allocation'!AE$2,'Rate Assumptions'!$A:$A,0),2) -> 3988.5862 | AF66: =INDEX('Rate Assumptions'!$A:$B,MATCH('Base Allocation'!AF$2,'Rate Assumptions'!$A:$A,0),2) -> 3456.4415 | AG66: =INDEX('Rate Assumptions'!$A:$B,MATCH('Base Allocation'!AG$2,'Rate Assumptions'!$A:$A,0),2) -> 5634.5606 | AH66: =INDEX('Rate Assumptions'!$A:$B,MATCH('Base Allocation'!AH$2,'Rate Assumptions'!$A:$A,0),2) -> 5634.5606 | AI66: =AD66+SUMPRODUCT(Z66:AC66,AE66:AH66) -> 89151389
A67: South Orange County | B67: 24706.37 | C67: 2243.0898 | D67: 415.98 | F67: 593.07 | G67: =B67-E67-F67 -> 24113.3 | H67: 23956.44 | I67: 2042.12 | J67: 977.03 | L67: 693.52 | M67: =H67-K67-L67 -> 23262.92 | N67: 23248.43 | O67: 2104.67 | P67: 1070.21 | Q67: 0 | R67: 750.08 | S67: =N67-Q67-R67 -> 22498.35 | T67: =IF((H67-B67)*(1/3)+(N67-H67)*(2/3) + N67>0,N67+(H67-B67)*(1/3)+(N67-H67)*(2/3),N67) -> 22526.447 | U67: =IF((I67-C67)*(1/3)+(O67-I67)*(2/3) + O67>0,O67+(I67-C67)*(1/3)+(O67-I67)*(2/3),O67) -> 2079.3801 | V67: =IF((J67-D67)*(1/3)+(P67-J67)*(2/3) + P67>0,P67+(J67-D67)*(1/3)+(P67-J67)*(2/3),P67) -> 1319.3467 | W67: =IF((K67-E67)*(1/3)+(Q67-K67)*(2/3) + Q67>0,Q67+(K67-E67)*(1/3)+(Q67-K67)*(2/3),Q67) -> 0 | X67: =IF((L67-F67)*(1/3)+(R67-L67)*(2/3) + R67>0,R67+(L67-F67)*(1/3)+(R67-L67)*(2/3),R67) -> 821.27 | Y67: =T67-W67-X67 -> 21705.177 | Z67: =AVERAGE(Y67,S67,M67) -> 22488.816 | AA67: =U67 -> 2079.3801 | AB67: =V67 -> 1319.3467 | AC67: =SUM(W67:X67) -> 821.27 | AD67: 9439458.2 | AE67: =INDEX('Rate Assumptions'!$A:$B,MATCH('Base Allocation'!AE$2,'Rate Assumptions'!$A:$A,0),2) -> 3988.5862 | AF67: =INDEX('Rate Assumptions'!$A:$B,MATCH('Base Allocation'!AF$2,'Rate Assumptions'!$A:$A,0),2) -> 3456.4415 | AG67: =INDEX('Rate Assumptions'!$A:$B,MATCH('Base Allocation'!AG$2,'Rate Assumptions'!$A:$A,0),2) -> 5634.5606 | AH67: =INDEX('Rate Assumptions'!$A:$B,MATCH('Base Allocation'!AH$2,'Rate Assumptions'!$A:$A,0),2) -> 5634.5606 | AI67: =AD67+SUMPRODUCT(Z67:AC67,AE67:AH67) -> 1.1838673e+08
A68: Southwestern | B68: 15625.79 | C68: 212.31 | D68: 38.97 | E68: 28.75 | F68: 154.74 | G68: =B68-E68-F68 -> 15442.3 | H68: 13083.04 | I68: 196.28 | J68: 38.4 | K68: 72.45 | L68: 232.12 | M68: =H68-K68-L68 -> 12778.47 | N68: 14539.77 | O68: 252.74 | P68: 21.97 | Q68: 62.87 | R68: 232.12 | S68: =N68-Q68-R68 -> 14244.78 | T68: =IF((H68-B68)*(1/3)+(N68-H68)*(2/3) + N68>0,N68+(H68-B68)*(1/3)+(N68-H68)*(2/3),N68) -> 14663.34 | U68: =IF((I68-C68)*(1/3)+(O68-I68)*(2/3) + O68>0,O68+(I68-C68)*(1/3)+(O68-I68)*(2/3),O68) -> 285.03667 | V68: =IF((J68-D68)*(1/3)+(P68-J68)*(2/3) + P68>0,P68+(J68-D68)*(1/3)+(P68-J68)*(2/3),P68) -> 10.826667 | W68: =IF((K68-E68)*(1/3)+(Q68-K68)*(2/3) + Q68>0,Q68+(K68-E68)*(1/3)+(Q68-K68)*(2/3),Q68) -> 71.05 | X68: =IF((L68-F68)*(1/3)+(R68-L68)*(2/3) + R68>0,R68+(L68-F68)*(1/3)+(R68-L68)*(2/3),R68) -> 257.91333 | Y68: =T68-W68-X68 -> 14334.377 | Z68: =AVERAGE(Y68,S68,M68) -> 13785.876 | AA68: =U68 -> 285.03667 | AB68: =V68 -> 10.826667 | AC68: =SUM(W68:X68) -> 328.96333 | AD68: 9439458.2 | AE68: =INDEX('Rate Assumptions'!$A:$B,MATCH('Base Allocation'!AE$2,'Rate Assumptions'!$A:$A,0),2) -> 3988.5862 | AF68: =INDEX('Rate Assumptions'!$A:$B,MATCH('Base Allocation'!AF$2,'Rate Assumptions'!$A:$A,0),2) -> 3456.4415 | AG68: =INDEX('Rate Assumptions'!$A:$B,MATCH('Base Allocation'!AG$2,'Rate Assumptions'!$A:$A,0),2) -> 5634.5606 | AH68: =INDEX('Rate Assumptions'!$A:$B,MATCH('Base Allocation'!AH$2,'Rate Assumptions'!$A:$A,0),2) -> 5634.5606 | AI68: =AD68+SUMPRODUCT(Z68:AC68,AE68:AH68) -> 67325391
A69: State Center | B69: 26963.42 | C69: 231 | D69: 129.6 | F69: 951.28 | G69: =B69-E69-F69 -> 26012.14 | H69: 31058.822 | I69: 310.1 | J69: 171.51 | L69: 1450.43 | M69: =H69-K69-L69 -> 29608.392 | N69: 29862.79 | O69: 310.1 | P69: 171.51 | Q69: 0 | R69: 1651.08 | S69: =N69-Q69-R69 -> 28211.71 | T69: =IF((H69-B69)*(1/3)+(N69-H69)*(2/3) + N69>0,N69+(H69-B69)*(1/3)+(N69-H69)*(2/3),N69) -> 30430.569 | U69: =IF((I69-C69)*(1/3)+(O69-I69)*(2/3) + O69>0,O69+(I69-C69)*(1/3)+(O69-I69)*(2/3),O69) -> 336.46667 | V69: =IF((J69-D69)*(1/3)+(P69-J69)*(2/3) + P69>0,P69+(J69-D69)*(1/3)+(P69-J69)*(2/3),P69) -> 185.48 | W69: =IF((K69-E69)*(1/3)+(Q69-K69)*(2/3) + Q69>0,Q69+(K69-E69)*(1/3)+(Q69-K69)*(2/3),Q69) -> 0 | X69: =IF((L69-F69)*(1/3)+(R69-L69)*(2/3) + R69>0,R69+(L69-F69)*(1/3)+(R69-L69)*(2/3),R69) -> 1951.23 | Y69: =T69-W69-X69 -> 28479.339 | Z69: =AVERAGE(Y69,S69,M69) -> 28766.48 | AA69: =U69 -> 336.46667 | AB69: =V69 -> 185.48 | AC69: =SUM(W69:X69) -> 1951.23 | AD69: 15507678 | AE69: =INDEX('Rate Assumptions'!$A:$B,MATCH('Base Allocation'!AE$2,'Rate Assumptions'!$A:$A,0),2) -> 3988.5862 | AF69: =INDEX('Rate Assumptions'!$A:$B,MATCH('Base Allocation'!AF$2,'Rate Assumptions'!$A:$A,0),2) -> 3456.4415 | AG69: =INDEX('Rate Assumptions'!$A:$B,MATCH('Base Allocation'!AG$2,'Rate Assumptions'!$A:$A,0),2) -> 5634.5606 | AH69: =INDEX('Rate Assumptions'!$A:$B,MATCH('Base Allocation'!AH$2,'Rate Assumptions'!$A:$A,0),2) -> 5634.5606 | AI69: =AD69+SUMPRODUCT(Z69:AC69,AE69:AH69) -> 1.4344766e+08
A70: Ventura | B70: 25334.64 | C70: 72.23 | D70: 0 | F70: 592.75 | G70: =B70-E70-F70 -> 24741.89 | H70: 26548.328 | I70: 116.97 | J70: 1.69 | L70: 749.34 | M70: =H70-K70-L70 -> 25798.988 | N70: 24971.89 | O70: 113.95 | P70: 3.65 | Q70: 4.76 | R70: 1568.5 | S70: =N70-Q70-R70 -> 23398.63 | T70: =IF((H70-B70)*(1/3)+(N70-H70)*(2/3) + N70>0,N70+(H70-B70)*(1/3)+(N70-H70)*(2/3),N70) -> 24325.494 | U70: =IF((I70-C70)*(1/3)+(O70-I70)*(2/3) + O70>0,O70+(I70-C70)*(1/3)+(O70-I70)*(2/3),O70) -> 126.85 | V70: =IF((J70-D70)*(1/3)+(P70-J70)*(2/3) + P70>0,P70+(J70-D70)*(1/3)+(P70-J70)*(2/3),P70) -> 5.52 | W70: =IF((K70-E70)*(1/3)+(Q70-K70)*(2/3) + Q70>0,Q70+(K70-E70)*(1/3)+(Q70-K70)*(2/3),Q70) -> 7.9333333 | X70: =IF((L70-F70)*(1/3)+(R70-L70)*(2/3) + R70>0,R70+(L70-F70)*(1/3)+(R70-L70)*(2/3),R70) -> 2166.8033 | Y70: =T70-W70-X70 -> 22150.757 | Z70: =AVERAGE(Y70,S70,M70) -> 23782.792 | AA70: =U70 -> 126.85 | AB70: =V70 -> 5.52 | AC70: =SUM(W70:X70) -> 2174.7367 | AD70: 13484938 | AE70: =INDEX('Rate Assumptions'!$A:$B,MATCH('Base Allocation'!AE$2,'Rate Assumptions'!$A:$A,0),2) -> 3988.5862 | AF70: =INDEX('Rate Assumptions'!$A:$B,MATCH('Base Allocation'!AF$2,'Rate Assumptions'!$A:$A,0),2) -> 3456.4415 | AG70: =INDEX('Rate Assumptions'!$A:$B,MATCH('Base Allocation'!AG$2,'Rate Assumptions'!$A:$A,0),2) -> 5634.5606 | AH70: =INDEX('Rate Assumptions'!$A:$B,MATCH('Base Allocation'!AH$2,'Rate Assumptions'!$A:$A,0),2) -> 5634.5606 | AI70: =AD70+SUMPRODUCT(Z70:AC70,AE70:AH70) -> 1.2106789e+08
A71: Victor Valley | B71: 9420.2099 | C71: 54.72 | D71: 0 | F71: 994.72 | G71: =B71-E71-F71 -> 8425.4899 | H71: 9561.0414 | I71: 79.12 | J71: 0 | L71: 560.21 | M71: =H71-K71-L71 -> 9000.8314 | N71: 9596.02 | O71: 57.68 | P71: 0 | Q71: 0 | R71: 372.01 | S71: =N71-Q71-R71 -> 9224.01 | T71: =IF((H71-B71)*(1/3)+(N71-H71)*(2/3) + N71>0,N71+(H71-B71)*(1/3)+(N71-H71)*(2/3),N71) -> 9666.2829 | U71: =IF((I71-C71)*(1/3)+(O71-I71)*(2/3) + O71>0,O71+(I71-C71)*(1/3)+(O71-I71)*(2/3),O71) -> 51.52 | V71: =IF((J71-D71)*(1/3)+(P71-J71)*(2/3) + P71>0,P71+(J71-D71)*(1/3)+(P71-J71)*(2/3),P71) -> 0 | W71: =IF((K71-E71)*(1/3)+(Q71-K71)*(2/3) + Q71>0,Q71+(K71-E71)*(1/3)+(Q71-K71)*(2/3),Q71) -> 0 | X71: =IF((L71-F71)*(1/3)+(R71-L71)*(2/3) + R71>0,R71+(L71-F71)*(1/3)+(R71-L71)*(2/3),R71) -> 101.70667 | Y71: =T71-W71-X71 -> 9564.5762 | Z71: =AVERAGE(Y71,S71,M71) -> 9263.1392 | AA71: =U71 -> 51.52 | AB71: =V71 -> 0 | AC71: =SUM(W71:X71) -> 101.70667 | AD71: 4045480 | AE71: =INDEX('Rate Assumptions'!$A:$B,MATCH('Base Allocation'!AE$2,'Rate Assumptions'!$A:$A,0),2) -> 3988.5862 | AF71: =INDEX('Rate Assumptions'!$A:$B,MATCH('Base Allocation'!AF$2,'Rate Assumptions'!$A:$A,0),2) -> 3456.4415 | AG71: =INDEX('Rate Assumptions'!$A:$B,MATCH('Base Allocation'!AG$2,'Rate Assumptions'!$A:$A,0),2) -> 5634.5606 | AH71: =INDEX('Rate Assumptions'!$A:$B,MATCH('Base Allocation'!AH$2,'Rate Assumptions'!$A:$A,0),2) -> 5634.5606 | AI71: =AD71+SUMPRODUCT(Z71:AC71,AE71:AH71) -> 41743457
A72: West Hills | B72: 5148.6799 | C72: 351.55 | D72: 0 | F72: 340.41 | G72: =B72-E72-F72 -> 4808.2699 | H72: 5384.0108 | I72: 363.35 | J72: 0 | K72: 44.49 | L72: 512.37 | M72: =H72-K72-L72 -> 4827.1508 | N72: 5791.4 | O72: 319.88 | P72: 0 | Q72: 148.04 | R72: 316.95987 | S72: =N72-Q72-R72 -> 5326.4001 | T72: =IF((H72-B72)*(1/3)+(N72-H72)*(2/3) + N72>0,N72+(H72-B72)*(1/3)+(N72-H72)*(2/3),N72) -> 6141.4364 | U72: =IF((I72-C72)*(1/3)+(O72-I72)*(2/3) + O72>0,O72+(I72-C72)*(1/3)+(O72-I72)*(2/3),O72) -> 294.83333 | V72: =IF((J72-D72)*(1/3)+(P72-J72)*(2/3) + P72>0,P72+(J72-D72)*(1/3)+(P72-J72)*(2/3),P72) -> 0 | W72: =IF((K72-E72)*(1/3)+(Q72-K72)*(2/3) + Q72>0,Q72+(K72-E72)*(1/3)+(Q72-K72)*(2/3),Q72) -> 231.90333 | X72: =IF((L72-F72)*(1/3)+(R72-L72)*(2/3) + R72>0,R72+(L72-F72)*(1/3)+(R72-L72)*(2/3),R72) -> 244.00646 | Y72: =T72-W72-X72 -> 5665.5266 | Z72: =AVERAGE(Y72,S72,M72) -> 5273.0259 | AA72: =U72 -> 294.83333 | AB72: =V72 -> 0 | AC72: =SUM(W72:X72) -> 475.90979 | AD72: 8428084.3 | AE72: =INDEX('Rate Assumptions'!$A:$B,MATCH('Base Allocation'!AE$2,'Rate Assumptions'!$A:$A,0),2) -> 3988.5862 | AF72: =INDEX('Rate Assumptions'!$A:$B,MATCH('Base Allocation'!AF$2,'Rate Assumptions'!$A:$A,0),2) -> 3456.4415 | AG72: =INDEX('Rate Assumptions'!$A:$B,MATCH('Base Allocation'!AG$2,'Rate Assumptions'!$A:$A,0),2) -> 5634.5606 | AH72: =INDEX('Rate Assumptions'!$A:$B,MATCH('Base Allocation'!AH$2,'Rate Assumptions'!$A:$A,0),2) -> 5634.5606 | AI72: =AD72+SUMPRODUCT(Z72:AC72,AE72:AH72) -> 33160619
A73: West Kern | B73: 2609.5801 | C73: 31.34 | D73: 0 | E73: 58.7 | F73: 17.57 | G73: =B73-E73-F73 -> 2533.3101 | H73: 2827.0942 | I73: 0.42 | J73: 0 | K73: 44.04 | L73: 17.42 | M73: =H73-K73-L73 -> 2765.6342 | N73: 2909.06 | O73: 0 | P73: 0 | Q73: 50.127583 | R73: 0 | S73: =N73-Q73-R73 -> 2858.9324 | T73: =IF((H73-B73)*(1/3)+(N73-H73)*(2/3) + N73>0,N73+(H73-B73)*(1/3)+(N73-H73)*(2/3),N73) -> 3036.2086 | U73: =IF((I73-C73)*(1/3)+(O73-I73)*(2/3) + O73>0,O73+(I73-C73)*(1/3)+(O73-I73)*(2/3),O73) -> 0 | V73: =IF((J73-D73)*(1/3)+(P73-J73)*(2/3) + P73>0,P73+(J73-D73)*(1/3)+(P73-J73)*(2/3),P73) -> 0 | W73: =IF((K73-E73)*(1/3)+(Q73-K73)*(2/3) + Q73>0,Q73+(K73-E73)*(1/3)+(Q73-K73)*(2/3),Q73) -> 49.299305 | X73: =IF((L73-F73)*(1/3)+(R73-L73)*(2/3) + R73>0,R73+(L73-F73)*(1/3)+(R73-L73)*(2/3),R73) -> 0 | Y73: =T73-W73-X73 -> 2986.9093 | Z73: =AVERAGE(Y73,S73,M73) -> 2870.492 | AA73: =U73 -> 0 | AB73: =V73 -> 0 | AC73: =SUM(W73:X73) -> 49.299305 | AD73: 5332192.5 | AE73: =INDEX('Rate Assumptions'!$A:$B,MATCH('Base Allocation'!AE$2,'Rate Assumptions'!$A:$A,0),2) -> 3988.5862 | AF73: =INDEX('Rate Assumptions'!$A:$B,MATCH('Base Allocation'!AF$2,'Rate Assumptions'!$A:$A,0),2) -> 3456.4415 | AG73: =INDEX('Rate Assumptions'!$A:$B,MATCH('Base Allocation'!AG$2,'Rate Assumptions'!$A:$A,0),2) -> 5634.5606 | AH73: =INDEX('Rate Assumptions'!$A:$B,MATCH('Base Allocation'!AH$2,'Rate Assumptions'!$A:$A,0),2) -> 5634.5606 | AI73: =AD73+SUMPRODUCT(Z73:AC73,AE73:AH73) -> 17059177
A74: West Valley-Mission2 | B74: 11784.29 | C74: 1030.44 | D74: 0 | F74: 293.69 | G74: =B74-E74-F74 -> 11490.6 | H74: 11473.35 | I74: 1198.99 | J74: 0 | K74: 0.87 | L74: 497.63 | M74: =H74-K74-L74 -> 10974.85 | N74: 10022.19 | O74: 1198.99 | P74: 3.8018211 | Q74: 0 | R74: 410.43 | S74: =N74-Q74-R74 -> 9611.76 | T74: =IF((H74-B74)*(1/3)+(N74-H74)*(2/3) + N74>0,N74+(H74-B74)*(1/3)+(N74-H74)*(2/3),N74) -> 8951.1033 | U74: =IF((I74-C74)*(1/3)+(O74-I74)*(2/3) + O74>0,O74+(I74-C74)*(1/3)+(O74-I74)*(2/3),O74) -> 1255.1733 | V74: =IF((J74-D74)*(1/3)+(P74-J74)*(2/3) + P74>0,P74+(J74-D74)*(1/3)+(P74-J74)*(2/3),P74) -> 6.3363685 | W74: =IF((K74-E74)*(1/3)+(Q74-K74)*(2/3) + Q74>0,Q74+(K74-E74)*(1/3)+(Q74-K74)*(2/3),Q74) -> 0 | X74: =IF((L74-F74)*(1/3)+(R74-L74)*(2/3) + R74>0,R74+(L74-F74)*(1/3)+(R74-L74)*(2/3),R74) -> 420.27667 | Y74: =T74-W74-X74 -> 8530.8267 | Z74: =AVERAGE(Y74,S74,M74) -> 9705.8122 | AA74: =U74 -> 1255.1733 | AB74: =V74 -> 6.3363685 | AC74: =SUM(W74:X74) -> 420.27667 | AD74: 8090961 | AE74: =INDEX('Rate Assumptions'!$A:$B,MATCH('Base Allocation'!AE$2,'Rate Assumptions'!$A:$A,0),2) -> 3988.5862 | AF74: =INDEX('Rate Assumptions'!$A:$B,MATCH('Base Allocation'!AF$2,'Rate Assumptions'!$A:$A,0),2) -> 3456.4415 | AG74: =INDEX('Rate Assumptions'!$A:$B,MATCH('Base Allocation'!AG$2,'Rate Assumptions'!$A:$A,0),2) -> 5634.5606 | AH74: =INDEX('Rate Assumptions'!$A:$B,MATCH('Base Allocation'!AH$2,'Rate Assumptions'!$A:$A,0),2) -> 5634.5606 | AI74: =AD74+SUMPRODUCT(Z74:AC74,AE74:AH74) -> 53545640
A75: Yosemite | B75: 15038.76 | C75: 203.33 | D75: 186.56 | E75: 32.37 | F75: 209.8 | G75: =B75-E75-F75 -> 14796.59 | H75: 16104.27 | I75: 238.45011 | J75: 233.61 | K75: 76.53 | L75: 282.12 | M75: =H75-K75-L75 -> 15745.62 | N75: 15515.44 | O75: 275.23 | P75: 256.14 | Q75: 89.13 | R75: 313.32 | S75: =N75-Q75-R75 -> 15112.99 | T75: =IF((H75-B75)*(1/3)+(N75-H75)*(2/3) + N75>0,N75+(H75-B75)*(1/3)+(N75-H75)*(2/3),N75) -> 15478.057 | U75: =IF((I75-C75)*(1/3)+(O75-I75)*(2/3) + O75>0,O75+(I75-C75)*(1/3)+(O75-I75)*(2/3),O75) -> 311.45663 | V75: =IF((J75-D75)*(1/3)+(P75-J75)*(2/3) + P75>0,P75+(J75-D75)*(1/3)+(P75-J75)*(2/3),P75) -> 286.84333 | W75: =IF((K75-E75)*(1/3)+(Q75-K75)*(2/3) + Q75>0,Q75+(K75-E75)*(1/3)+(Q75-K75)*(2/3),Q75) -> 112.25 | X75: =IF((L75-F75)*(1/3)+(R75-L75)*(2/3) + R75>0,R75+(L75-F75)*(1/3)+(R75-L75)*(2/3),R75) -> 358.22667 | Y75: =T75-W75-X75 -> 15007.58 | Z75: =AVERAGE(Y75,S75,M75) -> 15288.73 | AA75: =U75 -> 311.45663 | AB75: =V75 -> 286.84333 | AC75: =SUM(W75:X75) -> 470.47667 | AD75: 8765209.6 | AE75: =INDEX('Rate Assumptions'!$A:$B,MATCH('Base Allocation'!AE$2,'Rate Assumptions'!$A:$A,0),2) -> 3988.5862 | AF75: =INDEX('Rate Assumptions'!$A:$B,MATCH('Base Allocation'!AF$2,'Rate Assumptions'!$A:$A,0),2) -> 3456.4415 | AG75: =INDEX('Rate Assumptions'!$A:$B,MATCH('Base Allocation'!AG$2,'Rate Assumptions'!$A:$A,0),2) -> 5634.5606 | AH75: =INDEX('Rate Assumptions'!$A:$B,MATCH('Base Allocation'!AH$2,'Rate Assumptions'!$A:$A,0),2) -> 5634.5606 | AI75: =AD75+SUMPRODUCT(Z75:AC75,AE75:AH75) -> 75089324
A76: Yuba | B76: 7446.38 | C76: 179.63 | D76: 0 | F76: 339.94 | G76: =B76-E76-F76 -> 7106.44 | H76: 7424.91 | I76: 197.27 | J76: 3.82 | L76: 397.51 | M76: =H76-K76-L76 -> 7027.4 | N76: 7477.98 | O76: 145.92 | P76: 2.1 | Q76: 0 | R76: 211.55792 | S76: =N76-Q76-R76 -> 7266.4221 | T76: =IF((H76-B76)*(1/3)+(N76-H76)*(2/3) + N76>0,N76+(H76-B76)*(1/3)+(N76-H76)*(2/3),N76) -> 7506.2033 | U76: =IF((I76-C76)*(1/3)+(O76-I76)*(2/3) + O76>0,O76+(I76-C76)*(1/3)+(O76-I76)*(2/3),O76) -> 117.56667 | V76: =IF((J76-D76)*(1/3)+(P76-J76)*(2/3) + P76>0,P76+(J76-D76)*(1/3)+(P76-J76)*(2/3),P76) -> 2.2266667 | W76: =IF((K76-E76)*(1/3)+(Q76-K76)*(2/3) + Q76>0,Q76+(K76-E76)*(1/3)+(Q76-K76)*(2/3),Q76) -> 0 | X76: =IF((L76-F76)*(1/3)+(R76-L76)*(2/3) + R76>0,R76+(L76-F76)*(1/3)+(R76-L76)*(2/3),R76) -> 106.77986 | Y76: =T76-W76-X76 -> 7399.4235 | Z76: =AVERAGE(Y76,S76,M76) -> 7231.0819 | AA76: =U76 -> 117.56667 | AB76: =V76 -> 2.2266667 | AC76: =SUM(W76:X76) -> 106.77986 | AD76: 10113702 | AE76: =INDEX('Rate Assumptions'!$A:$B,MATCH('Base Allocation'!AE$2,'Rate Assumptions'!$A:$A,0),2) -> 3988.5862 | AF76: =INDEX('Rate Assumptions'!$A:$B,MATCH('Base Allocation'!AF$2,'Rate Assumptions'!$A:$A,0),2) -> 3456.4415 | AG76: =INDEX('Rate Assumptions'!$A:$B,MATCH('Base Allocation'!AG$2,'Rate Assumptions'!$A:$A,0),2) -> 5634.5606 | AH76: =INDEX('Rate Assumptions'!$A:$B,MATCH('Base Allocation'!AH$2,'Rate Assumptions'!$A:$A,0),2) -> 5634.5606 | AI76: =AD76+SUMPRODUCT(Z76:AC76,AE76:AH76) -> 39976061
A77: zzzTotals | B77: =SUM(B5:B76) -> 1055591.8 | C77: =SUM(C5:C76) -> 29256.239 | D77: =SUM(D5:D76) -> 39472.12 | E77: =SUM(E5:E76) -> 2880.32 | F77: =SUM(F5:F76) -> 30057.92 | G77: =SUM(G5:G76) -> 1022653.6 | H77: =SUM(H5:H76) -> 1054297.2 | I77: =SUM(I5:I76) -> 31162.51 | ... AD77: =SUM(AD5:AD76) -> 6.2872988e+08 | AI77: =SUM(AI5:AI76) -> 5.2045806e+09
A79: 2017-18 rate | W79: 5312.6989 | X79: 5312.6989 | AA79: 3259 | AB79: 5312.6989 | AC79: 5312.6989
W80: =W81*W77 -> 28276764 | X80: =X81*X77 -> 2.0211943e+08 | AA80: =AA77*AA81 -> 1.2140383e+08 | AB80: =AB77*AB81 -> 2.2221452e+08 | AC80: =AC77*AC81 -> 2.3039619e+08
A81: 2019-20 rate | W81: =W79*1.0271*1.0326 -> 5634.5606 | X81: =X79*1.0271*1.0326 -> 5634.5606 | AA81: =AA79*1.0271*1.0326 -> 3456.4415 | AB81: =AB79*1.0271*1.0326 -> 5634.5606 | AC81: =AC79*1.0271*1.0326 -> 5634.5606

Sheet Supplemental Allocation
B1: 2016-17 | E1: 2017-18 | H1: 2018-19 | K1: 2019-20 Projection | N1: Rates
B2: Pell Grant Recipients Totals | C2: AB540 Headcount | D2: California Promise Grant Recipients Totals | E2: Pell Grant Recipients Totals | F2: AB540 Headcount | G2: California Promise Grant Recipients Totals | H2: Pell Grant Recipients Totals | I2: AB540 Headcount | J2: California Promise Grant Recipients Totals | K2: Pell Grant Recipients Totals | L2: AB540 Headcount | M2: California Promise Grant Recipients Totals | N2: Pell Grant Recipients | O2: AB 540 Students | P2: Promise Grant Recipients | Q2: Supplemental Allocation
A3: District
A4: Allan Hancock | B4: 2927 | C4: 855 | D4: 9027 | E4: 2815 | F4: 766 | G4: 8840 | H4: ? | K4: =E4+(E4-B4) -> 2703 | L4: =F4+(F4-C4) -> 677 | M4: =G4+(G4-D4) -> 8653 | N4: =INDEX('Rate Assumptions'!$A:$B,MATCH(N$2,'Rate Assumptions'!$A:$A,0),2) -> 929.5688 | O4: =INDEX('Rate Assumptions'!$A:$B,MATCH(O$2,'Rate Assumptions'!$A:$A,0),2) -> 929.5688 | P4: =INDEX('Rate Assumptions'!$A:$B,MATCH(P$2,'Rate Assumptions'!$A:$A,0),2) -> 929.5688 | Q4: =SUMPRODUCT(K4:M4,N4:P4) -> 11185501
A5: Antelope | B5: 7779 | C5: 510 | D5: 13873 | E5: 7896 | F5: 515 | G5: 13978 | K5: =E5+(E5-B5) -> 8013 | L5: =F5+(F5-C5) -> 520 | M5: =G5+(G5-D5) -> 14083 | N5: =INDEX('Rate Assumptions'!$A:$B,MATCH(N$2,'Rate Assumptions'!$A:$A,0),2) -> 929.5688 | O5: =INDEX('Rate Assumptions'!$A:$B,MATCH(O$2,'Rate Assumptions'!$A:$A,0),2) -> 929.5688 | P5: =INDEX('Rate Assumptions'!$A:$B,MATCH(P$2,'Rate Assumptions'!$A:$A,0),2) -> 929.5688 | Q5: =SUMPRODUCT(K5:M5,N5:P5) -> 21023128
A6: Barstow | B6: 2196 | C6: 59 | D6: 3580 | E6: 2130 | F6: 68 | G6: 3333 | K6: =E6+(E6-B6) -> 2064 | L6: =F6+(F6-C6) -> 77 | M6: =G6+(G6-D6) -> 3086 | N6: =INDEX('Rate Assumptions'!$A:$B,MATCH(N$2,'Rate Assumptions'!$A:$A,0),2) -> 929.5688 | O6: =INDEX('Rate Assumptions'!$A:$B,MATCH(O$2,'Rate Assumptions'!$A:$A,0),2) -> 929.5688 | P6: =INDEX('Rate Assumptions'!$A:$B,MATCH(P$2,'Rate Assumptions'!$A:$A,0),2) -> 929.5688 | Q6: =SUMPRODUCT(K6:M6,N6:P6) -> 4858856.1
A7: Butte | B7: 5586 | C7: 305 | D7: 8577 | E7: 5206 | F7: 303 | G7: 8205 | K7: =E7+(E7-B7) -> 4826 | L7: =F7+(F7-C7) -> 301 | M7: =G7+(G7-D7) -> 7833 | N7: =INDEX('Rate Assumptions'!$A:$B,MATCH(N$2,'Rate Assumptions'!$A:$A,0),2) -> 929.5688 | O7: =INDEX('Rate Assumptions'!$A:$B,MATCH(O$2,'Rate Assumptions'!$A:$A,0),2) -> 929.5688 | P7: =INDEX('Rate Assumptions'!$A:$B,MATCH(P$2,'Rate Assumptions'!$A:$A,0),2) -> 929.5688 | Q7: =SUMPRODUCT(K7:M7,N7:P7) -> 12047212
A8: Cabrillo | B8: 3086 | C8: 521 | D8: 7142 | E8: 2886 | F8: 513 | G8: 6737 | K8: =E8+(E8-B8) -> 2686 | L8: =F8+(F8-C8) -> 505 | M8: =G8+(G8-D8) -> 6332 | N8: =INDEX('Rate Assumptions'!$A:$B,MATCH(N$2,'Rate Assumptions'!$A:$A,0),2) -> 929.5688 | O8: =INDEX('Rate Assumptions'!$A:$B,MATCH(O$2,'Rate Assumptions'!$A:$A,0),2) -> 929.5688 | P8: =INDEX('Rate Assumptions'!$A:$B,MATCH(P$2,'Rate Assumptions'!$A:$A,0),2) -> 929.5688 | Q8: =SUMPRODUCT(K8:M8,N8:P8) -> 8852283.7
A9: Cerritos | B9: 10754 | C9: 1610 | D9: 18971 | E9: 10455 | F9: 1586 | G9: 18362 | K9: =E9+(E9-B9) -> 10156 | L9: =F9+(F9-C9) -> 1562 | M9: =G9+(G9-D9) -> 17753 | N9: =INDEX('Rate Assumptions'!$A:$B,MATCH(N$2,'Rate Assumptions'!$A:$A,0),2) -> 929.5688 | O9: =INDEX('Rate Assumptions'!$A:$B,MATCH(O$2,'Rate Assumptions'!$A:$A,0),2) -> 929.5688 | P9: =INDEX('Rate Assumptions'!$A:$B,MATCH(P$2,'Rate Assumptions'!$A:$A,0),2) -> 929.5688 | Q9: =SUMPRODUCT(K9:M9,N9:P9) -> 27395322
A10: Chabot-Las Positas | B10: 5107 | C10: 283 | D10: 11658 | E10: 4787 | F10: 696 | G10: 11272 | K10: =E10+(E10-B10) -> 4467 | L10: =F10+(F10-C10) -> 1109 | M10: =G10+(G10-D10) -> 10886 | N10: =INDEX('Rate Assumptions'!$A:$B,MATCH(N$2,'Rate Assumptions'!$A:$A,0),2) -> 929.5688 | O10: =INDEX('Rate Assumptions'!$A:$B,MATCH(O$2,'Rate Assumptions'!$A:$A,0),2) -> 929.5688 | P10: =INDEX('Rate Assumptions'!$A:$B,MATCH(P$2,'Rate Assumptions'!$A:$A,0),2) -> 929.5688 | Q10: =SUMPRODUCT(K10:M10,N10:P10) -> 15302562
A11: Chaffey | B11: 8812 | C11: 884 | D11: 17781 | E11: 8010 | F11: 1343 | G11: 18275 | K11: =E11+(E11-B11) -> 7208 | L11: =F11+(F11-C11) -> 1802 | M11: =G11+(G11-D11) -> 18769 | N11: =INDEX('Rate Assumptions'!$A:$B,MATCH(N$2,'Rate Assumptions'!$A:$A,0),2) -> 929.5688 | O11: =INDEX('Rate Assumptions'!$A:$B,MATCH(O$2,'Rate Assumptions'!$A:$A,0),2) -> 929.5688 | P11: =INDEX('Rate Assumptions'!$A:$B,MATCH(P$2,'Rate Assumptions'!$A:$A,0),2) -> 929.5688 | Q11: =SUMPRODUCT(K11:M11,N11:P11) -> 25822492
A12: Citrus | B12: 4898 | C12: 457 | D12: 10958 | E12: 5010 | F12: 501 | G12: 11058 | K12: =E12+(E12-B12) -> 5122 | L12: =F12+(F12-C12) -> 545 | M12: =G12+(G12-D12) -> 11158 | N12: =INDEX('Rate Assumptions'!$A:$B,MATCH(N$2,'Rate Assumptions'!$A:$A,0),2) -> 929.5688 | O12: =INDEX('Rate Assumptions'!$A:$B,MATCH(O$2,'Rate Assumptions'!$A:$A,0),2) -> 929.5688 | P12: =INDEX('Rate Assumptions'!$A:$B,MATCH(P$2,'Rate Assumptions'!$A:$A,0),2) -> 929.5688 | Q12: =SUMPRODUCT(K12:M12,N12:P12) -> 15639995
A13: Coast | B13: 12015 | C13: 1280 | D13: 31151 | E13: 11222 | F13: 1342 | G13: 32107 | K13: =E13+(E13-B13) -> 10429 | L13: =F13+(F13-C13) -> 1404 | M13: =G13+(G13-D13) -> 33063 | N13: =INDEX('Rate Assumptions'!$A:$B,MATCH(N$2,'Rate Assumptions'!$A:$A,0),2) -> 929.5688 | O13: =INDEX('Rate Assumptions'!$A:$B,MATCH(O$2,'Rate Assumptions'!$A:$A,0),2) -> 929.5688 | P13: =INDEX('Rate Assumptions'!$A:$B,MATCH(P$2,'Rate Assumptions'!$A:$A,0),2) -> 929.5688 | Q13: =SUMPRODUCT(K13:M13,N13:P13) -> 41733921
A14: Compton | B14: 2838 | C14: 788 | D14: 5544 | E14: 2459 | F14: 341 | G14: 5230 | K14: =E14+(E14-B14) -> 2080 | L14: =F14+(F14-C14) -> -106 | M14: =G14+(G14-D14) -> 4916 | N14: =INDEX('Rate Assumptions'!$A:$B,MATCH(N$2,'Rate Assumptions'!$A:$A,0),2) -> 929.5688 | O14: =INDEX('Rate Assumptions'!$A:$B,MATCH(O$2,'Rate Assumptions'!$A:$A,0),2) -> 929.5688 | P14: =INDEX('Rate Assumptions'!$A:$B,MATCH(P$2,'Rate Assumptions'!$A:$A,0),2) -> 929.5688 | Q14: =SUMPRODUCT(K14:M14,N14:P14) -> 6404729
A15: Contra Costa | B15: 9025 | C15: 2275 | D15: 18504 | E15: 8978 | F15: 1245 | G15: 18682 | K15: =E15+(E15-B15) -> 8931 | L15: =F15+(F15-C15) -> 215 | M15: =G15+(G15-D15) -> 18860 | N15: =INDEX('Rate Assumptions'!$A:$B,MATCH(N$2,'Rate Assumptions'!$A:$A,0),2) -> 929.5688 | O15: =INDEX('Rate Assumptions'!$A:$B,MATCH(O$2,'Rate Assumptions'!$A:$A,0),2) -> 929.5688 | P15: =INDEX('Rate Assumptions'!$A:$B,MATCH(P$2,'Rate Assumptions'!$A:$A,0),2) -> 929.5688 | Q15: =SUMPRODUCT(K15:M15,N15:P15) -> 26033504
A16: Copper Mountain | B16: 1087 | C16: 60 | D16: 1843 | E16: 1133 | F16: 22 | G16: 1948 | K16: =E16+(E16-B16) -> 1179 | L16: =F16+(F16-C16) -> -16 | M16: =G16+(G16-D16) -> 2053 | N16: =INDEX('Rate Assumptions'!$A:$B,MATCH(N$2,'Rate Assumptions'!$A:$A,0),2) -> 929.5688 | O16: =INDEX('Rate Assumptions'!$A:$B,MATCH(O$2,'Rate Assumptions'!$A:$A,0),2) -> 929.5688 | P16: =INDEX('Rate Assumptions'!$A:$B,MATCH(P$2,'Rate Assumptions'!$A:$A,0),2) -> 929.5688 | Q16: =SUMPRODUCT(K16:M16,N16:P16) -> 2989493.3
... A75: Yuba | B75: 4370 | C75: 382 | D75: 8067 | E75: 4137 | F75: 360 | G75: 7764 | K75: =E75+(E75-B75) -> 3904 | L75: =F75+(F75-C75) -> 338 | M75: =G75+(G75-D75) -> 7461 | N75: =INDEX('Rate Assumptions'!$A:$B,MATCH(N$2,'Rate Assumptions'!$A:$A,0),2) -> 929.5688 | O75: =INDEX('Rate Assumptions'!$A:$B,MATCH(O$2,'Rate Assumptions'!$A:$A,0),2) -> 929.5688 | P75: =INDEX('Rate Assumptions'!$A:$B,MATCH(P$2,'Rate Assumptions'!$A:$A,0),2) -> 929.5688 | Q75: =SUMPRODUCT(K75:M75,N75:P75) -> 10878744
A76: Statewide Total | B76: =SUM(B4:B75) -> 460621 | C76: =SUM(C4:C75) -> 63006 | D76: =SUM(D4:D75) -> 1003618 | E76: =SUM(E4:E75) -> 448989 | F76: =SUM(F4:F75) -> 60500 | G76: =SUM(G4:G75) -> 989748 | K76: =SUM(K4:K75) -> 437357 | L76: =SUM(L4:L75) -> 57994 | M76: =SUM(M4:M75) -> 975878 | Q76: =SUM(Q4:Q75) -> 1.3676086e+09

Sheet Success Allocation
B1: 2016-17 | Z1: 2017-18 | AX1: 2018-19 | BV1: 2019-20 Projection | CT1: Model Inputs (3-Year Averages) | DR1: Rate
B2: All Students | J2: Pell Grant Students Only | R2: Promise Grant Students Only | Z2: All Students | AH2: Pell Grant Students Only | AP2: Promise Grant Students Only | AX2: All Students | BF2: Pell Grant Students Only | BN2: Promise Grant Students Only | BV2: All Students | CD2: Pell Grant Students Only | CL2: Promise Grant Students Only | CT2: All Students | DB2: Pell Grant Students Only | DJ2: Promise Grant Students Only | DR2: All Students | DZ2: Pell Grant Students Only | EH2: Promise Grant Students Only
A3: District | B3: Associate Degrees for Transfers | C3: Associate Degrees | D3: Baccalaureate Degrees | E3: Credit Certificates | F3: Transfer Level Math and English | G3: Nine or More CTE Units | H3: Transfers | I3: Regional Living Wage | J3: Associate Degrees for Transfers | K3: Associate Degrees | L3: Baccalaureate Degrees | M3: Credit Certificates | N3: Transfer Level Math and English | O3: Nine or More CTE Units | P3: Transfers | Q3: Regional Living Wage | R3: Associate Degrees for Transfers | S3: Associate Degrees | T3: Baccalaureate Degrees | U3: Credit Certificates | V3: Transfer Level Math and English | W3: Nine or More CTE Units | X3: Transfers | Y3: Regional Living Wage | Z3: Associate Degrees for Transfers | AA3: Associate Degrees | AB3: Baccalaureate Degrees | AC3: Credit Certificates | AD3: Transfer Level Math and English | AE3: Nine or More CTE Units | AF3: Transfers | AG3: Regional Living Wage | AH3: Associate Degrees for Transfers | AI3: Associate Degrees | AJ3: Baccalaureate Degrees | AK3: Credit Certificates | AL3: Transfer Level Math and English | AM3: Nine or More CTE Units | AN3: Transfers | AO3: Regional Living Wage | AP3: Associate Degrees for Transfers | AQ3: Associate Degrees | AR3: Baccalaureate Degrees | AS3: Credit Certificates | AT3: Transfer Level Math and English | AU3: Nine or More CTE Units | AV3: Transfers | AW3: Regional Living Wage | AX3: Associate Degrees for Transfers | AY3: Associate Degrees | AZ3: Baccalaureate Degrees | BA3: Credit Certificates | BB3: Transfer Level Math and English | BC3: Nine or More CTE Units | BD3: Transfers | BE3: Regional Living Wage | BF3: Associate Degrees for Transfers | BG3: Associate Degrees | BH3: Baccalaureate Degrees | BI3: Credit Certificates | BJ3: Transfer Level Math and English | BK3: Nine or More CTE Units | BL3: Transfers | BM3: Regional Living Wage | BN3: Associate Degrees for Transfers | BO3: Associate Degrees | BP3: Baccalaureate Degrees | BQ3: Credit Certificates | BR3: Transfer Level Math and English | BS3: Nine or More CTE Units | BT3: Transfers | BU3: Regional Living Wage | BV3: Associate Degrees for Transfers | BW3: Associate Degrees | BX3: Baccalaureate Degrees | BY3: Credit Certificates | BZ3: Transfer Level Math and English | CA3: Nine or More CTE Units | CB3: Transfers | CC3: Regional Living Wage | CD3: Associate Degrees for Transfers | CE3: Associate Degrees | CF3: Baccalaureate Degrees | CG3: Credit Certificates | CH3: Transfer Level Math and English | CI3: Nine or More CTE Units | CJ3: Transfers | CK3: Regional Living Wage | CL3: Associate Degrees for Transfers | CM3: Associate Degrees | CN3: Baccalaureate Degrees | CO3: Credit Certificates | CP3: Transfer Level Math and English | CQ3: Nine or More CTE Units | CR3: Transfers | CS3: Regional Living Wage | CT3: Associate Degrees for Transfers | CU3: Associate Degrees | CV3: Baccalaureate Degrees | CW3: Credit Certificates | CX3: Transfer Level Math and English | CY3: Nine or More CTE Units | CZ3: Transfers | DA3: Regional Living Wage | DB3: Associate Degrees for Transfers | DC3: Associate Degrees | DD3: Baccalaureate Degrees | DE3: Credit Certificates | DF3: Transfer Level Math and English | DG3: Nine or More CTE Units | DH3: Transfers | DI3: Regional Living Wage | DJ3: Associate Degrees for Transfers | DK3: Associate Degrees | DL3: Baccalaureate Degrees | DM3: Credit Certificates | DN3: Transfer Level Math and English | DO3: Nine or More CTE Units | DP3: Transfers | DQ3: Regional Living Wage | DR3: Associate Degrees for Transfers | DS3: Associate Degrees | DT3: Baccalaureate Degrees | DU3: Credit Certificates | DV3: Transfer Level Math and English | DW3: Nine or More CTE Units | DX3: Transfers | DY3: Regional Living Wage | DZ3: Associate Degrees for Transfers PELL GRANT | EA3: Associate Degrees PELL GRANT | EB3: Baccalaureate Degrees PELL GRANT | EC3: Credit Certificates PELL GRANT | ED3: Transfer Level Math and English PELL GRANT | EE3: Nine or More CTE Units PELL GRANT | EF3: Transfers PELL GRANT | EG3: Regional Living Wage PELL GRANT | EH3: Associate Degrees for Transfers PROMISE GRANT | EI3: Associate Degrees PROMISE GRANT | EJ3: Baccalaureate Degrees PROMISE GRANT | EK3: Credit Certificates PROMISE GRANT | EL3: Transfer Level Math and English PROMISE GRANT | EM3: Nine or More CTE Units PROMISE GRANT | EN3: Transfers PROMISE GRANT | EO3: Regional Living Wage PROMISE GRANT | EP3: Success Allocation
A4: Allan Hancock | B4: 247 | C4: 643 | D4: 0 | E4: 259 | F4: 216 | G4: 1933 | H4: 803 | I4: 2511 | J4: 133 | K4: 346 | L4: 0 | M4: 120 | N4: 93 | O4: 877 | P4: 289 | Q4: 435 | R4: 195 | S4: 520 | T4: 0 | U4: 194 | V4: 156 | W4: 1417 | X4: 467 | Y4: 919 | Z4: 272 | AA4: 577 | AB4: 0 | AC4: 244 | AD4: 190 | AE4: 1915 | AF4: 865 | AG4: 2224 | AH4: 161 | AI4: 311 | AJ4: 0 | AK4: 126 | AL4: 83 | AM4: 793 | AN4: 328 | AO4: 447 | AP4: 225 | AQ4: 475 | AR4: 0 | AS4: 193 | AT4: 136 | AU4: 1366 | AV4: 551 | AW4: 943 | BV4: =Z4+(Z4-B4) -> 297 | BW4: =AA4+(AA4-C4) -> 511 | BX4: =AB4+(AB4-D4) -> 0 | BY4: =AC4+(AC4-E4) -> 229 | BZ4: =AD4+(AD4-F4) -> 164 | CA4: =AE4+(AE4-G4) -> 1897 | CB4: =AF4+(AF4-H4) -> 927 | CC4: =AG4+(AG4-I4) -> 1937 | ... CS4: =AW4+(AW4-Y4) -> 967 | CT4: =AVERAGE(BV4,Z4,B4) -> 272 | CU4: =AVERAGE(BW4,AA4,C4) -> 577 | CV4: =AVERAGE(BX4,AB4,D4) -> 0 | CW4: =AVERAGE(BY4,AC4,E4) -> 244 | CX4: =AVERAGE(BZ4,AD4,F4) -> 190 | CY4: =AVERAGE(CA4,AE4,G4) -> 1915 | CZ4: =AVERAGE(CB4,AF4,H4) -> 865 | DA4: =AVERAGE(CC4,AG4,I4) -> 2224 | ... DQ4: =AVERAGE(CS4,AW4,Y4) -> 943 | DR4: =INDEX('Rate Assumptions'!$A$1:$C$32,MATCH('Success Allocation'!DR$3,'Rate Assumptions'!$A$1:$A$32,0),MATCH($DR$1,'Rate Assumptions'!$A$1:$C$1,0)) -> 2291.7552 | DS4: =INDEX('Rate Assumptions'!$A$1:$C$32,MATCH('Success Allocation'!DS$3,'Rate Assumptions'!$A$1:$A$32,0),MATCH($DR$1,'Rate Assumptions'!$A$1:$C$1,0)) -> 1718.8164 | DT4: =INDEX('Rate Assumptions'!$A$1:$C$32,MATCH('Success Allocation'!DT$3,'Rate Assumptions'!$A$1:$A$32,0),MATCH($DR$1,'Rate Assumptions'!$A$1:$C$1,0)) -> 1718.8164 | DU4: =INDEX('Rate Assumptions'!$A$1:$C$32,MATCH('Success Allocation'!DU$3,'Rate Assumptions'!$A$1:$A$32,0),MATCH($DR$1,'Rate Assumptions'!$A$1:$C$1,0)) -> 1145.8776 | DV4: =INDEX('Rate Assumptions'!$A$1:$C$32,MATCH('Success Allocation'!DV$3,'Rate Assumptions'!$A$1:$A$32,0),MATCH($DR$1,'Rate Assumptions'!$A$1:$C$1,0)) -> 1145.8776 | DW4: =INDEX('Rate Assumptions'!$A$1:$C$32,MATCH('Success Allocation'!DW$3,'Rate Assumptions'!$A$1:$A$32,0),MATCH($DR$1,'Rate Assumptions'!$A$1:$C$1,0)) -> 572.93879 | DX4: =INDEX('Rate Assumptions'!$A$1:$C$32,MATCH('Success Allocation'!DX$3,'Rate Assumptions'!$A$1:$A$32,0),MATCH($DR$1,'Rate Assumptions'!$A$1:$C$1,0)) -> 859.40819 | DY4: =INDEX('Rate Assumptions'!$A$1:$C$32,MATCH('Success Allocation'!DY$3,'Rate Assumptions'!$A$1:$A$32,0),MATCH($DR$1,'Rate Assumptions'!$A$1:$C$1,0)) -> 572.93879 | ... EO4: =INDEX('Rate Assumptions'!$A$1:$C$32,MATCH('Success Allocation'!EO$3,'Rate Assumptions'!$A$1:$A$32,0),MATCH($DR$1,'Rate Assumptions'!$A$1:$C$1,0)) -> 144.38595 | EP4: =SUMPRODUCT(BV4:CS4,DR4:EO4) -> 6696154
A5: Antelope | B5: 406 | C5: 775 | D5: 0 | E5: 191 | F5: 206 | G5: 2138 | H5: 966 | I5: 1001 | J5: 286 | K5: 512 | L5: 0 | M5: 135 | N5: 122 | O5: 1421 | P5: 549 | Q5: 502 | R5: 347 | S5: 640 | T5: 0 | U5: 162 | V5: 157 | W5: 1796 | X5: 771 | Y5: 724 | Z5: 485 | AA5: 676 | AB5: 0 | AC5: 254 | AD5: 187 | AE5: 2033 | AF5: 992 | AG5: 1147 | AH5: 340 | AI5: 458 | AJ5: 0 | AK5: 164 | AL5: 97 | AM5: 1318 | AN5: 568 | AO5: 595 | AP5: 415 | AQ5: 564 | AR5: 0 | AS5: 207 | AT5: 139 | AU5: 1693 | AV5: 788 | AW5: 874 | BV5: =Z5+(Z5-B5) -> 564 | BW5: =AA5+(AA5-C5) -> 577 | BX5: =AB5+(AB5-D5) -> 0 | BY5: =AC5+(AC5-E5) -> 317 | BZ5: =AD5+(AD5-F5) -> 168 | CA5: =AE5+(AE5-G5) -> 1928 | CB5: =AF5+(AF5-H5) -> 1018 | CC5: =AG5+(AG5-I5) -> 1293 | ... CS5: =AW5+(AW5-Y5) -> 1024 | CT5: =AVERAGE(BV5,Z5,B5) -> 485 | CU5: =AVERAGE(BW5,AA5,C5) -> 676 | CV5: =AVERAGE(BX5,AB5,D5) -> 0 | CW5: =AVERAGE(BY5,AC5,E5) -> 254 | CX5: =AVERAGE(BZ5,AD5,F5) -> 187 | CY5: =AVERAGE(CA5,AE5,G5) -> 2033 | CZ5: =AVERAGE(CB5,AF5,H5) -> 992 | DA5: =AVERAGE(CC5,AG5,I5) -> 1147 | ... DQ5: =AVERAGE(CS5,AW5,Y5) -> 874 | DR5: =INDEX('Rate Assumptions'!$A$1:$C$32,MATCH('Success Allocation'!DR$3,'Rate Assumptions'!$A$1:$A$32,0),MATCH($DR$1,'Rate Assumptions'!$A$1:$C$1,0)) -> 2291.7552 | DS5: =INDEX('Rate Assumptions'!$A$1:$C$32,MATCH('Success Allocation'!DS$3,'Rate Assumptions'!$A$1:$A$32,0),MATCH($DR$1,'Rate Assumptions'!$A$1:$C$1,0)) -> 1718.8164 | DT5: =INDEX('Rate Assumptions'!$A$1:$C$32,MATCH('Success Allocation'!DT$3,'Rate Assumptions'!$A$1:$A$32,0),MATCH($DR$1,'Rate Assumptions'!$A$1:$C$1,0)) -> 1718.8164 | DU5: =INDEX('Rate Assumptions'!$A$1:$C$32,MATCH('Success Allocation'!DU$3,'Rate Assumptions'!$A$1:$A$32,0),MATCH($DR$1,'Rate Assumptions'!$A$1:$C$1,0)) -> 1145.8776 | DV5: =INDEX('Rate Assumptions'!$A$1:$C$32,MATCH('Success Allocation'!DV$3,'Rate Assumptions'!$A$1:$A$32,0),MATCH($DR$1,'Rate Assumptions'!$A$1:$C$1,0)) -> 1145.8776 | DW5: =INDEX('Rate Assumptions'!$A$1:$C$32,MATCH('Success Allocation'!DW$3,'Rate Assumptions'!$A$1:$A$32,0),MATCH($DR$1,'Rate Assumptions'!$A$1:$C$1,0)) -> 572.93879 | DX5: =INDEX('Rate Assumptions'!$A$1:$C$32,MATCH('Success Allocation'!DX$3,'Rate Assumptions'!$A$1:$A$32,0),MATCH($DR$1,'Rate Assumptions'!$A$1:$C$1,0)) -> 859.40819 | DY5: =INDEX('Rate Assumptions'!$A$1:$C$32,MATCH('Success Allocation'!DY$3,'Rate Assumptions'!$A$1:$A$32,0),MATCH($DR$1,'Rate Assumptions'!$A$1:$C$1,0)) -> 572.93879 | ... EO5: =INDEX('Rate Assumptions'!$A$1:$C$32,MATCH('Success Allocation'!EO$3,'Rate Assumptions'!$A$1:$A$32,0),MATCH($DR$1,'Rate Assumptions'!$A$1:$C$1,0)) -> 144.38595 | EP5: =SUMPRODUCT(BV5:CS5,DR5:EO5) -> 8031644.8
